Workbook

Sheet LA MAR P1
H3: =18.17% -> 0.1817 | I3: =9.72% -> 0.0972 | J3: =8.333333% -> 0.08333333 | K3: 0.09
B4: CÁLCULO DE COSTO MENSUAL DE PERSONAL EN PLANILLA MYPE | H4: =18.17%/2 -> 0.09085 | I4: =9.72%/2 -> 0.0486 | J4: =8.333333%/2 -> 0.041666665 | K4: 0.09 | M4: ↓ | N4: 30 | O4: 8 | P4: 60
B6: N° | C6: CARGO | D6: DATOS PERSONALES | E6: BASICO | F6: ASIG. FAMILIAR | G6: REMUN. IMPONIBLE | H6: GRATIFICACIONES Julio y Diciembre | I6: CTS | J6: VACACIONES | K6: ESSALUD | M6: COSTO MENSUAL | N6: COSTO DIARIO | O6: COSTO POR HORA | P6: COSTO POR MIN | R6: AFP/ONP | S6: RTA 5TA | T6: NETO
L7: MOVILIDAD
B9: 1 | C9: MOZO | D9: MEZA ARCIA ALEJANDRO JOSE | E9: 779.8 | F9: 0 | G9: =E9+F9 -> 779.8 | H9: =G9*$H$3 -> 141.68966 | I9: =G9*$I$3 -> 75.79656 | J9: =G9*$J$3 -> 64.983331 | K9: =G9*$K$4 -> 70.182 | L9: 0 | M9: =G9+H9+I9+J9+K9+L9 -> 1132.4516 | N9: =M9/$N$4 -> 37.748385 | O9: =N9/$O$4 -> 4.7185481 | P9: =O9/$P$4 -> 0.078642469 | R9: =G9*11.97% -> 93.34206 | S9: 0 | T9: =G9+L9-R9-S9 -> 686.45794
B10: =B9+1 -> 2 | C10: COCINERA | D10: BRETONECHE DIAPIS ANA LUCIA | E10: 1908.19 | F10: 102.5 | G10: =E10+F10 -> 2010.69 | H10: =G10*$H$4 -> 182.67119 | I10: =G10*$I$4 -> 97.719534 | J10: =G10*$J$4 -> 83.778747 | K10: =G10*$K$4 -> 180.9621 | L10: 0 | M10: =G10+H10+I10+J10+K10+L10 -> 2555.8216 | N10: =M10/$N$4 -> 85.194052 | O10: =N10/$O$4 -> 10.649257 | P10: =O10/$P$4 -> 0.17748761 | R10: =G10*11.74% -> 236.05501 | S10: 0 | T10: =G10+L10-R10-S10 -> 1774.635
B11: =B10+1 -> 3 | C11: COCINERO | D11: ARANA CAMPIAN THALIA MISHEL | E11: 1537.34 | G11: =E11+F11 -> 1537.34 | H11: =G11*$H$4 -> 139.66734 | I11: =G11*$I$4 -> 74.714724 | J11: =G11*$J$4 -> 64.055831 | K11: =G11*$K$4 -> 138.3606 | L11: 0 | M11: =G11+H11+I11+J11+K11+L11 -> 1954.1385 | N11: =M11/$N$4 -> 65.13795 | O11: =N11/$O$4 -> 8.1422437 | P11: =O11/$P$4 -> 0.13570406 | R11: =G11*11.92% -> 183.25093 | S11: 0 | T11: =G11+L11-R11-S11 -> 1354.0891
B12: 4 | C12: JEFA DE BARRA | D12: LLANTOY LLAMOCCA GRACE MELANY | E12: 1422.21 | F12: 0 | G12: =E12+F12 -> 1422.21 | H12: =G12*$H$4 -> 129.20778 | I12: =G12*$I$4 -> 69.119406 | J12: =G12*$J$4 -> 59.258748 | K12: =G12*$K$4 -> 127.9989 | L12: 0 | M12: =G12+H12+I12+J12+K12+L12 -> 1807.7948 | N12: =M12/$N$4 -> 60.259828 | O12: =N12/$O$4 -> 7.5324785 | P12: =O12/$P$4 -> 0.12554131 | R12: =G12*11.97% -> 170.23854 | S12: 0 | T12: =G12+L12-R12-S12 -> 1251.9715
B13: 5 | C13: AYUDANTE DE COCINA | D13: REYNA TORO FLORDELUCERO MYLIN | E13: 1025 | G13: =E13+F13 -> 1025 | H13: =G13*$H$4 -> 93.12125 | I13: =G13*$I$4 -> 49.815 | J13: =G13*$J$4 -> 42.708332 | K13: =G13*$K$4 -> 92.25 | L13: 0 | M13: =G13+H13+I13+J13+K13+L13 -> 1302.8946 | N13: =M13/$N$4 -> 43.429819 | O13: =N13/$O$4 -> 5.4287274 | P13: =O13/$P$4 -> 0.09047879 | R13: =G13*11.92% -> 122.18 | S13: 0 | T13: =G13+L13-R13-S13 -> 902.82
B14: 6 | C14: ASISTENTE DE LOGISTICA | D14: MAMANI HUAMANI YAMIR JOSE | E14: 800 | G14: =E14+F14 -> 800 | H14: =G14*$H$4 -> 72.68 | I14: =G14*$I$4 -> 38.88 | J14: =G14*$J$4 -> 33.333332 | K14: =G14*$K$4 -> 72 | L14: 0 | M14: =G14+H14+I14+J14+K14+L14 -> 1016.8933 | N14: =M14/$N$4 -> 33.896444 | O14: =N14/$O$4 -> 4.2370556 | P14: =O14/$P$4 -> 0.070617593 | R14: =G14*11.92% -> 95.36 | S14: 0 | T14: =G14+L14-R14-S14 -> 704.64
B15: 7 | C15: JEFE DE COCINA | D15: CHUNGA VILLAR PEDRO GIOMAR | E15: 3000 | F15: 102.5 | G15: =E15+F15 -> 3102.5 | H15: =G15*$H$4 -> 281.86213 | I15: =G15*$I$4 -> 150.7815 | J15: =G15*$J$4 -> 129.27083 | K15: =G15*$K$4 -> 279.225 | L15: 0 | M15: =G15+H15+I15+J15+K15+L15 -> 3943.6395 | N15: =M15/$N$4 -> 131.45465 | O15: =N15/$O$4 -> 16.431831 | P15: =O15/$P$4 -> 0.27386385 | R15: =G15*11.92% -> 369.818 | S15: 0 | T15: =G15+L15-R15-S15 -> 2732.682
B16: 8 | C16: MOZO | D16: ASIN VINCES VICTOR ANDRES | E16: 1270.8 | G16: =E16+F16 -> 1270.8 | H16: =G16*$H$4 -> 115.45218 | I16: =G16*$I$4 -> 61.76088 | J16: =G16*$J$4 -> 52.949998 | K16: =G16*$K$4 -> 114.372 | L16: 0 | M16: =G16+H16+I16+J16+K16+L16 -> 1615.3351 | N16: =M16/$N$4 -> 53.844502 | O16: =N16/$O$4 -> 6.7305627 | P16: =O16/$P$4 -> 0.11217605 | R16: =G16*11.92% -> 151.47936 | S16: 0 | T16: =G16+L16-R16-S16 -> 1119.3206
D18: TOTALES PLANILLA - | E18: =SUM(E9:E17) -> 11743.34 | F18: =SUM(F9:F17) -> 205 | G18: =SUM(G9:G17) -> 11948.34 | H18: =SUM(H9:H17) -> 1156.3515 | I18: =SUM(I9:I17) -> 618.5876 | J18: =SUM(J9:J17) -> 530.33915 | K18: =SUM(K9:K17) -> 1075.3506 | L18: =SUM(L9:L17) -> 0 | M18: =SUM(M9:M17) -> 15328.969 | N18: =SUM(N9:N13) -> 291.77003 | O18: =SUM(O9:O13) -> 36.471254 | P18: =SUM(P9:P13) -> 0.60785424 | R18: =SUM(R9:R17) -> 1421.7239 | S18: =SUM(S9:S17) -> 0 | T18: =SUM(T9:T17) -> 10526.616
B21: N° | C21: CARGO | D21: DATOS PERSONALES | E21: BASICO | F21: ASIG. FAMILIAR | G21: REMUN. IMPONIBLE | H21: GRATIFICACIONES Julio y Diciembre | I21: CTS | J21: VACACIONES | K21: ESSALUD | M21: COSTO MENSUAL | N21: COSTO DIARIO | O21: COSTO POR HORA | P21: COSTO POR MIN | R21: AFP/ONP | S21: RTA 5TA | T21: NETO
L22: MOVILIDAD
B24: 1 | C24: CHEF EJECUTIVO | D24: DANIEL BENITES SEBAN (*RGL) | E24: 4208.6 | F24: 0 | G24: =E24+F24 -> 4208.6 | H24: =G24*$H$3 -> 764.70262 | I24: =G24*$I$3 -> 409.07592 | J24: =G24*$J$3 -> 350.71665 | K24: =G24*$K$4 -> 378.774 | L24: 0 | M24: =G24+H24+I24+J24+K24+L24 -> 6111.8692 | N24: =M24/$N$4 -> 203.72897 | O24: =N24/$O$4 -> 25.466122 | P24: =O24/$P$4 -> 0.42443536 | R24: =G24*11.97% -> 503.76942 | S24: 204 | T24: =G24+L24-R24-S24 -> 3500.8306
B25: =B24+1 -> 2 | C25: BARMAN JEFE | D25: FERNANDEZ RUIZ JENNER JOEL | E25: 1706.7 | F25: 102.5 | G25: =E25+F25 -> 1809.2 | H25: =G25*$H$4 -> 164.36582 | I25: =G25*$I$4 -> 87.92712 | J25: =G25*$J$4 -> 75.38333 | K25: =G25*$K$4 -> 162.828 | L25: 0 | M25: =G25+H25+I25+J25+K25+L25 -> 2299.7043 | N25: =M25/$N$4 -> 76.656809 | O25: =N25/$O$4 -> 9.5821011 | P25: =O25/$P$4 -> 0.15970169 | R25: =G25*11.74% -> 212.40008 | S25: 0 | T25: =G25+L25-R25-S25 -> 1596.7999
B26: =B25+1 -> 3 | C26: JEFE DE SALON | D26: MORALES GONZALES CARLOS DANIEL | E26: 1562.4 | G26: =E26+F26 -> 1562.4 | H26: =G26*$H$4 -> 141.94404 | I26: =G26*$I$4 -> 75.93264 | J26: =G26*$J$4 -> 65.099997 | K26: =G26*$K$4 -> 140.616 | L26: 0 | M26: =G26+H26+I26+J26+K26+L26 -> 1985.9927 | N26: =M26/$N$4 -> 66.199756 | O26: =N26/$O$4 -> 8.2749695 | P26: =O26/$P$4 -> 0.13791616 | R26: =G26*11.92% -> 186.23808 | S26: 0 | T26: =G26+L26-R26-S26 -> 1376.1619
B27: 4 | C27: BARMAN | D27: VERA VILLALOBOS ALDA ARECELY | E27: 1463.2 | G27: =E27+F27 -> 1463.2 | H27: =G27*$H$4 -> 132.93172 | I27: =G27*$I$4 -> 71.11152 | J27: =G27*$J$4 -> 60.966664 | K27: =G27*$K$4 -> 131.688 | L27: 0 | M27: =G27+H27+I27+J27+K27+L27 -> 1859.8979 | N27: =M27/$N$4 -> 61.996597 | O27: =N27/$O$4 -> 7.7495746 | P27: =O27/$P$4 -> 0.12915958 | R27: =G27*13% -> 190.216 | S27: 0 | T27: =G27+L27-R27-S27 -> 1272.984
B28: 5 | C28: BARMAN | D28: PARIONA YUPA YERSON ALDAHIR | E28: 1459.7 | F28: 0 | G28: =E28+F28 -> 1459.7 | H28: =G28*$H$4 -> 132.61375 | I28: =G28*$I$4 -> 70.94142 | J28: =G28*$J$4 -> 60.820831 | K28: =G28*$K$4 -> 131.373 | L28: 0 | M28: =G28+H28+I28+J28+K28+L28 -> 1855.449 | N28: =M28/$N$4 -> 61.8483 | O28: =N28/$O$4 -> 7.7310375 | P28: =O28/$P$4 -> 0.12885062 | R28: =G28*11.97% -> 174.72609 | S28: 0 | T28: =G28+L28-R28-S28 -> 1284.9739
B29: 6 | C29: COCINERO | D29: SINTI SANTIVAÑEZ JEAN PAUL | E29: 1686.22 | G29: =E29+F29 -> 1686.22 | H29: =G29*$H$4 -> 153.19309 | I29: =G29*$I$4 -> 81.950292 | J29: =G29*$J$4 -> 70.259164 | K29: =G29*$K$4 -> 151.7598 | L29: 0 | M29: =G29+H29+I29+J29+K29+L29 -> 2143.3823 | N29: =M29/$N$4 -> 71.446078 | O29: =N29/$O$4 -> 8.9307598 | P29: =O29/$P$4 -> 0.148846 | R29: =G29*11.74% -> 197.96223 | S29: 0 | T29: =G29+L29-R29-S29 -> 1488.2578
B30: 7 | C30: ASISTENTE DE LOGISTICA | D30: MAMANI HUAMANI YAMIR JOSE | E30: 800 | G30: =E30+F30 -> 800 | H30: =G30*$H$4 -> 72.68 | I30: =G30*$I$4 -> 38.88 | J30: =G30*$J$4 -> 33.333332 | K30: =G30*$K$4 -> 72 | L30: 0 | M30: =G30+H30+I30+J30+K30+L30 -> 1016.8933 | N30: =M30/$N$4 -> 33.896444 | O30: =N30/$O$4 -> 4.2370556 | P30: =O30/$P$4 -> 0.070617593 | R30: =G30*11.92% -> 95.36 | S30: 0 | T30: =G30+L30-R30-S30 -> 704.64
B31: 8 | C31: COCINERO | D31: SOTERO ROMAN JULIO MARTIN | E31: 2104.35 | G31: =E31+F31 -> 2104.35 | H31: =G31*$H$4 -> 191.1802 | I31: =G31*$I$4 -> 102.27141 | J31: =G31*$J$4 -> 87.681246 | K31: =G31*$K$4 -> 189.3915 | L31: 0 | M31: =G31+H31+I31+J31+K31+L31 -> 2674.8744 | N31: =M31/$N$4 -> 89.162478 | O31: =N31/$O$4 -> 11.14531 | P31: =O31/$P$4 -> 0.18575516 | R31: =G31*13.29% -> 279.66811 | S31: 0 | T31: =G31+L31-R31-S31 -> 1824.6819
B32: 9 | C32: AYUDANTE DE COCINA | D32: ANDRICH PAREDES RODRIGO ALBERTO | E32: 1300 | G32: =E32+F32 -> 1300 | H32: =G32*$H$4 -> 118.105 | I32: =G32*$I$4 -> 63.18 | J32: =G32*$J$4 -> 54.166664 | K32: =G32*$K$4 -> 117 | L32: 0 | M32: =G32+H32+I32+J32+K32+L32 -> 1652.4517 | N32: =M32/$N$4 -> 55.081722 | O32: =N32/$O$4 -> 6.8852153 | P32: =O32/$P$4 -> 0.11475359 | R32: =G32*13.29% -> 172.77 | S32: 0 | T32: =G32+L32-R32-S32 -> 1127.23
B33: 10 | C33: COCINERA | D33: ANDRICH PAREDES VALERIA ALEJANDRA | E33: 1762.5 | G33: =E33+F33 -> 1762.5 | H33: =G33*$H$4 -> 160.12313 | I33: =G33*$I$4 -> 85.6575 | J33: =G33*$J$4 -> 73.437497 | K33: =G33*$K$4 -> 158.625 | L33: 0 | M33: =G33+H33+I33+J33+K33+L33 -> 2240.3431 | N33: =M33/$N$4 -> 74.678104 | O33: =N33/$O$4 -> 9.334763 | P33: =O33/$P$4 -> 0.15557938 | R33: =G33*13.29% -> 234.23625 | S33: 0 | T33: =G33+L33-R33-S33 -> 1528.2638
D35: TOTALES PLANILLA - | E35: =SUM(E24:E34) -> 18053.67 | F35: =SUM(F24:F34) -> 102.5 | G35: =SUM(G24:G34) -> 18156.17 | H35: =SUM(H24:H34) -> 2031.8394 | I35: =SUM(I24:I34) -> 1086.9278 | J35: =SUM(J24:J34) -> 931.86538 | K35: =SUM(K24:K34) -> 1634.0553 | L35: =SUM(L24:L34) -> 0 | M35: =SUM(M24:M34) -> 23840.858 | N35: =SUM(N24:N33) -> 794.69526 | O35: =SUM(O24:O33) -> 99.336908 | P35: =SUM(P24:P33) -> 1.6556151 | R35: =SUM(R24:R34) -> 2247.3463 | S35: =SUM(S24:S34) -> 204 | T35: =SUM(T24:T34) -> 15704.824
E37: =+E18+E35 -> 29797.01

Sheet Hoja1
D2: N° | E2: RELACIÓN DE PERSONAL LA MARIPOSARIO
D3: 1 | E3: ANA LUCIA BRETONECHE DIAPIS
D4: 2 | E4: YAMIR JOSE MAMANI HUAMANI
D5: 3 | E5: JOSE LUIS LOPEZ TOVAR
D6: 4 | E6: CALIXTO VIECENTE BLAS
D7: 5 | E7: PEDRO GIOMAR CHUNGA VILLAR
D8: 6 | E8: ALDA ARECELY VERA VILLALOBOS
D9: 7 | E9: ANGIRBER AGBRIEL CARARQUEL HERNANDEZ
D10: 8 | E10: CALIXTO VIECENTE BLAS
D11: 9 | E11: SUSY MILAGRO ALEJOS ARDELAS
D12: 10 | E12: FERNANDO MOYA HUAMANI
D13: 11 | E13: DARIO TELLO FLORES

Sheet AFP SBS
A3: Al mes de devengue 2025-02
A4: AFP | B4: Comisión | C4: Comisión | D4: Prima de | E4: Porcentaje de aporte obligatorio al Fondo de Pensiones (%) | F4: Remuneración Máxima Asegurable (S/.)
B5: Fija (S/). /2 | C5: Variable (%) | D5: Seguros (%) /3
A6: HABITAT | C6: 1.47 | D6: 1.37 | E6: 10 | F6: 12027.91
A7: INTEGRA | C7: 1.55 | D7: 1.37 | E7: 10 | F7: 12027.91
A8: PRIMA | C8: 1.6 | D8: 1.37 | E8: 10 | F8: 12027.91
A9: PROFUTURO | C9: 1.69 | D9: 1.37 | E9: 10 | F9: 12027.91
A11: * Comisiones descontadas sobre la Remuneración Bruta. No se considera descuentos por permanencia puesto que tales descuentos no afectan las retenciones del empleador.
A12: 1/ Las comisiones y primas retenidas correspondientes al mes de devengue "t" deben pagarse dentro de los 5 primeros días útiles del mes "t+1".
A13: 2/ A partir de Enero de 1997 se eliminó el cobro de Comisión Fija.
A14: 3/ Porcentaje a descontar sobre la Remuneración Bruta hasta el límite determinado por la Remuneración Máxima Asegurable (art. 67° del Título VII del Compendio de Normas reglamentarias del SPP).
A16: Al mes de devengue 2025-03
A17: AFP | B17: Comisión | C17: Comisión | D17: Prima de | E17: Porcentaje de aporte obligatorio al Fondo de Pensiones (%) | F17: Remuneración Máxima Asegurable (S/.)
B18: Fija (S/). /2 | C18: Variable (%) | D18: Seguros (%) /3
A19: HABITAT | C19: 1.47 | D19: 1.37 | E19: 10 | F19: 12027.91
A20: INTEGRA | C20: 1.55 | D20: 1.37 | E20: 10 | F20: 12027.91
A21: PRIMA | C21: 1.6 | D21: 1.37 | E21: 10 | F21: 12027.91
A22: PROFUTURO | C22: 1.69 | D22: 1.37 | E22: 10 | F22: 12027.91
A24: * Comisiones descontadas sobre la Remuneración Bruta. No se considera descuentos por permanencia puesto que tales descuentos no afectan las retenciones del empleador.
A25: 1/ Las comisiones y primas retenidas correspondientes al mes de devengue "t" deben pagarse dentro de los 5 primeros días útiles del mes "t+1".
A26: 2/ A partir de Enero de 1997 se eliminó el cobro de Comisión Fija.
A27: 3/ Porcentaje a descontar sobre la Remuneración Bruta hasta el límite determinado por la Remuneración Máxima Asegurable (art. 67° del Título VII del Compendio de Normas reglamentarias del SPP).
A29: Al mes de devengue 2025-04
A30: AFP | B30: Comisión | C30: Comisión | D30: Prima de | E30: Porcentaje de aporte obligatorio al Fondo de Pensiones (%) | F30: Remuneración Máxima Asegurable (S/.)
B31: Fija (S/). /2 | C31: Variable (%) | D31: Seguros (%) /3
A32: HABITAT | C32: 1.47 | D32: 1.37 | E32: 10 | F32: 12137.47
A33: INTEGRA | C33: 1.55 | D33: 1.37 | E33: 10 | F33: 12137.47
A34: PRIMA | C34: 1.6 | D34: 1.37 | E34: 10 | F34: 12137.47
A35: PROFUTURO | C35: 1.69 | D35: 1.37 | E35: 10 | F35: 12137.47
A36: * Comisiones descontadas sobre la Remuneración Bruta. No se considera descuentos por permanencia puesto que tales descuentos no afectan las retenciones del empleador.
A37: 1/ Las comisiones y primas retenidas correspondientes al mes de devengue "t" deben pagarse dentro de los 5 primeros días útiles del mes "t+1".
A38: 2/ A partir de Enero de 1997 se eliminó el cobro de Comisión Fija.
A39: 3/ Porcentaje a descontar sobre la Remuneración Bruta hasta el límite determinado por la Remuneración Máxima Asegurable (art. 67° del Título VII del Compendio de Normas reglamentarias del SPP).
A41: Al mes de devengue 2025-05
A42: AFP | B42: Comisión | C42: Comisión | D42: Prima de | E42: Porcentaje de aporte obligatorio al Fondo de Pensiones (%) | F42: Remuneración Máxima Asegurable (S/.)
B43: Fija (S/). /2 | C43: Variable (%) | D43: Seguros (%) /3
A44: HABITAT | C44: 1.47 | D44: 1.37 | E44: 10 | F44: 12137.47
A45: INTEGRA | C45: 1.55 | D45: 1.37 | E45: 10 | F45: 12137.47
A46: PRIMA | C46: 1.6 | D46: 1.37 | E46: 10 | F46: 12137.47
A47: PROFUTURO | C47: 1.69 | D47: 1.37 | E47: 10 | F47: 12137.47
A49: * Comisiones descontadas sobre la Remuneración Bruta. No se considera descuentos por permanencia puesto que tales descuentos no afectan las retenciones del empleador.
A50: 1/ Las comisiones y primas retenidas correspondientes al mes de devengue "t" deben pagarse dentro de los 5 primeros días útiles del mes "t+1".
A51: 2/ A partir de Enero de 1997 se eliminó el cobro de Comisión Fija.
A52: 3/ Porcentaje a descontar sobre la Remuneración Bruta hasta el límite determinado por la Remuneración Máxima Asegurable (art. 67° del Título VII del Compendio de Normas reglamentarias del SPP).
A54: Al mes de devengue 2025-06
A55: AFP | B55: Comisión | C55: Comisión | D55: Prima de | E55: Porcentaje de aporte obligatorio al Fondo de Pensiones (%) | F55: Remuneración Máxima Asegurable (S/.)
B56: Fija (S/). /2 | C56: Variable (%) | D56: Seguros (%) /3
A57: HABITAT | C57: 1.47 | D57: 1.37 | E57: 10 | F57: 12137.47
A58: INTEGRA | C58: 1.55 | D58: 1.37 | E58: 10 | F58: 12137.47
A59: PRIMA | C59: 1.6 | D59: 1.37 | E59: 10 | F59: 12137.47
A60: PROFUTURO | C60: 1.69 | D60: 1.37 | E60: 10 | F60: 12137.47
A62: * Comisiones descontadas sobre la Remuneración Bruta. No se considera descuentos por permanencia puesto que tales descuentos no afectan las retenciones del empleador.
A63: 1/ Las comisiones y primas retenidas correspondientes al mes de devengue "t" deben pagarse dentro de los 5 primeros días útiles del mes "t+1".
A64: 2/ A partir de Enero de 1997 se eliminó el cobro de Comisión Fija.
A65: 3/ Porcentaje a descontar sobre la Remuneración Bruta hasta el límite determinado por la Remuneración Máxima Asegurable (art. 67° del Título VII del Compendio de Normas reglamentarias del SPP).
A67: Al mes de devengue 2025-07
A68: AFP | B68: Comisión | C68: Comisión | D68: Prima de | E68: Porcentaje de aporte obligatorio al Fondo de Pensiones (%) | F68: Remuneración Máxima Asegurable (S/.)
B69: Fija (S/). /2 | C69: Variable (%) | D69: Seguros (%) /3
A70: HABITAT | C70: 1.47 | D70: 1.37 | E70: 10 | F70: 12184.88
A71: INTEGRA | C71: 1.55 | D71: 1.37 | E71: 10 | F71: 12184.88
A72: PRIMA | C72: 1.6 | D72: 1.37 | E72: 10 | F72: 12184.88
A73: PROFUTURO | C73: 1.69 | D73: 1.37 | E73: 10 | F73: 12184.88
A75: * Comisiones descontadas sobre la Remuneración Bruta. No se considera descuentos por permanencia puesto que tales descuentos no afectan las retenciones del empleador.
A76: 1/ Las comisiones y primas retenidas correspondientes al mes de devengue "t" deben pagarse dentro de los 5 primeros días útiles del mes "t+1".
A77: 2/ A partir de Enero de 1997 se eliminó el cobro de Comisión Fija.
A78: 3/ Porcentaje a descontar sobre la Remuneración Bruta hasta el límite determinado por la Remuneración Máxima Asegurable (art. 67° del Título VII del Compendio de Normas reglamentarias del SPP).
A80: Al mes de devengue 2025-08
A81: AFP | B81: Comisión | C81: Comisión | D81: Prima de | E81: Porcentaje de aporte obligatorio al Fondo de Pensiones (%) | F81: Remuneración Máxima Asegurable (S/.)
B82: Fija (S/). /2 | C82: Variable (%) | D82: Seguros (%) /3
A83: HABITAT | C83: 1.47 | D83: 1.37 | E83: 10 | F83: 12178.56
A84: INTEGRA | C84: 1.55 | D84: 1.37 | E84: 10 | F84: 12178.56
A85: PRIMA | C85: 1.6 | D85: 1.37 | E85: 10 | F85: 12178.56
A86: PROFUTURO | C86: 1.69 | D86: 1.37 | E86: 10 | F86: 12178.56
A88: * Comisiones descontadas sobre la Remuneración Bruta. No se considera descuentos por permanencia puesto que tales descuentos no afectan las retenciones del empleador.
A89: 1/ Las comisiones y primas retenidas correspondientes al mes de devengue "t" deben pagarse dentro de los 5 primeros días útiles del mes "t+1".
A90: 2/ A partir de Enero de 1997 se eliminó el cobro de Comisión Fija.
A91: 3/ Porcentaje a descontar sobre la Remuneración Bruta hasta el límite determinado por la Remuneración Máxima Asegurable (art. 67° del Título VII del Compendio de Normas reglamentarias del SPP).
A93: Mes de devengue :
A94: Al mes de devengue 2025-09 1/
A95: AFP | B95: COMISIÓN | C95: COMISIÓN | D95: PRIMA DE | E95: APORTE OBLIGATORIO AL FONDO DE PENSIONES | F95: REMUNERACIÓN MÁXIMA ASEGURABLE
B96: SOBRE FLUJO | C96: ANUAL SOBRE | D96: SEGUROS (%) 3/ | E96: (% Remuneración Bruta Mensual)
B97: (% Remuneración Bruta Mensual) | C97: SALDO | D97: (% Remuneración Bruta Mensual)
A98: HABITAT | B98: 1,47% | C98: 1,25% | D98: 1,37% | E98: 10,00% | F98: 12178.56
A99: INTEGRA | B99: 1,55% | C99: 0,78% | D99: 1,37% | E99: 10,00% | F99: 12178.56
A100: PRIMA | B100: 1,60% | C100: 1,25% | D100: 1,37% | E100: 10,00% | F100: 12178.56
A101: PROFUTURO | B101: 1,69% | C101: 0,68% | D101: 1,37% | E101: 10,00% | F101: 12178.56
A103: 1/ Las comisiones sobre la remuneración y las primas retenidas correspondientes a un determinado mes deben pagarse dentro de los 5 primeros dÍas útiles del mes siguiente.
A104: 2/ A partir de Enero de 1997 se eliminó el cobro de Comisión Fija.
A105: 3/ Porcentaje a descontar sobre la Remuneración Bruta hasta el límite determinado por el Reglamentode la Ley del SPP(Remuneración Máxima Asegurable Art. 67° del Título VII del Compendio de Normas reglamentarias del SPP).
A106: *** A partir de Febrero de 2023, el componente de flujo de la Comisión Mixta es 0%, resultando únicamente en Comisión anulado sobre saldo.
A108: Al mes de devengue 2025-10 1/
A109: AFP | B109: COMISIÓN | C109: COMISIÓN | D109: PRIMA DE | E109: APORTE OBLIGATORIO AL FONDO DE PENSIONES | F109: REMUNERACIÓN MÁXIMA ASEGURABLE
B110: SOBRE FLUJO | C110: ANUAL SOBRE | D110: SEGUROS (%) 3/ | E110: (% Remuneración Bruta Mensual)
B111: (% Remuneración Bruta Mensual) | C111: SALDO | D111: (% Remuneración Bruta Mensual)
A112: HABITAT | B112: 1,47% | C112: 1,25% | D112: 1,37% | E112: 10,00% | F112: 12 178,56
A113: INTEGRA | B113: 1,55% | C113: 0,78% | D113: 1,37% | E113: 10,00% | F113: 12 178,56
A114: PRIMA | B114: 1,60% | C114: 1,25% | D114: 1,37% | E114: 10,00% | F114: 12 178,56
A115: PROFUTURO | B115: 1,69% | C115: 0,68% | D115: 1,37% | E115: 10,00% | F115: 12 178,56
A117: 1/ Las comisiones sobre la remuneración y las primas retenidas correspondientes a un determinado mes deben pagarse dentro de los 5 primeros dÍas útiles del mes siguiente.
A118: 2/ A partir de Enero de 1997 se eliminó el cobro de Comisión Fija.
...

Sheet PLANILLA MENSUAL
B1: 1 | C1: 2 | I1: 6 | S1: 14 | X1: 16 | Y1: 17 | Z1: 18 | AA1: 19 | AB1: 20 | AF1: 21 | AH1: 22 | AM1: 24 | AN1: 25 | AO1: 26 | AP1: 27 | AQ1: 28 | AR1: 29 | AS1: 30 | AT1: 31 | AU1: 32 | AV1: 33 | AW1: 34 | AX1: 35 | AY1: 36 | AZ1: 37 | BD1: 39 | BK1: 41 | BL1: 42 | BM1: 43 | BN1: 44 | BQ1: 48 | BU1: 75 | BV1: 76 | BW1: 77 | BX1: 78 | BY1: 79 | BZ1: 80 | CA1: 81 | CB1: 82 | CC1: 83 | CD1: 84 | CE1: 85 | CF1: 86 | CG1: 87 | CH1: 88 | CI1: 89 | CJ1: 90 | CK1: 91 | CL1: 92 | CM1: 93 | CN1: 94 | CO1: 95 | CP1: 96 | CQ1: 97 | CR1: 98 | CS1: 99 | CT1: 100 | CU1: 101 | CV1: 102 | CW1: 103 | CX1: 104 | CY1: 105 | CZ1: 106 | DA1: 107 | DB1: 108 | DC1: 109 | DD1: 110 | DE1: 111 | DF1: 112 | DG1: 113 | DH1: 114 | DI1: 115 | DJ1: 116 | DK1: 117 | DL1: 118 | DM1: 119 | DN1: 120 | DO1: 121 | DP1: 122 | DQ1: 123 | DR1: 124 | DS1: 125 | DT1: 126 | DU1: 127 | DV1: 128 | DW1: 129 | DX1: 130 | DY1: 131 | DZ1: 132 | EA1: 133 | EB1: 134 | EC1: 135 | ED1: 136 | EE1: 137 | EF1: 138 | EG1: 139 | EH1: 140 | EI1: 141 | EJ1: 142 | EK1: 143 | EL1: 144 | EM1: 145 | EN1: 146 | EO1: 147 | EP1: 148 | EQ1: 149 | ER1: 150 | ES1: 151 | ET1: 152 | EU1: 153 | EV1: 154 | EW1: 155 | EX1: 156 | EY1: 157 | EZ1: 158
B2: INDUSTRIAL PROCESS S.R.L.
B3: R.U.C.: 20514706302
B4: PLANILLA DE REMUNERACIONES MES DE JULIO 2026
B6: (EXPRESADO EN NUEVOS SOLES)
C8: TRABAJADOR | I8: DATOS DEL PERSONAL | S8: REMUNERACIONES | AQ8: DESCUENTOS | BK8: TOTAL | BL8: NETO A | BM8: APORTACION
B9: N° | C9: APELLIDOS | E9: FECHA | F9: FECHA | G9: FECHA | I9: AFP | S9: REMUNER. | T9: ASIGNAC. | U9: SUBSIDIO | V9: COMISION | W9: COMISION | X9: HORAS | Y9: HORAS | Z9: FERIADOS | AB9: VACACIONES | AC9: VACACIONES | AD9: VACACIONES | AE9: VACACIONES | AF9: CTS | AG9: VALES | AH9: GRATIFIC. | AI9: BONIF | AJ9: BONIF | AK9: DEVOL | AL9: UTILIDAD | AM9: BONO | AO9: REMUNER | AP9: REMUNERA. | AQ9: ONP | AS9: A.F.P. | BD9: GRATI | BE9: PTMOS | BF9: SEGURO | BG9: SEGURO | BH9: VALES | BI9: OTROS | BJ9: RENTA | BK9: DESCUENT. | BL9: PAGAR | BM9: ESSALUD | BO9: SEGURO | BP9: SEGURO | BQ9: BCO
C10: PATERNO | D10: DNI, CE | E10: DE | F10: DE | G10: DE | H10: CARGO | I10: Y | J10: SUELDO BASE | K10: ASIG FAM | L10: TOTAL DIAS | M10: DESCANSO MEDICO | N10: SUBSIDIO | O10: DIAS NO LAB Y/O | P10: TOTAL DIAS | Q10: HRS X DIA | R10: TOTAL HRS | S10: PERCIBIDA | T10: FAMILIAR | V10: DEL MES | W10: PROMEDIO | X10: EXTRAS | Y10: EXTRAS | AA10: MOVIL | AB10: TRUNCAS | AC10: INDE. | AE10: COMPENSACIÓN | AG10: CONSUMO | AI10: 0.09 | AK10: RTA 5TA | AM10: EXTRAOR | AN10: DESC. | AO10: BRUTA | AP10: AFECTA | AQ10: % | AR10: S/. | AS10: APORTE | AU10: COMISION | AW10: PRIMA | AY10: TOTAL A.F.P. | BA10: FALTAS | BB10: TARDAN | BC10: ADELANTO | BF10: PACIFICO | BG10: EPS | BH10: CONSUMO | BI10: DSCTOS | BJ10: 5TA CATEG | BO10: VIDA LEY | BP10: PRIVADO | BR10: POR | BS10: DIF | BU10: ADELANTO | BX10: A PAGAR
E11: NACIMIENTO | F11: INGRESO | G11: CESE | I11: ONP | L11: MES | M11: DESCANSO | O11: VACAC | P11: LABOR | R11: MES | W11: VACACIONES | X11: 0.25 | Y11: 0.35 | AG11: OBSEQUIO | AM11: U OTRO | AS11: % | AT11: OBLIG | AU11: % | AV11: S/. | AW11: % | AX11: SEGURO | AY11: % | AZ11: S/. | BB11: ZAS | BH11: OBSEQUIOS | BM11: % | BN11: S/. | BP11: EPS | BR11: REEMB
A12: VTAS | B12: 1 | C12: ORIHUELA AGUIRRE ERNESTO JULIO | D12: 10305226 | E12: 27747 | F12: 39114 | H12: GERENTE GENERAL | I12: INTEGRA | J12: 13000 | K12: 113 | L12: 30 | P12: =+L12-M12-O12 -> 30 | Q12: 8 | R12: =+P12*Q12 -> 240 | S12: =+J12-AD12-U12 -> 13000 | T12: =K12 -> 113 | U12: =(J12)/30*N12 -> 0 | V12: =+[1]Resumen!$D$17 -> 7240.2251 | X12: =H.E!L6 -> 0 | Y12: =H.E!M6 -> 0 | Z12: =H.E!N6 -> 0 | AD12: =(J12+K12)/30*O12 -> 0 | AO12: =SUM(S12:AM12)-AN12 -> 20353.225 | AP12: =+AO12-AA12-AF12-AG12-AH12-AI12-AL12-AM12-AK12-BA12-BB12 -> 20353.225 | AS12: 0.1 | AT12: =+AP12*AS12 -> 2035.3225 | AU12: 0 | AV12: =+AP12*AU12 -> 0 | AW12: 0.0137 | AX12: =12672.65*AW12 -> 173.61531 | AY12: =+AS12+AU12+AW12 -> 0.1137 | AZ12: =+AT12+AV12+AX12 -> 2208.9378 | BA12: =TARDANZA!K6 -> 0 | BB12: =TARDANZA!L6 -> 0 | BC12: 4600 | BF12: =+'SEGURO PACIFICO'!L30 -> 279.80508 | BJ12: ='RTA 5TA VTAS'!D126 -> 5902.2157 | BK12: =+AZ12+SUM(BA12:BJ12)+AR12 -> 12990.959 | BL12: =(+AO12-BK12) -> 7362.2665 | BM12: 0.09 | BN12: =AP12*BM12 -> 1831.7903 | BO12: 47.24 | BQ12: BBVA | BU12: =BL12/2 -> 3681.1332 | BV12: 4600 | BW12: BBVA
A13: ADM | B13: =+B12+1 -> 2 | C13: MARTINEZ CASTILLO GIOVANNA RAQUEL | D13: 9594953 | E13: 26364 | F13: 41548 | H13: JEFE DE ADMINISTRACION | I13: PROFUTURO | J13: 6500 | K13: 113 | L13: 30 | P13: =+L13-M13-O13 -> 30 | Q13: 8 | R13: =+P13*Q13 -> 240 | S13: =+J13-AD13-U13 -> 6500 | T13: =K13 -> 113 | U13: =(J13)/30*N13 -> 0 | X13: =H.E!L7 -> 0 | Y13: =H.E!M7 -> 0 | Z13: =H.E!N7 -> 0 | AA13: =100/19*17 -> 89.473684 | AD13: =(J13+K13)/30*O13 -> 0 | AO13: =SUM(S13:AM13)-AN13 -> 6702.4737 | AP13: =+AO13-AA13-AF13-AG13-AH13-AI13-AL13-AM13-AK13-BA13-BB13 -> 6613 | AS13: 0.1 | AT13: =+AP13*AS13 -> 661.3 | AU13: 0 | AV13: =+AP13*AU13 -> 0 | AW13: 0.0137 | AX13: =+AP13*AW13 -> 90.5981 | AY13: =+AS13+AU13+AW13 -> 0.1137 | AZ13: =+AT13+AV13+AX13 -> 751.8981 | BA13: =TARDANZA!K7 -> 0 | BB13: =TARDANZA!L7 -> 0 | BC13: 2700 | BF13: =+'SEGURO PACIFICO'!L31 -> 238.02119 | BJ13: ='RTA 5TA'!D118 -> 530.03032 | BK13: =+AZ13+SUM(BA13:BJ13)+AR13 -> 4219.9496 | BL13: =(+AO13-BK13) -> 2482.5241 | BM13: 0.09 | BN13: =AP13*BM13 -> 595.17 | BO13: 23.8407 | BQ13: BBVA | BU13: =BL13/2 -> 1241.262 | BV13: 2700 | BW13: BBVA
A14: SOPORTE | B14: =+B13+1 -> 3 | C14: SALVADOR ROJAS ELVIS ALFONSO | D14: 46335654 | E14: 33029 | F14: 42327 | H14: SUPERVISOR DE SOPORTE TECNICO Y MANTENIMINENTO | I14: INTEGRA | J14: 4000 | K14: 113 | L14: 30 | P14: =+L14-M14-O14 -> 30 | Q14: 8 | R14: =+P14*Q14 -> 240 | S14: =+J14-AD14-U14 -> 4000 | T14: =K14 -> 113 | U14: =(J14)/30*N14 -> 0 | X14: =H.E!L8 -> 0 | Y14: =H.E!M8 -> 0 | Z14: =H.E!N8 -> 0 | AA14: =100/19*17 -> 89.473684 | AD14: =(J14+K14)/30*O14 -> 0 | AO14: =SUM(S14:AM14)-AN14 -> 4202.4737 | AP14: =+AO14-AA14-AF14-AG14-AH14-AI14-AL14-AM14-AK14-BA14-BB14 -> 4030.74 | AS14: 0.1 | AT14: =+AP14*AS14 -> 403.074 | AU14: 0.0155 | AV14: =+AP14*AU14 -> 62.47647 | AW14: 0.0137 | AX14: =+AP14*AW14 -> 55.221138 | AY14: =+AS14+AU14+AW14 -> 0.1292 | AZ14: =+AT14+AV14+AX14 -> 520.77161 | BA14: =TARDANZA!K8 -> 0 | BB14: =TARDANZA!L8 -> 82.26 | BC14: 1720 | BJ14: ='RTA 5TA'!H118 -> 160.75494 | BK14: =+AZ14+SUM(BA14:BJ14)+AR14 -> 2483.7866 | BL14: =(+AO14-BK14) -> 1718.6871 | BM14: 0.09 | BN14: =AP14*BM14 -> 362.7666 | BO14: 6.17 | BQ14: BCP | BU14: =BL14/2 -> 859.34357 | BV14: 1720 | BW14: BCP
A15: SOPORTE | B15: =+B14+1 -> 4 | C15: LOLI RODRIGUEZ JANIO RICHARD | D15: 41675364 | E15: 29556 | F15: 42513 | H15: COORDINADOR DE SOPORTE TECNICO | I15: PRIMA | J15: 4000 | K15: 113 | L15: 30 | O15: 1 | P15: =+L15-M15-O15 -> 29 | Q15: 8 | R15: =+P15*Q15 -> 232 | S15: =+J15-AD15-U15 -> 3862.9 | T15: =K15 -> 113 | U15: =(J15)/30*N15 -> 0 | X15: =H.E!L9 -> 0 | Y15: =H.E!M9 -> 0 | Z15: =H.E!N9 -> 0 | AA15: =100/19*17 -> 89.473684 | AD15: =(J15+K15)/30*O15 -> 137.1 | AO15: =SUM(S15:AM15)-AN15 -> 4202.4737 | AP15: =+AO15-AA15-AF15-AG15-AH15-AI15-AL15-AM15-AK15-BA15-BB15 -> 4113 | AS15: 0.1 | AT15: =+AP15*AS15 -> 411.3 | AU15: 0.016 | AV15: =+AP15*AU15 -> 65.808 | AW15: 0.0137 | AX15: =+AP15*AW15 -> 56.3481 | AY15: =+AS15+AU15+AW15 -> 0.1297 | AZ15: =+AT15+AV15+AX15 -> 533.4561 | BA15: =TARDANZA!K9 -> 0 | BB15: =TARDANZA!L9 -> 0 | BC15: 1730 | BJ15: ='RTA 5TA'!E118 -> 140.09305 | BK15: =+AZ15+SUM(BA15:BJ15)+AR15 -> 2403.5491 | BL15: =(+AO15-BK15) -> 1798.9245 | BM15: 0.09 | BN15: =AP15*BM15 -> 370.17 | BO15: 16.0407 | BQ15: BCP | BU15: =BL15/2 -> 899.46227 | BV15: 1730 | BW15: BCP
A16: LOGISTICA | B16: =+B15+1 -> 5 | C16: PEREZ CAJAHUANCA ARACELLI IRAIDA | D16: 44425022 | E16: 31996 | F16: 42917 | H16: COORDINADOR DE LOGISTICA | I16: INTEGRA | J16: 3600 | L16: 30 | P16: =+L16-M16-O16 -> 30 | Q16: 8 | R16: =+P16*Q16 -> 240 | S16: =+J16-AD16-U16 -> 3600 | T16: =K16 -> 0 | U16: =(J16)/30*N16 -> 0 | X16: =H.E!L10 -> 0 | Y16: =H.E!M10 -> 0 | Z16: =H.E!N10 -> 0 | AA16: =100/19*17 -> 89.473684 | AD16: =(J16+K16)/30*O16 -> 0 | AJ16: 640 | AO16: =SUM(S16:AM16)-AN16 -> 4329.4737 | AP16: =+AO16-AA16-AF16-AG16-AH16-AI16-AL16-AM16-AK16-BA16-BB16 -> 4159 | AS16: 0.1 | AT16: =+AP16*AS16 -> 415.9 | AU16: 0.0155 | AV16: =+AP16*AU16 -> 64.4645 | AW16: 0.0137 | AX16: =+AP16*AW16 -> 56.9783 | AY16: =+AS16+AU16+AW16 -> 0.1292 | AZ16: =+AT16+AV16+AX16 -> 537.3428 | BA16: =TARDANZA!K10 -> 0 | BB16: =TARDANZA!L10 -> 81 | BC16: 1500 | BF16: =+'SEGURO PACIFICO'!L32 -> 148.94068 | BJ16: ='RTA 5TA'!F118 -> 149.81427 | BK16: =+AZ16+SUM(BA16:BJ16)+AR16 -> 2417.0977 | BL16: =(+AO16-BK16) -> 1912.3759 | BM16: 0.09 | BN16: =AP16*BM16 -> 374.31 | BO16: 13.104 | BQ16: BBVA | BU16: =BL16/2 -> 956.18797 | BV16: 1500 | BW16: BBVA
A17: MARKET | B17: =+B16+1 -> 6 | C17: PORTOCARRERO TAFUR GLORI MAGRI | D17: 43172155 | E17: 31249 | F17: 42948 | H17: JEFE DE MARKETING Y CALIDAD | I17: INTEGRA | J17: 6500 | K17: 113 | L17: 30 | P17: =+L17-M17-O17 -> 30 | Q17: 8 | R17: =+P17*Q17 -> 240 | S17: =+J17-AD17-U17 -> 6500 | T17: =K17 -> 113 | U17: =(J17)/30*N17 -> 0 | X17: =H.E!L11 -> 0 | Y17: =H.E!M11 -> 0 | Z17: =H.E!N11 -> 0 | AD17: =(J17+K17)/30*O17 -> 0 | AO17: =SUM(S17:AM17)-AN17 -> 6613 | AP17: =+AO17-AA17-AF17-AG17-AH17-AI17-AL17-AM17-AK17-BA17-BB17 -> 6613 | AS17: 0.1 | AT17: =+AP17*AS17 -> 661.3 | AU17: 0.0155 | AV17: =+AP17*AU17 -> 102.5015 | AW17: 0.0137 | AX17: =+AP17*AW17 -> 90.5981 | AY17: =+AS17+AU17+AW17 -> 0.1292 | AZ17: =+AT17+AV17+AX17 -> 854.3996 | BA17: =TARDANZA!K11 -> 0 | BB17: =TARDANZA!L11 -> 0 | BC17: 2400 | BF17: =+'SEGURO PACIFICO'!L33+405.39 -> 664.72898 | BJ17: ='RTA 5TA'!G118 -> 1341.4388 | BK17: =+AZ17+SUM(BA17:BJ17)+AR17 -> 5260.5674 | BL17: =(+AO17-BK17) -> 1352.4326 | BM17: 0.09 | BN17: =AP17*BM17 -> 595.17 | BO17: 23.8407 | BQ17: BBVA | BU17: =BL17/2 -> 676.2163 | BV17: 2400 | BW17: BBVA
A18: VTAS | B18: =+B17+1 -> 7 | C18: ECHEVARRIA SOTO JORGE LUIS | D18: 45538866 | E18: 32147 | F18: 42955 | H18: COORDINADOR COMERCIAL | I18: ONP | J18: 4500 | K18: 113 | L18: 30 | O18: 10 | P18: =+L18-M18-O18 -> 20 | Q18: 8 | R18: =+P18*Q18 -> 160 | S18: =+J18-AD18-U18 -> 2962.3333 | T18: =K18 -> 113 | U18: =(J18)/30*N18 -> 0 | V18: =+[1]Resumen!$D$22 -> 8688.2701 | W18: =(SUM(COMISIONES!E3:J3)/6/30)*'PLANILLA MENSUAL'!O18 -> 3203.8078 | X18: =H.E!L12 -> 0 | Y18: =H.E!M12 -> 0 | Z18: =H.E!N12 -> 0 | AD18: =(J18+K18)/30*O18 -> 1537.6667 | AO18: =SUM(S18:AM18)-AN18 -> 16505.078 | AP18: =+AO18-AA18-AF18-AG18-AH18-AI18-AL18-AM18-AK18-BA18-BB18 -> 16505.078 | AQ18: 0.13 | AR18: =+AP18*AQ18 -> 2145.6601 | BA18: =TARDANZA!K12 -> 0 | BB18: =TARDANZA!L12 -> 0 | BC18: 1200 | BG18: ='HT. EPS'!E41 -> 507.88292 | BJ18: ='RTA 5TA VTAS'!E126 -> 4309.9144 | BK18: =+AZ18+SUM(BA18:BJ18)+AR18 -> 8163.4575 | BL18: =(+AO18-BK18) -> 8341.6204 | BM18: 0.09 | BN18: =AP18*BM18 -> 1485.457 | BO18: 17.99 | BP18: EPS | BQ18: BBVA | BU18: =BL18/2 -> 4170.8102 | BV18: 1200 | BW18: BBVA
A19: VTAS | B19: =+B18+1 -> 8 | C19: MONTOYA MEDRANO ANDREA BELEN JOSEPHINE | D19: 71127068 | E19: 34500 | F19: 43045 | H19: ASISTENTE DE GERENCIA | I19: ONP | J19: 2800 | L19: 30 | M19: 1 | O19: 7 | P19: =+L19-M19-O19 -> 22 | Q19: 8 | R19: =+P19*Q19 -> 176 | S19: =+J19-AD19-U19 -> 2146.6667 | T19: =K19 -> 0 | U19: =(J19)/30*N19 -> 0 | X19: =H.E!L13 -> 0 | Y19: =H.E!M13 -> 0 | Z19: =H.E!N13 -> 0 | AD19: =(J19+K19)/30*O19 -> 653.33333 | AJ19: 800 | AO19: =SUM(S19:AM19)-AN19 -> 3600 | AP19: =+AO19-AA19-AF19-AG19-AH19-AI19-AL19-AM19-AK19-BA19-BB19 -> 3577.6389 | AQ19: 0.13 | AR19: =+AP19*AQ19 -> 465.09306 | BA19: =TARDANZA!K13 -> 0 | BB19: =TARDANZA!L13 -> 22.361111 | BC19: 1200 | BG19: ='HT. EPS'!E42 -> 53.645628 | BJ19: ='RTA 5TA'!M118 -> 44.698615 | BK19: =+AZ19+SUM(BA19:BJ19)+AR19 -> 1785.7984 | BL19: =(+AO19-BK19) -> 1814.2016 | BM19: 0.09 | BN19: =AP19*BM19 -> 321.9875 | BO19: 3.15 | BP19: EPS | BQ19: BCP | BU19: =BL19/2 -> 907.1008 | BV19: 1200 | BW19: BCP
A20: MARKET | B20: =+B19+1 -> 9 | C20: VERGARA BALDEON GEANNINA LIZBETH | D20: 46497553 | E20: 33124 | F20: 44018 | H20: ESPECIALISTA EN MARKETING | I20: INTEGRA | J20: 2600 | L20: 30 | P20: =+L20-M20-O20 -> 30 | Q20: 8 | R20: =+P20*Q20 -> 240 | S20: =+J20-AD20-U20 -> 2600 | T20: =K20 -> 0 | U20: =(J20)/30*N20 -> 0 | X20: =H.E!L14 -> 0 | Y20: =H.E!M14 -> 0 | Z20: =H.E!N14 -> 0 | AD20: =(J20+K20)/30*O20 -> 0 | AO20: =SUM(S20:AM20)-AN20 -> 2600 | AP20: =+AO20-AA20-AF20-AG20-AH20-AI20-AL20-AM20-AK20-BA20-BB20 -> 2586.2778 | AS20: 0.1 | AT20: =+AP20*AS20 -> 258.62778 | AU20: 0 | AV20: =+AP20*AU20 -> 0 | AW20: 0.0137 | AX20: =+AP20*AW20 -> 35.432006 | AY20: =+AS20+AU20+AW20 -> 0.1137 | AZ20: =+AT20+AV20+AX20 -> 294.05978 | BA20: =TARDANZA!K14 -> 0 | BB20: =TARDANZA!L14 -> 13.722222 | BC20: 1150 | BG20: ='HT. EPS'!E43 -> 53.645628 | BJ20: =+'RTA 5TA'!I118 -> 0 | BK20: =+AZ20+SUM(BA20:BJ20)+AR20 -> 1511.4276 | BL20: =(+AO20-BK20) -> 1088.5724 | BM20: 0.09 | BN20: =AP20*BM20 -> 232.765 | BO20: 3.75 | BP20: EPS | BQ20: BCP | BU20: =BL20/2 -> 544.28618 | BV20: 1150 | BW20: BCP
A21: ALMACEN | B21: =+B20+1 -> 10 | C21: CASTILLO ENCARNACION MANUEL LEONIDAS | D21: 44030334 | E21: 31334 | F21: 44321 | H21: REPARTO | I21: PRIMA | J21: 2200 | K21: 113 | L21: 30 | O21: 2 | P21: =+L21-M21-O21 -> 28 | Q21: 8 | R21: =+P21*Q21 -> 224 | S21: =+J21-AD21-U21 -> 2045.8 | T21: =K21 -> 113 | U21: =(J21)/30*N21 -> 0 | X21: =H.E!L15 -> 0 | Y21: =H.E!M15 -> 0 | Z21: =H.E!N15 -> 0 | AA21: =100/19*16 -> 84.210526 | AD21: =(J21+K21)/30*O21 -> 154.2 | AO21: =SUM(S21:AM21)-AN21 -> 2397.2105 | AP21: =+AO21-AA21-AF21-AG21-AH21-AI21-AL21-AM21-AK21-BA21-BB21 -> 2293.8856 | AS21: 0.1 | AT21: =+AP21*AS21 -> 229.38856 | AU21: 0.016 | AV21: =+AP21*AU21 -> 36.70217 | AW21: 0.0137 | AX21: =+AP21*AW21 -> 31.426233 | AY21: =+AS21+AU21+AW21 -> 0.1297 | AZ21: =+AT21+AV21+AX21 -> 297.51697 | BA21: =TARDANZA!K15 -> 0 | BB21: =TARDANZA!L15 -> 19.114375 | BC21: 1000 | BE21: 500 | BJ21: ='RTA 5TA'!U118 -> 9.7576 | BK21: =+AZ21+SUM(BA21:BJ21)+AR21 -> 1826.3889 | BL21: =(+AO21-BK21) -> 570.82159 | BM21: 0.09 | BN21: =AP21*BM21 -> 206.44971 | BO21: 8.2407 | BQ21: BBVA | BU21: =BL21/2 -> 285.41079 | BV21: 1000 | BW21: BBVA
A22: VTAS | B22: =+B21+1 -> 11 | C22: QUEVEDO SALAS LUIS ALBERTO | D22: 7882846 | E22: 26945 | F22: 44593 | H22: EJECUTIVO COMERCIAL | I22: PRIMA | J22: 3800 | K22: 113 | L22: 30 | P22: =+L22-M22-O22 -> 30 | Q22: 8 | R22: =+P22*Q22 -> 240 | S22: =+J22-AD22-U22 -> 3800 | T22: =K22 -> 113 | U22: =(J22)/30*N22 -> 0 | V22: =COMISIONES!K4 -> 4452.19 | X22: =H.E!L16 -> 0 | Y22: =H.E!M16 -> 0 | Z22: =H.E!N16 -> 0 | AD22: =(J22+K22)/30*O22 -> 0 | AO22: =SUM(S22:AM22)-AN22 -> 8365.19 | AP22: =+AO22-AA22-AF22-AG22-AH22-AI22-AL22-AM22-AK22-BA22-BB22 -> 8365.19 | AS22: 0.1 | AT22: =+AP22*AS22 -> 836.519 | AU22: 0 | AV22: =+AP22*AU22 -> 0 | AW22: 0.0137 | AX22: =+AP22*AW22 -> 114.6031 | AY22: =+AS22+AU22+AW22 -> 0.1137 | AZ22: =+AT22+AV22+AX22 -> 951.1221 | BA22: =TARDANZA!K16 -> 0 | BB22: =TARDANZA!L16 -> 0 | BC22: 1460 | BG22: ='HT. EPS'!E44 -> 53.645628 | BJ22: ='RTA 5TA VTAS'!F126 -> 986.822 | BK22: =+AZ22+SUM(BA22:BJ22)+AR22 -> 3451.5897 | BL22: =(+AO22-BK22) -> 4913.6003 | BM22: 0.09 | BN22: =AP22*BM22 -> 752.8671 | BO22: 14.09 | BP22: EPS | BQ22: INTERB | BR22: BCP | BU22: =BL22/2 -> 2456.8001 | BV22: 1460 | BW22: INTERB | BX22: 1460
A23: ADM | B23: =+B22+1 -> 12 | C23: PORTOCARRERO GOMEZ MARIA DEICY | D23: 42544684 | E23: 30874 | F23: 44697 | H23: LIMPIEZA | I23: PROFUTURO | J23: 1500 | K23: 113 | L23: 30 | O23: 15 | P23: =+L23-M23-O23 -> 15 | Q23: 8 | R23: =+P23*Q23 -> 120 | S23: =+J23-AD23-U23 -> 693.5 | T23: =K23 -> 113 | U23: =(J23)/30*N23 -> 0 | X23: =H.E!L17 -> 0 | Y23: =H.E!M17 -> 0 | Z23: =H.E!N17 -> 0 | AD23: =(J23+K23)/30*O23 -> 806.5 | AO23: =SUM(S23:AM23)-AN23 -> 1613 | AP23: =+AO23-AA23-AF23-AG23-AH23-AI23-AL23-AM23-AK23-BA23-BB23 -> 1613 | AS23: 0.1 | AT23: =+AP23*AS23 -> 161.3 | AU23: 0 | AV23: =+AP23*AU23 -> 0 | AW23: 0.0137 | AX23: =+AP23*AW23 -> 22.0981 | AY23: =+AS23+AU23+AW23 -> 0.1137 | AZ23: =+AT23+AV23+AX23 -> 183.3981 | BA23: =TARDANZA!K17 -> 0 | BB23: =TARDANZA!L17 -> 0 | BC23: 710 | BK23: =+AZ23+SUM(BA23:BJ23)+AR23 -> 893.3981 | BL23: =(+AO23-BK23) -> 719.6019 | BM23: 0.09 | BN23: =AP23*BM23 -> 145.17 | BO23: 5.1207 | BQ23: BCP | BU23: =BL23/2 -> 359.80095 | BV23: 710 | BW23: BCP
A24: CONTA | B24: =+B23+1 -> 13 | C24: LOBO QUISPE ELISA FIORELLA | D24: 43415173 | E24: 31370 | F24: 45005 | G24: 46265 | H24: ANALISTA CONTABLE | I24: INTEGRA | J24: 3000 | L24: 30 | P24: =+L24-M24-O24 -> 30 | Q24: 8 | R24: =+P24*Q24 -> 240 | S24: =+J24-AD24-U24 -> 3000 | T24: =K24 -> 0 | U24: =(J24)/30*N24 -> 0 | X24: =H.E!L18 -> 3109.38 | Y24: =H.E!M18 -> 715.5 | Z24: =H.E!N18 -> 0 | AA24: =100/19*16 -> 84.210526 | AD24: =(J24+K24)/30*O24 -> 0 | AO24: =SUM(S24:AM24)-AN24 -> 6909.0905 | AP24: =+AO24-AA24-AF24-AG24-AH24-AI24-AL24-AM24-AK24-BA24-BB24 -> 6752.7967 | AS24: 0.1 | AT24: =+AP24*AS24 -> 675.27967 | AU24: 0 | AV24: =+AP24*AU24 -> 0 | AW24: 0.0137 | AX24: =+AP24*AW24 -> 92.513314 | AY24: =+AS24+AU24+AW24 -> 0.1137 | AZ24: =+AT24+AV24+AX24 -> 767.79298 | BA24: =TARDANZA!K18 -> 0 | BB24: =TARDANZA!L18 -> 72.083333 | BC24: 1310 | BG24: ='HT. EPS'!E45 -> 53.645628 | BK24: =+AZ24+SUM(BA24:BJ24)+AR24 -> 2203.5219 | BL24: =(+AO24-BK24) -> 4705.5686 | BM24: 0.09 | BN24: =AP24*BM24 -> 607.7517 | BO24: 11.7 | BP24: EPS | BQ24: BBVA | BU24: =BL24/2 -> 2352.7843 | BV24: 1310 | BW24: BBVA
A25: PROYECTO | B25: =+B24+1 -> 14 | C25: RIOS HOLSEN JAIME JUNIOR | D25: 48335342 | E25: 34355 | F25: 45307 | H25: ANALISTA DE PROYECTOS | I25: HABITAT | J25: 3200 | L25: 30 | O25: 3 | P25: =+L25-M25-O25 -> 27 | Q25: 8 | R25: =+P25*Q25 -> 216 | S25: =+J25-AD25-U25 -> 2880 | T25: =K25 -> 0 | U25: =(J25)/30*N25 -> 0 | X25: =H.E!L19 -> 0 | Y25: =H.E!M19 -> 0 | Z25: =H.E!N19 -> 0 | AD25: =(J25+K25)/30*O25 -> 320 | AO25: =SUM(S25:AM25)-AN25 -> 3200 | AP25: =+AO25-AA25-AF25-AG25-AH25-AI25-AL25-AM25-AK25-BA25-BB25 -> 3162.6667 | AS25: 0.1 | AT25: =+AP25*AS25 -> 316.26667 | AU25: 0 | AW25: 0.0137 | AX25: =+AP25*AW25 -> 43.328533 | AY25: =+AS25+AU25+AW25 -> 0.1137 | AZ25: =+AT25+AV25+AX25 -> 359.5952 | BA25: =TARDANZA!K19 -> 0 | BB25: =TARDANZA!L19 -> 37.333333 | BC25: 1400 | BJ25: ='RTA 5TA'!K118 -> 50.065 | BK25: =+AZ25+SUM(BA25:BJ25)+AR25 -> 1846.9935 | BL25: =(+AO25-BK25) -> 1353.0065 | BM25: 0.09 | BN25: =AP25*BM25 -> 284.64 | BO25: 4.2 | BQ25: BCP | BU25: =BL25/2 -> 676.50323 | BV25: 1400 | BW25: BCP
A26: VTAS | B26: =+B25+1 -> 15 | C26: ESTRADA SANTOS JUAN MIGUEL | D26: 25849757 | E26: 45341 | F26: 45341 | H26: INGENIERIA COMERCIAL | I26: INTEGRA | J26: 2800 | K26: 113 | L26: 30 | P26: =+L26-M26-O26-N26 -> 30 | Q26: 8 | R26: =+P26*Q26 -> 240 | S26: =+J26 -> 2800 | T26: =K26 -> 113 | V26: =COMISIONES!K5 -> 1459.82 | X26: =H.E!L20 -> 0 | Y26: =H.E!M20 -> 0 | Z26: =H.E!N20 -> 0 | AD26: =(J26+K26)/30*O26 -> 0 | AE26: =VACACIONES!T6+VACACIONES!W6 -> 2370.2849 | AO26: =SUM(S26:AM26)-AN26 -> 6743.1048 | AP26: =+AO26-AA26-AF26-AG26-AH26-AI26-AL26-AM26-AK26-BA26-BB26 -> 6736.2269 | AS26: 0.1 | AT26: =+AP26*AS26 -> 673.62269 | AU26: 0.0155 | AV26: =+AP26*AU26 -> 104.41152 | AW26: 0.0137 | AX26: =+AP26*AW26 -> 92.286309 | AY26: =+AS26+AU26+AW26 -> 0.1292 | AZ26: =+AT26+AV26+AX26 -> 870.32052 | BA26: =TARDANZA!K20 -> 0 | BB26: =TARDANZA!L20 -> 6.8779167 | BC26: =1150+2064.04 -> 3214.04 | BE26: 350 | BG26: ='HT. EPS'!E46 -> 507.88292 | BJ26: ='RTA 5TA VTAS'!G126+'RTA 5TA VTAS'!G127 -> 649.05571 | BK26: =+AZ26+SUM(BA26:BJ26)+AR26 -> 5598.1771 | BL26: =(+AO26-BK26) -> 1144.9278 | BM26: 0.09 | BN26: =AP26*BM26 -> 606.26042 | BO26: 11.36 | BP26: EPS | BQ26: BCP | BR26: ='[2]PLANILLA MENSUAL'!$BS$26+1000 -> 1291.6844 | BS26: =+BR26+BL26 -> 2436.6122 | BU26: =BL26/2 -> 572.46389 | BV26: 1150 | BW26: BCP
A27: ADM | B27: =+B26+1 -> 16 | C27: PORTOCARRERO TAFUR MARIA LOIDI | D27: 45654429 | E27: 30383 | F27: 45398 | H27: AUXILIAR ADMINISTRATIVO | I27: ONP | J27: 1200 | L27: 30 | P27: =+L27-M27-O27 -> 30 | Q27: 8 | R27: =+P27*Q27 -> 240 | S27: =+J27-AD27-U27 -> 1200 | T27: =K27 -> 0 | U27: =(J27)/30*N27 -> 0 | X27: =H.E!L21 -> 0 | Y27: =H.E!M21 -> 0 | Z27: =H.E!N21 -> 0 | AD27: =(J27+K27)/30*O27 -> 0 | AO27: =SUM(S27:AM27)-AN27 -> 1200 | AP27: =+AO27-AA27-AF27-AG27-AH27-AI27-AL27-AM27-AK27-BA27-BB27 -> 1200 | AQ27: 0.13 | AR27: =+AP27*AQ27 -> 156 | BA27: =TARDANZA!K21 -> 0 | BB27: =TARDANZA!L21 -> 0 | BC27: 520 | BI27: =+[3]AGO.26!$C$14 -> 22.36 | BK27: =+AZ27+SUM(BA27:BJ27)+AR27 -> 698.36 | BL27: =(+AO27-BK27) -> 501.64 | BM27: 0.09 | BN27: =AP27*BM27 -> 108 | BO27: 4.4 | BQ27: BBVA | BU27: =BL27/2 -> 250.82 | BV27: 520 | BW27: BBVA
A28: PROYECTO | B28: =+B27+1 -> 17 | C28: ZEVALLOS DELGADO LUIS EDUARDO | D28: 74450353 | E28: 34560 | F28: 45418 | H28: INGENIERIO DE PROYECTOS | I28: INTEGRA | J28: 2800 | L28: 30 | P28: =+L28-M28-O28 -> 30 | Q28: 8 | R28: =+P28*Q28 -> 240 | S28: =+J28-AD28-U28 -> 2800 | T28: =K28 -> 0 | U28: =(J28)/30*N28 -> 0 | X28: =H.E!L22 -> 0 | Y28: =H.E!M22 -> 0 | Z28: =H.E!N22 -> 0 | AD28: =(J28+K28)/30*O28 -> 0 | AO28: =SUM(S28:AM28)-AN28 -> 2800 | AP28: =+AO28-AA28-AF28-AG28-AH28-AI28-AL28-AM28-AK28-BA28-BB28 -> 2792.0278 | AS28: 0.1 | AT28: =+AP28*AS28 -> 279.20278 | AU28: 0 | AV28: =+AP28*AU28 -> 0 | AW28: 0.0137 | AX28: =+AP28*AW28 -> 38.250781 | AY28: =+AS28+AU28+AW28 -> 0.1137 | AZ28: =+AT28+AV28+AX28 -> 317.45356 | BA28: =TARDANZA!K22 -> 0 | BB28: =TARDANZA!L22 -> 7.9722222 | BC28: 1240 | BE28: 350 | BJ28: ='RTA 5TA'!N118 -> 122.77299 | BK28: =+AZ28+SUM(BA28:BJ28)+AR28 -> 2038.1988 | BL28: =(+AO28-BK28) -> 761.80123 | BM28: 0.09 | BN28: =AP28*BM28 -> 251.2825 | BO28: 3.75 | BQ28: BCP | BU28: =BL28/2 -> 380.90061 | BV28: 1240 | BW28: BCP
A29: VTAS | B29: =+B28+1 -> 18 | C29: BALLLESTEROS DI SERI MARIA PAULA | D29: 09877161 | E29: 26434 | F29: 45474 | H29: ASISTENTE ADMINISTRATIVO | I29: PRIMA | J29: 2800 | L29: 30 | O29: 8 | P29: =+L29-M29-O29 -> 22 | Q29: 8 | R29: =+P29*Q29 -> 176 | S29: =+J29-AD29-U29 -> 2053.3333 | T29: =K29 -> 0 | U29: =(J29)/30*N29 -> 0 | X29: =H.E!L23 -> 0 | Y29: =H.E!M23 -> 0 | Z29: =H.E!N23 -> 0 | AD29: =(J29+K29)/30*O29 -> 746.66667 | AO29: =SUM(S29:AM29)-AN29 -> 2800 | AP29: =+AO29-AA29-AF29-AG29-AH29-AI29-AL29-AM29-AK29-BA29-BB29 -> 2791.4444 | AS29: 0.1 | AT29: =+AP29*AS29 -> 279.14444 | AU29: 0.016 | AV29: =+AP29*AU29 -> 44.663111 | AW29: 0.0137 | AX29: =+AP29*AW29 -> 38.242789 | AY29: =+AS29+AU29+AW29 -> 0.1297 | AZ29: =+AT29+AV29+AX29 -> 362.05034 | BA29: =TARDANZA!K23 -> 0 | BB29: =TARDANZA!L23 -> 8.5555556 | BC29: 1220 | BG29: ='HT. EPS'!E47 -> 53.645628 | BJ29: ='RTA 5TA'!O118 -> 100.91581 | BK29: =+AZ29+SUM(BA29:BJ29)+AR29 -> 1745.1673 | BL29: =(+AO29-BK29) -> 1054.8327 | BM29: 0.09 | BN29: =AP29*BM29 -> 251.23 | BO29: 9.75 | BP29: EPS | BQ29: BCP | BU29: =BL29/2 -> 527.41633 | BV29: 1220 | BW29: BCP
A30: SOPORTE | B30: =+B29+1 -> 19 | C30: OCAMPO ORTEGA JEAN PAUL | D30: 73231901 | E30: 34632 | F30: 45537 | H30: ASISTENTE DE SOPORTE TECNICO | I30: PRIMA | J30: 2500 | L30: 30 | O30: 4 | P30: =+L30-M30-O30 -> 26 | Q30: 8 | R30: =+P30*Q30 -> 208 | S30: =+J30-AD30-U30 -> 2166.6667 | T30: =K30 -> 0 | U30: =(J30)/30*N30 -> 0 | X30: =H.E!L24 -> 184.89583 | Y30: =H.E!M24 -> 123.04688 | Z30: =H.E!N24 -> 0 | AD30: =(J30+K30)/30*O30 -> 333.33333 | AO30: =SUM(S30:AM30)-AN30 -> 2807.9427 | AP30: =+AO30-AA30-AF30-AG30-AH30-AI30-AL30-AM30-AK30-BA30-BB30 -> 2788.6719 | AS30: 0.1 | AT30: =+AP30*AS30 -> 278.86719 | AU30: 0 | AV30: =+AP30*AU30 -> 0 | AW30: 0.0137 | AX30: =+AP30*AW30 -> 38.204805 | AY30: =+AS30+AU30+AW30 -> 0.1137 | AZ30: =+AT30+AV30+AX30 -> 317.07199 | BA30: =TARDANZA!K24 -> 0 | BB30: =TARDANZA!L24 -> 19.270833 | BC30: 1100 | BJ30: ='RTA 5TA'!S118 -> 47.532185 | BK30: =+AZ30+SUM(BA30:BJ30)+AR30 -> 1483.875 | BL30: =(+AO30-BK30) -> 1324.0677 | BM30: 0.09 | BN30: =AP30*BM30 -> 250.98047 | BO30: 3 | BQ30: BBVA | BU30: =BL30/2 -> 662.03385 | BV30: 1100 | BW30: BBVA
A31: SOPORTE | B31: =+B30+1 -> 20 | C31: OLIVOS SAAVEDRA LANDHERT ANDERSON | D31: 73885455 | E31: 35803 | F31: 45581 | H31: ASISTENTE DE SOPORTE TECNICO | I31: INTEGRA | J31: 2500 | L31: 30 | O31: 8 | P31: =+L31-M31-O31 -> 22 | Q31: 8 | R31: =+P31*Q31 -> 176 | S31: =+J31-AD31-U31 -> 1833.3333 | T31: =K31 -> 0 | U31: =(J31)/30*N31 -> 0 | X31: =H.E!L25 -> 112.84722 | Y31: =H.E!M25 -> 89.0625 | Z31: =H.E!N25 -> 166.66667 | AD31: =(J31+K31)/30*O31 -> 666.66667 | AO31: =SUM(S31:AM31)-AN31 -> 2868.5764 | AP31: =+AO31-AA31-AF31-AG31-AH31-AI31-AL31-AM31-AK31-BA31-BB31 -> 2866.8403 | AS31: 0.1 | AT31: =+AP31*AS31 -> 286.68403 | AU31: 0 | AV31: =+AP31*AU31 -> 0 | AW31: 0.0137 | AX31: =+AP31*AW31 -> 39.275712 | AY31: =+AS31+AU31+AW31 -> 0.1137 | AZ31: =+AT31+AV31+AX31 -> 325.95974 | BA31: =TARDANZA!K25 -> 0 | BB31: =TARDANZA!L25 -> 1.7361111 | BC31: 1100 | BJ31: ='RTA 5TA'!R118 -> 35.787375 | BK31: =+AZ31+SUM(BA31:BJ31)+AR31 -> 1463.4832 | BL31: =(+AO31-BK31) -> 1405.0932 | BM31: 0.09 | BN31: =AP31*BM31 -> 258.01562 | BO31: 3 | BQ31: BCP | BU31: =BL31/2 -> 702.54658 | BV31: 1100 | BW31: BCP
A32: ALMACEN | B32: =+B31+1 -> 21 | C32: YUPANQUI SAMANIEGO RENATO LUIS | D32: 73952223 | E32: 36779 | F32: 45627 | H32: ASISTENTE DE ALMACEN | I32: INTEGRA | J32: 2500 | L32: 30 | P32: =+L32-M32-O32 -> 30 | Q32: 8 | R32: =+P32*Q32 -> 240 | S32: =+J32-AD32-U32 -> 2500 | T32: =K32 -> 0 | U32: =(J32)/30*N32 -> 0 | X32: =H.E!L26 -> 0 | Y32: =H.E!M26 -> 0 | Z32: =H.E!N26 -> 0 | AD32: =(J32+K32)/30*O32 -> 0 | AO32: =SUM(S32:AM32)-AN32 -> 2500 | AP32: =+AO32-AA32-AF32-AG32-AH32-AI32-AL32-AM32-AK32-BA32-BB32 -> 2485.7639 | AS32: 0.1 | AT32: =+AP32*AS32 -> 248.57639 | AU32: 0 | AV32: =+AP32*AU32 -> 0 | AW32: 0.0137 | AX32: =+AP32*AW32 -> 34.054965 | AY32: =+AS32+AU32+AW32 -> 0.1137 | AZ32: =+AT32+AV32+AX32 -> 282.63135 | BA32: =TARDANZA!K26 -> 0 | BB32: =TARDANZA!L26 -> 14.236111 | BC32: 1100 | BJ32: ='RTA 5TA'!Q118 -> 35.232335 | BK32: =+AZ32+SUM(BA32:BJ32)+AR32 -> 1432.0998 | BL32: =(+AO32-BK32) -> 1067.9002 | BM32: 0.09 | BN32: =AP32*BM32 -> 223.71875 | BO32: 3.3 | BQ32: BCP | BU32: =BL32/2 -> 533.9501 | BV32: 1100 | BW32: BCP
A33: CONTA | B33: =+B32+1 -> 22 | C33: TUCTO PEREZ CESAR ANTONIO | D33: 46452115 | E33: 32383 | F33: 45658 | H33: ASISTENTE CONTABLE | I33: PRIMA | J33: 2800 | L33: 30 | P33: =+L33-M33-O33 -> 30 | Q33: 8 | R33: =+P33*Q33 -> 240 | S33: =+J33-AD33-U33 -> 2800 | T33: =K33 -> 0 | U33: =(J33)/30*N33 -> 0 | X33: =H.E!L27 -> 0 | Y33: =H.E!M27 -> 0 | Z33: =H.E!N27 -> 0 | AD33: =(J33+K33)/30*O33 -> 0 | AO33: =SUM(S33:AM33)-AN33 -> 2800 | AP33: =+AO33-AA33-AF33-AG33-AH33-AI33-AL33-AM33-AK33-BA33-BB33 -> 2800 | AS33: 0.1 | AT33: =+AP33*AS33 -> 280 | AU33: 0 | AV33: =+AP33*AU33 -> 0 | AW33: 0.0137 | AX33: =+AP33*AW33 -> 38.36 | AY33: =+AS33+AU33+AW33 -> 0.1137 | AZ33: =+AT33+AV33+AX33 -> 318.36 | BA33: =TARDANZA!K27 -> 0 | BB33: =TARDANZA!L27 -> 0 | BC33: 1240 | BG33: ='HT. EPS'!E48 -> 50.679526 | BJ33: ='RTA 5TA'!P118 -> 102.19036 | BK33: =+AZ33+SUM(BA33:BJ33)+AR33 -> 1711.2299 | BL33: =(+AO33-BK33) -> 1088.7701 | BM33: 0.09 | BN33: =AP33*BM33 -> 252 | BO33: 9.75 | BP33: EPS | BQ33: BCP | BU33: =BL33/2 -> 544.38506 | BV33: 1240 | BW33: BCP
A34: VTAS | B34: =+B33+1 -> 23 | C34: AREVALO VELA CESAR ANTONIO | D34: 71114663 | E34: 36860 | F34: 45658 | H34: EJECUTIVO COMERCIAL | I34: PRIMA | J34: 2500 | L34: 30 | O34: 7 | P34: =+L34-M34-O34 -> 23 | Q34: 8 | R34: =+P34*Q34 -> 184 | S34: =+J34-AD34-U34 -> 1916.6667 | T34: =K34 -> 0 | U34: =(J34)/30*N34 -> 0 | V34: =COMISIONES!K8 -> 1528.25 | W34: =(SUM(COMISIONES!E8:J8)/180)*'PLANILLA MENSUAL'!O34 -> 328.56524 | X34: =H.E!L28 -> 0 | Y34: =H.E!M28 -> 0 | Z34: =H.E!N28 -> 0 | AD34: =(J34+K34)/30*O34 -> 583.33333 | AO34: =SUM(S34:AM34)-AN34 -> 4356.8152 | AP34: =+AO34-AA34-AF34-AG34-AH34-AI34-AL34-AM34-AK34-BA34-BB34 -> 4346.3986 | AS34: 0.1 | AT34: =+AP34*AS34 -> 434.63986 | AU34: 0 | AV34: =+AP34*AU34 -> 0 | AW34: 0.0137 | AX34: =+AP34*AW34 -> 59.54566 | AY34: =+AS34+AU34+AW34 -> 0.1137 | AZ34: =+AT34+AV34+AX34 -> 494.18552 | BA34: =TARDANZA!K28 -> 0 | BB34: =TARDANZA!L28 -> 10.416667 | BC34: 1000 | BJ34: ='RTA 5TA VTAS'!I126 -> 185.12032 | BK34: =+AZ34+SUM(BA34:BJ34)+AR34 -> 1689.7225 | BL34: =(+AO34-BK34) -> 2667.0927 | BM34: 0.09 | BN34: =AP34*BM34 -> 391.17587 | BO34: 2.7 | BQ34: BCP | BU34: =BL34/2 -> 1333.5464 | BV34: 1000 | BW34: BCP
A35: VTAS | B35: =+B34+1 -> 24 | C35: SICCHA ARCE LUIS FRANCISCO | D35: 73735818 | E35: 36161 | F35: 45689 | H35: EJECUTIVO COMERCIAL | I35: INTEGRA | J35: 2500 | L35: 30 | O35: 7 | P35: =+L35-M35-O35 -> 23 | Q35: 8 | R35: =+P35*Q35 -> 184 | S35: =+J35-AD35-U35 -> 1916.6667 | T35: =K35 -> 0 | U35: =(J35)/30*N35 -> 0 | V35: =COMISIONES!K7 -> 1091.36 | W35: =(SUM(COMISIONES!E7:J7)/180)*'PLANILLA MENSUAL'!O35 -> 288.75348 | X35: =H.E!L29 -> 0 | Y35: =H.E!M29 -> 0 | Z35: =H.E!N29 -> 0 | AD35: =(J35+K35)/30*O35 -> 583.33333 | AO35: =SUM(S35:AM35)-AN35 -> 3880.1135 | AP35: =+AO35-AA35-AF35-AG35-AH35-AI35-AL35-AM35-AK35-BA35-BB35 -> 3880.1135 | AS35: 0.1 | AT35: =+AP35*AS35 -> 388.01135 | AU35: 0 | AV35: =+AP35*AU35 -> 0 | AW35: 0.0137 | AX35: =+AP35*AW35 -> 53.157555 | AY35: =+AS35+AU35+AW35 -> 0.1137 | AZ35: =+AT35+AV35+AX35 -> 441.1689 | BA35: =TARDANZA!K29 -> 0 | BB35: =TARDANZA!L29 -> 0 | BC35: 1050 | BJ35: ='RTA 5TA VTAS'!H126 -> 148.21148 | BK35: =+AZ35+SUM(BA35:BJ35)+AR35 -> 1639.3804 | BL35: =(+AO35-BK35) -> 2240.7331 | BM35: 0.09 | BN35: =AP35*BM35 -> 349.21021 | BO35: 3.75 | BQ35: BBVA | BU35: =BL35/2 -> 1120.3666 | BV35: 1050 | BW35: BBVA
A36: MARKET | B36: =+B35+1 -> 25 | C36: JIMENEZ PUYEN LUIS ANTONIO | D36: 6802763 | E36: 28259 | F36: 45698 | H36: ESPECIALISTA EN GESTION Y SST | I36: ONP | J36: 2800 | L36: 30 | O36: 2 | P36: =+L36-M36-O36 -> 28 | Q36: 8 | R36: =+P36*Q36 -> 224 | S36: =+J36-AD36-U36 -> 2613.3333 | T36: =K36 -> 0 | U36: =(J36)/30*N36 -> 0 | X36: =H.E!L30 -> 0 | Y36: =H.E!M30 -> 0 | Z36: =H.E!N30 -> 0 | AD36: =(J36+K36)/30*O36 -> 186.66667 | AO36: =SUM(S36:AM36)-AN36 -> 2800 | AP36: =+AO36-AA36-AF36-AG36-AH36-AI36-AL36-AM36-AK36-BA36-BB36 -> 2790.0833 | AQ36: 0.13 | AR36: =+AP36*AQ36 -> 362.71083 | BA36: =TARDANZA!K30 -> 0 | BB36: =TARDANZA!L30 -> 9.9166667 | BC36: 1200 | BJ36: ='RTA 5TA'!L118 -> 8.0266667 | BK36: =+AZ36+SUM(BA36:BJ36)+AR36 -> 1580.6542 | BL36: =(+AO36-BK36) -> 1219.3458 | BM36: 0.09 | BN36: =AP36*BM36 -> 251.1075 | BO36: 10.92 | BQ36: BCP | BU36: =BL36/2 -> 609.67292 | BV36: 1200 | BW36: BCP
A37: SOPORTE | B37: =+B36+1 -> 26 | C37: SILVA SANTISTEBAN RONAL JHUNIOR | D37: 48461873 | E37: 34304 | F37: 45719 | H37: ASISTENTE DE SOPORTE TECNICO | I37: INTEGRA | J37: 2000 | L37: 30 | O37: 7 | P37: =+L37-M37-O37 -> 23 | Q37: 8 | R37: =+P37*Q37 -> 184 | S37: =+J37-AD37-U37 -> 1533.3333 | T37: =K37 -> 0 | U37: =(J37)/30*N37 -> 0 | X37: =H.E!L31 -> 439.40972 | Y37: =H.E!M31 -> 237.9375 | Z37: =H.E!N31 -> 0 | AD37: =(J37+K37)/30*O37 -> 466.66667 | AO37: =SUM(S37:AM37)-AN37 -> 2677.3472 | AP37: =+AO37-AA37-AF37-AG37-AH37-AI37-AL37-AM37-AK37-BA37-BB37 -> 2672.4861 | AS37: 0.1 | AT37: =+AP37*AS37 -> 267.24861 | AU37: 0 | AV37: =+AP37*AU37 -> 0 | AW37: 0.0137 | AX37: =+AP37*AW37 -> 36.61306 | AY37: =+AS37+AU37+AW37 -> 0.1137 | AZ37: =+AT37+AV37+AX37 -> 303.86167 | BA37: =TARDANZA!K31 -> 0 | BB37: =TARDANZA!L31 -> 4.8611111 | BC37: 880 | BK37: =+AZ37+SUM(BA37:BJ37)+AR37 -> 1188.7228 | BL37: =(+AO37-BK37) -> 1488.6244 | BM37: 0.09 | BN37: =AP37*BM37 -> 240.52375 | BO37: 2.55 | BQ37: BCP | BU37: =BL37/2 -> 744.31222 | BV37: 880 | BW37: BCP
A38: LOGISTICA | B38: =+B37+1 -> 27 | C38: ELGUERA SOTO LUCERO ESTEFANIA | D38: 71932804 | E38: 35956 | F38: 45778 | H38: ASISTENTE LOGISTICA | I38: PRIMA | J38: 2200 | L38: 30 | M38: 1 | P38: =+L38-M38-O38 -> 29 | Q38: 8 | R38: =+P38*Q38 -> 232 | S38: =+J38-AD38-U38 -> 2200 | T38: =K38 -> 0 | U38: =(J38)/30*N38 -> 0 | X38: =H.E!L32 -> 0 | Y38: =H.E!M32 -> 0 | Z38: =H.E!N32 -> 0 | AD38: =(J38+K38)/30*O38 -> 0 | AO38: =SUM(S38:AM38)-AN38 -> 2200 | AP38: =+AO38-AA38-AF38-AG38-AH38-AI38-AL38-AM38-AK38-BA38-BB38 -> 2194.9583 | AS38: 0.1 | AT38: =+AP38*AS38 -> 219.49583 | AU38: 0 | AV38: =+AP38*AU38 -> 0 | AW38: 0.0137 | AX38: =+AP38*AW38 -> 30.070929 | AY38: =+AS38+AU38+AW38 -> 0.1137 | AZ38: =+AT38+AV38+AX38 -> 249.56676 | BA38: =TARDANZA!K32 -> 0 | BB38: =TARDANZA!L32 -> 5.0416667 | BC38: 970 | BG38: ='HT. EPS'!E49 -> 53.645628 | BK38: =+AZ38+SUM(BA38:BJ38)+AR38 -> 1278.2541 | BL38: =(+AO38-BK38) -> 921.74594 | BM38: 0.09 | BN38: =AP38*BM38 -> 197.54625 | BO38: 2.86 | BP38: EPS | BQ38: BCP | BU38: =BL38/2 -> 460.87297 | BV38: 970 | BW38: BCP
A39: VTAS | B39: =+B38+1 -> 28 | C39: ESTACIO CAYETANO FRANK BRIAN | D39: 72192314 | E39: 34152 | F39: 45778 | H39: EJECUTIVO COMERCIAL | I39: INTEGRA | J39: 2300 | L39: 30 | P39: =+L39-M39-O39 -> 30 | Q39: 8 | R39: =+P39*Q39 -> 240 | S39: =+J39-AD39-U39 -> 2300 | T39: =K39 -> 0 | U39: =(J39)/30*N39 -> 0 | V39: =COMISIONES!K9 -> 3375.75 | X39: =H.E!L33 -> 0 | Y39: =H.E!M33 -> 0 | Z39: =H.E!N33 -> 0 | AD39: =(J39+K39)/30*O39 -> 0 | AO39: =SUM(S39:AM39)-AN39 -> 5675.75 | AP39: =+AO39-AA39-AF39-AG39-AH39-AI39-AL39-AM39-AK39-BA39-BB39 -> 5673.6736 | AS39: 0.1 | AT39: =+AP39*AS39 -> 567.36736 | AU39: 0 | AV39: =+AP39*AU39 -> 0 | AW39: 0.0137 | AX39: =+AP39*AW39 -> 77.729328 | AY39: =+AS39+AU39+AW39 -> 0.1137 | AZ39: =+AT39+AV39+AX39 -> 645.09669 | BA39: =TARDANZA!K33 -> 0 | BB39: =TARDANZA!L33 -> 2.0763889 | BC39: 940 | BG39: ='HT. EPS'!E50 -> 53.645628 | BJ39: ='RTA 5TA VTAS'!J126 -> 405.80361 | BK39: =+AZ39+SUM(BA39:BJ39)+AR39 -> 2046.6223 | BL39: =(+AO39-BK39) -> 3629.1277 | BM39: 0.09 | BN39: =AP39*BM39 -> 510.63063 | BO39: 3 | BP39: EPS | BQ39: BCP | BU39: =BL39/2 -> 1814.5638 | BV39: 940 | BW39: BCP
A40: ALMACEN | B40: =+B39+1 -> 29 | C40: SALAZAR VELASQUEZ HECTOR ALEXANDER | D40: 41995632 | E40: 30308 | F40: 45782 | H40: CHOFER DE REPARTO | I40: ONP | J40: 2500 | K40: 113 | L40: 30 | P40: =+L40-M40-O40 -> 30 | Q40: 8 | R40: =+P40*Q40 -> 240 | S40: =+J40-AD40-U40 -> 2500 | T40: =K40 -> 113 | U40: =(J40)/30*N40 -> 0 | X40: =H.E!L34 -> 0 | Y40: =H.E!M34 -> 0 | Z40: =H.E!N34 -> 0 | AD40: =(J40+K40)/30*O40 -> 0 | AO40: =SUM(S40:AM40)-AN40 -> 2613 | AP40: =+AO40-AA40-AF40-AG40-AH40-AI40-AL40-AM40-AK40-BA40-BB40 -> 2587.9587 | AQ40: 0.13 | AR40: =+AP40*AQ40 -> 336.43464 | BA40: =TARDANZA!K34 -> 0 | BB40: =TARDANZA!L34 -> 25.04125 | BC40: 1130 | BJ40: ='RTA 5TA'!T118 -> 16.84944 | BK40: =+AZ40+SUM(BA40:BJ40)+AR40 -> 1508.3253 | BL40: =(+AO40-BK40) -> 1104.6747 | BM40: 0.09 | BN40: =AP40*BM40 -> 232.91629 | BO40: 8.24 | BQ40: BBVA | BU40: =BL40/2 -> 552.33734 | BV40: 1130 | BW40: BBVA
A41: VTAS | B41: =+B40+1 -> 30 | C41: RICRA DAVALOS GIUSSEPPE RENATO | D41: 70608078 | E41: 36556 | F41: 45789 | H41: ASISTENTE DE VENTAS | I41: INTEGRA | J41: 1800 | L41: 30 | P41: =+L41-M41-O41 -> 30 | Q41: 8 | R41: =+P41*Q41 -> 240 | S41: =+J41-AD41-U41 -> 1800 | T41: =K41 -> 0 | U41: =(J41)/30*N41 -> 0 | V41: =COMISIONES!K10 -> 1440.1 | X41: =H.E!L35 -> 0 | Y41: =H.E!M35 -> 0 | Z41: =H.E!N35 -> 0 | AD41: =(J41+K41)/30*O41 -> 0 | AO41: =SUM(S41:AM41)-AN41 -> 3240.1 | AP41: =+AO41-AA41-AF41-AG41-AH41-AI41-AL41-AM41-AK41-BA41-BB41 -> 3211.6 | AS41: 0.1 | AT41: =+AP41*AS41 -> 321.16 | AU41: 0 | AV41: =+AP41*AU41 -> 0 | AW41: 0.0137 | AX41: =+AP41*AW41 -> 43.99892 | AY41: =+AS41+AU41+AW41 -> 0.1137 | AZ41: =+AT41+AV41+AX41 -> 365.15892 | BA41: =TARDANZA!K35 -> 0 | BB41: =TARDANZA!L35 -> 28.5 | BC41: 790 | BK41: =+AZ41+SUM(BA41:BJ41)+AR41 -> 1183.6589 | BL41: =(+AO41-BK41) -> 2056.4411 | BM41: 0.09 | BN41: =AP41*BM41 -> 289.044 | BO41: 2.25 | BQ41: BBVA | BU41: =BL41/2 -> 1028.2205 | BV41: 790 | BW41: BBVA | EL41: =4000+113 -> 4113 | EN41: =4000/30 -> 133.33333
A42: ALMACEN | B42: =+B41+1 -> 31 | C42: DIAZ ESCALANTE LUIS MIGUEL DAVID | D42: 45469176 | E42: 32412 | F42: 45796 | H42: CHOFER DE REPARTO | I42: PRIMA | J42: 1700 | K42: 113 | L42: 30 | O42: 2 | P42: =+L42-M42-O42 -> 28 | Q42: 8 | R42: =+P42*Q42 -> 224 | S42: =+J42-AD42-U42 -> 1579.1333 | T42: =K42 -> 113 | U42: =(J42)/30*N42 -> 0 | X42: =H.E!L36 -> 0 | Y42: =H.E!M36 -> 0 | Z42: =H.E!N36 -> 0 | AD42: =(J42+K42)/30*O42 -> 120.86667 | AO42: =SUM(S42:AM42)-AN42 -> 1813 | AP42: =+AO42-AA42-AF42-AG42-AH42-AI42-AL42-AM42-AK42-BA42-BB42 -> 1746.5129 | AS42: 0.1 | AT42: =+AP42*AS42 -> 174.65129 | AU42: 0 | AV42: =+AP42*AU42 -> 0 | AW42: 0.0137 | AX42: =+AP42*AW42 -> 23.927227 | AY42: =+AS42+AU42+AW42 -> 0.1137 | AZ42: =+AT42+AV42+AX42 -> 198.57852 | BA42: =TARDANZA!K36 -> 56.666667 | BB42: =TARDANZA!L36 -> 9.8204167 | BC42: 800 | BK42: =+AZ42+SUM(BA42:BJ42)+AR42 -> 1065.0656 | BL42: =(+AO42-BK42) -> 747.9344 | BM42: 0.09 | BN42: =AP42*BM42 -> 157.18616 | BO42: 7.07 | BQ42: BBVA | BU42: =BL42/2 -> 373.9672 | BV42: 800 | BW42: BBVA | EL42: =EL41/30 -> 137.1
A43: SOPORTE | B43: =+B42+1 -> 32 | C43: HIPOLITO GUANILO ARNOLD JIMMY | D43: 75676708 | E43: 34883 | F43: 45946 | H43: AUXILIAR DE SOPORTE | I43: HABITAT | J43: 1500 | K43: 113 | L43: 30 | P43: =+L43-M43-O43 -> 30 | Q43: 8 | R43: =+P43*Q43 -> 240 | S43: =+J43-AD43-U43 -> 1500 | T43: =K43 -> 113 | U43: =(J43)/30*N43 -> 0 | X43: =H.E!L37 -> 332.40122 | Y43: =H.E!M37 -> 172.08694 | Z43: =H.E!N37 -> 0 | AD43: =(J43+K43)/30*O43 -> 0 | AO43: =SUM(S43:AM43)-AN43 -> 2117.4882 | AP43: =+AO43-AA43-AF43-AG43-AH43-AI43-AL43-AM43-AK43-BA43-BB43 -> 2116.256 | AS43: 0.1 | AT43: =+AP43*AS43 -> 211.6256 | AU43: 0 | AV43: =+AP43*AU43 -> 0 | AW43: 0.0137 | AX43: =+AP43*AW43 -> 28.992707 | AY43: =+AS43+AU43+AW43 -> 0.1137 | AZ43: =+AT43+AV43+AX43 -> 240.61831 | BA43: =TARDANZA!K37 -> 0 | BB43: =TARDANZA!L37 -> 1.2321528 | BC43: 720 | BK43: =+AZ43+SUM(BA43:BJ43)+AR43 -> 961.85046 | BL43: =(+AO43-BK43) -> 1155.6377 | BM43: 0.09 | BN43: =AP43*BM43 -> 190.46304 | BO43: 2.27 | BQ43: BCP | BU43: =BL43/2 -> 577.81885 | BV43: 720 | BW43: BCP
A44: VTAS | B44: =+B43+1 -> 33 | C44: MONTOYA MEDRANO VIVIAN MICHELE ALEXANDRA | D44: 71127067 | E44: 35153 | F44: 46083 | H44: ASISTENTE DE VENTAS | I44: PRIMA | J44: 2000 | L44: 30 | P44: =+L44-M44-O44 -> 30 | Q44: 8 | R44: =+P44*Q44 -> 240 | S44: =+J44-AD44-U44 -> 2000 | T44: =K44 -> 0 | U44: =(J44)/30*N44 -> 0 | X44: =H.E!L38 -> 0 | Y44: =H.E!M38 -> 0 | Z44: =H.E!N38 -> 0 | AD44: =(J44+K44)/30*O44 -> 0 | AO44: =SUM(S44:AM44)-AN44 -> 2000 | AP44: =+AO44-AA44-AF44-AG44-AH44-AI44-AL44-AM44-AK44-BA44-BB44 -> 1988.0556 | AS44: 0.1 | AT44: =+AP44*AS44 -> 198.80556 | AU44: 0 | AV44: =+AP44*AU44 -> 0 | AW44: 0.0137 | AX44: =+AP44*AW44 -> 27.236361 | AY44: =+AS44+AU44+AW44 -> 0.1137 | AZ44: =+AT44+AV44+AX44 -> 226.04192 | BA44: =TARDANZA!K38 -> 0 | BB44: =TARDANZA!L38 -> 11.944444 | BC44: 880 | BK44: =+AZ44+SUM(BA44:BJ44)+AR44 -> 1117.9864 | BL44: =(+AO44-BK44) -> 882.01364 | BM44: 0.09 | BN44: =AP44*BM44 -> 178.925 | BO44: 3 | BQ44: BBVA | BU44: =BL44/2 -> 441.00682 | BV44: 880 | BW44: BBVA
A45: PROYECTO | B45: =+B44+1 -> 34 | C45: ALARCON OLIVERA AMBAR TIFFANY | D45: 74217394 | E45: 34877 | F45: 46160 | H45: ASISTENTE DE PROYECTOS | I45: PROFUTURO | J45: 2850 | L45: 30 | P45: =+L45-M45-O45 -> 30 | Q45: 8 | R45: =+P45*Q45 -> 240 | S45: =+J45-AD45-U45 -> 2850 | T45: =K45 -> 0 | U45: =(J45)/30*N45 -> 0 | X45: =H.E!L39 -> 0 | Y45: =H.E!M39 -> 0 | Z45: =H.E!N39 -> 0 | AD45: =(J45+K45)/30*O45 -> 0 | AO45: =SUM(S45:AM45)-AN45 -> 2850 | AP45: =+AO45-AA45-AF45-AG45-AH45-AI45-AL45-AM45-AK45-BA45-BB45 -> 2782.7083 | AS45: 0.1 | AT45: =+AP45*AS45 -> 278.27083 | AU45: 0 | AV45: =+AP45*AU45 -> 0 | AW45: 0.0137 | AX45: =+AP45*AW45 -> 38.123104 | AY45: =+AS45+AU45+AW45 -> 0.1137 | AZ45: =+AT45+AV45+AX45 -> 316.39394 | BA45: =TARDANZA!K39 -> 0 | BB45: =TARDANZA!L39 -> 67.291667 | BC45: 1230 | BK45: =+AZ45+SUM(BA45:BJ45)+AR45 -> 1613.6856 | BL45: =(+AO45-BK45) -> 1236.3144 | BM45: 0.09 | BN45: =AP45*BM45 -> 250.44375 | BO45: 4.81 | BQ45: BBVA | BU45: =BL45/2 -> 618.1572 | BV45: 1230 | BW45: BBVA
A46: SOPORTE | B46: =+B45+1 -> 35 | C46: BURGA MUÑOZ HELDER ALEXANDER | D46: 72326112 | E46: 35254 | F46: 46181 | H46: ASISTENTE DE SOPORTE TECNICO | I46: INTEGRA | J46: 1700 | L46: 30 | P46: =+L46-M46-O46 -> 30 | Q46: 8 | R46: =+P46*Q46 -> 240 | S46: =+J46-AD46-U46 -> 1700 | T46: =K46 -> 0 | U46: =(J46)/30*N46 -> 0 | X46: =H.E!L40 -> 265.625 | Y46: =H.E!M40 -> 175.63125 | Z46: =H.E!N40 -> 0 | AD46: =(J46+K46)/30*O46 -> 0 | AO46: =SUM(S46:AM46)-AN46 -> 2141.2562 | AP46: =+AO46-AA46-AF46-AG46-AH46-AI46-AL46-AM46-AK46-BA46-BB46 -> 2139.9576 | AS46: 0.1 | AT46: =+AP46*AS46 -> 213.99576 | AU46: 0 | AV46: =+AP46*AU46 -> 0 | AW46: 0.0137 | AX46: =+AP46*AW46 -> 29.31742 | AY46: =+AS46+AU46+AW46 -> 0.1137 | AZ46: =+AT46+AV46+AX46 -> 243.31318 | BA46: =TARDANZA!K40 -> 0 | BB46: =TARDANZA!L40 -> 1.2986111 | BC46: 750 | BK46: =+AZ46+SUM(BA46:BJ46)+AR46 -> 994.61179 | BL46: =(+AO46-BK46) -> 1146.6445 | BM46: 0.09 | BN46: =AP46*BM46 -> 192.59619 | BO46: 2.55 | BQ46: BBVA | BU46: =BL46/2 -> 573.32223 | BV46: 750 | BW46: BBVA
A47: SOPORTE | B47: =+B46+1 -> 36 | C47: RIVERA CORRALES JUAN EDUARDO | D47: 72705177 | E47: 36894 | F47: 46188 | H47: ASISTENTE DE SOPORTE TECNICO | I47: INTEGRA | J47: 2800 | L47: 30 | P47: =+L47-M47-O47 -> 30 | Q47: 8 | R47: =+P47*Q47 -> 240 | S47: =+J47-AD47-U47 -> 2800 | T47: =K47 -> 0 | U47: =(J47)/30*N47 -> 0 | X47: =H.E!L41 -> 0 | Y47: =H.E!M41 -> 0 | Z47: =H.E!N41 -> 0 | AD47: =(J47+K47)/30*O47 -> 0 | AO47: =SUM(S47:AM47)-AN47 -> 2800 | AP47: =+AO47-AA47-AF47-AG47-AH47-AI47-AL47-AM47-AK47-BA47-BB47 -> 2780.3611 | AS47: 0.1 | AT47: =+AP47*AS47 -> 278.03611 | AU47: 0 | AV47: =+AP47*AU47 -> 0 | AW47: 0.0137 | AX47: =+AP47*AW47 -> 38.090947 | AY47: =+AS47+AU47+AW47 -> 0.1137 | AZ47: =+AT47+AV47+AX47 -> 316.12706 | BA47: =TARDANZA!K41 -> 0 | BB47: =TARDANZA!L41 -> 19.638889 | BC47: 1240 | BK47: =+AZ47+SUM(BA47:BJ47)+AR47 -> 1575.7659 | BL47: =(+AO47-BK47) -> 1224.2341 | BM47: 0.09 | BN47: =AP47*BM47 -> 250.2325 | BO47: 4.2 | BQ47: BBVA | BU47: =BL47/2 -> 612.11703 | BV47: 1240 | BW47: BBVA
A48: SOPORTE | B48: =+B47+1 -> 37 | C48: MELO HUAMAN CARLOS MANUEL | D48: 72368094 | E48: 37634 | F48: 46188 | H48: AUXILIAR DE SOPORTE TECNICO | I48: PROFUTURO | J48: 1400 | L48: 30 | P48: =+L48-M48-O48 -> 30 | Q48: 8 | R48: =+P48*Q48 -> 240 | S48: =+J48-AD48-U48 -> 1400 | T48: =K48 -> 0 | U48: =(J48)/30*N48 -> 0 | X48: =H.E!L42 -> 0 | Y48: =H.E!M42 -> 0 | Z48: =H.E!N42 -> 0 | AD48: =(J48+K48)/30*O48 -> 0 | AO48: =SUM(S48:AM48)-AN48 -> 1400 | AP48: =+AO48-AA48-AF48-AG48-AH48-AI48-AL48-AM48-AK48-BA48-BB48 -> 1397.2778 | AS48: 0.1 | AT48: =+AP48*AS48 -> 139.72778 | AU48: 0 | AV48: =+AP48*AU48 -> 0 | AW48: 0.0137 | AX48: =+AP48*AW48 -> 19.142706 | AY48: =+AS48+AU48+AW48 -> 0.1137 | AZ48: =+AT48+AV48+AX48 -> 158.87048 | BA48: =TARDANZA!K42 -> 0 | BB48: =TARDANZA!L42 -> 2.7222222 | BC48: 620 | BK48: =+AZ48+SUM(BA48:BJ48)+AR48 -> 781.59271 | BL48: =(+AO48-BK48) -> 618.40729 | BM48: 0.09 | BN48: =AP48*BM48 -> 125.755 | BO48: 2.1 | BQ48: BBVA | BU48: =BL48/2 -> 309.20365 | BV48: 620 | BW48: BBVA
A49: RR.HH | B49: =+B48+1 -> 38 | C49: FARFAN LAUREL CIELO CARMIN | D49: 70351677 | E49: 35876 | F49: 46188 | H49: ASISTENTE DE RR.HH | I49: INTEGRA | J49: 2000 | L49: 30 | P49: =+L49-M49-O49 -> 30 | Q49: 8 | R49: =+P49*Q49 -> 240 | S49: =+J49-AD49-U49 -> 2000 | T49: =K49 -> 0 | U49: =(J49)/30*N49 -> 0 | X49: =H.E!L43 -> 0 | Y49: =H.E!M43 -> 0 | Z49: =H.E!N43 -> 0 | AD49: =(J49+K49)/30*O49 -> 0 | AO49: =SUM(S49:AM49)-AN49 -> 2000 | AP49: =+AO49-AA49-AF49-AG49-AH49-AI49-AL49-AM49-AK49-BA49-BB49 -> 1925.5556 | AS49: 0.1 | AT49: =+AP49*AS49 -> 192.55556 | AU49: 0 | AV49: =+AP49*AU49 -> 0 | AW49: 0.0137 | AX49: =+AP49*AW49 -> 26.380111 | AY49: =+AS49+AU49+AW49 -> 0.1137 | AZ49: =+AT49+AV49+AX49 -> 218.93567 | BA49: =TARDANZA!K43 -> 66.666667 | BB49: =TARDANZA!L43 -> 7.7777778 | BC49: 880 | BK49: =+AZ49+SUM(BA49:BJ49)+AR49 -> 1173.3801 | BL49: =(+AO49-BK49) -> 826.61989 | BM49: 0.09 | BN49: =AP49*BM49 -> 173.3 | BO49: 3 | BQ49: BCP | BU49: =BL49/2 -> 413.30994 | BV49: 880 | BW49: BCP
A50: ALMACEN | B50: =+B49+1 -> 39 | C50: ORTIZ PAREDES CESAR PAUL | D50: 71473884 | E50: 35473 | F50: 46195 | H50: AUXILIAR DE ALMACEN | I50: PRIMA | J50: 1200 | K50: 113 | L50: 30 | P50: =+L50-M50-O50 -> 30 | Q50: 8 | R50: =+P50*Q50 -> 240 | S50: =+J50-AD50-U50 -> 1200 | T50: =K50 -> 113 | U50: =(J50)/30*N50 -> 0 | X50: =H.E!L44 -> 0 | Y50: =H.E!M44 -> 0 | Z50: =H.E!N44 -> 0 | AD50: =(J50+K50)/30*O50 -> 0 | AO50: =SUM(S50:AM50)-AN50 -> 1313 | AP50: =+AO50-AA50-AF50-AG50-AH50-AI50-AL50-AM50-AK50-BA50-BB50 -> 1310.5381 | AS50: 0.1 | AT50: =+AP50*AS50 -> 131.05381 | AU50: 0 | AV50: =+AP50*AU50 -> 0 | AW50: 0.0137 | AX50: =+AP50*AW50 -> 17.954372 | AY50: =+AS50+AU50+AW50 -> 0.1137 | AZ50: =+AT50+AV50+AX50 -> 149.00818 | BA50: =TARDANZA!K44 -> 0 | BB50: =TARDANZA!L44 -> 2.461875 | BC50: 580 | BK50: =+AZ50+SUM(BA50:BJ50)+AR50 -> 731.47006 | BL50: =(+AO50-BK50) -> 581.52994 | BM50: 0.09 | BN50: =AP50*BM50 -> 117.94843 | BO50: 1.8 | BQ50: BBVA | BU50: =BL50/2 -> 290.76497 | BV50: 580 | BW50: BBVA
A51: VTAS | B51: =+B50+1 -> 40 | C51: PAREDES CHAMOCHUMBI ANA GABRIEL | D51: 41782489 | E51: 30375 | F51: 46204 | H51: EJECUTIVO COMERCIAL | I51: INTEGRA | J51: 2000 | L51: 30 | P51: =+L51-M51-O51 -> 30 | Q51: 8 | R51: =+P51*Q51 -> 240 | S51: =+J51-AD51-U51 -> 2000 | U51: =(J51)/30*N51 -> 0 | V51: =COMISIONES!K11 -> 323.01 | X51: =H.E!L45 -> 0 | Y51: =H.E!M45 -> 0 | Z51: =H.E!N45 -> 0 | AD51: =(J51+K51)/30*O51 -> 0 | AO51: =SUM(S51:AM51)-AN51 -> 2323.01 | AP51: =+AO51-AA51-AF51-AG51-AH51-AI51-AL51-AM51-AK51-BA51-BB51 -> 2321.3433 | AS51: 0.1 | AT51: =+AP51*AS51 -> 232.13433 | AU51: 0.0155 | AV51: =+AP51*AU51 -> 35.980822 | AW51: 0.0137 | AX51: =+AP51*AW51 -> 31.802404 | AY51: =+AS51+AU51+AW51 -> 0.1292 | AZ51: =+AT51+AV51+AX51 -> 299.91756 | BA51: =TARDANZA!K45 -> 0 | BB51: =TARDANZA!L45 -> 1.6666667 | BC51: 870 | BK51: =+AZ51+SUM(BA51:BJ51)+AR51 -> 1171.5842 | BL51: =(+AO51-BK51) -> 1151.4258 | BM51: 0.09 | BN51: =AP51*BM51 -> 208.9209 | BO51: 7.8 | BQ51: BBVA | BU51: =BL51/2 -> 575.71289 | BV51: 870 | BW51: BBVA
A52: CONTA | B52: =+B51+1 -> 41 | C52: ARAGON LOPEZ EDUARDO ALEJANDRO | D52: 71325082 | E52: 34608 | F52: 46245 | H52: ASISTENTE CONTABLE | I52: PRIMA | J52: 2500 | K52: 113 | L52: =31-11+1 -> 21 | P52: =+L52-M52-O52 -> 21 | Q52: 8 | R52: =+P52*Q52 -> 168 | S52: =+J52/30*L52 -> 1750 | T52: 113 | U52: =(J52)/30*N52 -> 0 | X52: =H.E!L46 -> 0 | Y52: =H.E!M46 -> 0 | Z52: =H.E!N46 -> 0 | AD52: =(J52+K52)/30*O52 -> 0 | AO52: =SUM(S52:AM52)-AN52 -> 1863 | AP52: =+AO52-AA52-AF52-AG52-AH52-AI52-AL52-AM52-AK52-BA52-BB52 -> 1857.5563 | AS52: 0.1 | AT52: =+AP52*AS52 -> 185.75563 | AU52: 0 | AV52: =+AP52*AU52 -> 0 | AW52: 0.0137 | AX52: =+AP52*AW52 -> 25.448521 | AY52: =+AS52+AU52+AW52 -> 0.1137 | AZ52: =+AT52+AV52+AX52 -> 211.20415 | BA52: =TARDANZA!K46 -> 0 | BB52: =TARDANZA!L46 -> 5.44375 | BK52: =+AZ52+SUM(BA52:BJ52)+AR52 -> 216.6479 | BL52: =(+AO52-BK52) -> 1646.3521 | BM52: 0.09 | BN52: =AP52*BM52 -> 167.18006 | BO52: 3.75 | BQ52: BBVA
A53: ALMACEN | B53: =+B52+1 -> 42 | C53: PALOMINO DELGADO CESAR JAIRO | D53: 74862129 | E53: 36264 | F53: 46245 | H53: ASISTENTE DE ALMACEN | I53: INTEGRA | J53: 1600 | L53: =31-11+1 -> 21 | P53: =+L53-M53-O53 -> 21 | Q53: 8 | R53: =+P53*Q53 -> 168 | S53: =+J53/30*L53 -> 1120 | U53: =(J53)/30*N53 -> 0 | X53: =H.E!L47 -> 0 | Y53: =H.E!M47 -> 0 | Z53: =H.E!N47 -> 0 | AD53: =(J53+K53)/30*O53 -> 0 | AO53: =SUM(S53:AM53)-AN53 -> 1120 | AP53: =+AO53-AA53-AF53-AG53-AH53-AI53-AL53-AM53-AK53-BA53-BB53 -> 1065.8889 | AS53: 0.1 | AT53: =+AP53*AS53 -> 106.58889 | AU53: 0 | AV53: =+AP53*AU53 -> 0 | AW53: 0.0137 | AX53: =+AP53*AW53 -> 14.602678 | AY53: =+AS53+AU53+AW53 -> 0.1137 | AZ53: =+AT53+AV53+AX53 -> 121.19157 | BA53: =TARDANZA!K47 -> 53.333333 | BB53: =TARDANZA!L47 -> 0.77777778 | BK53: =+AZ53+SUM(BA53:BJ53)+AR53 -> 175.30268 | BL53: =(+AO53-BK53) -> 944.69732 | BM53: 0.09 | BN53: =1130*9% -> 101.7 | BO53: 2.4 | BQ53: BBVA
A54: CONTA | B54: 43 | C54: FRANCO LOPEZ EMERSON JOEL | D54: 72534235 | E54: 34441 | F54: 46251 | H54: ASISTENTE CONTABLE | I54: PRIMA | J54: 1800 | L54: =31-17+1 -> 15 | P54: =+L54-M54-O54 -> 15 | Q54: 8 | R54: =+P54*Q54 -> 120 | S54: =+J54/30*L54 -> 900 | U54: =(J54)/30*N54 -> 0 | X54: =H.E!L48 -> 0 | Y54: =H.E!M48 -> 0 | Z54: =H.E!N48 -> 0 | AD54: =(J54+K54)/30*O54 -> 0 | AO54: =SUM(S54:AM54)-AN54 -> 900 | AP54: =+AO54-AA54-AF54-AG54-AH54-AI54-AL54-AM54-AK54-BA54-BB54 -> 896.625 | AS54: 0.1 | AT54: =+AP54*AS54 -> 89.6625 | AU54: 0 | AV54: =+AP54*AU54 -> 0 | AW54: 0.0137 | AX54: =+AP54*AW54 -> 12.283762 | AY54: =+AS54+AU54+AW54 -> 0.1137 | AZ54: =+AT54+AV54+AX54 -> 101.94626 | BA54: =TARDANZA!K48 -> 0 | BB54: =TARDANZA!L48 -> 3.375 | BK54: =+AZ54+SUM(BA54:BJ54)+AR54 -> 105.32126 | BL54: =(+AO54-BK54) -> 794.67874 | BM54: 0.09 | BN54: =1130*9% -> 101.7 | BO54: 2.7 | BQ54: BCP | BR54: 19119202409072
A55: ALMACEN | B55: 44 | C55: GUZMAN LIVIA ALFREDO SANTIAGO | D55: 10882203 | E55: 28684 | F55: 46252 | H55: COORDINADOR DE ALMACÉN | I55: INTEGRA | J55: 3500 | K55: 113 | L55: =31-18+1 -> 14 | P55: =+L55-M55-O55 -> 14 | Q55: 8 | R55: =+P55*Q55 -> 112 | S55: =+J55/30*L55 -> 1633.3333 | T55: 113 | U55: =(J55)/30*N55 -> 0 | X55: =H.E!L49 -> 0 | Y55: =H.E!M49 -> 0 | Z55: =H.E!N49 -> 0 | AD55: =(J55+K55)/30*O55 -> 0 | AO55: =SUM(S55:AM55)-AN55 -> 1746.3333 | AP55: =+AO55-AA55-AF55-AG55-AH55-AI55-AL55-AM55-AK55-BA55-BB55 -> 1746.3333 | AS55: 0.1 | AT55: =+AP55*AS55 -> 174.63333 | AU55: 0 | AV55: =+AP55*AU55 -> 0 | AW55: 0.0137 | AX55: =+AP55*AW55 -> 23.924767 | AY55: =+AS55+AU55+AW55 -> 0.1137 | AZ55: =+AT55+AV55+AX55 -> 198.5581 | BA55: =TARDANZA!K49 -> 0 | BB55: =TARDANZA!L49 -> 0 | BK55: =+AZ55+SUM(BA55:BJ55)+AR55 -> 198.5581 | BL55: =(+AO55-BK55) -> 1547.7752 | BM55: 0.09 | BN55: =AP55*BM55 -> 157.17 | BO55: 13.65 | BQ55: BCP | BR55: 19119202411074
U56: =(J56)/30*N56 -> 0 | BK56: =+AZ56+SUM(BA56:BJ56)+AR56 -> 0 | BV56: 0
J57: =SUM(J12:J56) -> 128250 | K57: =SUM(K12:K56) -> 1808 | S57: =SUM(S12:S56) -> 116957 | T57: =SUM(T12:T56) -> 1808 | U57: =SUM(U12:U56) -> 0 | V57: =SUM(V12:V56) -> 29598.975 | W57: =SUM(W12:W56) -> 3821.1265 | X57: =SUM(X12:X56) -> 4444.559 | Y57: =SUM(Y12:Y56) -> 1513.2651 | Z57: =SUM(Z12:Z56) -> 166.66667 | ... AB57: =SUM(AB12:AB56) -> 0 | AD57: =SUM(AD12:AD56) -> 7296.3333 | AE57: =SUM(AE12:AE56) -> 2370.2849 | AF57: =SUM(AF12:AF56) -> 0 | AG57: =SUM(AG12:AG56) -> 0 | AH57: =SUM(AH12:AH56) -> 0 | AI57: =SUM(AI12:AI56) -> 0 | AJ57: =SUM(AJ12:AJ56) -> 1440 | AK57: =SUM(AK12:AK56) -> 0 | ... AP57: =SUM(AP12:AP56) -> 168631.72 | AR57: =SUM(AR12:AR56) -> 3465.8986 | AT57: =SUM(AT12:AT56) -> 14197.096 | AV57: =SUM(AV12:AV56) -> 517.00809 | AX57: =SUM(AX12:AX56) -> 1839.7782 | AZ57: =SUM(AZ12:AZ56) -> 16553.882 | BA57: =SUM(BA12:BA56) -> 176.66667 | BB57: =SUM(BB12:BB56) -> 607.82812 | BC57: =SUM(BC12:BC56) -> 51344.04 | BD57: =SUM(BD12:BD56) -> 0 | BE57: =SUM(BE12:BE56) -> 1200 | BF57: =SUM(BF12:BF56) -> 1331.4959 | BG57: =SUM(BG12:BG56) -> 1441.9648 | ... BL57: =SUM(BL12:BL56) -> 78315.287 | BN57: =SUM(BN12:BN56) -> 15203.628 | BO57: =SUM(BO12:BO56) -> 344.1575 | BV57: =SUM(BV12:BV56) -> 49280
V58: =+COMISIONES!J12 -> 31418.044 | W58: =VACACIONES!T13 -> 3298.1341 | AP58: =+AO57-AP57 -> 1310.8106 | BA58: 0 | BB58: 0 | BG58: ='HT. EPS'!E51 -> 1441.9648 | BJ58: =-'RTA 5TA'!X118 -> -15483.103 | BS58: RXH
C59: LL.BB.SS | BJ59: =+BJ58+BJ57 -> 0
BR60: MRK | BS60: Gabriela | BT60: 930 | BU60: =(2000/30*29)-BT60 -> 1003.3333 | BW60: BBVA | BX60: 001105790250627369
A61: CONTA | B61: =+B60+1 -> 1 | C61: LOBO QUISPE ELISA FIORELLA | D61: 43415173 | E61: 31370 | F61: 45005 | H61: ANALISTA CONTABLE | I61: INTEGRA | J61: 3000 | AB61: =[4]FIORELLA!$L$46 -> 1250 | AC61: =[4]FIORELLA!$L$52+[4]FIORELLA!$L$55 -> 2700 | AD61: =[4]FIORELLA!$L$48+[4]FIORELLA!$L$51 -> 3400 | AF61: 1166.6667 | AH61: 1000 | AI61: 90 | AK61: =[4]FIORELLA!$L$66 -> 270.40551 | AO61: =SUM(K61:AN61) -> 9877.0722 | AP61: =AB61+AD61 -> 4650 | AS61: 0.1 | AT61: =+AP61*AS61 -> 465 | AU61: 0 | AV61: =+AP61*AU61 -> 0 | AW61: 0.0137 | AX61: =+AP61*AW61 -> 63.705 | AY61: =+AS61+AU61+AW61 -> 0.1137 | AZ61: =+AT61+AV61+AX61 -> 528.705 | BK61: =+AZ61+SUM(BA61:BJ61)+AR61 -> 528.705 | BL61: =(+AO61-BK61) -> 9348.3672 | BM61: 0.09 | BN61: =AP61*BM61 -> 418.5 | BP61: EPS | BQ61: BBVA | BR61: MRK | BS61: Bryan | BT61: =1800/30*14 -> 840 | BU61: =(1800/30*29)-BT61 -> 900 | BW61: BBVA | BX61: 001105790234579494
BV63: =SUM(BU59:BU61) -> 1903.3333
S64: =SUBTOTAL(9,S60:S61) -> 0 | T64: =SUBTOTAL(9,T60:T61) -> 0 | U64: =SUBTOTAL(9,U60:U61) -> 0 | V64: =SUBTOTAL(9,V60:V61) -> 0 | W64: =SUBTOTAL(9,W60:W61) -> 0 | X64: =SUBTOTAL(9,X60:X61) -> 0 | Y64: =SUBTOTAL(9,Y60:Y61) -> 0 | Z64: =SUBTOTAL(9,Z60:Z61) -> 0 | AA64: =SUBTOTAL(9,AA61:AA63) -> 0 | AB64: =SUBTOTAL(9,AB61:AB63) -> 1250 | AC64: =SUM(AC60:AC63) -> 2700 | AD64: =SUM(AD60:AD63) -> 3400 | AE64: =SUM(AE60:AE63) -> 0 | AF64: =SUM(AF60:AF63) -> 1166.6667 | AG64: =SUM(AG60:AG63) -> 0 | AH64: =SUM(AH60:AH63) -> 1000 | AI64: =SUM(AI60:AI63) -> 90 | AJ64: =SUM(AJ60:AJ63) -> 0 | ... BQ64: =SUM(BQ60:BQ63) -> 0
S66: =+S64+S57 -> 116957 | T66: =+T64+T57 -> 1808 | U66: =+U64+U57 -> 0 | V66: =+V64+V57 -> 29598.975 | W66: =+W64+W57 -> 3821.1265 | X66: =+X57+X60 -> 4444.559 | Y66: =+Y57+Y60 -> 1513.2651 | Z66: =+Z57+Z60 -> 166.66667 | AA66: =+AA64+AA57 -> 526.31579 | AB66: =+AB64+AB57 -> 1250 | AC66: =+AC64+AC57 -> 2700 | AD66: =+AD64+AD57 -> 10696.333 | AE66: =+AE64+AE57 -> 2370.2849 | AF66: =+AF64+AF57 -> 1166.6667 | AG66: =+AG64+AG57 -> 0 | AH66: =+AH64+AH57 -> 1000 | ... BQ66: =+BQ64+BQ57 -> 0
C67: MODIFICACIONES EN PLANILLA SEGÚN PAGO | BG67: =+'HT. EPS'!E51 -> 1441.9648 | BJ67: =+'RTA 5TA'!X118 -> 15483.103
C68: INGRESO REAL DE ANA PAREDES
C69: ESSALUD EMERSON Y CESAR | P69: K0011 | Q69: ADM | S69: =+SUMIF($A$12:$A$47,"ADM",S$12:S$56) -> 8393.5 | T69: =+SUMIF($A$12:$A$47,"ADM",T$12:T$56) -> 226 | U69: =+SUMIF($A$12:$A$47,"ADM",U$12:U$56) -> 0 | V69: =+SUMIF($A$12:$A$47,"ADM",V$12:V$56) -> 0 | W69: =+SUMIF($A$12:$A$47,"ADM",W$12:W$56) -> 0 | X69: =+SUMIF($A$12:$A$47,"ADM",X$12:X$56) -> 0 | Y69: =+SUMIF($A$12:$A$47,"ADM",Y$12:Y$56) -> 0 | Z69: =+SUMIF($A$12:$A$47,"ADM",Z$12:Z$56) -> 0 | ... AB69: =+SUMIF($A$12:$A$47,"ADM",AB$12:AB$56) -> 0 | AD69: =+SUMIF($A$12:$A$47,"ADM",AD$12:AD$56) -> 806.5 | AF69: =+SUMIF($A$12:$A$47,"ADM",AF$12:AF$56) -> 0 | AG69: =+SUMIF($A$12:$A$47,"ADM",AG$12:AG$56) -> 0 | AH69: =+SUMIF($A$12:$A$47,"ADM",AH$12:AH$56) -> 0 | AI69: =+SUMIF($A$12:$A$47,"ADM",AI$12:AI$56) -> 0 | AJ69: =+SUMIF($A$12:$A$47,"ADM",AJ$12:AJ$56) -> 0 | AK69: =+SUMIF($A$12:$A$47,"ADM",AK$12:AK$56) -> 0 | AL69: =+SUMIF($A$12:$A$47,"ADM",AL$12:AL$56) -> 0 | AM69: =+SUMIF($A$12:$A$47,"ADM",AM$12:AM$56) -> 0 | ... AP69: =+SUMIF($A$12:$A$47,"ADM",AP$12:AP$56) -> 9426 | AR69: CONCEPTOS | AS69: O.N.P. | AT69: ESSALUD | AU69: APORTE | AV69: COMISION | AW69: PRIMA | AX69: I.RTA.5 | AY69: TOTALES | BI69: PAGOS FIN DE MES | BN69: =+SUMIF($A$12:$A$47,"ADM",BN$12:BN$56) -> 848.34 | BO69: =+SUMIF($A$12:$A$47,"ADM",BO$12:BO$56) -> 33.3614 | BU69: PAGOS 1RA QUINCENA MES
C70: VACACIONES OLIVOS | P70: K0012 | Q70: CONTA | S70: =+SUMIF($A$12:$A$47,"CONTA",S$12:S$56) -> 5800 | T70: =+SUMIF($A$12:$A$47,"CONTA",T$12:T$56) -> 0 | U70: =+SUMIF($A$12:$A$47,"CONTA",U$12:U$56) -> 0 | V70: =+SUMIF($A$12:$A$47,"CONTA",V$12:V$56) -> 0 | W70: =+SUMIF($A$12:$A$47,"CONTA",W$12:W$56) -> 0 | X70: =+SUMIF($A$12:$A$47,"CONTA",X$12:X$56) -> 3109.38 | Y70: =+SUMIF($A$12:$A$47,"CONTA",Y$12:Y$56) -> 715.5 | Z70: =+SUMIF($A$12:$A$47,"CONTA",Z$12:Z$56) -> 0 | ... AB70: =+SUMIF($A$12:$A$47,"CONTA",AB$12:AB$56) -> 0 | AD70: =+SUMIF($A$12:$A$47,"CONTA",AD$12:AD$56) -> 0 | AF70: =+SUMIF($A$12:$A$47,"CONTA",AF$12:AF$56) -> 0 | AG70: =+SUMIF($A$12:$A$47,"CONTA",AG$12:AG$56) -> 0 | AH70: =+SUMIF($A$12:$A$47,"CONTA",AH$12:AH$56) -> 0 | AI70: =+SUMIF($A$12:$A$47,"CONTA",AI$12:AI$56) -> 0 | AJ70: =+SUMIF($A$12:$A$47,"CONTA",AJ$12:AJ$56) -> 0 | AK70: =+SUMIF($A$12:$A$47,"CONTA",AK$12:AK$56) -> 0 | AL70: =+SUMIF($A$12:$A$47,"CONTA",AL$12:AL$56) -> 0 | AM70: =+SUMIF($A$12:$A$47,"CONTA",AM$12:AM$56) -> 0 | ... AP70: =+SUMIF($A$12:$A$47,"CONTA",AP$12:AP$56) -> 9552.7967 | AR70: O.N.P. | AS70: =+AR66 -> 3465.8986 | AY70: =SUM(AS70:AX70) -> 3465.8986 | BI70: BBVA | BJ70: =+SUMIF($BQ$12:$BQ$56,"BBVA",$BL$12:$BL$56) -> 44134.72 | BN70: =+SUMIF($A$12:$A$47,"CONTA",BN$12:BN$56) -> 859.7517 | BO70: =+SUMIF($A$12:$A$47,"CONTA",BO$12:BO$56) -> 21.45 | BU70: BBVA | BV70: =+SUMIF($BQ$12:$BQ$56,"BBVA",$BV$12:$BV$56) -> 26270
P71: K0013 | Q71: LOGISTICA | S71: =+SUMIF($A$12:$A$47,"LOGISTICA",S$12:S$56) -> 5800 | T71: =+SUMIF($A$12:$A$47,"LOGISTICA",T$12:T$56) -> 0 | U71: =+SUMIF($A$12:$A$47,"LOGISTICA",U$12:U$56) -> 0 | V71: =+SUMIF($A$12:$A$47,"LOGISTICA",V$12:V$56) -> 0 | W71: =+SUMIF($A$12:$A$47,"LOGISTICA",W$12:W$56) -> 0 | X71: =+SUMIF($A$12:$A$47,"LOGISTICA",X$12:X$56) -> 0 | Y71: =+SUMIF($A$12:$A$47,"LOGISTICA",Y$12:Y$56) -> 0 | Z71: =+SUMIF($A$12:$A$47,"LOGISTICA",Z$12:Z$56) -> 0 | ... AB71: =+SUMIF($A$12:$A$47,"LOGISTICA",AB$12:AB$56) -> 0 | AD71: =+SUMIF($A$12:$A$47,"LOGISTICA",AD$12:AD$56) -> 0 | AF71: =+SUMIF($A$12:$A$47,"LOGISTICA",AF$12:AF$56) -> 0 | AG71: =+SUMIF($A$12:$A$47,"LOGISTICA",AG$12:AG$56) -> 0 | AH71: =+SUMIF($A$12:$A$47,"LOGISTICA",AH$12:AH$56) -> 0 | AI71: =+SUMIF($A$12:$A$47,"LOGISTICA",AI$12:AI$56) -> 0 | AJ71: =+SUMIF($A$12:$A$47,"LOGISTICA",AJ$12:AJ$56) -> 640 | AK71: =+SUMIF($A$12:$A$47,"LOGISTICA",AK$12:AK$56) -> 0 | AL71: =+SUMIF($A$12:$A$47,"LOGISTICA",AL$12:AL$56) -> 0 | AM71: =+SUMIF($A$12:$A$47,"LOGISTICA",AM$12:AM$56) -> 0 | ... AP71: =+SUMIF($A$12:$A$47,"LOGISTICA",AP$12:AP$56) -> 6353.9583 | AR71: ESSALUD | AT71: =+BN66 -> 15622.128 | AY71: =SUM(AS71:AX71) -> 15622.128 | BI71: BCP | BJ71: =+SUMIF($BQ$12:$BQ$56,"BCP",$BL$12:$BL$56)+BR26 -> 30558.652 | BN71: =+SUMIF($A$12:$A$47,"LOGISTICA",BN$12:BN$56) -> 571.85625 | BO71: =+SUMIF($A$12:$A$47,"LOGISTICA",BO$12:BO$56) -> 15.964 | BU71: BCP | BV71: =+SUMIF($BQ$12:$BQ$56,"BCP",$BV$12:$BV$56) -> 21550 | BW71: BCP
BI72: INTERBANK | BJ72: =+SUMIF($BQ$12:$BQ$56,"INTERB",$BL$12:$BL$56) -> 4913.6003 | BU72: INTERB | BV72: =+BV22 -> 1460 | BW72: BCP
P73: K0021 | Q73: VTAS | S73: =+SUMIF($A$12:$A$47,"VTAS",S$12:S$56) -> 36695.667 | T73: =+SUMIF($A$12:$A$47,"VTAS",T$12:T$56) -> 452 | U73: =+SUMIF($A$12:$A$47,"VTAS",U$12:U$56) -> 0 | V73: =+SUMIF($A$12:$A$47,"VTAS",V$12:V$56) -> 29275.965 | W73: =+SUMIF($A$12:$A$47,"VTAS",W$12:W$56) -> 3821.1265 | X73: =+SUMIF($A$12:$A$47,"VTAS",X$12:X$56) -> 0 | Y73: =+SUMIF($A$12:$A$47,"VTAS",Y$12:Y$56) -> 0 | Z73: =+SUMIF($A$12:$A$47,"VTAS",Z$12:Z$56) -> 0 | ... AB73: =+SUMIF($A$12:$A$47,"VTAS",AB$12:AB$56) -> 0 | AD73: =+SUMIF($A$12:$A$47,"VTAS",AD$12:AD$56) -> 4104.3333 | AF73: =+SUMIF($A$12:$A$47,"VTAS",AF$12:AF$56) -> 0 | AG73: =+SUMIF($A$12:$A$47,"VTAS",AG$12:AG$56) -> 0 | AH73: =+SUMIF($A$12:$A$47,"VTAS",AH$12:AH$56) -> 0 | AI73: =+SUMIF($A$12:$A$47,"VTAS",AI$12:AI$56) -> 0 | AJ73: =+SUMIF($A$12:$A$47,"VTAS",AJ$12:AJ$56) -> 800 | AK73: =+SUMIF($A$12:$A$47,"VTAS",AK$12:AK$56) -> 0 | AL73: =+SUMIF($A$12:$A$47,"VTAS",AL$12:AL$56) -> 0 | AM73: =+SUMIF($A$12:$A$47,"VTAS",AM$12:AM$56) -> 0 | ... AP73: =+SUMIF($A$12:$A$47,"VTAS",AP$12:AP$56) -> 77428.644 | AR73: PRIMA | AU73: =+SUMIF($I$12:$I$56,"PRIMA",AT$12:AT$56) -> 3749.2837 | AV73: =+SUMIF($I$12:$I$56,"PRIMA",AV$12:AV$56) -> 147.17328 | AW73: =+SUMIF($I$12:$I$56,"PRIMA",AX$12:AX$56) -> 513.65186 | AY73: =SUM(AS73:AX73) -> 4410.1088 | BJ73: =SUM(BJ70:BJ72) -> 79606.972 | BN73: =+SUMIF($A$12:$A$47,"VTAS",BN$12:BN$56) -> 6968.578 | BO73: =+SUMIF($A$12:$A$47,"VTAS",BO$12:BO$56) -> 118.28 | BV73: =SUM(BV70:BV72) -> 49280
P74: K0022 | Q74: SOPORTE | S74: =+SUMIF($A$12:$A$47,"SOPORTE",S$12:S$56) -> 19396.233 | T74: =+SUMIF($A$12:$A$47,"SOPORTE",T$12:T$56) -> 339 | U74: =+SUMIF($A$12:$A$47,"SOPORTE",U$12:U$56) -> 0 | V74: =+SUMIF($A$12:$A$47,"SOPORTE",V$12:V$56) -> 0 | W74: =+SUMIF($A$12:$A$47,"SOPORTE",W$12:W$56) -> 0 | X74: =+SUMIF($A$12:$A$47,"SOPORTE",X$12:X$56) -> 1335.179 | Y74: =+SUMIF($A$12:$A$47,"SOPORTE",Y$12:Y$56) -> 797.76506 | Z74: =+SUMIF($A$12:$A$47,"SOPORTE",Z$12:Z$56) -> 166.66667 | ... AB74: =+SUMIF($A$12:$A$47,"SOPORTE",AB$12:AB$56) -> 0 | AD74: =+SUMIF($A$12:$A$47,"SOPORTE",AD$12:AD$56) -> 1603.7667 | AF74: =+SUMIF($A$12:$A$47,"SOPORTE",AF$12:AF$56) -> 0 | AG74: =+SUMIF($A$12:$A$47,"SOPORTE",AG$12:AG$56) -> 0 | AH74: =+SUMIF($A$12:$A$47,"SOPORTE",AH$12:AH$56) -> 0 | AI74: =+SUMIF($A$12:$A$47,"SOPORTE",AI$12:AI$56) -> 0 | AJ74: =+SUMIF($A$12:$A$47,"SOPORTE",AJ$12:AJ$56) -> 0 | AK74: =+SUMIF($A$12:$A$47,"SOPORTE",AK$12:AK$56) -> 0 | AL74: =+SUMIF($A$12:$A$47,"SOPORTE",AL$12:AL$56) -> 0 | AM74: =+SUMIF($A$12:$A$47,"SOPORTE",AM$12:AM$56) -> 0 | ... AP74: =+SUMIF($A$12:$A$47,"SOPORTE",AP$12:AP$56) -> 23508.313 | AR74: INTEGRA | AU74: =+SUMIF($I$12:$I$56,"INTEGRA",AT$12:AT$56)+AT61 -> 9144.3211 | AV74: =+SUMIF($I$12:$I$56,"INTEGRA",AV$12:AV$56) -> 369.83481 | AW74: =+SUMIF($I$12:$I$56,"INTEGRA",AX$12:AX$56)+AX61 -> 1147.5481 | AY74: =SUM(AS74:AX74) -> 10661.704 | BN74: =+SUMIF($A$12:$A$47,"SOPORTE",BN$12:BN$56) -> 2115.7482 | BO74: =+SUMIF($A$12:$A$47,"SOPORTE",BO$12:BO$56) -> 39.7807
P75: K0023 | Q75: PROYECTOS | S75: =+SUMIF($A$12:$A$47,"PROYECTO",S$12:S$56) -> 8530 | T75: =+SUMIF($A$12:$A$47,"PROYECTO",T$12:T$56) -> 0 | U75: =+SUMIF($A$12:$A$47,"PROYECTO",U$12:U$56) -> 0 | V75: =+SUMIF($A$12:$A$47,"PROYECTO",V$12:V$56) -> 0 | W75: =+SUMIF($A$12:$A$47,"PROYECTO",W$12:W$56) -> 0 | X75: =+SUMIF($A$12:$A$47,"PROYECTO",X$12:X$56) -> 0 | Y75: =+SUMIF($A$12:$A$47,"PROYECTO",Y$12:Y$56) -> 0 | Z75: =+SUMIF($A$12:$A$47,"PROYECTO",Z$12:Z$56) -> 0 | ... AB75: =+SUMIF($A$12:$A$47,"PROYECTO",AB$12:AB$56) -> 0 | AD75: =+SUMIF($A$12:$A$47,"PROYECTO",AD$12:AD$56) -> 320 | AF75: =+SUMIF($A$12:$A$47,"PROYECTO",AF$12:AF$56) -> 0 | AG75: =+SUMIF($A$12:$A$47,"PROYECTO",AG$12:AG$56) -> 0 | AH75: =+SUMIF($A$12:$A$47,"PROYECTO",AH$12:AH$56) -> 0 | AI75: =+SUMIF($A$12:$A$47,"PROYECTO",AI$12:AI$56) -> 0 | AJ75: =+SUMIF($A$12:$A$47,"PROYECTO",AJ$12:AJ$56) -> 0 | AK75: =+SUMIF($A$12:$A$47,"PROYECTO",AK$12:AK$56) -> 0 | AL75: =+SUMIF($A$12:$A$47,"PROYECTO",AL$12:AL$56) -> 0 | AM75: =+SUMIF($A$12:$A$47,"PROYECTO",AM$12:AM$56) -> 0 | ... AP75: =+SUMIF($A$12:$A$47,"PROYECTO",AP$12:AP$56) -> 8737.4028 | AR75: PROFUTURO | AU75: =+SUMIF($I$12:$I$56,"PROFUTURO",AT$12:AT$56) -> 1240.5986 | AV75: =+SUMIF($I$12:$I$56,"PROFUTURO",AV$12:AV$56) -> 0 | AW75: =+SUMIF($I$12:$I$56,"PROFUTURO",AX$12:AX$56) -> 169.96201 | AY75: =SUM(AS75:AX75) -> 1410.5606 | BN75: =+SUMIF($A$12:$A$47,"PROYECTO",BN$12:BN$56) -> 786.36625 | BO75: =+SUMIF($A$12:$A$47,"PROYECTO",BO$12:BO$56) -> 12.76
P76: K0024 | Q76: MARKETING | S76: =+SUMIF($A$12:$A$47,"MARKET",S$12:S$56) -> 11713.333 | T76: =+SUMIF($A$12:$A$47,"MARKET",T$12:T$56) -> 113 | U76: =+SUMIF($A$12:$A$47,"MARKET",U$12:U$56) -> 0 | V76: =+SUMIF($A$12:$A$47,"MARKET",V$12:V$56) -> 0 | W76: =+SUMIF($A$12:$A$47,"MARKET",W$12:W$56) -> 0 | X76: =+SUMIF($A$12:$A$47,"MARKET",X$12:X$56) -> 0 | Y76: =+SUMIF($A$12:$A$47,"MARKET",Y$12:Y$56) -> 0 | Z76: =+SUMIF($A$12:$A$47,"MARKET",Z$12:Z$56) -> 0 | ... AB76: =+SUMIF($A$12:$A$47,"MARKET",AB$12:AB$56) -> 0 | AD76: =+SUMIF($A$12:$A$47,"MARKET",AD$12:AD$56) -> 186.66667 | AF76: =+SUMIF($A$12:$A$47,"MARKET",AF$12:AF$56) -> 0 | AG76: =+SUMIF($A$12:$A$47,"MARKET",AG$12:AG$56) -> 0 | AH76: =+SUMIF($A$12:$A$47,"MARKET",AH$12:AH$56) -> 0 | AI76: =+SUMIF($A$12:$A$47,"MARKET",AI$12:AI$56) -> 0 | AJ76: =+SUMIF($A$12:$A$47,"MARKET",AJ$12:AJ$56) -> 0 | AK76: =+SUMIF($A$12:$A$47,"MARKET",AK$12:AK$56) -> 0 | AL76: =+SUMIF($A$12:$A$47,"MARKET",AL$12:AL$56) -> 0 | AM76: =+SUMIF($A$12:$A$47,"MARKET",AM$12:AM$56) -> 0 | ... AP76: =+SUMIF($A$12:$A$47,"MARKET",AP$12:AP$56) -> 11989.361 | AR76: HABITAT | AU76: =+SUMIF($I$12:$I$56,"HABITAT",AT$12:AT$56) -> 527.89227 | AV76: =+SUMIF($I$12:$I$56,"HABITAT",AV$12:AV$56) -> 0 | AW76: =+SUMIF($I$12:$I$56,"HABITAT",AX$12:AX$56) -> 72.321241 | AY76: =SUM(AS76:AX76) -> 600.21351 | BI76: JAVIER | BJ76: 700 | BK76: bbva | BN76: =+SUMIF($A$12:$A$47,"MARKET",BN$12:BN$56) -> 1079.0425 | BO76: =+SUMIF($A$12:$A$47,"MARKET",BO$12:BO$56) -> 38.5107 | BU76: YSABEL | BV76: 2300 | BW76: BCP
P77: K0025 | Q77: ALMACEN | S77: =+SUMIF($A$12:$A$47,"ALMACEN",S$12:S$56) -> 8624.9333 | T77: =+SUMIF($A$12:$A$47,"ALMACEN",T$12:T$56) -> 339 | U77: =+SUMIF($A$12:$A$47,"ALMACEN",U$12:U$56) -> 0 | V77: =+SUMIF($A$12:$A$47,"ALMACEN",V$12:V$56) -> 0 | W77: =+SUMIF($A$12:$A$47,"ALMACEN",W$12:W$56) -> 0 | X77: =+SUMIF($A$12:$A$47,"ALMACEN",X$12:X$56) -> 0 | Y77: =+SUMIF($A$12:$A$47,"ALMACEN",Y$12:Y$56) -> 0 | Z77: =+SUMIF($A$12:$A$47,"ALMACEN",Z$12:Z$56) -> 0 | ... AB77: =+SUMIF($A$12:$A$47,"ALMACEN",AB$12:AB$56) -> 0 | AD77: =+SUMIF($A$12:$A$47,"ALMACEN",AD$12:AD$56) -> 275.06667 | AF77: =+SUMIF($A$12:$A$47,"ALMACEN",AF$12:AF$56) -> 0 | AG77: =+SUMIF($A$12:$A$47,"ALMACEN",AG$12:AG$56) -> 0 | AH77: =+SUMIF($A$12:$A$47,"ALMACEN",AH$12:AH$56) -> 0 | AI77: =+SUMIF($A$12:$A$47,"ALMACEN",AI$12:AI$56) -> 0 | AJ77: =+SUMIF($A$12:$A$47,"ALMACEN",AJ$12:AJ$56) -> 0 | AK77: =+SUMIF($A$12:$A$47,"ALMACEN",AK$12:AK$56) -> 0 | AL77: =+SUMIF($A$12:$A$47,"ALMACEN",AL$12:AL$56) -> 0 | AM77: =+SUMIF($A$12:$A$47,"ALMACEN",AM$12:AM$56) -> 0 | ... AP77: =+SUMIF($A$12:$A$47,"ALMACEN",AP$12:AP$56) -> 9114.1212 | AR77: I.RTA.5 | AX77: =+BJ66 -> 15483.103 | AY77: =SUM(AS77:AX77) -> 15483.103 | BI77: RICARDO | BJ77: 1000 | BK77: BCP | BN77: =+SUMIF($A$12:$A$47,"ALMACEN",BN$12:BN$56) -> 820.27091 | BO77: =+SUMIF($A$12:$A$47,"ALMACEN",BO$12:BO$56) -> 26.8507 | BU77: RICARDO | BV77: 1000 | BW77: BCP
AR78: LLBBSS | AT78: =+BN63 -> 0 | AY78: 0 | BI78: LIQ FIORELLA | BJ78: =+BL61 -> 9348.3672 | BK78: bbva | BU78: publicidad | BV78: 1000 | BW78: bbva
S79: =SUM(S69:S77) -> 104953.67 | T79: =SUM(T69:T77) -> 1469 | V79: =SUM(V69:V77) -> 29275.965 | W79: =SUM(W69:W77) -> 3821.1265 | X79: =SUM(X69:X77) -> 4444.559 | Y79: =SUM(Y69:Y77) -> 1513.2651 | Z79: =SUM(Z69:Z77) -> 166.66667 | AA79: =SUM(AA69:AA77) -> 526.31579 | AB79: =SUM(AB69:AB77) -> 0 | AD79: =SUM(AD69:AD77) -> 7296.3333 | AF79: =SUM(AF69:AF77) -> 0 | AG79: =SUM(AG69:AG77) -> 0 | AH79: =SUM(AH69:AH77) -> 0 | AI79: =SUM(AI69:AI77) -> 0 | AJ79: =SUM(AJ69:AJ77) -> 1440 | AL79: =SUM(AL69:AL77) -> 0 | AM79: =SUM(AM69:AM77) -> 0 | AN79: =SUM(AN69:AN77) -> 0 | AO79: =SUM(AO69:AO77) -> 157277.18 | AP79: =SUM(AP69:AP77) -> 156110.6 | AS79: =SUM(AS70:AS78) -> 3465.8986 | AT79: =SUM(AT70:AT78) -> 15622.128 | AU79: =SUM(AU70:AU78) -> 14662.096 | AV79: =SUM(AV70:AV78) -> 517.00809 | AW79: =SUM(AW70:AW78) -> 1903.4832 | AX79: =SUM(AX70:AX78) -> 15483.103 | AY79: =SUM(AY70:AY78) -> 51653.717 | BN79: =SUM(BN69:BN77) -> 14049.954 | BO79: =SUM(BO69:BO77) -> 306.9575
AP81: =+AP57-AP18-AP19-AP27-AP36-AP40+AP63 -> 141970.96 | AR81: BASE EPS | AT81: =+SUMIF($BP$12:$BP$56,"EPS",BN$12:BN$56) -> 5218.4956 | AU81: =+AT82*AW81 -> 1047.9942 | AV81: 3904 | AW81: =+AV81/AV83 -> 0.80329218
AR82: CREDITO EPS | AT82: =+AT81*25/100 -> 1304.6239 | AU82: =+AT82*AW82 -> 256.62972 | AV82: 956 | AW82: =+AV82/AV83 -> 0.19670782 | AX82: =-AK60 -> 0 | BJ82: =SUM(BJ73:BJ81) -> 90655.339
AU83: =SUBTOTAL(9,AU81:AU82) -> 1304.6239 | AV83: =SUBTOTAL(9,AV81:AV82) -> 4860
AR84: ESSALUD POR PAGAR | AT84: =+AZ71-AT82 -> -1304.6239 | AX84: =+AX79+AX82 -> 15483.103
BI85: BCP | BJ85: =+BJ71+BJ72+BJ77 -> 36472.252 | BK85: 18000 | BL85: =+BJ85-BK85 -> 18472.252 | BM85: =+BM87-BM86 -> 22325 | BU85: BCP | BV85: =+BV77+BV76+BV71+BV72+BU59 -> 26310 | BX85: =+BX87-BX86 -> 30552
BI86: BBVA | BJ86: =+BJ70+BJ76+BJ78 -> 54183.087 | BK86: 32000 | BL86: =+BJ86-BK86 -> 22183.087 | BM86: 28000 | BU86: BBVA | BV86: =+BV80+BV79+BV78+BV70+BV81+BU60+BU61 -> 29173.333 | BX86: 30000
BJ87: =SUM(BJ85:BJ86) -> 90655.339 | BL87: =+BL86+BL85 -> 40655.339 | BM87: =15000*3.355 -> 50325 | BV87: =SUM(BV85:BV86) -> 55483.333 | BX87: =18000*3.364 -> 60552
BL88: =+BL87/3.355 -> 12117.836
BV89: =+BV87/3.364 -> 16493.262
BW1048575: BBVA

Sheet PRESTAMOS
A2: APELLIDOS Y NOMBRES | B2: DNI | C2: FECHA DE INGRESO | D2: FECHA DE PRESATMO | E2: MONTO | F2: VALOR DE CUOTA | G2: N° DE CUOTAS | H2: INICIO DE CUOTAS | I2: FIN DE CUOTAS | J2: OBS
A3: ESTRADA SANTOS JUAN MIGUEL | B3: 25849757 | C3: 45341 | D3: 46241 | E3: 1400 | F3: 350 | G3: 4 | H3: 46265 | I3: 46325
A4: ZEVALLOS DELGADO LUIS EDUARDO | B4: 45418 | C4: 45418 | D4: 46254 | E4: 2500 | F4: 500 | G4: 5 | H4: 46295 | I4: 46387 | J4: SE DESCUENTA UNA CUOTA EN GRATIFICACIÓN

Sheet H.E
D3: TOTAL | G3: TOTAL
D4: INGRESOS | E4: ASIGNACION FAMILIAR | G4: INGRESOS | H4: 0.25 | I4: 0.35 | J4: FERIADO/DESCANSO | K4: TOTAL | L4: PAGO 25% | M4: PAGO 35% | N4: PAGO 100%
B5: Nº | C5: APELLIDOS Y NOMBRES | H5: HORAS | I5: HORAS | J5: DIAS | K5: HORAS
B6: 1 | C6: ORIHUELA AGUIRRE ERNESTO JULIO | D6: 13000 | E6: 113 | G6: =+D6+E6 -> 13113 | K6: =SUM(H6:I6) -> 0 | L6: =((G6/30)/8)*H6*1.25 -> 0 | M6: =((G6/30)/8)*I6*1.35 -> 0 | N6: =((G6/30))*J6*2 -> 0
B7: =+B6+1 -> 2 | C7: MARTINEZ CASTILLO GIOVANNA RAQUEL | D7: 6500 | E7: 113 | G7: =+D7+E7 -> 6613 | K7: =SUM(H7:I7) -> 0 | L7: =((G7/30)/8)*H7*1.25 -> 0 | M7: =((G7/30)/8)*I7*1.35 -> 0 | N7: =((G7/30))*J7*2 -> 0
B8: =+B7+1 -> 3 | C8: SALVADOR ROJAS ELVIS ALFONSO | D8: 4000 | E8: 113 | G8: =+D8+E8 -> 4113 | K8: =SUM(H8:I8) -> 0 | L8: =((G8/30)/8)*H8*1.25 -> 0 | M8: =((G8/30)/8)*I8*1.35 -> 0 | N8: =((G8/30))*J8*2 -> 0
B9: =+B8+1 -> 4 | C9: LOLI RODRIGUEZ JANIO RICHARD | D9: 4000 | E9: 113 | G9: =+D9+E9 -> 4113 | K9: =SUM(H9:I9) -> 0 | L9: =((G9/30)/8)*H9*1.25 -> 0 | M9: =((G9/30)/8)*I9*1.35 -> 0 | N9: =((G9/30))*J9*2 -> 0
B10: =+B9+1 -> 5 | C10: PEREZ CAJAHUANCA ARACELLI IRAIDA | D10: 3600 | G10: =+D10+E10 -> 3600 | K10: =SUM(H10:I10) -> 0 | L10: =((G10/30)/8)*H10*1.25 -> 0 | M10: =((G10/30)/8)*I10*1.35 -> 0 | N10: =((G10/30))*J10*2 -> 0
B11: =+B10+1 -> 6 | C11: PORTOCARRERO TAFUR GLORI MAGRI | D11: 6500 | E11: 113 | G11: =+D11+E11 -> 6613 | K11: =SUM(H11:I11) -> 0 | L11: =((G11/30)/8)*H11*1.25 -> 0 | M11: =((G11/30)/8)*I11*1.35 -> 0 | N11: =((G11/30))*J11*2 -> 0
B12: =+B11+1 -> 7 | C12: ECHEVARRIA SOTO JORGE LUIS | D12: 4500 | E12: 113 | G12: =+D12+E12 -> 4613 | K12: =SUM(H12:I12) -> 0 | L12: =((G12/30)/8)*H12*1.25 -> 0 | M12: =((G12/30)/8)*I12*1.35 -> 0 | N12: =((G12/30))*J12*2 -> 0
B13: =+B12+1 -> 8 | C13: MONTOYA MEDRANO ANDREA BELEN JOSEPHINE | D13: 2800 | G13: =+D13+E13 -> 2800 | K13: =SUM(H13:I13) -> 0 | L13: =((G13/30)/8)*H13*1.25 -> 0 | M13: =((G13/30)/8)*I13*1.35 -> 0 | N13: =((G13/30))*J13*2 -> 0
B14: =+B13+1 -> 9 | C14: VERGARA BALDEON GEANNINA LIZBETH | D14: 2600 | G14: =+D14+E14 -> 2600 | K14: =SUM(H14:I14) -> 0 | L14: =((G14/30)/8)*H14*1.25 -> 0 | M14: =((G14/30)/8)*I14*1.35 -> 0 | N14: =((G14/30))*J14*2 -> 0
B15: =+B14+1 -> 10 | C15: CASTILLO ENCARNACION MANUEL LEONIDAS | D15: 2200 | E15: 113 | G15: =+D15+E15 -> 2313 | K15: =SUM(H15:I15) -> 0 | L15: =((G15/30)/8)*H15*1.25 -> 0 | M15: =((G15/30)/8)*I15*1.35 -> 0 | N15: =((G15/30))*J15*2 -> 0
B16: =+B15+1 -> 11 | C16: QUEVEDO SALAS LUIS ALBERTO | D16: 3800 | E16: 113 | G16: =+D16+E16 -> 3913 | K16: =SUM(H16:I16) -> 0 | L16: =((G16/30)/8)*H16*1.25 -> 0 | M16: =((G16/30)/8)*I16*1.35 -> 0 | N16: =((G16/30))*J16*2 -> 0
B17: =+B16+1 -> 12 | C17: PORTOCARRERO GOMEZ MARIA DEICY | D17: 1500 | E17: 113 | G17: =+D17+E17 -> 1613 | K17: =SUM(H17:I17) -> 0 | L17: =((G17/30)/8)*H17*1.25 -> 0 | M17: =((G17/30)/8)*I17*1.35 -> 0 | N17: =((G17/30))*J17*2 -> 0
B18: =+B17+1 -> 13 | C18: LOBO QUISPE ELISA FIORELLA | D18: 3000 | G18: =+D18+E18 -> 3000 | K18: =SUM(H18:I18) -> 0 | L18: 3109.38 | M18: 715.5 | N18: =((G18/30))*J18*2 -> 0
B19: =+B18+1 -> 14 | C19: RIOS HOLSEN JAIME JUNIOR | D19: 3200 | G19: =+D19+E19 -> 3200 | K19: =SUM(H19:I19) -> 0 | L19: =((G19/30)/8)*H19*1.25 -> 0 | M19: =((G19/30)/8)*I19*1.35 -> 0 | N19: =((G19/30))*J19*2 -> 0
B20: =+B19+1 -> 15 | C20: ESTRADA SANTOS JUAN MIGUEL | D20: 2800 | E20: 113 | G20: =+D20+E20 -> 2913 | K20: =SUM(H20:I20) -> 0 | L20: =((G20/30)/8)*H20*1.25 -> 0 | M20: =((G20/30)/8)*I20*1.35 -> 0 | N20: =((G20/30))*J20*2 -> 0
B21: =+B20+1 -> 16 | C21: PORTOCARRERO TAFUR MARIA LOIDI | D21: 1200 | G21: =+D21+E21 -> 1200 | K21: =SUM(H21:I21) -> 0 | L21: =((G21/30)/8)*H21*1.25 -> 0 | M21: =((G21/30)/8)*I21*1.35 -> 0 | N21: =((G21/30))*J21*2 -> 0
B22: =+B21+1 -> 17 | C22: ZEVALLOS DELGADO LUIS EDUARDO | D22: 2800 | G22: =+D22+E22 -> 2800 | K22: =SUM(H22:I22) -> 0 | L22: =((G22/30)/8)*H22*1.25 -> 0 | M22: =((G22/30)/8)*I22*1.35 -> 0 | N22: =((G22/30))*J22*2 -> 0
B23: =+B22+1 -> 18 | C23: BALLLESTEROS DI SERI MARIA PAULA | D23: 2800 | G23: =+D23+E23 -> 2800 | K23: =SUM(H23:I23) -> 0 | L23: =((G23/30)/8)*H23*1.25 -> 0 | M23: =((G23/30)/8)*I23*1.35 -> 0 | N23: =((G23/30))*J23*2 -> 0
B24: =+B23+1 -> 19 | C24: OCAMPO ORTEGA JEAN PAUL | D24: 2500 | G24: =+D24+E24 -> 2500 | H24: =(14*60+12)/60 -> 14.2 | I24: =(8*60+45)/60 -> 8.75 | K24: =SUM(H24:I24) -> 22.95 | L24: =((G24/30)/8)*H24*1.25 -> 184.89583 | M24: =((G24/30)/8)*I24*1.35 -> 123.04688 | N24: =((G24/30))*J24*2 -> 0
B25: =+B24+1 -> 20 | C25: OLIVOS SAAVEDRA LANDHERT ANDERSON | D25: 2500 | G25: =+D25+E25 -> 2500 | H25: =(8*60+40)/60 -> 8.6666667 | I25: =(6*60+20)/60 -> 6.3333333 | J25: 1 | K25: =SUM(H25:I25) -> 15 | L25: =((G25/30)/8)*H25*1.25 -> 112.84722 | M25: =((G25/30)/8)*I25*1.35 -> 89.0625 | N25: =((G25/30))*J25*2 -> 166.66667
B26: =+B25+1 -> 21 | C26: YUPANQUI SAMANIEGO RENATO LUIS | D26: 2500 | G26: =+D26+E26 -> 2500 | K26: =SUM(H26:I26) -> 0 | L26: =((G26/30)/8)*H26*1.25 -> 0 | M26: =((G26/30)/8)*I26*1.35 -> 0 | N26: =((G26/30))*J26*2 -> 0
B27: =+B26+1 -> 22 | C27: TUCTO PEREZ CESAR ANTONIO | D27: 2800 | G27: =+D27+E27 -> 2800 | K27: =SUM(H27:I27) -> 0 | L27: =((G27/30)/8)*H27*1.25 -> 0 | M27: =((G27/30)/8)*I27*1.35 -> 0 | N27: =((G27/30))*J27*2 -> 0
B28: =+B27+1 -> 23 | C28: AREVALO VELA CESAR ANTONIO | D28: 2500 | G28: =+D28+E28 -> 2500 | K28: =SUM(H28:I28) -> 0 | L28: =((G28/30)/8)*H28*1.25 -> 0 | M28: =((G28/30)/8)*I28*1.35 -> 0 | N28: =((G28/30))*J28*2 -> 0
B29: =+B28+1 -> 24 | C29: SICCHA ARCE LUIS FRANCISCO | D29: 2500 | G29: =+D29+E29 -> 2500 | K29: =SUM(H29:I29) -> 0 | L29: =((G29/30)/8)*H29*1.25 -> 0 | M29: =((G29/30)/8)*I29*1.35 -> 0 | N29: =((G29/30))*J29*2 -> 0
B30: =+B29+1 -> 25 | C30: JIMENEZ PUYEN LUIS ANTONIO | D30: 2800 | G30: =+D30+E30 -> 2800 | K30: =SUM(H30:I30) -> 0 | L30: =((G30/30)/8)*H30*1.25 -> 0 | M30: =((G30/30)/8)*I30*1.35 -> 0 | N30: =((G30/30))*J30*2 -> 0
B31: =+B30+1 -> 26 | C31: SILVA SANTISTEBAN RONAL JHUNIOR | D31: 2000 | G31: =+D31+E31 -> 2000 | H31: =(42*60+11)/60 -> 42.183333 | I31: =(21*60+9)/60 -> 21.15 | K31: =SUM(H31:I31) -> 63.333333 | L31: =((G31/30)/8)*H31*1.25 -> 439.40972 | M31: =((G31/30)/8)*I31*1.35 -> 237.9375 | N31: =((G31/30))*J31*2 -> 0
B32: =+B31+1 -> 27 | C32: ELGUERA SOTO LUCERO ESTEFANIA | D32: 2200 | G32: =+D32+E32 -> 2200 | K32: =SUM(H32:I32) -> 0 | L32: =((G32/30)/8)*H32*1.25 -> 0 | M32: =((G32/30)/8)*I32*1.35 -> 0 | N32: =((G32/30))*J32*2 -> 0
B33: =+B32+1 -> 28 | C33: ESTACIO CAYETANO FRANK BRIAN | D33: 2300 | G33: =+D33+E33 -> 2300 | K33: =SUM(H33:I33) -> 0 | L33: =((G33/30)/8)*H33*1.25 -> 0 | M33: =((G33/30)/8)*I33*1.35 -> 0 | N33: =((G33/30))*J33*2 -> 0
B34: =+B33+1 -> 29 | C34: SALAZAR VELASQUEZ HECTOR ALEXANDER | D34: 2500 | E34: 113 | G34: =+D34+E34 -> 2613 | K34: =SUM(H34:I34) -> 0 | L34: =((G34/30)/8)*H34*1.25 -> 0 | M34: =((G34/30)/8)*I34*1.35 -> 0 | N34: =((G34/30))*J34*2 -> 0
B35: =+B34+1 -> 30 | C35: RICRA DAVALOS GIUSSEPPE RENATO | D35: 1800 | G35: =+D35+E35 -> 1800 | K35: =SUM(H35:I35) -> 0 | L35: =((G35/30)/8)*H35*1.25 -> 0 | M35: =((G35/30)/8)*I35*1.35 -> 0 | N35: =((G35/30))*J35*2 -> 0
B36: =+B35+1 -> 31 | C36: DIAZ ESCALANTE LUIS MIGUEL DAVID | D36: 1700 | E36: 113 | G36: =+D36+E36 -> 1813 | K36: =SUM(H36:I36) -> 0 | L36: =((G36/30)/8)*H36*1.25 -> 0 | M36: =((G36/30)/8)*I36*1.35 -> 0 | N36: =((G36/30))*J36*2 -> 0
B37: =+B36+1 -> 32 | C37: HIPOLITO GUANILO ARNOLD JIMMY | D37: 1500 | E37: 113 | G37: =+D37+E37 -> 1613 | H37: =(39*60+34)/60 -> 39.566667 | I37: =(18*60+58)/60 -> 18.966667 | K37: =SUM(H37:I37) -> 58.533333 | L37: =((G37/30)/8)*H37*1.25 -> 332.40122 | M37: =((G37/30)/8)*I37*1.35 -> 172.08694 | N37: =((G37/30))*J37*2 -> 0
B38: =+B37+1 -> 33 | C38: MONTOYA MEDRANO VIVIAN MICHELE ALEXANDRA | D38: 2000 | G38: =+D38+E38 -> 2000 | K38: =SUM(H38:I38) -> 0 | L38: =((G38/30)/8)*H38*1.25 -> 0 | M38: =((G38/30)/8)*I38*1.35 -> 0 | N38: =((G38/30))*J38*2 -> 0
B39: =+B38+1 -> 34 | C39: ALARCON OLIVERA AMBAR TIFFANY | D39: 2850 | G39: =+D39+E39 -> 2850 | K39: =SUM(H39:I39) -> 0 | L39: =((G39/30)/8)*H39*1.25 -> 0 | M39: =((G39/30)/8)*I39*1.35 -> 0 | N39: =((G39/30))*J39*2 -> 0
B40: =+B39+1 -> 35 | C40: BURGA MUÑOZ HELDER ALEXANDER | D40: 1700 | G40: =+D40+E40 -> 1700 | H40: 30 | I40: =(18*60+22)/60 -> 18.366667 | K40: =SUM(H40:I40) -> 48.366667 | L40: =((G40/30)/8)*H40*1.25 -> 265.625 | M40: =((G40/30)/8)*I40*1.35 -> 175.63125 | N40: =((G40/30))*J40*2 -> 0
B41: =+B40+1 -> 36 | C41: RIVERA CORRALES JUAN EDUARDO | D41: 2800 | G41: =+D41+E41 -> 2800 | K41: =SUM(H41:I41) -> 0 | L41: =((G41/30)/8)*H41*1.25 -> 0 | M41: =((G41/30)/8)*I41*1.35 -> 0 | N41: =((G41/30))*J41*2 -> 0
B42: =+B41+1 -> 37 | C42: MELO HUAMAN CARLOS MANUEL | D42: 1400 | G42: =+D42+E42 -> 1400 | K42: =SUM(H42:I42) -> 0 | L42: =((G42/30)/8)*H42*1.25 -> 0 | M42: =((G42/30)/8)*I42*1.35 -> 0 | N42: =((G42/30))*J42*2 -> 0
B43: =+B42+1 -> 38 | C43: FARFAN LAUREL CIELO CARMIN | D43: 2000 | G43: =+D43+E43 -> 2000 | K43: =SUM(H43:I43) -> 0 | L43: =((G43/30)/8)*H43*1.25 -> 0 | M43: =((G43/30)/8)*I43*1.35 -> 0 | N43: =((G43/30))*J43*2 -> 0
B44: =+B43+1 -> 39 | C44: ORTIZ PAREDES CESAR PAUL | D44: 1200 | E44: 113 | G44: =+D44+E44 -> 1313 | K44: =SUM(H44:I44) -> 0 | L44: =((G44/30)/8)*H44*1.25 -> 0 | M44: =((G44/30)/8)*I44*1.35 -> 0 | N44: =((G44/30))*J44*2 -> 0
B45: =+B44+1 -> 40 | C45: PAREDES CHAMOCHUMBI ANA GABRIEL | D45: 2000 | G45: =+D45+E45 -> 2000 | K45: =SUM(H45:I45) -> 0 | L45: =((G45/30)/8)*H45*1.25 -> 0 | M45: =((G45/30)/8)*I45*1.35 -> 0 | N45: =((G45/30))*J45*2 -> 0
B46: =+B45+1 -> 41 | C46: ARAGON LOPEZ EDUARDO ALEJANDRO | D46: 2500 | E46: 113 | G46: =+D46+E46 -> 2613 | K46: =SUM(H46:I46) -> 0 | L46: =((G46/30)/8)*H46*1.25 -> 0 | M46: =((G46/30)/8)*I46*1.35 -> 0 | N46: =((G46/30))*J46*2 -> 0
B47: =+B46+1 -> 42 | C47: PALOMINO DELGADO CESAR JAIRO | D47: 1600 | G47: =+D47+E47 -> 1600 | K47: =SUM(H47:I47) -> 0 | L47: =((G47/30)/8)*H47*1.25 -> 0 | M47: =((G47/30)/8)*I47*1.35 -> 0 | N47: =((G47/30))*J47*2 -> 0
B48: =+B47+1 -> 43 | C48: FRANCO LOPEZ EMERSON JOEL | D48: 1800 | G48: =+D48+E48 -> 1800 | K48: =SUM(H48:I48) -> 0 | L48: =((G48/30)/8)*H48*1.25 -> 0 | M48: =((G48/30)/8)*I48*1.35 -> 0 | N48: =((G48/30))*J48*2 -> 0
B49: =+B48+1 -> 44 | C49: GUZMAN LIVIA ALFREDO SANTIAGO | D49: 3500 | E49: 113 | G49: =+D49+E49 -> 3613 | K49: =SUM(H49:I49) -> 0 | L49: =((G49/30)/8)*H49*1.25 -> 0 | M49: =((G49/30)/8)*I49*1.35 -> 0 | N49: =((G49/30))*J49*2 -> 0

Sheet COMISIONES
A1: No | D1: año 2026 | P1: TOTAL | Q1: PROMEDIO COMISIONES
B2: APELLIDOS Y NOMBRES | D2: ENERO | E2: FEBRERO | F2: MARZO | G2: ABRIL | H2: MAYO | I2: JUNIO | J2: JULIO | K2: AGOSTO | L2: SETIEMBRE | M2: OCTUBRE | N2: NOVIEMBRE | O2: DICIEMBRE
A3: 1 | B3: ECHEVARRIA SOTO JORGE LUIS | D3: 9122.3397 | E3: 6019.6636 | F3: 8538.4969 | G3: 12937.093 | H3: 8462.9701 | I3: 8965.188 | J3: 12745.128 | K3: 8688.2701 | P3: =SUM(D3:O3) -> 75479.149 | Q3: =+P3/6 -> 12579.858
A4: =+A3+1 -> 2 | B4: QUEVEDO SALAS LUIS ALBERTO | D4: 2501.7108 | E4: 2599.7564 | F4: 3287.0806 | G4: 2509.8714 | H4: 3359.019 | I4: 4331.4263 | J4: 1771.0376 | K4: 4452.19 | P4: =SUM(D4:O4) -> 24812.092 | Q4: =+P4/6 -> 4135.3487
A5: =+A4+1 -> 3 | B5: ESTRADA SANTOS JUAN MIGUEL | D5: 1375.3927 | E5: 2137.4428 | F5: 1953.9544 | G5: 1486.9737 | H5: 1343.5632 | I5: 1994.6996 | J5: 2048.7845 | K5: 1459.82 | P5: =SUM(D5:O5) -> 13800.631 | Q5: =+P5/6 -> 2300.1051
A6: =+A5+1 -> 4 | B6: ERNESTO ORIHUELA AGUIRRE | D6: 5568.2823 | E6: 4483.2372 | F6: 6098.9263 | G6: 9240.781 | H6: 6044.9787 | I6: 6403.7057 | J6: 7965.7048 | K6: 7240.2251 | P6: =SUM(D6:O6) -> 53045.841 | Q6: =+P6/6 -> 8840.9735
A7: =+A6+1 -> 5 | B7: SICCHA ARCE LUIS FRANCISCO | D7: 404.14905 | E7: 749.2803 | F7: 531.69465 | G7: 3286.2737 | H7: 700.75905 | I7: 1556.8993 | J7: 600.18255 | K7: 1091.36 | P7: =SUM(D7:O7) -> 8920.5986 | Q7: =+P7/6 -> 1486.7664
A8: =+A7+1 -> 6 | B8: AREVALO VELA CESAR ANTONIO | D8: 2429.1964 | E8: 842.6241 | F8: 846.33225 | G8: 2406.4389 | H8: 1799.1559 | I8: 662.7648 | J8: 1891.5045 | K8: 1528.25 | P8: =SUM(D8:O8) -> 12406.267 | Q8: =+P8/6 -> 2067.7111
A9: =+A8+1 -> 7 | B9: ESTACIO CAYETANO FRANK BRIAN | D9: 872.05845 | E9: 1100.9444 | F9: 3369.7662 | G9: 937.3611 | H9: 1449.1908 | I9: 1482.3352 | J9: 3142.0137 | K9: 3375.75 | P9: =SUM(D9:O9) -> 15729.42 | Q9: =+P9/6 -> 2621.57
A10: 8 | B10: RICRA DAVALOS GIUSSEPPE RENATO | I10: 887.808 | J10: 1180.9678 | K10: 1440.1 | P10: =SUM(D10:O10) -> 3508.8758 | Q10: =+P10/6 -> 584.81264
A11: 9 | B11: PAREDES CHAMOCHUMBI ANA GABRIEL | J11: 72.72075 | K11: 323.01 | P11: =SUM(D11:O11) -> 395.73075 | Q11: =+P11/6 -> 65.955125
C12: =SUM(C3:C10) -> 0 | D12: =SUM(D3:D10) -> 22273.129 | E12: =SUM(E3:E10) -> 17932.949 | F12: =SUM(F3:F10) -> 24626.251 | G12: =SUM(G3:G10) -> 32804.793 | H12: =SUM(H3:H10) -> 23159.637 | I12: =SUM(I3:I10) -> 26284.827 | J12: =SUM(J3:J11) -> 31418.044 | K12: =SUM(K3:K11) -> 29598.975 | L12: =SUM(L3:L10) -> 0 | M12: =SUM(M3:M10) -> 0 | N12: =SUM(N3:N10) -> 0 | O12: =SUM(O3:O10) -> 0 | P12: =SUM(P3:P10) -> 207702.87 | Q12: =SUM(Q3:Q10) -> 34617.146
A22: No | C22: 2024 | D22: año 2025 | P22: TOTAL | Q22: PROMEDIO COMISIONES | V22: -
B23: APELLIDOS Y NOMBRES | C23: DICIEMBRE | D23: ENERO | E23: FEBRERO | F23: MARZO | G23: ABRIL | H23: MAYO | I23: JUNIO | J23: JULIO | K23: AGOSTO | L23: SETIEMBRE | M23: OCTUBRE | N23: NOVIEMBRE | O23: DICIEMBRE
A24: 1 | B24: ECHEVARRIA SOTO JORGE LUIS | C24: 3749.9306 | D24: 5009.5509 | E24: 7448.2999 | F24: 9200.1916 | G24: 9329.5001 | H24: 8939.95 | I24: 12112.493 | J24: 7881.04 | K24: 7297.3057 | L24: 7289.3865 | M24: 10135.684 | N24: 5083.407 | O24: 4295.24 | P24: =SUM(D24:O24) -> 94022.049 | Q24: =+P24/6 -> 15670.341
A25: =+A24+1 -> 2 | B25: QUEVEDO SALAS LUIS ALBERTO | C25: 2506.3845 | D25: 7095.9636 | E25: 2310.1339 | F25: 1816.4344 | G25: 5069.9014 | H25: 1552.32 | I25: 2245.63 | J25: 4212.23 | K25: 2680.1595 | L25: 4362.1779 | M25: 4957.9692 | N25: 1243.59 | O25: 1724.21 | P25: =SUM(D25:O25) -> 39270.72 | Q25: =+P25/6 -> 6545.12
A26: =+A25+1 -> 3 | B26: VIDAL MELO ALEX FERNANDO | C26: 260.4894 | D26: 432.22245 | E26: 217.75095 | F26: 534.52605 | G26: 1015.8413 | H26: 0 | I26: 0 | P26: =SUM(D26:O26) -> 2200.3407 | Q26: =+P26/6 -> 366.72345
A27: =+A26+1 -> 4 | B27: ESTRADA SANTOS JUAN MIGUEL | C27: 872.8485 | D27: 1473.3036 | E27: 2995.61 | F27: 2739.9275 | G27: 1961.3279 | H27: 1835.52 | I27: 2977.69 | J27: 2142.75 | K27: 2792.4066 | L27: 1457.0637 | M27: 1122.8265 | N27: 2531.97 | O27: 829.3 | P27: =SUM(D27:O27) -> 24859.696 | Q27: =+P27/6 -> 4143.2826
A28: =+A27+1 -> 5 | B28: ERNESTO ORIHUELA AGUIRRE | C28: 3217.1824 | D28: 5674.875 | E28: 4496.0072 | F28: 5380.4996 | G28: 6572.6463 | H28: 5345.58 | I28: 6844.2282 | J28: 5943.65 | K28: 5512.5559 | L28: 6117.8439 | M28: 7150.9868 | N28: 4317.9892 | O28: 3580.75 | P28: =SUM(D28:O28) -> 66937.612 | Q28: =+P28/6 -> 11156.269
A29: =+A28+1 -> 6 | B29: SICCHA ARCE LUIS FRANCISCO | E29: 516.2268 | F29: 1351.7901 | G29: 1744.5441 | H29: 2470.72 | I29: 916.03 | J29: 1335.61 | K29: 1408.1795 | L29: 3396.5073 | M29: 1826.0354 | N29: 633.57 | O29: 1496.32 | P29: =SUM(D29:O29) -> 17095.533 | Q29: =+P29/6 -> 2849.2555
A30: 7 | B30: AREVALO VELA CESAR ANTONIO | F30: 498.6291 | G30: 596.82435 | H30: 1085.98 | I30: 917.48 | J30: 1345.58 | K30: 1584.3099 | L30: 1237.6771 | M30: 2344.5985 | N30: 2158.28 | O30: 1263.82 | P30: =SUM(D30:O30) -> 13033.179 | Q30: =+P30/6 -> 2172.1965
A31: 8 | B31: ESTACIO CAYETANO FRANK BRIAN | H31: 152.23 | I31: 1363.37 | J31: 913.74 | K31: 775.30635 | L31: 610.71905 | M31: 1065.8465 | N31: 1303.15 | O31: 1133.38 | P31: =SUM(D31:O31) -> 7317.7418 | Q31: =+P31/6 -> 1219.6236
P32: =SUM(D32:O32) -> 0 | Q32: =+P32/6 -> 0
C33: =SUM(C24:C32) -> 10606.835 | D33: =SUM(D24:D32) -> 19685.916 | E33: =SUM(E24:E32) -> 17984.029 | F33: =SUM(F24:F32) -> 21521.998 | G33: =SUM(G24:G32) -> 26290.585 | H33: =SUM(H24:H32) -> 21382.3 | I33: =SUM(I24:I32) -> 27376.921 | J33: =SUM(J24:J32) -> 23774.6 | ... Q33: =SUM(Q24:Q32) -> 44122.812
E34: 17984.029 | F34: 21521.998 | H34: =+'[5]PLANILLA MENSUAL'!S74 -> 0 | I34: =+'[5]PLANILLA MENSUAL'!S74 -> 0 | J34: =+[6]Resumen!$D$13 -> 23774.612 | K34: =+[7]COMISIONES!$K$13 -> 22050.223 | L34: =+[8]Resumen!$D$13 -> 24471.375 | M34: =+[9]Resumen!$D$13 -> 28603.947 | N34: =+[10]Resumen!$D$13 -> 17271.957 | O34: =+[11]Resumen!$D$13 -> 14323

Sheet RTA 5TA VTAS
B2: CALCULO QUINTA CATEGORIA DEL IMPUESTO A LA RENTA - 2026
B4: MESES | D4: ERNESTO | E4: JORGE | F4: LUIS | G4: JUAN | H4: LUIS | I4: CESAR | J4: FRANK | K4: GIUSSEPPE | L4: TOTALES
D5: ORIHUELA | E5: ECHEVARRIA | F5: QUEVEDO | G5: ESTRADA | H5: SICCHA | I5: AREVALO | J5: ESTACIO | K5: RICRA
B6: ENERO
B7: SUELDO + ASIG FAM | D7: 12113 | E7: 4613 | F7: 3613 | G7: 2913 | H7: 2500 | I7: 1800 | J7: 2000 | K7: 1500 | L7: =SUM(D7:K7) -> 31052
B8: COMISIONES | D8: 5568.2823 | E8: 9122.3397 | F8: 2501.7108 | G8: 1375.3927 | H8: 404.14905 | I8: 2429.1964 | J8: 872.05845 | L8: =SUM(D8:J8) -> 22273.129
B9: VACACIONES PROMEDIO | E9: 1399.4021 | F9: 639.34455 | L9: =SUM(D9:J9) -> 2038.7467
B11: FEBRERO
B12: SUELDO + ASIG FAM | D12: 12113 | E12: 4613 | F12: 3613 | G12: 2913 | H12: 2500 | I12: 1800 | J12: 2000 | K12: 1500 | L12: =SUM(D12:J12) -> 29552
B13: COMISIONES | D13: =+COMISIONES!E6 -> 4483.2372 | E13: =+COMISIONES!E3 -> 6019.6636 | F13: =+COMISIONES!E4 -> 2599.7564 | G13: =+COMISIONES!E5 -> 2137.4428 | H13: =+COMISIONES!E7 -> 749.2803 | I13: =+COMISIONES!E8 -> 842.6241 | J13: =+COMISIONES!E9 -> 1100.9444 | L13: =SUM(D13:J13) -> 17932.949
L14: =SUM(D14:I14) -> 0
B15: MARZO
B16: SUELDO + ASIG FAM | D16: 12113 | E16: 4613 | F16: 3613 | G16: 2913 | H16: 2500 | I16: 1800 | J16: 2000 | K16: 1500 | L16: =SUM(D16:J16) -> 29552
B17: COMISIONES | D17: 6098.9263 | E17: 8538.4969 | F17: 3287.0806 | G17: 1953.9544 | H17: 531.69465 | I17: 846.33225 | J17: 3369.7662 | L17: =SUM(D17:J17) -> 24626.251
B18: VACACIONES PROMEDIO | L18: =SUM(D18:J18) -> 0
B19: UTILIDADES | D19: 22726.82 | E19: 17322.29 | F19: 10739.88 | G19: 8723.49 | H19: 7286.82 | I19: 6752.33 | J19: 4444.65 | K19: 3376.6529 | L19: =SUM(D19:K19) -> 81372.933 | M19: NO SE CONSIDERA EN LA PROYECCION DE RENTA
B21: ABRIL | L21: =SUM(D21:I21) -> 0
B22: SUELDO + ASIG FAM | D22: 12113 | E22: 4613 | F22: 3613 | G22: 2913 | H22: 2500 | I22: 2200 | J22: 2000 | K22: 1500 | L22: =SUM(D22:J22) -> 29952
B23: COMISIONES | D23: 9240.781 | E23: 12937.093 | F23: 2509.8714 | G23: 1486.9737 | H23: 2406.4389 | I23: 3286.2737 | J23: 937.3611 | L23: =SUM(D23:J23) -> 32804.793
B24: VACACIONES PROMEDIO | L24: =SUM(D24:J24) -> 0
B25: COMISION TRIMESTRAL | L25: =SUM(D25:J25) -> 0
B26: MAYO | L26: =SUM(D26:J26) -> 0
B27: SUELDO + ASIG FAM | L27: =SUM(D27:J27) -> 0
B28: COMISIONES | L28: =SUM(D28:J28) -> 0
B29: VACACIONES PROMEDIO | L29: =SUM(D29:J29) -> 0
L30: =SUM(D30:J30) -> 0
B31: JUNIO | L31: =SUM(D31:J31) -> 0
B32: SUELDO + ASIG FAM | L32: =SUM(D32:J32) -> 0
B33: COMISIONES | L33: =SUM(D33:J33) -> 0
L34: =SUM(D34:J34) -> 0
B35: JULIO | L35: =SUM(D35:J35) -> 0
B36: SUELDO + ASIG FAM | L36: =SUM(D36:J36) -> 0
B37: COMISIONES | L37: =SUM(D37:J37) -> 0
B38: GRATIFICACION JULIO | L38: =SUM(D38:J38) -> 0
B39: VACACIONES PROMEDIO | L39: =SUM(D39:J39) -> 0
L40: =SUM(D40:J40) -> 0
B41: AGOSTO | L41: =SUM(D41:J41) -> 0
B42: SUELDO + ASIG FAM | L42: =SUM(D42:J42) -> 0
B43: COMISIONES | L43: =SUM(D43:J43) -> 0
L44: =SUM(D44:J44) -> 0
B45: SEPTIEMBRE | L45: =SUM(D45:J45) -> 0
B46: SUELDO + ASIG FAM | L46: =SUM(D46:J46) -> 0
B47: COMISIONES | L47: =SUM(D47:J47) -> 0
B48: PROMEDIO DE VACACIONES | L48: =SUM(D48:J48) -> 0
L49: =SUM(D49:J49) -> 0
B50: OCTUBRE | L50: =SUM(D50:J50) -> 0
B51: SUELDO + ASIG FAM | L51: =SUM(D51:J51) -> 0
B52: COMISIONES | L52: =SUM(D52:J52) -> 0
B53: PROMEDIO DE VACACIONES | L53: =SUM(D53:J53) -> 0
B54: GRATIFICACION | L54: =SUM(D54:J54) -> 0
B55: BONO EXTRAORDINARIO | L55: =SUM(D55:J55) -> 0
L56: =SUM(D56:J56) -> 0
B57: NOVIEMBRE | L57: =SUM(D57:J57) -> 0
B58: SUELDO + ASIG FAM | L58: =SUM(D58:J58) -> 0
B59: COMISIONES | L59: =SUM(D59:J59) -> 0
L60: =SUM(D60:J60) -> 0
B61: DICIEMBRE | L61: =SUM(D61:J61) -> 0
B62: SUELDO + ASIG FAM | L62: =SUM(D62:J62) -> 0
B63: COMISIONES | L63: =SUM(D63:J63) -> 0
B64: PROMEDIO VACACIONES | L64: =SUM(D64:J64) -> 0
B65: GRATIFICACION DICIEMBRE | L65: =SUM(D65:J65) -> 0
B66: VALES PAVO OBSEQUIO | L66: =SUM(D66:J66) -> 0
L67: =SUM(D67:J67) -> 0
L68: =SUM(D68:J68) -> 0
L69: =SUM(D69:J69) -> 0
B70: MAYO | L70: =SUM(D70:J70) -> 0
B71: SUELDO + ASIG FAM | D71: 13113 | E71: 4613 | F71: =3800+113 -> 3913 | G71: 2913 | H71: 2500 | I71: 2500 | J71: =2300+113 -> 2413 | K71: 1800 | L71: =SUM(D71:J71) -> 31965
B72: COMISIONES | D72: 6044.9787 | E72: 8462.9701 | F72: 3359.019 | G72: 1343.5632 | H72: 700.75905 | I72: 1799.1559 | J72: 1449.1908 | K72: 887.808 | L72: =SUM(D72:J72) -> 23159.637
B73: VACACIONES PROMEDIO | L73: =SUM(D73:J73) -> 0
B74: COMISION TRIMESTRAL | L74: =SUM(D74:J74) -> 0
B76: JUNIO
B77: SUELDO + ASIG FAM | D77: 13113 | E77: 4613 | F77: =3800+113 -> 3913 | G77: 2913 | H77: 2500 | I77: 2500 | J77: =2300+113 -> 2413 | K77: 1800
B78: COMISIONES | D78: =+[12]Resumen!$D$15 -> 6403.7057 | E78: =+[12]Resumen!$D$23 -> 8965.188 | F78: =+[12]Resumen!$F$4 -> 4331.4263 | G78: =+[12]Resumen!$F$6 -> 1994.6996 | H78: =+[12]Resumen!$F$5 -> 1556.8993 | I78: =+[12]Resumen!$F$8 -> 662.7648 | J78: =+[12]Resumen!$F$7 -> 1482.3352 | K78: =+[12]Resumen!$F$11 -> 887.808
B79: VACACIONES PROMEDIO
B80: COMISION TRIMESTRAL
B82: JULIO
B83: SUELDO + ASIG FAM | D83: 13113 | E83: 4613 | F83: 3913 | G83: 2913 | H83: 2500 | I83: 2500 | J83: 2413 | K83: 1800
B84: COMISIONES | D84: 7965.7048 | E84: 12745.128 | F84: 1771.0376 | G84: 2048.7845 | H84: 600.18255 | I84: 1891.5045 | J84: 3142.0137 | K84: 1180.9678
B85: VACACIONES PROMEDIO | E85: 300.25418 | F85: 1445.8006 | G85: 57.177925 | J85: 358.23108
B86: GRATIFICACION | D86: 21167.421 | E86: 14846.482 | F86: 7642.147 | G86: 4044.8881 | H86: 4038.2785 | I86: 4357.5497 | J86: 4180.4509 | K86: 1962
B87: COMISION TRIMESTRAL
B89: AGOSTO
B90: SUELDO + ASIG FAM | D90: 13113 | E90: 4613 | F90: 3913 | G90: 2913 | H90: 2500 | I90: 2500 | J90: 2413 | K90: 1800
B91: COMISIONES | D91: 7240.2251 | E91: 8688.2701 | F91: =COMISIONES!K4 -> 4452.19 | G91: =COMISIONES!K5 -> 1459.82 | H91: =COMISIONES!K7 -> 1091.36 | I91: =COMISIONES!K8 -> 1528.25 | J91: =COMISIONES!K9 -> 3375.75 | K91: =COMISIONES!K10 -> 1440.1
B92: VACACIONES PROMEDIO | E92: ='PLANILLA MENSUAL'!W18 -> 3203.8078 | H92: ='PLANILLA MENSUAL'!W35 -> 288.75348 | I92: ='PLANILLA MENSUAL'!W34 -> 328.56524
B93: GRATIFICACION
B94: COMISION TRIMESTRAL | L94: =SUM(D94:J94) -> 0
B95: COMPENSACIÓN DE VACACIONES | G95: ='PLANILLA MENSUAL'!AE26 -> 2370.2849
L96: =SUM(D96:J96) -> 0
B97: TOTAL PERCIBIDO | D97: =SUM(D6:D96)-D19 -> 175117.26 | E97: =SUM(E6:E96)-E19 -> 132133.1 | F97: =SUM(F6:F96)-F19 -> 64643.384 | G97: =SUM(G6:G96)-G19-G95 -> 41206.697 | H97: =SUM(H6:H96)-H19 -> 32367.796 | I97: =SUM(I6:I96)-I19 -> 35572.217 | J97: =SUM(J6:J96)-J19 -> 37920.102 | K97: =SUM(K6:K96) -> 22935.337 | L97: =SUM(D97:J97) -> 518960.55
B98: TOTAL REMUNERACIONES | D98: =+D149 -> 298842.99 | E98: =+E149 -> 221935.39 | F98: =+F149 -> 109899.5 | G98: =+G149 -> 70118.574 | H98: =+H149 -> 54187.133 | I98: =+I149 -> 59084.731 | J98: =+J149 -> 68167.303 | K98: =+K149 -> 0 | L98: =SUM(L6:L97) -> 875241.99 | M98: =SUM(L6:L96) -> 356281.44
B99: DEDUCCION 7UITS | D99: =5500*7 -> 38500 | E99: =5500*7 -> 38500 | F99: =5500*7 -> 38500 | G99: =5500*7 -> 38500 | H99: =5500*7 -> 38500 | I99: =5500*7 -> 38500 | J99: =5500*7 -> 38500 | K99: =5500*7 -> 38500 | L99: =SUM(D99:I99) -> 231000
B100: BASE IMPONIBLE | D100: =+D98-D99 -> 260342.99 | E100: =+E98-E99 -> 183435.39 | F100: =+F98-F99 -> 71399.501 | G100: =+G98-G99 -> 31618.574 | H100: =+H98-H99 -> 15687.133 | I100: =+I98-I99 -> 20584.731 | J100: =+J98-J99 -> 29667.303 | L100: =SUM(D100:I100) -> 583068.32
B103: CALCULO IR 5TA CATEG.
B104: Hasta 5 UIT S/ 27,500 (5500 UIT) | C104: 0.08 | D104: =+(5500*5)*$C$104 -> 2200 | E104: =+(5500*5)*$C$104 -> 2200 | F104: =+(5500*5)*$C$104 -> 2200 | G104: =+(5500*5)*$C$104 -> 2200 | H104: =+(H100)*$C$104 -> 1254.9706 | I104: =+(I100)*$C$104 -> 1646.7785 | J104: =+(J100)*$C$104 -> 2373.3842 | L104: =SUM(D104:J104) -> 14075.133 | U104: =5350*5 -> 26750 | V104: =+U104*8/100 -> 2140
B105: Por el exceso de 5 UIT S/ 27,500 y hasta 20 UIT 110,000 | C105: 0.14 | D105: =+(110000-27500)*$C$105 -> 11550 | E105: =+(+E100-27500)*$C$105 -> 21830.955 | F105: =+(+F100-27500)*$C$105 -> 6145.9302 | G105: =+(+G100-27500)*$C$105 -> 576.60037 | J105: =+(+J100-27500)*$C$105 -> 303.42238 | L105: =SUM(D105:J105) -> 40406.908 | U105: =107000-U104 -> 80250 | V105: =+U105*14/100 -> 11235
B106: Por el exceso de 20 UIT S/ 110,000 y hasta 35 UIT 192,500 | C106: 0.17 | D106: =+(D100-110000)*$C$106 -> 25558.309 | E106: =+(+E100-110000)*$C$106 -> 12484.017 | L106: =SUM(D106:J106) -> 38042.326 | U106: =187250-107000 -> 80250 | V106: =+U106*17/100 -> 13642.5
B107: Por el exceso de 35 UIT S/ 192,500 y hasta 45 UIT 247,500 | C107: 0.2 | D107: =+(D100-192500)*$C$107 -> 13568.598 | U107: =205292.52-187250 -> 18042.52 | V107: =+U107*0.2 -> 3608.504
D108: =SUM(D104:D107) -> 52876.907 | E108: =SUM(E104:E106) -> 36514.972 | F108: =SUM(F104:F106) -> 8345.9302 | G108: =SUM(G104:G106) -> 2776.6004 | H108: =SUM(H104:H106) -> 1254.9706 | I108: =SUM(I104:I106) -> 1646.7785 | J108: =SUM(J104:J106) -> 2676.8066 | L108: =SUM(L104:L106) -> 92524.367 | U108: =SUM(U104:U107) -> 205292.52 | V108: =SUM(V104:V107) -> 30626.004
B109: RETENCIONES
...

Sheet RTA 5TA
B2: CALCULO QUINTA CATEGORIA DEL IMPUESTO A LA RENTA - 2025
D3: 1 | E3: =+D3+1 -> 2 | F3: =+E3+1 -> 3 | G3: =+F3+1 -> 4 | H3: =+G3+1 -> 5
D4: GIOVANNA | E4: RIHARD | F4: ARACELLI | G4: GLORI | H4: ELVIS | I4: GEANNINA | J4: FIORELLA | K4: JAIME | L4: LUIS | M4: BELEN | N4: LUIS | O4: MARIA PAULA | P4: CESAR | Q4: RENATO | R4: LANDER | S4: JEAN PAUL | T4: HECTOR | U4: MANUEL | V4: TOTALES
B5: MES | D5: MARTINEZ | E5: LOLI | F5: ARAIDA | G5: PORTOCARRERO | H5: SALVADOR | I5: VERGARA | J5: LOBO | K5: RIOS | L5: JIMENEZ | M5: MONTOYA | N5: ZEVALLOS | O5: BALLESTEROS | P5: TUCTO | Q5: YUPANQUI | R5: OLIVOS | S5: OCAMPO | T5: SALAZAR | U5: CASTILLO
B6: ENERO | V6: =SUM(D6:U6) -> 0
B7: SUELDO + ASIG FAM | D7: =6000+113 -> 6113 | E7: =4000+113 -> 4113 | F7: 3360 | G7: =6000+113 -> 6113 | H7: =4000+113 -> 4113 | I7: 2500 | J7: 3000 | K7: 2800 | L7: 2800 | M7: 2100 | N7: 2500 | O7: 2500 | P7: 2500 | Q7: 2200 | R7: 2000 | S7: 2000 | T7: 2113 | U7: 2113 | V7: =SUM(D7:U7) -> 54938
B8: BONO | F8: 640 | M8: 800 | V8: =SUM(D8:U8) -> 1440
B9: MOVILIDAD | D9: 95.238095 | E9: 76.190476 | F9: 53.333333 | H9: 66.666667 | J9: 90.47619 | U9: 90.48 | V9: =SUM(D9:U9) -> 472.38476
B10: HORAS EXTRAS | E10: 290.48063 | H10: 1311.0188 | K10: =+'[5]PLANILLA MENSUAL'!U27 -> 197.75 | N10: 786.97917 | R10: 267.29167 | S10: 802.91667 | V10: =SUM(D10:U10) -> 3656.4369
V11: =SUM(D11:U11) -> 0
B12: FEBRERO | V12: =SUM(D12:U12) -> 0
B13: SUELDO + ASIG FAM | D13: =6000+113 -> 6113 | E13: =4000+113 -> 4113 | F13: 3360 | G13: =6000+113 -> 6113 | H13: =4000+113 -> 4113 | I13: 2500 | J13: 3000 | K13: 2800 | L13: 2800 | M13: 2100 | N13: 2500 | O13: 2500 | P13: 2500 | Q13: 2200 | R13: 2000 | S13: 2000 | T13: 2113 | U13: 2113 | V13: =SUM(D13:U13) -> 54938
B14: BONO | F14: 640 | M14: 800 | V14: =SUM(D14:U14) -> 1440
B15: MOVILIDAD | D15: 100 | E15: 100 | F15: 100 | H15: 65 | J15: 60 | U15: 100 | V15: =SUM(D15:U15) -> 525
V16: =SUM(D16:U16) -> 0
B17: MARZO | V17: =SUM(D17:U17) -> 0
B18: SUELDO + ASIG FAM | D18: =6000+113 -> 6113 | E18: =4000+113 -> 4113 | F18: 3360 | G18: =6000+113 -> 6113 | H18: =4000+113 -> 4113 | I18: 2500 | J18: 3000 | K18: 2800 | L18: 2800 | M18: 2100 | N18: 2500 | O18: 2500 | P18: 2500 | Q18: 2200 | R18: 2000 | S18: 2000 | T18: 2113 | U18: 2113 | V18: =SUM(D18:U18) -> 54938
B19: BONO | F19: 640 | M19: 800 | V19: =SUM(D19:U19) -> 1440
B20: MOVILIDAD | D20: 100 | E20: 100 | F20: 90 | H20: 75 | J20: 100 | U20: 100 | V20: =SUM(D20:U20) -> 565
B21: HORAS EXTRAS | D21: 407.53 | J21: 331.14 | V21: =SUM(D21:U21) -> 738.67
B22: UTILIDADES | D22: 10984.79 | E22: 8491.98 | F22: 7025.49 | G22: 10355.57 | H22: 7080.15 | I22: 5958.32 | J22: 7005.9 | K22: 6432.12 | L22: 5954.52 | M22: 5918.4 | N22: 6391.45 | O22: 6304.7384 | P22: 6982.8977 | Q22: 6452.0209 | R22: 6227.3593 | S22: 5939.7149 | T22: 5529.58 | U22: 5929.2 | V22: =SUM(D22:U22) -> 124964.2 | W22: NO SE CONSIDERA EN LA PROYECCION
V23: =SUM(D23:U23) -> 0
B24: ABRIL | V24: =SUM(D24:U24) -> 0
B25: SUELDO + ASIG FAM | D25: =6000+113 -> 6113 | E25: =4000+113 -> 4113 | F25: 3360 | G25: =6000+113 -> 6113 | H25: =4000+113 -> 4113 | I25: 2500 | J25: 3000 | K25: 2800 | L25: 2800 | M25: 2100 | N25: 2500 | O25: 2500 | P25: 2500 | Q25: 2200 | R25: 2000 | S25: 2000 | T25: 2613 | U25: 2313 | V25: =SUM(D25:U25) -> 55638
B26: BONO | F26: 640 | M26: 800 | V26: =SUM(D26:U26) -> 1440
B27: MOVILIDAD | D27: 55 | E27: 45 | F27: 90 | H27: 90 | J27: 90 | U27: 100 | V27: =SUM(D27:U27) -> 470
V28: =SUM(D28:U28) -> 0
B29: MAYO | V29: =SUM(D29:U29) -> 0
B30: SUELDO + ASIG FAM | D30: 6613 | E30: 4113 | F30: 3600 | G30: 6613 | H30: 4113 | I30: 2600 | J30: 3000 | K30: 3200 | L30: 2800 | M30: 2800 | N30: 2800 | O30: 2800 | P30: 2500 | Q30: 2500 | R30: 2500 | S30: 2500 | T30: 2613 | U30: 2313 | V30: =SUM(D30:U30) -> 59978
B31: BONO | F31: 640 | M31: 800 | V31: =SUM(D31:U31) -> 1440
B32: MOVILIDAD | D32: 100 | E32: 100 | F32: 76.190476 | J32: 100 | U32: 85.61 | V32: =SUM(D32:U32) -> 461.80048
B33: HORAS EXTRAS | V33: =SUM(D33:U33) -> 0
V34: =SUM(D34:U34) -> 0
B35: JUNIO | V35: =SUM(D35:U35) -> 0
B36: SUELDO + ASIG FAM | D36: 6613 | E36: 4113 | F36: 3600 | G36: 6613 | H36: 4113 | I36: 2600 | J36: 3000 | K36: 3200 | L36: 2800 | M36: 2800 | N36: 2800 | O36: 2800 | P36: 2500 | Q36: 2500 | R36: 2500 | S36: 2500 | T36: 2613 | U36: 2313 | V36: =SUM(D36:U36) -> 59978
B37: BONO | F37: 640 | M37: 800 | V37: =SUM(D37:U37) -> 1440
B38: MOVILIDAD | D38: 100 | E38: 100 | F38: 100 | J38: 100 | U38: 100 | V38: =SUM(D38:U38) -> 500
B39: HORAS EXTRAS | H39: =HH.EE!I3 -> 1406.5603 | N39: =HH.EE!I8 -> 1102.5 | R39: 792.06 | S39: 1278.13 | V39: =SUM(D39:U39) -> 4579.2503
V40: =SUM(D40:U40) -> 0
B41: JULIO | V41: =SUM(D41:U41) -> 0
B42: SUELDO + ASIG FAM | V42: =SUM(D42:U42) -> 0
B43: MOVILIDAD | V43: =SUM(D43:U43) -> 0
B44: GRATIFICACION JULIO | V44: =SUM(D44:U44) -> 0
V45: =SUM(D45:U45) -> 0
B46: AGOSTO | V46: =SUM(D46:U46) -> 0
B47: SUELDO + ASIG FAM | V47: =SUM(D47:U47) -> 0
B48: MOVILIDAD | V48: =SUM(D48:U48) -> 0
V49: =SUM(D49:U49) -> 0
B50: SEPTIEMBRE | V50: =SUM(D50:U50) -> 0
B51: SUELDO + ASIG FAM | V51: =SUM(D51:U51) -> 0
B52: MOVILIDAD | V52: =SUM(D52:U52) -> 0
B53: BONO | V53: =SUM(D53:U53) -> 0
B54: COMPRA DE VACACIONES | V54: =SUM(D54:U54) -> 0
V55: =SUM(D55:U55) -> 0
B56: OCTUBRE | V56: =SUM(D56:U56) -> 0
B57: SUELDO + ASIG FAM | V57: =SUM(D57:U57) -> 0
B58: MOVILIDAD | V58: =SUM(D58:U58) -> 0
B59: BONO | V59: =SUM(D59:U59) -> 0
V60: =SUM(D60:U60) -> 0
B61: NOVIEMBRE | V61: =SUM(D61:U61) -> 0
B62: SUELDO + ASIG FAM | V62: =SUM(D62:U62) -> 0
B63: MOVILIDAD | V63: =SUM(D63:U63) -> 0
B64: BONO | V64: =SUM(D64:U64) -> 0
B65: HORAS EXTRAS | V65: =SUM(D65:U65) -> 0
V66: =SUM(D66:U66) -> 0
B67: DICIEMBRE | V67: =SUM(D67:U67) -> 0
B68: SUELDO + ASIG FAM | V68: =SUM(D68:U68) -> 0
B69: GRATIFICACION | V69: =SUM(D69:U69) -> 0
B70: HORAS EXTRAS | V70: =SUM(D70:U70) -> 0
B71: BONO | V71: =SUM(D71:U71) -> 0
B72: MOVILIDAD | V72: =SUM(D72:U72) -> 0 | AB72: ingresos Glori
B73: VALE CONSUMO | V73: =SUM(D73:U73) -> 0
V74: =SUM(D74:U74) -> 0 | AB74: Anthia | AC74: =+(1130+113)*12 -> 14916 | AD74: sueldo
B75: INGRESOS ANTHIA - QUANTUM | V75: =SUM(D75:U75) -> 0 | AC75: =+(1243*1.09)*2 -> 2709.74 | AD75: Gratificacion
V76: =SUM(D76:U76) -> 0 | AC76: =SUM(AC74:AC75) -> 17625.74
B77: JULIO | V77: =SUM(D77:U77) -> 0
B78: SUELDO + ASIG FAM | D78: 6613 | E78: 4113 | F78: 3600 | G78: 6613 | H78: 4113 | I78: 2600 | J78: 3000 | K78: 3200 | L78: 2800 | M78: 2800 | N78: 2800 | O78: 2800 | P78: 2800 | Q78: 2500 | R78: 2500 | S78: 2500 | T78: 2613 | U78: 2313 | V78: =SUM(D78:U78) -> 60278 | AB78: Quantum | AC78: =+(3113*12) -> 37356 | AD78: sueldo
B79: BONO | F79: 640 | M79: 800 | V79: =SUM(D79:U79) -> 1440 | AC79: =+(3113*1.09)*2 -> 6786.34 | AD79: Gratificacion
B80: MOVILIDAD | D80: 100 | E80: 100 | F80: ='PLANILLA MENSUAL'!AA16 -> 89.473684 | H80: 100 | J80: 100 | U80: 100 | V80: =SUM(D80:U80) -> 589.47368 | AC80: =SUM(AC78:AC79) -> 44142.34
B81: HORAS EXTRAS | F81: 240 | H81: =HH.EE!I45 -> 0 | N81: =HH.EE!I50 -> 0 | T81: 327.17 | U81: 406.22 | V81: =SUM(D81:U81) -> 973.39
V82: =SUM(D82:U82) -> 0 | AC82: =+AC80+AC76 -> 61768.08
B83: AGOSTO | V83: =SUM(D83:U83) -> 0
B84: SUELDO + ASIG FAM | D84: 6613 | E84: 4113 | F84: 3600 | G84: 6613 | H84: 4113 | I84: 2600 | J84: 3000 | K84: 3200 | L84: 2800 | M84: 2800 | N84: 2800 | O84: 2800 | P84: 2800 | Q84: 2500 | R84: 2500 | S84: 2500 | T84: 2613 | U84: 2313 | V84: =SUM(D84:U84) -> 60278
B85: BONO | F85: 640 | M85: 800 | V85: =SUM(D85:U85) -> 1440
B86: MOVILIDAD | U86: 100 | V86: =SUM(D86:U86) -> 100
B87: HORAS EXTRAS | J87: 3824.88 | N87: =HH.EE!I57 -> 0 | V87: =SUM(D87:U87) -> 3824.88
V88: =SUM(D88:U88) -> 0
V89: =SUM(D89:U89) -> 0
V90: =SUM(D90:U90) -> 0
B91: TOTAL REMUNERACIONES | D91: =+(6113*4)+(6613*8)+7208.17+7208.17+D9+D15+D20+D21+D27+D32+D38+D80+D86 -> 92830.108 | E91: =+(4113*12)+4483.17+4483.17+E10+E15+E8+E9+E20+E27+E32+E38+E80+E86 -> 59234.011 | F91: =+((3360*4)+(640*12)+(3600*8))+4621.6+4621.6+F9+F15+F20+F27+F32+F38+F80+F81+F86 -> 60002.197 | G91: =+((6113*4)+(6613*8))+7208.17+7208.17+$AC$82 -> 153540.42 | H91: =+(4113*12)+4483.17+4483.17+H10+H9+H15+H20+H27+H39+H32+H37+H80+H86 -> 61436.586 | I91: =+((2500*4)+(2600*8))+2834+2834+I22 -> 42426.32 | J91: =+(3000*12)+3270+3270+J9+J15+J20+J21+J27+J32+J38+J80+J86+J87 -> 47336.496 | K91: =+((2800*4)+(3200*8))+3488+3488+K10 -> 43973.75 | L91: =+(2800*12)+3052+3052 -> 39704 | M91: =+((2100*4)+(2800*8))+3052+3052+M8+M14+M19+M26+M31+M37+M79+M85 -> 43304 | N91: =+((2500*4)+(2800*8))+3052+3052+N10+N39+N22 -> 46784.929 | O91: =+((2500*4)+(2800*8))+3052+3052+O22 -> 44808.738 | P91: =+((2500*6)+(2800*6))+3052+3052+P22 -> 44886.898 | Q91: =+((2200*4)+(2500*8))+2725+2725+Q22 -> 40702.021 | R91: =+((2000*4)+(2500*8))+2725+2725+R10+R22+R39 -> 40736.711 | S91: =+((2000*4)+(2500*8))+2725+2725+S10+S22+S39 -> 41470.762 | T91: =+((2000*4)+(2500*8))+2848.17+2848.17+T22+T81 -> 39553.09 | U91: =+((2113*4)+(2313*8))+2521.17+2521.17+U9+U15+U20+U22+U27+U32+U38+U81+U80+U86 -> 39109.85 | V91: =SUM(D91:U91) -> 981840.89 | X91: =2850*6+2850*1.09 -> 20206.5
B92: DEDUCCION 7UITS | D92: =5500*7 -> 38500 | E92: =5500*7 -> 38500 | F92: =5500*7 -> 38500 | G92: =5500*7 -> 38500 | H92: =5500*7 -> 38500 | I92: =5500*7 -> 38500 | J92: =5500*7 -> 38500 | K92: =5500*7 -> 38500 | ... U92: =5500*7 -> 38500 | V92: =SUM(D92:U92) -> 693000
B93: BASE IMPONIBLE | D93: =+D91-D92 -> 54330.108 | E93: =+E91-E92 -> 20734.011 | F93: =+F91-F92 -> 21502.197 | G93: =+G91-G92 -> 115040.42 | H93: =+H91-H92 -> 22936.586 | I93: =+I91-I92 -> 3926.32 | J93: =+J91-J92 -> 8836.4962 | K93: =+K91-K92 -> 5473.75 | ... U93: =+U91-U92 -> 609.85 | V93: =SUM(D93:U93) -> 288840.89
B96: CALCULO IR 5TA CATEG.
B97: Hasta 5 UIT S/ 27,500 (5500 UIT) | C97: 0.08 | D97: =+(5500*5)*$C$97 -> 2200 | E97: =+(E93)*$C$97 -> 1658.7209 | F97: =+(F93)*$C$97 -> 1720.1758 | G97: =+(5500*5)*$C$97 -> 2200 | H97: =+(H93)*$C$97 -> 1834.9269 | J97: =+(J93)*$C$97 -> 706.9197 | K97: =+(K93)*$C$97 -> 437.9 | L97: =+(L93)*$C$97 -> 96.32 | M97: =+(M93)*$C$97 -> 384.32 | N97: =+(N93)*$C$97 -> 662.79433 | O97: =+(O93)*$C$97 -> 504.69907 | P97: =+(P93)*$C$97 -> 510.95182 | Q97: =+(Q93)*$C$97 -> 176.16168 | ... U97: =+(U93)*$C$97 -> 48.788 | V97: =SUM(D97:N97) -> 11902.078
B98: Por el exceso de 5 UIT S/ 27,500 y hasta 20 UIT 110,000 | C98: 0.14 | D98: =+(+D93-27500)*$C$98 -> 3756.2151 | G98: =+(+G93-27500)*$C$98 -> 12255.659 | V98: =SUM(D98:N98) -> 16011.874
B99: Por el exceso de 20 UIT S/ 110,000 y hasta 35 UIT 192,500 | C99: 0.17 | G99: =+(+G93-110000)*$C$99 -> 856.8714 | V99: =SUM(D99:N99) -> 856.8714
D100: =SUM(D97:D99) -> 5956.2151 | E100: =SUM(E97:E99) -> 1658.7209 | F100: =SUM(F97:F99) -> 1720.1758 | G100: =SUM(G97:G99) -> 15312.53 | H100: =SUM(H97:H99) -> 1834.9269 | J100: =SUM(J97:J99) -> 706.9197 | K100: =SUM(K97:K99) -> 437.9 | L100: =SUM(L97:L99) -> 96.32 | M100: =SUM(M97:M99) -> 384.32 | N100: =SUM(N97:N99) -> 662.79433 | O100: =SUM(O97:O99) -> 504.69907 | P100: =SUM(P97:P99) -> 510.95182 | Q100: =SUM(Q97:Q99) -> 176.16168 | ... V100: =SUM(V97:V99) -> 28770.823
B101: RETENCIONES | V101: =SUM(D101:N101) -> 0
B102: ENERO | D102: 428.01624 | E102: 134.08547 | F102: 125.73333 | G102: 1145.2549 | H102: 140.88906 | I102: 0 | J102: 26.933333 | K102: 9.345 | L102: 8.0266667 | M102: 0 | N102: 0 | O102: 0 | V102: =SUM(D102:N102) -> 2018.284
B103: FEBRERO | D103: 426.80406 | E103: 135.36686 | F103: 131.50303 | G103: 1145.2549 | H103: 141.84663 | I103: 0 | J103: 28.027706 | K103: 9.345 | L103: 8.0266667 | M103: 19.069091 | V103: =SUM(D103:N103) -> 2045.2439
...

Sheet SEGURO PACIFICO
C1: SEGURO LA POSITIVA
C3: Aporte mensuales
C4: de 15 a 44 años hombres | D4: 327 | E4: Se modifico apartir del 01.01.19
C5: de 15 a 44 años mujeres | D5: 213
I8: PORCENTAJES | K8: SALDO POR DESCONTAR AL TRAB | L8: INPROCESS
I9: 0.3 | J9: 0.5
B10: Nº | C10: APELLIDOS Y NOMBRES | D10: DNI Nº | E10: Nº poliza | F10: FECHA DE NAC. | G10: FECHA DE INGRESO | H10: REMUNERACION | I10: 0 a 12 meses | J10: de 13 a 24 meses | O10: ASUME INPROCESS
M11: =+L11 -> 0 | N11: =+M11*0.18 -> 0 | O11: =+N11+M11 -> 0 | P11: =+K11+K13+K14 -> 0 | Q11: =+P11+O11 -> 0
B12: 1 | C12: GIOVANNA RAQUEL MARTINEZ CASTILLO | D12: 9594953 | E12: 611220200 | F12: 26364 | G12: 41548 | H12: 5085 | J12: =+$D$4*$J$9 -> 163.5 | K12: =+$D$4-J12 -> 163.5 | L12: =+J12/1.18 -> 138.55932 | M12: =+L12 -> 138.55932 | N12: =+M12*0.18 -> 24.940678 | O12: =+N12+M12 -> 163.5 | P12: =+K12 -> 163.5 | Q12: =+P12+O12 -> 327
I15: =SUMA(I11:I13) -> #NAME? | J15: =SUMA(J11:J14) -> #NAME? | K15: =SUMA(K11:K14) -> #NAME? | L15: =SUMA(L11:L14) -> #NAME? | O15: =SUMA(O11:O12) -> #NAME? | Q15: =SUMA(Q11:Q12) -> #NAME?
C18: SEGURO PACIFICO
C20: Aporte mensuales
C21: ORIHUELA AGUIRRE ERNESTO JULIO | D21: 660.34
C22: PORTOCARRERO TAFUR GLORI MAGRI | D22: 612.04
C23: GIOVANNA MARTINEZ | D23: 561.73
C24: ARACELLI PEREZ | D24: 351.5
C25: LADY OLAYA
I27: PORCENTAJES | K27: SALDO POR DESCONTAR AL TRAB | L27: INPROCESS
I28: 0.2 | J28: 0.5
B29: Nº | C29: APELLIDOS Y NOMBRES | D29: DNI Nº | E29: Nº poliza | F29: FECHA DE NAC. | G29: FECHA DE INGRESO | H29: REMUNERACION | I29: 0 a 12 meses | J29: de 13 a 24 meses | O29: ASUME INPROCESS
B30: 1 | C30: ORIHUELA AGUIRRE ERNESTO JULIO | D30: 10305226 | E30: 13481668 | F30: 27747 | G30: 35462 | H30: 10000 | J30: =+D21/2 -> 330.17 | K30: =+D21-J30 -> 330.17 | L30: =+J30/1.18 -> 279.80508 | M30: =+L30 -> 279.80508 | N30: =+M30*0.18 -> 50.364915 | O30: =+N30+M30 -> 330.17 | P30: =+D21-O30 -> 330.17 | Q30: =+P30+O30 -> 660.34
B31: 2 | C31: MARTINEZ CASTILLO GIOVANNA | D31: 9594953 | E31: 16647534 | F31: 26364 | G31: 41548 | J31: =+D23/2 -> 280.865 | K31: =+D23-J31 -> 280.865 | L31: =+J31/1.18 -> 238.02119 | M31: =+L31 -> 238.02119 | N31: =+M31*0.18 -> 42.843814 | O31: =+N31+M31 -> 280.865 | P31: =+D23-O31 -> 280.865 | Q31: =+P31+O31 -> 561.73
B32: 3 | C32: PEREZ CAJAHUANCA ARACELLI | D32: 44425022 | E32: 16647538 | F32: 31996 | G32: 42917 | J32: =+D24/2 -> 175.75 | K32: =+D24-J32 -> 175.75 | L32: =+J32/1.18 -> 148.94068 | M32: =+L32 -> 148.94068 | N32: =+M32*0.18 -> 26.809322 | O32: =+N32+M32 -> 175.75 | P32: =+D24-O32 -> 175.75 | Q32: =+P32+O32 -> 351.5
B33: 4 | C33: PORTOCARRERO TAFUR GLORI MAGRI | D33: 43172155 | E33: 26350 | F33: 31249 | G33: 42948 | J33: =+D22/2 -> 306.02 | K33: =+D22-J33 -> 306.02 | L33: =+J33/1.18 -> 259.33898 | M33: =+L33 -> 259.33898 | N33: =+M33*0.18 -> 46.681017 | O33: =+N33+M33 -> 306.02 | P33: =+D22-O33 -> 306.02 | Q33: =+P33+O33 -> 612.04
M34: =+L34 -> 0 | N34: =+M34*0.18 -> 0 | O34: =+N34+M34 -> 0
I35: =SUM(I30:I33) -> 0 | J35: =SUM(J30:J33) -> 1092.805 | K35: =SUM(K30:K33) -> 1092.805 | L35: =SUM(L30:L33) -> 926.10593 | O35: =SUM(O30:O33) -> 1092.805 | P35: =SUM(P30:P33) -> 1092.805 | Q35: =SUM(Q30:Q33) -> 2185.61
C41: SEGURO PACIFICO
C43: Aporte mensuales
C44: ORIHUELA AGUIRRE ERNESTO JULIO | D44: =605.94/1.18 -> 513.50847
C45: PORTOCARRERO TAFUR GLORI MAGRI | D45: =612.04/1.18 -> 518.67797
C46: GIOVANNA MARTINEZ | D46: =548/ 1.18 -> 464.40678
C47: ARACELLI PEREZ | D47: =351.5/1.18 -> 297.88136
I50: PORCENTAJES | K50: SALDO POR DESCONTAR AL TRAB | L50: INPROCESS | M50: TOTAL FACTURACION
I51: 0.2 | J51: 0.5
B52: Nº | C52: APELLIDOS Y NOMBRES | D52: DNI Nº | E52: Nº poliza | F52: FECHA DE NAC. | G52: FECHA DE INGRESO | H52: REMUNERACION | I52: 0 a 12 meses | J52: de 13 a 24 meses
B53: 1 | C53: ORIHUELA AGUIRRE ERNESTO JULIO | D53: 10305226 | E53: 13481668 | F53: 27747 | G53: 35462 | H53: 10000 | J53: =+D44/2 -> 256.75424 | K53: =+D44-J53 -> 256.75424 | L53: =605.93-K53 -> 349.17576 | M53: =+L53+K53 -> 605.93
B54: 2 | C54: MARTINEZ CASTILLO GIOVANNA | D54: 9594953 | E54: 16647534 | F54: 26364 | G54: 41548 | J54: =+D46/2 -> 232.20339 | K54: =+D46-J54 -> 232.20339 | L54: =548-K54 -> 315.79661 | M54: =+L54+K54 -> 548
B55: 3 | C55: PEREZ CAJAHUANCA ARACELLI | D55: 44425022 | E55: 16647538 | F55: 31996 | G55: 42917 | J55: =+D47/2 -> 148.94068 | K55: =+D47-J55 -> 148.94068 | L55: =351.5-K55 -> 202.55932 | M55: =+L55+K55 -> 351.5
B56: 4 | C56: PORTOCARRERO TAFUR GLORI MAGRI | D56: 43172155 | E56: 26350 | F56: 31249 | G56: 42948 | J56: =+D45/2 -> 259.33898 | K56: =+D45-J56 -> 259.33898 | L56: =612.304-K56 -> 352.96502 | M56: =+L56+K56 -> 612.304
M57: =+L57 -> 0 | N57: =+M57*0.18 -> 0
I58: =SUM(I53:I56) -> 0 | J58: =SUM(J53:J56) -> 897.23729 | K58: =SUM(K53:K56) -> 897.23729 | L58: =SUM(L53:L56) -> 1220.4967 | M58: =SUM(M53:M56) -> 2117.734

Sheet VACACIONES
B2: No | D2: año 2026 | P2: TOTAL | Q2: PROMEDIO COMISIONES
C3: APELLIDOS Y NOMBRES | D3: ENERO | E3: FEBRERO | F3: MARZO | G3: ABRIL | H3: MAYO | I3: JUNIO | J3: JULIO | K3: AGOSTO | L3: SETIEMBRE | M3: OCTUBRE | N3: NOVIEMBRE | O3: DICIEMBRE | R3: DIA | S3: VACACIONES | T3: TOTAL
B4: 1 | C4: ECHEVARRIA SOTO JORGE LUIS | D4: 9122.3397 | E4: 6019.6636 | F4: 8538.4969 | G4: 12937.093 | H4: 8462.9701 | I4: 8965.188 | J4: 12745.128 | P4: =SUM(E4:O4) -> 57668.54 | Q4: =+P4/6 -> 9611.4233 | R4: =Q4/30 -> 320.38078 | S4: 1 | T4: =S4*R4 -> 320.38078
B5: =+B4+1 -> 2 | C5: QUEVEDO SALAS LUIS ALBERTO | D5: 2501.7108 | E5: 2599.7564 | F5: 3287.0806 | G5: 2509.8714 | H5: 3359.019 | I5: 4331.4263 | J5: 1771.0376 | P5: =SUM(D5:O5) -> 20359.902 | Q5: =+P5/6 -> 3393.317 | R5: =Q5/30 -> 113.11057 | S5: 14 | T5: =S5*R5 -> 1583.5479
B6: =+B5+1 -> 3 | C6: ESTRADA SANTOS JUAN MIGUEL | D6: 1375.3927 | E6: 2137.4428 | F6: 1953.9544 | G6: 1486.9737 | H6: 1343.5632 | I6: 1994.6996 | J6: 2048.7845 | P6: =SUM(E6:O6) -> 10965.418 | Q6: =+P6/6 -> 1827.5697 | R6: =Q6/30 -> 60.91899 | S6: 15 | T6: =S6*R6 -> 913.78485 | W6: =2913/30*15 -> 1456.5
B7: =+B6+1 -> 4 | C7: ERNESTO ORIHUELA AGUIRRE | D7: 5568.2823 | E7: 4483.2372 | F7: 6098.9263 | G7: 9240.781 | H7: 6044.9787 | I7: 6403.7057 | J7: 7965.7048 | P7: =SUM(D7:O7) -> 45805.616 | Q7: =+P7/6 -> 7634.2693 | R7: =Q7/30 -> 254.47564 | S7: 0 | T7: =S7*R7 -> 0
B8: =+B7+1 -> 5 | C8: SICCHA ARCE LUIS FRANCISCO | D8: 404.14905 | E8: 749.2803 | F8: 531.69465 | G8: 3286.2737 | H8: 700.75905 | I8: 1556.8993 | J8: 600.18255 | P8: =SUM(D8:O8) -> 7829.2386 | Q8: =+P8/6 -> 1304.8731 | R8: =Q8/30 -> 43.49577 | S8: 0 | T8: =S8*R8 -> 0
B9: =+B8+1 -> 6 | C9: AREVALO VELA CESAR ANTONIO | D9: 2429.1964 | E9: 842.6241 | F9: 846.33225 | G9: 2406.4389 | H9: 1799.1559 | I9: 662.7648 | J9: 1891.5045 | P9: =SUM(D9:O9) -> 10878.017 | Q9: =+P9/6 -> 1813.0028 | R9: =Q9/30 -> 60.433427 | S9: 0 | T9: =S9*R9 -> 0
B10: =+B9+1 -> 7 | C10: ESTACIO CAYETANO FRANK BRIAN | D10: 872.05845 | E10: 1100.9444 | F10: 3369.7662 | G10: 937.3611 | H10: 1449.1908 | I10: 1482.3352 | J10: 3142.0137 | P10: =SUM(D10:O10) -> 12353.67 | Q10: =+P10/6 -> 2058.945 | R10: =Q10/30 -> 68.6315 | S10: 7 | T10: =S10*R10 -> 480.4205
B11: 8 | C11: RICRA DAVALOS GIUSSEPPE RENATO | I11: 887.808 | J11: 1180.9678 | P11: =SUM(D11:O11) -> 2068.7758 | Q11: =+P11/6 -> 344.79597 | R11: =Q11/30 -> 11.493199 | S11: 0 | T11: =S11*R11 -> 0
J12: 72.72075 | R12: =Q12/30 -> 0
D13: =SUM(D4:D11) -> 22273.129 | E13: =SUM(E4:E11) -> 17932.949 | F13: =SUM(F4:F11) -> 24626.251 | G13: =SUM(G4:G11) -> 32804.793 | H13: =SUM(H4:H11) -> 23159.637 | I13: =SUM(I4:I11) -> 26284.827 | J13: =SUM(J4:J11) -> 31345.323 | K13: =SUM(K4:K11) -> 0 | ... Q13: =SUM(Q4:Q11) -> 27988.196 | T13: =SUM(T4:T11) -> 3298.1341

Sheet HT. EPS
A1: CALCULO DEL 2.25%
A3: NOMBRE DE LA EMPRESA: | B3: INDUSTRIAL PROCESS SRL - IN PROCESS SRL
A4: FECHA: | B4: 45771
A5: ASESOR COMERCIAL: | B5: CAROL CUBA
A7: Composición de Grupo
A8: Titular Solo | B8: 8 | C8: =+B8+B9+B10+B11+B12+B13 -> 10
A9: Titular con 1 Dependiente | E9: DH: CONYUGE, CONVIVIENTE CON UNION DE HECHOS E HIJOS HASTA LOS 18 AÑOS
A10: Titular con 2 Dependientes | B10: 1
A11: Titular con 3 Dependientes | B11: 1
A12: Titular con 4 Dependientes | B12: 0
A13: Titular con 5 Dependientes
A14: Hijos mayores de 18 años
G15: ESSALUD MENSUAL | I15: =SUMIF('PLANILLA MENSUAL'!BP12:BP67,"EPS",'PLANILLA MENSUAL'!BN12:BN67) -> 5636.9956 | J15: 5262.91 | K15: =+I15-J15 -> 374.08561
A16: Según población afiliada a la fecha | I16: =+I14*9% -> 0
A17: N° Total de Afiliados | B17: 10 | C17: total de afiliados | E17: TITULARES | G17: ESSALUD ANUAL | I17: =+I15*12 -> 67643.947
A18: Essalud Anual | B18: =+I17 -> 67643.947
A19: Credito Anual | B19: =B18*25% -> 16910.987
A20: Credito Mensual | B20: =B19/12 -> 1409.2489
A21: Credito x Afiliado | B21: =B20/B17 -> 140.92489 | C21: credito 2.25
B23: Facturación | G23: Costo sin IGV | L23: CREDITO A FAVOR DEL TRABAJADOR | M23: Descuento Trab.
A25: 10 a mas afiliados
B26: BASE PEAS | C26: BASE ESENCIAL | D26: BASE PLUS | E26: ADICIONAL 1 | F26: ADICIONAL 2 | G26: BASE PEAS | H26: BASE ESENCIAL | I26: BASE PLUS | J26: ADICIONAL 1 | K26: ADICIONAL 2 | L26: POR PERSONA | M26: BASE PEAS | N26: BASE ESENCIAL | O26: BASE PLUS | P26: ADICIONAL 1 | Q26: ADICIONAL 2
A28: Titular | B28: 185 | C28: 263 | D28: 268 | E28: 339 | F28: 416 | G28: =+B28/1.18 -> 156.77966 | H28: =+C28/1.18 -> 222.88136 | I28: =+D28/1.18 -> 227.11864 | J28: =+E28/1.18 -> 287.28814 | K28: =+F28/1.18 -> 352.54237 | L28: =+B21 -> 140.92489 | M28: =+G28-L28 -> 15.854771 | N28: =+H28-L28 -> 81.956466 | O28: =+I28-L28 -> 86.193754 | P28: =+J28-L28 -> 146.36325 | Q28: =+K28-L28 -> 211.61748
A29: Titular mas 1 | B29: =+B28*2 -> 370 | C29: =+C28*2 -> 526 | D29: =+D28*2 -> 536 | E29: =+E28*2 -> 678 | F29: =+F28*2 -> 832 | G29: =+B29/1.18 -> 313.55932 | H29: =+C29/1.18 -> 445.76271 | I29: =+D29/1.18 -> 454.23729 | J29: =+E29/1.18 -> 574.57627 | K29: =+F29/1.18 -> 705.08475 | L29: =+L28*2 -> 281.84978 | M29: =+G29-L29 -> 31.709542 | N29: =+H29-L29 -> 163.91293 | O29: =+I29-L29 -> 172.38751 | P29: =+J29-L29 -> 292.72649 | Q29: =+K29-L29 -> 423.23497 | S29: =+L28*0.18 -> 25.36648 | T29: =+L28+S29 -> 166.29137
A30: Titular mas 2 | B30: =+B28*3 -> 555 | C30: =+C28*3 -> 789 | D30: =+D28*3 -> 804 | E30: =+E28*3 -> 1017 | F30: =+F28*3 -> 1248 | G30: =+B30/1.18 -> 470.33898 | H30: =+C30/1.18 -> 668.64407 | I30: =+D30/1.18 -> 681.35593 | J30: =+E30/1.18 -> 861.86441 | K30: =+F30/1.18 -> 1057.6271 | L30: =+L28*3 -> 422.77467 | M30: =+G30-L30 -> 47.564313 | N30: =+H30-L30 -> 245.8694 | O30: =+I30-L30 -> 258.58126 | P30: =+J30-L30 -> 439.08974 | Q30: =+K30-L30 -> 634.85245
A31: Titular mas 3 | B31: =+B28*4 -> 740 | C31: =+C28*4 -> 1052 | D31: =+D28*4 -> 1072 | E31: =+E28*4 -> 1356 | F31: =+F28*4 -> 1664 | G31: =+B31/1.18 -> 627.11864 | H31: =+C31/1.18 -> 891.52542 | I31: =+D31/1.18 -> 908.47458 | J31: =+E31/1.18 -> 1149.1525 | K31: =+F31/1.18 -> 1410.1695 | L31: =+L28*4 -> 563.69956 | M31: =+G31-L31 -> 63.419083 | N31: =+H31-L31 -> 327.82586 | O31: =+I31-L31 -> 344.77502 | P31: =+J31-L31 -> 585.45298 | Q31: =+K31-L31 -> 846.46993
A32: Titular mas 4 | B32: 740 | C32: 956 | D32: 976 | E32: 1356 | F32: 1664 | G32: =+B32/1.18 -> 627.11864 | H32: =+C32/1.18 -> 810.16949 | I32: =+D32/1.18 -> 827.11864 | J32: =+E32/1.18 -> 1149.1525 | K32: =+F32/1.18 -> 1410.1695 | L32: =+L28*5 -> 704.62445 | M32: =+G32-L32 -> -77.505807 | N32: =+H32-L32 -> 105.54504 | O32: =+I32-L32 -> 122.49419 | P32: =+J32-L32 -> 444.52809 | Q32: =+K32-L32 -> 705.54504
M33: BASE PEAS | N33: BASE ESENCIAL | O33: BASE PLUS | P33: ADICIONAL 1 | Q33: ADICIONAL 2
A34: Hijos mayores de 18 años | M34: 185 | N34: =+C28 -> 263 | O34: =+D28 -> 268 | P34: =+E28 -> 339 | Q34: =+F28 -> 416
A35: NOTA: CALCULO REALIZADO EN BASE A LA INFORMACION PROPORCIONADA POR LA EMPRESA. EL MONTO DEL CRÉDITO PODRÁ VARIAR SEGÚN EL NÚMERO REAL DE TITULARES, SU COMPOSICIÓN FAMILIAR Y EL APORTE A ESSALUD CORRESPONDIENTE.
K37: PLAN PLUS | M37: 01 TITULAR | O37: =+O28*0.7 -> 60.335628 | P37: 7 | Q37: =+O37*P37 -> 422.34939
B39: MONTO
A40: NOMBRES Y APELLIDOS | B40: AGOSTO | C40: JULIO DESCONTAR | D40: JUNIO A FAVOR | E40: TOTAL DE DESCUENTO | L40: ESTRADA | M40: 02 DEPENDIENTES | O40: =+I28*2 -> 454.23729
A41: ECHEVARRIA SOTO JORGE LUIS | B41: =O46 -> 514.57292 | C41: 0.73 | D41: -7.42 | E41: =SUM(B41:D41) -> 507.88292 | M41: TITULAR | O41: =+O28*0.7 -> 60.335628
A42: MONTOYA MEDRANO ANDREA BELEN JOSEPHINE | B42: =O37 -> 60.335628 | C42: 0.73 | D42: -7.42 | E42: =SUM(B42:D42) -> 53.645628 | O42: =SUM(O40:O41) -> 514.57292
A43: VERGARA BALDEON GEANNINA LIZBETH | B43: =O37 -> 60.335628 | C43: 0.73 | D43: -7.42 | E43: =SUM(B43:D43) -> 53.645628
A44: QUEVEDO SALAS LUIS ALBERTO | B44: =O37 -> 60.335628 | C44: 0.73 | D44: -7.42 | E44: =SUM(B44:D44) -> 53.645628 | L44: ECHEVARRIA | M44: 02 DEPENDIENTES | O44: =+I28*2 -> 454.23729
A45: LOBO QUISPE ELISA FIORELLA | B45: =O37 -> 60.335628 | C45: 0.73 | D45: -7.42 | E45: =SUM(B45:D45) -> 53.645628 | M45: TITULAR | O45: =+O28*0.7 -> 60.335628
A46: ESTRADA SANTOS JUAN MIGUEL | B46: =O42 -> 514.57292 | C46: 0.73 | D46: -7.42 | E46: =SUM(B46:D46) -> 507.88292 | O46: =SUM(O44:O45) -> 514.57292
A47: BALLLESTEROS DI SERI MARIA PAULA | B47: =O37 -> 60.335628 | C47: 0.73 | D47: -7.42 | E47: =SUM(B47:D47) -> 53.645628
A48: TUCTO PEREZ CESAR ANTONIO | B48: =O51 -> 57.369526 | C48: 0.73 | D48: -7.42 | E48: =SUM(B48:D48) -> 50.679526
A49: ELGUERA SOTO LUCERO ESTEFANIA | B49: =O37 -> 60.335628 | C49: 0.73 | D49: -7.42 | E49: =SUM(B49:D49) -> 53.645628
A50: ESTACIO CAYETANO FRANK BRIAN | B50: =O37 -> 60.335628 | C50: 0.73 | D50: -7.42 | E50: =SUM(B50:D50) -> 53.645628
E51: =SUM(E41:E50) -> 1441.9648 | F51: TOTAL DESCUENTO | K51: PLAN ESENCIAL | M51: 01 TITULAR | O51: =+N28*0.7 -> 57.369526 | P51: 1 | Q51: =+O51*P51 -> 57.369526
Q53: =+Q37+O42+O46+Q51 -> 1508.8648 | R53: TOTAL DESCUENTO
N59: 13 | O59: 268 | P59: =+N59*O59 -> 3484
N60: 1 | O60: 263 | P60: =+N60*O60 -> 263
P61: =SUM(P59:P60) -> 3747

Sheet TARDANZA
L2: 30 | O2: REMUNER.
D3: TOTAL | G3: TOTAL | I3: FALTAS | M3: IMPORTE | O3: AFECTA A
D4: INGRESOS | G4: INGRESOS | H4: DESCUENTOS POR TARDANZA | I4: INJUSTIFICADAS | J4: TOTAL | K4: DESCUENTO POR FALTA | L4: DESCUENTO POR TARDANZA | M4: A | O4: IMPUESTO | P4: 30
B5: Nº | C5: APELLIDOS Y NOMBRES | H5: MINUTOS | I5: PERMISO | J5: MINUTOS | M5: DESCONTAR
B6: 1 | C6: ORIHUELA AGUIRRE ERNESTO JULIO | D6: 13000 | I6: 0 | K6: 0 | L6: 0 | M6: 0
B7: =+B6+1 -> 2 | C7: MARTINEZ CASTILLO GIOVANNA RAQUEL | D7: 6500 | I7: 0 | J7: 0 | K7: 0 | L7: 0 | M7: 0
B8: =+B7+1 -> 3 | C8: SALVADOR ROJAS ELVIS ALFONSO | D8: 4000 | H8: 288 | J8: 0 | K8: 0 | L8: 82.26 | M8: 0
B9: =+B8+1 -> 4 | C9: LOLI RODRIGUEZ JANIO RICHARD | D9: 4000 | J9: 0 | K9: 0 | L9: 0 | M9: 0
B10: =+B9+1 -> 5 | C10: PEREZ CAJAHUANCA ARACELLI IRAIDA | D10: 3600 | H10: 324 | J10: 0 | K10: 0 | L10: 81 | M10: 0
B11: =+B10+1 -> 6 | C11: PORTOCARRERO TAFUR GLORI MAGRI | D11: 6500 | J11: 0 | K11: 0 | L11: 0 | M11: 0
B12: =+B11+1 -> 7 | C12: ECHEVARRIA SOTO JORGE LUIS | D12: 4500 | J12: 0 | K12: 0 | L12: 0 | M12: 0
B13: =+B12+1 -> 8 | C13: MONTOYA MEDRANO ANDREA BELEN JOSEPHINE | D13: 2800 | H13: 115 | J13: 0 | K13: 0 | L13: 22.361111 | M13: 0
B14: =+B13+1 -> 9 | C14: VERGARA BALDEON GEANNINA LIZBETH | D14: 2600 | H14: 76 | J14: 0 | K14: 0 | L14: 13.722222 | M14: 0
B15: =+B14+1 -> 10 | C15: CASTILLO ENCARNACION MANUEL LEONIDAS | D15: 2200 | H15: 119 | J15: 0 | K15: 0 | L15: 19.114375 | M15: 0
B16: =+B15+1 -> 11 | C16: QUEVEDO SALAS LUIS ALBERTO | D16: 3800 | J16: 0 | K16: 0 | L16: 0 | M16: 0
B17: =+B16+1 -> 12 | C17: PORTOCARRERO GOMEZ MARIA DEICY | D17: 1500 | J17: 0 | K17: 0 | L17: 0 | M17: 0
B18: =+B17+1 -> 13 | C18: LOBO QUISPE ELISA FIORELLA | D18: 3000 | H18: 346 | J18: 0 | K18: 0 | L18: 72.083333 | M18: 0
B19: =+B18+1 -> 14 | C19: RIOS HOLSEN JAIME JUNIOR | D19: 3200 | H19: 168 | J19: 0 | K19: 0 | L19: 37.333333 | M19: 0
B20: =+B19+1 -> 15 | C20: ESTRADA SANTOS JUAN MIGUEL | D20: 2800 | H20: 34 | J20: 0 | K20: 0 | L20: 6.8779167 | M20: 0
B21: =+B20+1 -> 16 | C21: PORTOCARRERO TAFUR MARIA LOIDI | D21: 1200 | J21: 0 | K21: 0 | L21: 0 | M21: 0
B22: =+B21+1 -> 17 | C22: ZEVALLOS DELGADO LUIS EDUARDO | D22: 2800 | H22: 41 | J22: 0 | K22: 0 | L22: 7.9722222 | M22: 0
B23: =+B22+1 -> 18 | C23: BALLLESTEROS DI SERI MARIA PAULA | D23: 2800 | H23: 44 | J23: 0 | K23: 0 | L23: 8.5555556 | M23: 0
B24: =+B23+1 -> 19 | C24: OCAMPO ORTEGA JEAN PAUL | D24: 2500 | H24: 111 | J24: 0 | K24: 0 | L24: 19.270833 | M24: 0
B25: =+B24+1 -> 20 | C25: OLIVOS SAAVEDRA LANDHERT ANDERSON | D25: 2500 | H25: 10 | J25: 0 | K25: 0 | L25: 1.7361111 | M25: 0
B26: =+B25+1 -> 21 | C26: YUPANQUI SAMANIEGO RENATO LUIS | D26: 2500 | H26: 82 | J26: 0 | K26: 0 | L26: 14.236111 | M26: 0
B27: =+B26+1 -> 22 | C27: TUCTO PEREZ CESAR ANTONIO | D27: 2800 | J27: 0 | K27: 0 | L27: 0 | M27: 0
B28: =+B27+1 -> 23 | C28: AREVALO VELA CESAR ANTONIO | D28: 2500 | H28: 60 | J28: 0 | K28: 0 | L28: 10.416667 | M28: 0
B29: =+B28+1 -> 24 | C29: SICCHA ARCE LUIS FRANCISCO | D29: 2500 | H29: 0 | J29: 0 | K29: 0 | L29: 0 | M29: 0
B30: =+B29+1 -> 25 | C30: JIMENEZ PUYEN LUIS ANTONIO | D30: 2800 | H30: 51 | J30: 0 | K30: 0 | L30: 9.9166667
B31: =+B30+1 -> 26 | C31: SILVA SANTISTEBAN RONAL JHUNIOR | D31: 2000 | H31: 35 | J31: 0 | K31: 0 | L31: 4.8611111
B32: =+B31+1 -> 27 | C32: ELGUERA SOTO LUCERO ESTEFANIA | D32: 2200 | H32: 33 | J32: 0 | K32: 0 | L32: 5.0416667
B33: =+B32+1 -> 28 | C33: ESTACIO CAYETANO FRANK BRIAN | D33: 2300 | H33: 13 | J33: 0 | K33: 0 | L33: 2.0763889
B34: =+B33+1 -> 29 | C34: SALAZAR VELASQUEZ HECTOR ALEXANDER | D34: 2500 | H34: 138 | J34: 0 | K34: 0 | L34: 25.04125
B35: =+B34+1 -> 30 | C35: RICRA DAVALOS GIUSSEPPE RENATO | D35: 1800 | H35: 228 | J35: 0 | K35: 0 | L35: 28.5 | O35: 0
B36: =+B35+1 -> 31 | C36: DIAZ ESCALANTE LUIS MIGUEL DAVID | D36: 1700 | H36: 78 | I36: 1 | J36: 0 | K36: 56.666667 | L36: 9.8204167
B37: =+B36+1 -> 32 | C37: HIPOLITO GUANILO ARNOLD JIMMY | D37: 1500 | H37: 11 | J37: 0 | K37: 0 | L37: 1.2321528
B38: =+B37+1 -> 33 | C38: MONTOYA MEDRANO VIVIAN MICHELE ALEXANDRA | D38: 2000 | H38: 86 | J38: 0 | K38: 0 | L38: 11.944444
B39: =+B38+1 -> 34 | C39: ALARCON OLIVERA AMBAR TIFFANY | D39: 2850 | H39: 340 | J39: 0 | K39: 0 | L39: 67.291667
B40: =+B39+1 -> 35 | C40: BURGA MUÑOZ HELDER ALEXANDER | D40: 1700 | H40: 11 | J40: 0 | K40: 0 | L40: 1.2986111
B41: =+B40+1 -> 36 | C41: RIVERA CORRALES JUAN EDUARDO | D41: 2800 | H41: 101 | J41: 0 | K41: 0 | L41: 19.638889
B42: =+B41+1 -> 37 | C42: MELO HUAMAN CARLOS MANUEL | D42: 1400 | H42: 28 | J42: 0 | K42: 0 | L42: 2.7222222
B43: =+B42+1 -> 38 | C43: FARFAN LAUREL CIELO CARMIN | D43: 2000 | H43: 56 | I43: 1 | J43: 0 | K43: 66.666667 | L43: 7.7777778
B44: =+B43+1 -> 39 | C44: ORTIZ PAREDES CESAR PAUL | D44: 1200 | H44: 27 | J44: 0 | K44: 0 | L44: 2.461875
B45: =+B44+1 -> 40 | C45: PAREDES CHAMOCHUMBI ANA GABRIEL | D45: 2000 | H45: 12 | J45: 0 | K45: 0 | L45: 1.6666667
B46: =+B45+1 -> 41 | C46: ARAGON LOPEZ EDUARDO ALEJANDRO | D46: 2500 | H46: 30 | J46: 0 | K46: 0 | L46: 5.44375
B47: =+B46+1 -> 42 | C47: PALOMINO DELGADO CESAR JAIRO | D47: 1600 | H47: 7 | I47: 1 | J47: 0 | K47: 53.333333 | L47: 0.77777778
B48: =+B47+1 -> 43 | C48: FRANCO LOPEZ EMERSON JOEL | D48: 1800 | H48: 27 | J48: 0 | K48: 0 | L48: 3.375
B49: =+B48+1 -> 44 | C49: GUZMAN LIVIA ALFREDO SANTIAGO | D49: 3500 | H49: 0 | J49: 1 | K49: 0 | L49: 0

Sheet SUBSIDIO
A1: COMISIONES
A2: 2025 | G2: 2026
A3: JULIO | B3: AGOSTO | C3: SETIEMBRE | D3: OCTUBRE | E3: NOVIEMBRE | F3: DICIEMBRE | G3: ENERO | H3: FEBRERO | I3: MARZO | J3: ABRIL | K3: MAYO | L3: JUNIO | M3: TOTAL
A4: 2142.75 | B4: 2792.4066 | C4: 1457.0637 | D4: 1122.8265 | E4: 2531.97 | F4: 829.3 | G4: 1375.3927 | H4: 2137.4428 | I4: 1953.9544 | J4: 1486.9737 | K4: 1343.5632 | L4: 1994.6996 | M4: =SUM(A4:L4) -> 21168.343 | N4: COMISIONES
A6: SUELDOS + ASIGNACION FAMILIAR
A7: 2025 | G7: 2026
A8: JULIO | B8: AGOSTO | C8: SETIEMBRE | D8: OCTUBRE | E8: NOVIEMBRE | F8: DICIEMBRE | G8: ENERO | H8: FEBRERO | I8: MARZO | J8: ABRIL | K8: MAYO | L8: JUNIO | M8: TOTAL
A9: 2913 | B9: 2913 | C9: 2913 | D9: 2913 | E9: 2913 | F9: 2913 | G9: 2913 | H9: 2913 | I9: 2913 | J9: 2913 | K9: 2913 | L9: 2913 | M9: =SUM(A9:L9) -> 34956
B13: COMISIONES | C13: SUELDO | D13: TOTAL | E13: DIARIO | F13: SUBSIDIO | G13: TOTAL
B14: =M4 -> 21168.343 | C14: =M9 -> 34956 | D14: =B14+C14 -> 56124.343 | E14: =D14/360 -> 155.90095 | F14: 5 | G14: =E14*F14 -> 779.50477
A21: ASEGURADO | C21: ESTRADA SANTOS JUAN MIGUEL
A22: FECHA DE INGRESO | C22: 46065
A23: INICIO DE SUBSIDIO | C23: 46205 | E23: FIN DE DESCANSO | G23: 46209 | I23: =G23-C23+1 -> 5 | J23: DIAS
A24: REMUNERACIÓN | C24: 2800
A25: ASIGNACIÓN FAMILIAR | C25: 113
A27: MES | B27: REMUNERACIÓN BASICA | C27: COMISIONES | D27: ASIGNACION FAMILIAR | E27: TOTAL
A28: 45839 | B28: 2800 | C28: 2142.75 | D28: 113 | E28: =SUM(B28:D28) -> 5055.75
A29: 45870 | B29: 2800 | C29: 2792.4066 | D29: 113 | E29: =SUM(B29:D29) -> 5705.4066
A30: 45901 | B30: 2800 | C30: 1457.0637 | D30: 113 | E30: =SUM(B30:D30) -> 4370.0637
A31: 45931 | B31: 2800 | C31: 1122.8265 | D31: 113 | E31: =SUM(B31:D31) -> 4035.8265
A32: 45962 | B32: 2800 | C32: 2531.97 | D32: 113 | E32: =SUM(B32:D32) -> 5444.97
A33: 45992 | B33: 2800 | C33: 829.3 | D33: 113 | E33: =SUM(B33:D33) -> 3742.3
A34: 46023 | B34: 2800 | C34: 1375.3927 | D34: 113 | E34: =SUM(B34:D34) -> 4288.3927
A35: 46054 | B35: 2800 | C35: 2137.4428 | D35: 113 | E35: =SUM(B35:D35) -> 5050.4428
A36: 46082 | B36: 2800 | C36: 1953.9544 | D36: 113 | E36: =SUM(B36:D36) -> 4866.9544
A37: 46113 | B37: 2800 | C37: 1486.9737 | D37: 113 | E37: =SUM(B37:D37) -> 4399.9737
A38: 46143 | B38: 2800 | C38: 1343.5632 | D38: 113 | E38: =SUM(B38:D38) -> 4256.5632
A39: 46174 | B39: 2800 | C39: 1994.6996 | D39: 113 | E39: =SUM(B39:D39) -> 4907.6996
B40: =SUM(B28:B39) -> 33600 | E40: =SUM(E28:E39) -> 56124.343
A43: TOTAL DE REMUNERACION | D43: =E40 -> 56124.343
A44: DIAS DEL AÑO | D44: 360
A45: SUBSIDIO DIARIO | D45: =D43/D44 -> 155.90095
A46: DIAS A SUBSIDIAR | D46: =I23 -> 5
A47: TOTAL DE SUBSICIO POR ENFERMEDAD | D47: =D46*D45 -> 779.50477 | E47: =D47 -> 779.50477

Sheet SEGURO VIDA LEY
A1: 1 | B1: 2 | H1: 6 | K1: 14
A3: R.U.C.: 20514706302
B8: TRABAJADOR | H8: DATOS DEL PERSONAL
A9: N° | B9: APELLIDOS | D9: FECHA | E9: FECHA | F9: FECHA | H9: AFP | K9: REMUNER.
B10: PATERNO | C10: DNI, CE | D10: DE | E10: DE | F10: DE | G10: CARGO | H10: Y | I10: SUELDO BASE | J10: ASIG FAM | K10: PERCIBIDA | L10: SUELDO | M10: PLANILLA | N10: TASA | O10: PRIMA
D11: NACIMIENTO | E11: INGRESO | F11: CESE | H11: ONP | L11: MENSUAL | M11: PERIODO | N11: % | O11: NETA | P11: MENSUAL
A12: =+A11+1 -> 1 | B12: AREVALO ILATOMA ALBERTO | C12: 47291951 | D12: 33557 | E12: 44896 | G12: ASISTENTE CONTABLE | H12: PROFUTURO | I12: 2500 | K12: 2500 | L12: =+J12+K12 -> 2500 | M12: =+L12*12 -> 30000 | N12: 0.15 | O12: =+M12*N12/100 -> 45
A13: =+A12+1 -> 2 | B13: AREVALO VELA CESAR ANTONIO | C13: 71114663 | D13: 36860 | E13: 45658 | G13: ASISTENTE VENTAS | H13: PRIMA | I13: 1800 | K13: 1800 | L13: =+J13+K13 -> 1800 | M13: =+L13*12 -> 21600 | N13: 0.15 | O13: =+M13*N13/100 -> 32.4
A14: =+A13+1 -> 3 | B14: BALLLESTEROS DI SERI MARIA PAULA | C14: 09877161 | D14: 26434 | E14: 45474 | G14: RECEPCIONISTA | H14: PRIMA | I14: 2050 | K14: 2050 | L14: =+J14+K14 -> 2050 | M14: =+L14*12 -> 24600 | N14: 0.39 | O14: =+M14*N14/100 -> 95.94
A15: =+A14+1 -> 4 | B15: CASTILLO ENCARNACION MANUEL LEONIDAS | C15: 44030334 | D15: 31334 | E15: 44321 | G15: REPARTO | H15: PRIMA | I15: 2000 | J15: 113 | K15: 2000 | L15: =+J15+K15 -> 2113 | M15: =+L15*12 -> 25356 | N15: 0.39 | O15: =+M15*N15/100 -> 98.8884
A16: =+A15+1 -> 5 | B16: CORREIA DUARTE ALEXANDER | C16: 001216312 | D16: 29546 | E16: 45691 | G16: PRODUCT MANAGER | H16: PRIMA | I16: 3200 | J16: 113 | K16: 3200 | L16: =+J16+K16 -> 3313 | M16: =+L16*12 -> 39756 | N16: 0.39 | O16: =+M16*N16/100 -> 155.0484
A17: =+A16+1 -> 6 | B17: ECHEVARRIA SOTO JORGE LUIS | C17: 45538866 | D17: 32147 | E17: 42955 | G17: COORDINADOR COMERC IAL | H17: ONP | I17: 4500 | K17: 10158.54 | L17: =+J17+K17 -> 10158.54 | M17: =+L17*12 -> 121902.48 | N17: 0.39 | O17: =+M17*N17/100 -> 475.41967
A18: =+A17+1 -> 7 | B18: ESTRADA SANTOS JUAN MIGUEL | C18: 25849757 | E18: 45341 | G18: INGENIERIA COMERCIAL | H18: INTEGRA | I18: 2800 | J18: 113 | K18: =3570.16-113 -> 3457.16 | L18: =+J18+K18 -> 3570.16 | M18: =+L18*12 -> 42841.92 | N18: 0.39 | O18: =+M18*N18/100 -> 167.08349
A19: =+A18+1 -> 8 | B19: JIMENEZ PUYEN LUIS ANTONIO | C19: 06802763 | D19: 28259 | E19: 45698 | G19: ESPECIALISTA EN GESTION Y SST | H19: ONP | I19: 2800 | K19: 2800 | L19: =+J19+K19 -> 2800 | M19: =+L19*12 -> 33600 | N19: 0.39 | O19: =+M19*N19/100 -> 131.04
A20: =+A19+1 -> 9 | B20: LOBO QUISPE ELISA FIORELLA | C20: 43415173 | D20: 31380 | E20: 45005 | G20: ASISTENTE ADMINISTRATIVO | H20: INTEGRA | I20: 3000 | K20: 3000 | L20: =+J20+K20 -> 3000 | M20: =+L20*12 -> 36000 | N20: 0.39 | O20: =+M20*N20/100 -> 140.4
A21: =+A20+1 -> 10 | B21: LOLI RODRIGUEZ JANIO RICHARD | C21: 41675364 | D21: 29556 | E21: 42513 | G21: COORDINADOR DE SOPORTE TECNICO | H21: INTEGRA | I21: 4000 | J21: 113 | K21: 4000 | L21: =+J21+K21 -> 4113 | M21: =+L21*12 -> 49356 | N21: 0.39 | O21: =+M21*N21/100 -> 192.4884
A22: =+A21+1 -> 11 | B22: LUGO YAGUARACUTO JORGE DEYVIS | C22: 003488571 | D22: 31311 | E22: 45512 | G22: ASISTENTE DE ALMACEN | H22: INTEGRA | I22: 1600 | J22: 113 | K22: 1600 | L22: =+J22+K22 -> 1713 | M22: =+L22*12 -> 20556 | N22: 0.39 | O22: =+M22*N22/100 -> 80.1684
A23: =+A22+1 -> 12 | B23: MARTINEZ CASTILLO GIOVANNA RAQUEL | C23: 9594953 | D23: 26364 | E23: 41548 | G23: JEFE DE ADMINISTRACION | H23: PROFUTURO | I23: 6000 | J23: 113 | K23: 6000 | L23: =+J23+K23 -> 6113 | M23: =+L23*12 -> 73356 | N23: 0.39 | O23: =+M23*N23/100 -> 286.0884
A24: =+A23+1 -> 13 | B24: MONTOYA MEDRANO ANDREA BELEN JOSEPHINE | C24: 71127068 | D24: 34500 | E24: 43045 | G24: ASISTENTE DE GERENCIA | H24: ONP | I24: 2100 | K24: 2100 | L24: =+J24+K24 -> 2100 | M24: =+L24*12 -> 25200 | N24: 0.15 | O24: =+M24*N24/100 -> 37.8
A25: =+A24+1 -> 14 | B25: OCAMPO ORTEGA JEAN PAUL | C25: 73231901 | D25: 34632 | E25: 45537 | G25: ASISTENTE DE SOPORTE TECNICO | H25: PRIMA | I25: 1700 | K25: 1700 | L25: =+J25+K25 -> 1700 | M25: =+L25*12 -> 20400 | N25: 0.15 | O25: =+M25*N25/100 -> 30.6
A26: =+A25+1 -> 15 | B26: OLIVOS SAAVEDRA LANDHERT ANDERSON | C26: 73885455 | D26: 35803 | E26: 45581 | G26: ASISTENTE DE SOPORTE TECNICO | H26: INTEGRA | I26: 2000 | K26: 1800 | L26: =+J26+K26 -> 1800 | M26: =+L26*12 -> 21600 | N26: 0.15 | O26: =+M26*N26/100 -> 32.4
A27: =+A26+1 -> 16 | B27: ORDOÑEZ JULCA JESUS ORLANDO | C27: 47442636 | D27: 33567 | E27: 45691 | G27: PRODUCT MANAGER | H27: INTEGRA | I27: 3200 | K27: 3200 | L27: =+J27+K27 -> 3200 | M27: =+L27*12 -> 38400 | N27: 0.15 | O27: =+M27*N27/100 -> 57.6
A28: 1 | B28: ORIHUELA AGUIRRE ERNESTO JULIO | C28: 10305226 | D28: 27747 | E28: 39114 | G28: GERENTE GENERAL | H28: INTEGRA | I28: 12000 | J28: 113 | K28: =12027.91-113 -> 11914.91 | L28: =+J28+K28 -> 12027.91 | M28: =+L28*12 -> 144334.92 | N28: 0.39 | O28: =+M28*N28/100 -> 562.90619
A29: =+A28+1 -> 2 | B29: PEREZ CAJAHUANCA ARACELLI IRAIDA | C29: 44425022 | D29: 31996 | E29: 42917 | G29: COORDINADOR DE LOGISTICA | H29: INTEGRA | I29: 3360 | K29: 3360 | L29: =+J29+K29 -> 3360 | M29: =+L29*12 -> 40320 | N29: 0.39 | O29: =+M29*N29/100 -> 157.248
A30: =+A29+1 -> 3 | B30: PORTOCARRERO GOMEZ MARIA DEICY | C30: 42544684 | D30: 30874 | E30: 44697 | G30: LIMPIEZA | H30: PROFUTURO | I30: 1200 | J30: 113 | K30: 1200 | L30: =+J30+K30 -> 1313 | M30: =+L30*12 -> 15756 | N30: 0.39 | O30: =+M30*N30/100 -> 61.4484
A31: =+A30+1 -> 4 | B31: PORTOCARRERO TAFUR GLORI MAGRI | C31: 43172155 | D31: 31249 | E31: 42948 | G31: JEFE DE MARKETING Y CALIDAD | H31: INTEGRA | I31: 6000 | J31: 113 | K31: 6000 | L31: =+J31+K31 -> 6113 | M31: =+L31*12 -> 73356 | N31: 0.39 | O31: =+M31*N31/100 -> 286.0884
A32: =+A31+1 -> 5 | B32: PORTOCARRERO TAFUR MARIA LOIDI | C32: 45654429 | D32: 30383 | E32: 45398 | G32: AUXILIAR DE ALMACEN | H32: ONP | I32: 1130 | K32: 1130 | L32: =+J32+K32 -> 1130 | M32: =+L32*12 -> 13560 | N32: 0.39 | O32: =+M32*N32/100 -> 52.884
A33: =+A32+1 -> 6 | B33: QUEVEDO SALAS LUIS ALBERTO | C33: 07882846 | D33: 26945 | E33: 44593 | G33: EJECUTIVO COMERCIAL | H33: PRIMA | I33: 3500 | J33: 113 | K33: =6895.21-113 -> 6782.21 | L33: =+J33+K33 -> 6895.21 | M33: =+L33*12 -> 82742.52 | N33: 0.39 | O33: =+M33*N33/100 -> 322.69583
A34: =+A33+1 -> 7 | B34: RAMOS ESPEJO JHONN MIGUEL | C34: 43831490 | D34: 31666 | E34: 45628 | G34: SUPERVISOR DE ALMACEN | H34: HABITAT | I34: 2800 | K34: 2800 | L34: =+J34+K34 -> 2800 | M34: =+L34*12 -> 33600 | N34: 0.39 | O34: =+M34*N34/100 -> 131.04
A35: =+A34+1 -> 8 | B35: RIOS HOLSEN JAIME JUNIOR | C35: 48335342 | D35: 34355 | E35: 45307 | G35: ASISTENTE DE SOPORTE TECNICO | H35: HABITAT | I35: 2000 | K35: 2000 | L35: =+J35+K35 -> 2000 | M35: =+L35*12 -> 24000 | N35: 0.15 | O35: =+M35*N35/100 -> 36
A36: =+A35+1 -> 9 | B36: SALAZAR VELASQUEZ HECTOR ALEXANDER | C36: 41995632 | D36: 30308 | E36: 45446 | G36: AUXILIAR DE ALMACEN | H36: ONP | I36: 2000 | J36: 113 | K36: 2000 | L36: =+J36+K36 -> 2113 | M36: =+L36*12 -> 25356 | N36: 0.39 | O36: =+M36*N36/100 -> 98.8884
A37: =+A36+1 -> 10 | B37: SALCEDO RIVAS DANIEL ALONSO | C37: 42953954 | D37: 31117 | E37: 45398 | G37: ASISTENTE LOGISTICO | H37: INTEGRA | I37: 2500 | J37: 113 | K37: 2500 | L37: =+J37+K37 -> 2613 | M37: =+L37*12 -> 31356 | N37: 0.39 | O37: =+M37*N37/100 -> 122.2884
A38: =+A37+1 -> 11 | B38: SALVADOR ROJAS ELVIS ALFONSO | C38: 46335654 | D38: 33029 | E38: 42327 | G38: SOPORTE TECNICO Y MANTENIMINENTO | H38: INTEGRA | I38: 3000 | J38: 113 | K38: 3000 | L38: =+J38+K38 -> 3113 | M38: =+L38*12 -> 37356 | N38: 0.15 | O38: =+M38*N38/100 -> 56.034
A39: =+A38+1 -> 12 | B39: SEGURA CHAVESTA CHRISTIAN GUILLERMO | C39: 72544254 | D39: 34906 | E39: 44972 | G39: ANALISTA DE PROYECTOS | H39: INTEGRA | I39: 2000 | K39: 2000 | L39: =+J39+K39 -> 2000 | M39: =+L39*12 -> 24000 | N39: 0.15 | O39: =+M39*N39/100 -> 36
A40: =+A39+1 -> 13 | B40: SICCHA ARCE LUIS FRANCISCO | C40: 73735818 | D40: 36161 | E40: 45689 | G40: EJECUTIVO COMERCIAL | H40: INTEGRA | I40: 2500 | K40: 2500 | L40: =+J40+K40 -> 2500 | M40: =+L40*12 -> 30000 | N40: 0.15 | O40: =+M40*N40/100 -> 45
A41: =+A40+1 -> 14 | B41: TUCTO PEREZ CESAR ANTONIO | C41: 46452115 | D41: 32383 | E41: 45658 | G41: ASISTENTE CONTABLE | H41: PRIMA | I41: 2400 | K41: 2400 | L41: =+J41+K41 -> 2400 | M41: =+L41*12 -> 28800 | N41: 0.15 | O41: =+M41*N41/100 -> 43.2
A42: =+A41+1 -> 15 | B42: VERGARA BALDEON GEANNINA LIZBETH | C42: 46497553 | D42: 33124 | E42: 44018 | G42: ESPECIALISTA EN MARKETING | H42: INTEGRA | I42: 2500 | K42: 2500 | L42: =+J42+K42 -> 2500 | M42: =+L42*12 -> 30000 | N42: 0.15 | O42: =+M42*N42/100 -> 45
A43: =+A42+1 -> 16 | B43: VIDAL MELO ALEX FERNANDO | C43: 70036224 | D43: 36115 | E43: 45306 | G43: EJECUTIVO COMERCIAL | H43: PRIMA | I43: 2000 | J43: 113 | K43: =2737.4-J43 -> 2624.4 | L43: =+J43+K43 -> 2737.4 | M43: =+L43*12 -> 32848.8 | N43: 0.15 | O43: =+M43*N43/100 -> 49.2732
A44: =+A43+1 -> 17 | B44: YUPANQUI SAMANIEGO RENATO LUIS | C44: 73952223 | D44: 10/09/200 | E44: 45627 | G44: ASISTENTE DE ALMACEN | H44: INTEGRA | I44: 2200 | K44: 2200 | L44: =+J44+K44 -> 2200 | M44: =+L44*12 -> 26400 | N44: 0.15 | O44: =+M44*N44/100 -> 39.6
A45: =+A44+1 -> 18 | B45: ZEVALLOS DELGADO LUIS EDUARDO | C45: 74450353 | D45: 34560 | E45: 45418 | G45: INGENIERIO TECNICO EN EL AREA DE VARIADORES | H45: INTEGRA | I45: 2000 | K45: 2000 | L45: =+J45+K45 -> 2000 | M45: =+L45*12 -> 24000 | N45: 0.15 | O45: =+M45*N45/100 -> 36
A46: =+A45+1 -> 19 | B46: TORRES VELA JOE RAMIRO | C46: 46544434 | D46: 33107 | E46: 45719 | G46: CHOFER | H46: PROFUTURO | I46: 1500 | K46: =50*29 -> 1450 | L46: =+J46+K46 -> 1450 | M46: =+L46*12 -> 17400 | O46: =+M46*N46/100 -> 0
A47: =+A46+1 -> 20 | B47: SILVA SANTISTEBAN RONAL JHUNIOR | C47: 48461873 | D47: 34304 | E47: 45719 | G47: TECNICO ELECTRICISTA | H47: INTEGRA | I47: 1700 | K47: 1700 | L47: =+J47+K47 -> 1700 | M47: =+L47*12 -> 20400 | O47: =+M47*N47/100 -> 0
K48: 2850 | L48: 2850 | M48: =+L48*12 -> 34200 | O48: =+M48*N48/100 -> 0
J50: =SUM(J12:J49) -> 1582 | K50: =SUM(K12:K49) -> 116277.22 | O50: =SUM(O12:O49) -> 4239.96
O52: 4239.96
O53: =+O52-O50 -> 2.4e-05

Sheet TRANSF

Sheet DIARIO
A1: INDUSTRIAL PROCESS
A3: COMPROBANTE
A4: Sub-Diario: P | C4: Moneda: MN
A5: Comprobante: 030001 | C5: Conversion: S
A6: Concepto: PROVISION PLANILLA MES ABRIL 2023 | C6: Tipo de Cambio: 3.829 | F6: Usuario: | G6: LTP
F7: IMPORTES | G7: IMPORTES
A8: Cuenta | B8: Descripción Cuenta | C8: Anexo | D8: Descripcion Anexo | E8: CC | F8: Debe | G8: Haber | H8: TD | I8: Nro. Doc. | J8: Fecha | K8: Glosa
A9: 62101001 | B9: SUELDOS | D9: ADM | E9: K0011 | F9: =+'[13]PLANILLA MENSUAL'!Q64 -> 9130 | G9: 0 | H9: 00 | I9: 003-2025 | J9: 45747 | K9: PROVISION PLANILLA MES MARZO 2025
A10: 62201001 | B10: ASIGNACION FAMILIAR | D10: ADM | E10: K0011 | F10: =+'[13]PLANILLA MENSUAL'!R64 -> 226 | G10: 0 | H10: 00 | I10: 003-2025 | J10: 45747 | K10: PROVISION PLANILLA MES MARZO 2025
A11: 62201007 | B11: PLANILLA MOVILIDAD | D11: ADM | E11: K0011 | F11: =+'[13]PLANILLA MENSUAL'!X64 -> 100 | G11: 0 | H11: 00 | I11: 003-2025 | J11: 45747 | K11: PROVISION PLANILLA MES MARZO 2025
A12: 62701001 | B12: REGIMEN DE PRESTACIONES DE SALUD | D12: ADM | E12: K0011 | F12: =+'[13]PLANILLA MENSUAL'!BI64 -> 842.04 | G12: 0 | H12: 00 | I12: 003-2025 | J12: 45747 | K12: PROVISION PLANILLA MES MARZO 2025
A14: 62101001 | B14: SUELDOS | D14: CONTA | E14: K0012 | F14: =+'[13]PLANILLA MENSUAL'!Q65 -> 8300 | G14: 0 | H14: 00 | I14: 003-2025 | J14: 45747 | K14: PROVISION PLANILLA MES MARZO 2025
A15: 62201007 | B15: PLANILLA MOVILIDAD | D15: CONTA | E15: K0012 | F15: =+'[13]PLANILLA MENSUAL'!X65 -> 100 | G15: 0 | H15: 00 | I15: 003-2025 | J15: 45747 | K15: PROVISION PLANILLA MES MARZO 2025
A16: 62701001 | B16: REGIMEN DE PRESTACIONES DE SALUD | D16: CONTA | E16: K0012 | F16: =+'[13]PLANILLA MENSUAL'!BI65 -> 747 | G16: 0 | H16: 00 | I16: 003-2025 | J16: 45747 | K16: PROVISION PLANILLA MES MARZO 2025
A18: 62101001 | B18: SUELDOS | D18: LOGISTICA | E18: K0013 | F18: =+'[13]PLANILLA MENSUAL'!Q66 -> 4960 | G18: 0 | H18: 00 | I18: 003-2025 | J18: 45747 | K18: PROVISION PLANILLA MES MARZO 2025
A19: 62201007 | B19: PLANILLA MOVILIDAD | D19: LOGISTICA | E19: K0013 | F19: =+'[13]PLANILLA MENSUAL'!X66 -> 76.190476 | G19: 0 | H19: 00 | I19: 003-2025 | J19: 45747 | K19: PROVISION PLANILLA MES MARZO 2025
A20: 62701001 | B20: REGIMEN DE PRESTACIONES DE SALUD | D20: LOGISTICA | E20: K0013 | F20: =+'[13]PLANILLA MENSUAL'!BI66 -> 579.6 | G20: 0 | H20: 00 | I20: 003-2025 | J20: 45747 | K20: PROVISION PLANILLA MES MARZO 2025
A22: 62101002 | B22: SUELDOS | D22: VENTAS | E22: K0021 | F22: =+'[13]PLANILLA MENSUAL'!Q68 -> 38800 | G22: 0 | H22: 00 | I22: 003-2025 | J22: 45747 | K22: PROVISION PLANILLA MES MARZO 2025
A23: 62201002 | B23: ASIGNACION FAMILIAR | D23: VENTAS | E23: K0021 | F23: =+'[13]PLANILLA MENSUAL'!R68 -> 452 | G23: 0 | H23: 00 | I23: 003-2025 | J23: 45747 | K23: PROVISION PLANILLA MES MARZO 2025
A24: 62102002 | B24: COMISIONES DEL PERIODO | D24: VENTAS | E24: K0021 | F24: =+'[13]PLANILLA MENSUAL'!S68 -> 23159.637 | G24: 0 | H24: 00 | I24: 003-2025 | J24: 45747 | K24: PROVISION PLANILLA MES MARZO 2025
A25: 62701002 | B25: REGIMEN DE PRESTACIONES DE SALUD | D25: VENTAS | E25: K0021 | F25: =+'[13]PLANILLA MENSUAL'!BI68 -> 5689.0473 | G25: 0 | H25: 00 | I25: 003-2025 | J25: 45747 | K25: PROVISION PLANILLA MES MARZO 2025
A27: 62101002 | B27: SUELDOS | D27: SOPORTE | E27: K0022 | F27: =+'[13]PLANILLA MENSUAL'!Q69 -> 19300 | G27: 0 | H27: 00 | I27: 003-2025 | J27: 45747 | K27: PROVISION PLANILLA MES MARZO 2025
A28: 62201002 | B28: ASIGNACION FAMILIAR | D28: SOPORTE | E28: K0022 | F28: =+'[13]PLANILLA MENSUAL'!R69 -> 339 | G28: 0 | H28: 00 | I28: 003-2025 | J28: 45747 | K28: PROVISION PLANILLA MES MARZO 2025
A29: 62101004 | B29: HORAS EXTRAS | D29: SOPORTE | E29: K0022 | F29: =+'[13]PLANILLA MENSUAL'!U69+'[13]PLANILLA MENSUAL'!V69 -> 0 | G29: 0 | H29: 00 | I29: 003-2025 | J29: 45747 | K29: PROVISION PLANILLA MES MARZO 2025
A30: 62201008 | B30: PLANILLA MOVILIDAD | D30: SOPORTE | E30: K0022 | F30: =+'[13]PLANILLA MENSUAL'!X69 -> 100 | G30: 0 | H30: 00 | I30: 003-2025 | J30: 45747 | K30: PROVISION PLANILLA MES MARZO 2025
A31: 62701002 | B31: REGIMEN DE PRESTACIONES DE SALUD | D31: SOPORTE | E31: K0022 | F31: =+'[13]PLANILLA MENSUAL'!BI69 -> 1767.51 | G31: 0 | H31: 00 | I31: 003-2025 | J31: 45747 | K31: PROVISION PLANILLA MES MARZO 2025
A33: 62101002 | B33: SUELDOS | D33: PROYECTO | E33: K0023 | F33: =+'[13]PLANILLA MENSUAL'!Q70 -> 3200 | G33: 0 | H33: 00 | I33: 003-2025 | J33: 45747 | K33: PROVISION PLANILLA MES MARZO 2025
A34: 62701002 | B34: REGIMEN DE PRESTACIONES DE SALUD | D34: PROYECTO | E34: K0023 | F34: =+'[13]PLANILLA MENSUAL'!BI70 -> 288 | G34: 0 | H34: 00 | I34: 003-2025 | J34: 45747 | K34: PROVISION PLANILLA MES MARZO 2025
A36: 62101002 | B36: SUELDOS | D36: MARKETING | E36: K0024 | F36: =+'[13]PLANILLA MENSUAL'!Q71 -> 12050 | G36: 0 | H36: 00 | I36: 003-2025 | J36: 45747 | K36: PROVISION PLANILLA MES MARZO 2025
A37: 62201002 | B37: ASIGNACION FAMILIAR | D37: MARKETING | E37: K0024 | F37: =+'[13]PLANILLA MENSUAL'!R71 -> 113 | G37: 0 | H37: 00 | I37: 003-2025 | J37: 45747 | K37: PROVISION PLANILLA MES MARZO 2025
A38: 62701002 | B38: REGIMEN DE PRESTACIONES DE SALUD | D38: MARKETING | E38: K0024 | F38: =+'[13]PLANILLA MENSUAL'!BI71 -> 1114.245 | G38: 0 | H38: 00 | I38: 003-2025 | J38: 45747 | K38: PROVISION PLANILLA MES MARZO 2025
A40: 62101002 | B40: SUELDOS | D40: ALMACEN | E40: K0025 | F40: =+'[13]PLANILLA MENSUAL'!Q72 -> 13006.967 | G40: 0 | H40: 00 | I40: 003-2025 | J40: 45747 | K40: PROVISION PLANILLA MES MARZO 2025
A41: 62201002 | B41: ASIGNACION FAMILIAR | D41: ALMACEN | E41: K0025 | F41: =+'[13]PLANILLA MENSUAL'!R72 -> 452 | G41: 0 | H41: 00 | I41: 003-2025 | J41: 45747 | K41: PROVISION PLANILLA MES MARZO 2025
A42: 62101004 | B42: HORAS EXTRAS | D42: ALMACEN | E42: K0025 | F42: =+'[13]PLANILLA MENSUAL'!U72+'[13]PLANILLA MENSUAL'!V72 -> 0 | G42: 0 | H42: 00 | I42: 003-2025 | J42: 45747 | K42: PROVISION PLANILLA MES MARZO 2025
A43: 62201008 | B43: PLANILLA MOVILIDAD | D43: ALMACEN | E43: K0025 | F43: =+'[13]PLANILLA MENSUAL'!X72 -> 100 | G43: 0 | H43: 00 | I43: 003-2025 | J43: 45747 | K43: PROVISION PLANILLA MES MARZO 2025
A44: 62701002 | B44: REGIMEN DE PRESTACIONES DE SALUD | D44: ALMACEN | E44: K0025 | F44: =+'[13]PLANILLA MENSUAL'!BI72 -> 1249.38 | G44: 0 | H44: 00 | I44: 003-2025 | J44: 45747 | K44: PROVISION PLANILLA MES MARZO 2025
A46: 14111001 | B46: PRESTAMOS DE PERSONAL EMPLEADOS M.N. | C46: 44030334 | D46: CASTILLO ENCARNACION MANUEL LEONIDAS | G46: =+'[13]PLANILLA MENSUAL'!AZ21 -> 500 | H46: 00 | I46: 14496 | J46: 45747 | K46: PROVISION PLANILLA MES MARZO 2025
A47: 14111001 | B47: PRESTAMOS DE PERSONAL EMPLEADOS M.N. | C47: 74450353 | D47: ZEVALLOS DELGADO LUIS EDUARDO | G47: =+'[13]PLANILLA MENSUAL'!AZ30 -> 500 | H47: 00 | I47: 012-2024 | J47: 45747 | K47: PROVISION PLANILLA MES MARZO 2025
A48: 14121001 | B48: ADELANTO DE REMUNERACION DE PERSONAL M.N | C48: 10305226 | D48: ORIHUELA AGUIRRE ERNESTO JULIO | G48: =+'[13]PLANILLA MENSUAL'!AY12 -> 10338.515 | H48: 00 | I48: 003-2025 | J48: 45747 | K48: PROVISION PLANILLA MES MARZO 2025
A49: 14121001 | B49: ADELANTO DE REMUNERACION DE PERSONAL M.N | C49: 09594953 | D49: MARTINEZ CASTILLO GIOVANNA RAQUEL | G49: =+'[13]PLANILLA MENSUAL'!AY13 -> 3565.9167 | H49: 00 | I49: 003-2025 | J49: 45747 | K49: PROVISION PLANILLA MES MARZO 2025
A50: 14121001 | B50: ADELANTO DE REMUNERACION DE PERSONAL M.N | C50: 46335654 | D50: SALVADOR ROJAS ELVIS ALFONSO | G50: =+'[13]PLANILLA MENSUAL'!AY14 -> 2410.1267 | H50: 00 | I50: 003-2025 | J50: 45747 | K50: PROVISION PLANILLA MES MARZO 2025
A51: 14121001 | B51: ADELANTO DE REMUNERACION DE PERSONAL M.N | C51: 41675364 | D51: LOLI RODRIGUEZ JANIO RICHARD | G51: =+'[13]PLANILLA MENSUAL'!AY15 -> 2399.25 | H51: 00 | I51: 003-2025 | J51: 45747 | K51: PROVISION PLANILLA MES MARZO 2025
A52: 14121001 | B52: ADELANTO DE REMUNERACION DE PERSONAL M.N | C52: 44425022 | D52: PEREZ CAJAHUANCA ARACELLI IRAIDA | G52: =+'[13]PLANILLA MENSUAL'!AY16 -> 2302.2222 | H52: 00 | I52: 003-2025 | J52: 45747 | K52: PROVISION PLANILLA MES MARZO 2025
A53: 14121001 | B53: ADELANTO DE REMUNERACION DE PERSONAL M.N | C53: 43172155 | D53: PORTOCARRERO TAFUR GLORI MAGRI | G53: =+'[13]PLANILLA MENSUAL'!AY17 -> 3565.9167 | H53: 00 | I53: 003-2025 | J53: 45747 | K53: PROVISION PLANILLA MES MARZO 2025
A54: 14121001 | B54: ADELANTO DE REMUNERACION DE PERSONAL M.N | C54: 45538866 | D54: ECHEVARRIA SOTO JORGE LUIS | G54: =+'[13]PLANILLA MENSUAL'!AY18 -> 7206.1772 | H54: 00 | I54: 003-2025 | J54: 45747 | K54: PROVISION PLANILLA MES MARZO 2025
A55: 14121001 | B55: ADELANTO DE REMUNERACION DE PERSONAL M.N | C55: 71127068 | D55: MONTOYA MEDRANO ANDREA BELEN JOSEPHINE | G55: =+'[13]PLANILLA MENSUAL'!AY19 -> 1625 | H55: 00 | I55: 003-2025 | J55: 45747 | K55: PROVISION PLANILLA MES MARZO 2025
A56: 14121001 | B56: ADELANTO DE REMUNERACION DE PERSONAL M.N | C56: 46497553 | D56: VERGARA BALDEON GEANNINA LIZBETH | G56: =+'[13]PLANILLA MENSUAL'!AY20 -> 1458.3333 | H56: 00 | I56: 003-2025 | J56: 45747 | K56: PROVISION PLANILLA MES MARZO 2025
A57: 14121001 | B57: ADELANTO DE REMUNERACION DE PERSONAL M.N | C57: 44030334 | D57: CASTILLO ENCARNACION MANUEL LEONIDAS | G57: =+'[13]PLANILLA MENSUAL'!AY21 -> 1232.5833 | H57: 00 | I57: 003-2025 | J57: 45747 | K57: PROVISION PLANILLA MES MARZO 2025
A58: 14121001 | B58: ADELANTO DE REMUNERACION DE PERSONAL M.N | C58: 07882846 | D58: QUEVEDO SALAS LUIS ALBERTO | G58: =+'[13]PLANILLA MENSUAL'!AY22 -> 3536.7371 | H58: 00 | I58: 003-2025 | J58: 45747 | K58: PROVISION PLANILLA MES MARZO 2025
A59: 14121001 | B59: ADELANTO DE REMUNERACION DE PERSONAL M.N | C59: 42544684 | D59: PORTOCARRERO GOMEZ MARIA DEICY | G59: =+'[13]PLANILLA MENSUAL'!AY23 -> 765.91667 | H59: 00 | I59: 003-2025 | J59: 45747 | K59: PROVISION PLANILLA MES MARZO 2025
A60: 14121001 | B60: ADELANTO DE REMUNERACION DE PERSONAL M.N | C60: 47291951 | D60: AREVALO ILATOMA ALBERTO | G60: =+'[13]PLANILLA MENSUAL'!AY24 -> 1633.3333 | H60: 00 | I60: 003-2025 | J60: 45747 | K60: PROVISION PLANILLA MES MARZO 2025
A61: 14121001 | B61: ADELANTO DE REMUNERACION DE PERSONAL M.N | C61: 72544254 | D61: SEGURA CHAVESTA CHRISTIAN GUILLERMO | G61: =+'[13]PLANILLA MENSUAL'!#REF! -> #REF! | H61: 00 | I61: 003-2025 | J61: 45747 | K61: PROVISION PLANILLA MES MARZO 2025
A62: 14121001 | B62: ADELANTO DE REMUNERACION DE PERSONAL M.N | C62: 43415173 | D62: LOBO QUISPE ELISA FIORELLA | G62: =+'[13]PLANILLA MENSUAL'!AY25 -> 1750 | H62: 00 | I62: 003-2025 | J62: 45747 | K62: PROVISION PLANILLA MES MARZO 2025
A63: 14121001 | B63: ADELANTO DE REMUNERACION DE PERSONAL M.N | C63: 48335342 | D63: RIOS HOLSEN JAIME JUNIOR | G63: =+'[13]PLANILLA MENSUAL'!AY26 -> 1633.3333 | H63: 00 | I63: 003-2025 | J63: 45747 | K63: PROVISION PLANILLA MES MARZO 2025
A64: 14121001 | B64: ADELANTO DE REMUNERACION DE PERSONAL M.N | C64: 25849757 | D64: ESTRADA SANTOS JUAN MIGUEL | G64: =+'[13]PLANILLA MENSUAL'!AY27 -> 2739.7348 | H64: 00 | I64: 003-2025 | J64: 45747 | K64: PROVISION PLANILLA MES MARZO 2025
A65: 14121001 | B65: ADELANTO DE REMUNERACION DE PERSONAL M.N | C65: 42953954 | D65: SALCEDO RIVAS DANIEL ALONSO | G65: =+'[13]PLANILLA MENSUAL'!AY28 -> 1524.25 | H65: 00 | I65: 003-2025 | J65: 45747 | K65: PROVISION PLANILLA MES MARZO 2025
A66: 14121001 | B66: ADELANTO DE REMUNERACION DE PERSONAL M.N | C66: 45654429 | D66: PORTOCARRERO TAFUR MARIA LOIDI | G66: =+'[13]PLANILLA MENSUAL'!AY29 -> 659.16667 | H66: 00 | I66: 003-2025 | J66: 45747 | K66: PROVISION PLANILLA MES MARZO 2025
A67: 14121001 | B67: ADELANTO DE REMUNERACION DE PERSONAL M.N | C67: 74450353 | D67: ZEVALLOS DELGADO LUIS EDUARDO | G67: =+'[13]PLANILLA MENSUAL'!AY30 -> 1465.2415 | H67: 00 | I67: 003-2025 | J67: 45747 | K67: PROVISION PLANILLA MES MARZO 2025
A68: 14121001 | B68: ADELANTO DE REMUNERACION DE PERSONAL M.N | C68: 09877161 | D68: BALLLESTEROS DI SERI MARIA PAULA | G68: =+'[13]PLANILLA MENSUAL'!AY31 -> 1458.3333 | H68: 00 | I68: 003-2025 | J68: 45747 | K68: PROVISION PLANILLA MES MARZO 2025
A69: 14121001 | B69: ADELANTO DE REMUNERACION DE PERSONAL M.N | C69: 73231901 | D69: OCAMPO ORTEGA JEAN PAUL | G69: =+'[13]PLANILLA MENSUAL'!AY32 -> 1171.5093 | H69: 00 | I69: 003-2025 | J69: 45747 | K69: PROVISION PLANILLA MES MARZO 2025
A70: 14121001 | B70: ADELANTO DE REMUNERACION DE PERSONAL M.N | C70: 73885455 | D70: OLIVOS SAAVEDRA LANDHERT ANDERSON | G70: =+'[13]PLANILLA MENSUAL'!AY33 -> 1173.3507 | H70: 00 | I70: 003-2025 | J70: 45747 | K70: PROVISION PLANILLA MES MARZO 2025
A71: 14121001 | B71: ADELANTO DE REMUNERACION DE PERSONAL M.N | C71: 73952223 | D71: YUPANQUI SAMANIEGO RENATO LUIS | G71: =+'[13]PLANILLA MENSUAL'!AY34 -> 1283.3333 | H71: 00 | I71: 003-2025 | J71: 45747 | K71: PROVISION PLANILLA MES MARZO 2025
A72: 14121001 | B72: ADELANTO DE REMUNERACION DE PERSONAL M.N | C72: 46452115 | D72: TUCTO PEREZ CESAR ANTONIO | G72: =+'[13]PLANILLA MENSUAL'!AY35 -> 1458.3333 | H72: 00 | I72: 003-2025 | J72: 45747 | K72: PROVISION PLANILLA MES MARZO 2025
A73: 14121001 | B73: ADELANTO DE REMUNERACION DE PERSONAL M.N | C73: 71114663 | D73: AREVALO VELA CESAR ANTONIO | G73: =+'[13]PLANILLA MENSUAL'!AY36 -> 2212.0566 | H73: 00 | I73: 003-2025 | J73: 45747 | K73: PROVISION PLANILLA MES MARZO 2025
A74: 14121001 | B74: ADELANTO DE REMUNERACION DE PERSONAL M.N | C74: 73735818 | D74: SICCHA ARCE LUIS FRANCISCO | G74: =+'[13]PLANILLA MENSUAL'!AY37 -> 2182.273 | H74: 00 | I74: 003-2025 | J74: 45747 | K74: PROVISION PLANILLA MES MARZO 2025
A75: 14121001 | B75: ADELANTO DE REMUNERACION DE PERSONAL M.N | C75: 47442636 | D75: ORDOÑEZ JULCA JESUS ORLANDO | G75: =+'[13]PLANILLA MENSUAL'!#REF! -> #REF! | H75: 00 | I75: 003-2025 | J75: 45747 | K75: PROVISION PLANILLA MES MARZO 2025
A76: 14121001 | B76: ADELANTO DE REMUNERACION DE PERSONAL M.N | C76: 06802763 | D76: JIMENEZ PUYEN LUIS ANTONIO | G76: =+'[13]PLANILLA MENSUAL'!AY38 -> 1633.3333 | H76: 00 | I76: 003-2025 | J76: 45747 | K76: PROVISION PLANILLA MES MARZO 2025
A77: 14121001 | B77: ADELANTO DE REMUNERACION DE PERSONAL M.N | C77: 48461873 | D77: SILVA SANTISTEBAN RONAL JHUNIOR | G77: =+'[13]PLANILLA MENSUAL'!AY39 -> 999.86431 | H77: 00 | I77: 003-2025 | J77: 45747 | K77: PROVISION PLANILLA MES MARZO 2025
A85: 14191001 | B85: OTROS CUENTAS POR COBRAR AL PERSONAL | C85: 20332970411 | D85: PACIFICO COMPAÑÍA DE SEGUROS | G85: =+'[13]PLANILLA MENSUAL'!#REF! -> #REF! | H85: 01 | I85: F090-118980 | J85: 45747 | K85: PROVISION PLANILLA MES MARZO 2025 | N85: 10305226 | O85: ORIHUELA AGUIRRE ERNESTO JULIO | R85: 302.92 | S85: =+G85-R85 -> #REF!
A86: 14191001 | B86: OTROS CUENTAS POR COBRAR AL PERSONAL | C86: 20332970411 | D86: PACIFICO COMPAÑÍA DE SEGUROS | G86: =+'[13]PLANILLA MENSUAL'!#REF! -> #REF! | H86: 01 | I86: F072-5022558 | J86: 45747 | K86: PROVISION PLANILLA MES MARZO 2025 | N86: 9594953 | O86: MARTINEZ CASTILLO GIOVANNA RAQUEL | R86: =543.33/2 -> 271.665 | S86: =+G86-R86 -> #REF!
A87: 14191001 | B87: OTROS CUENTAS POR COBRAR AL PERSONAL | C87: 20332970411 | D87: PACIFICO COMPAÑÍA DE SEGUROS | G87: =+'[13]PLANILLA MENSUAL'!#REF! -> #REF! | H87: 01 | I87: F077-384221 | J87: 45747 | K87: PROVISION PLANILLA MES MARZO 2025 | N87: 44425022 | O87: PEREZ CAJAHUANCA ARACELLI IRAIDA | R87: 158.34 | S87: =+G87-R87 -> #REF!
A88: 14191001 | B88: OTROS CUENTAS POR COBRAR AL PERSONAL | C88: 20332970411 | D88: PACIFICO COMPAÑÍA DE SEGUROS | G88: =+'[13]PLANILLA MENSUAL'!#REF! -> #REF! | H88: 01 | I88: F072-5022561 | J88: 45747 | K88: PROVISION PLANILLA MES MARZO 2025 | N88: 43172155 | O88: PORTOCARRERO TAFUR GLORI MAGRI | R88: 285 | S88: =+G88-R88 -> #REF!
A89: 14191001 | B89: OTROS CUENTAS POR COBRAR AL PERSONAL | C89: 45654429 | D89: PORTOCARRERO TAFUR MARIA LOIDI | G89: =+'[13]PLANILLA MENSUAL'!BB29 -> 0 | H89: 00 | I89: 003-2025 | J89: 45747 | K89: PROVISION PLANILLA MES MARZO 2025 | N89: CONSIDERAR RECIBO ENTEL
A90: 14121001 | B90: ADELANTO DE REMUNERACION DE PERSONAL M.N | C90: 74450353 | D90: ZEVALLOS DELGADO LUIS EDUARDO | G90: =+'[13]PLANILLA MENSUAL'!BB30 -> 0 | H90: 00 | I90: 011-2024 | J90: 45747 | K90: PROVISION PLANILLA MES MARZO 2025
A91: 40171003 | B91: RENTA DE QUINTA CATEGORIA | C91: 20131312955 | D91: SUNAT | G91: =+'[13]PLANILLA MENSUAL'!BE54 -> -11422.285 | H91: 00 | I91: 003-2025 | J91: 45747 | K91: PROVISION PLANILLA MES MARZO 2025
A92: 40311001 | B92: ESSALUD | C92: 20131312955 | D92: SUNAT | G92: =+'[13]PLANILLA MENSUAL'!AT66 -> 12926.042 | H92: 00 | I92: 003-2025 | J92: 45747 | K92: PROVISION PLANILLA MES MARZO 2025
A93: 40321001 | B93: ONP | C93: 20131312955 | D93: SUNAT | G93: =+'[13]PLANILLA MENSUAL'!AT65 -> 3018.4661 | H93: 00 | I93: 003-2025 | J93: 45747 | K93: PROVISION PLANILLA MES MARZO 2025
A94: 41701001 | B94: ADMIN DE FONDOS DE PENN - PRIMA | C94: 20510398158 | D94: PRIMA | G94: =+'[13]PLANILLA MENSUAL'!AT68 -> 4452.7932 | H94: 00 | I94: 003-2025 | J94: 45747 | K94: PROVISION PLANILLA MES MARZO 2025
A95: 41701002 | B95: ADMIN DE FONDOS PENS - INTEGRA | C95: 20157036794 | D95: INTEGRA | G95: =+'[13]PLANILLA MENSUAL'!AT69 -> 7711.222 | H95: 00 | I95: 003-2025 | J95: 45747 | K95: PROVISION PLANILLA MES MARZO 2025
A96: 41701003 | B96: ADMIN DE FONDOS DE PENN - PROFUTURO | C96: 20142829551 | D96: PROFUTURO | G96: =+'[13]PLANILLA MENSUAL'!AT70 -> 1404.8772 | H96: 00 | I96: 003-2025 | J96: 45747 | K96: PROVISION PLANILLA MES MARZO 2025
A97: 41701004 | B97: ADMIN DE FONDOS PENS - HABITAH | C97: 20551464971 | D97: HABITAH | G97: =+'[13]PLANILLA MENSUAL'!AT71 -> 626.8281 | H97: 00 | I97: 003-2025 | J97: 45747 | K97: PROVISION PLANILLA MES MARZO 2025
A98: 41101001 | B98: SUELDOS | C98: 10305226 | D98: ORIHUELA AGUIRRE ERNESTO JULIO | G98: =+'[13]PLANILLA MENSUAL'!BG12 -> 7600.217 | H98: 00 | I98: 003-2025 | J98: 45747 | K98: PROVISION PLANILLA MES MARZO 2025
A99: 41101001 | B99: SUELDOS | C99: 09594953 | D99: MARTINEZ CASTILLO GIOVANNA RAQUEL | G99: =+'[13]PLANILLA MENSUAL'!BG13 -> 2483.2015 | H99: 00 | I99: 003-2025 | J99: 45747 | K99: PROVISION PLANILLA MES MARZO 2025
A100: 41101001 | B100: SUELDOS | C100: 46335654 | D100: SALVADOR ROJAS ELVIS ALFONSO | G100: =+'[13]PLANILLA MENSUAL'!BG14 -> 1718.2538 | H100: 00 | I100: 003-2025 | J100: 45747 | K100: PROVISION PLANILLA MES MARZO 2025
A101: 41101001 | B101: SUELDOS | C101: 41675364 | D101: LOLI RODRIGUEZ JANIO RICHARD | G101: =+'[13]PLANILLA MENSUAL'!BG15 -> 1821.927 | H101: 00 | I101: 003-2025 | J101: 45747 | K101: PROVISION PLANILLA MES MARZO 2025
A102: 41101001 | B102: SUELDOS | C102: 44425022 | D102: PEREZ CAJAHUANCA ARACELLI IRAIDA | G102: =+'[13]PLANILLA MENSUAL'!BG16 -> 1975.2049 | H102: 00 | I102: 003-2025 | J102: 45747 | K102: PROVISION PLANILLA MES MARZO 2025
A103: 41101001 | B103: SUELDOS | C103: 43172155 | D103: PORTOCARRERO TAFUR GLORI MAGRI | G103: =+'[13]PLANILLA MENSUAL'!BG17 -> 1355.3326 | H103: 00 | I103: 003-2025 | J103: 45747 | K103: PROVISION PLANILLA MES MARZO 2025
A104: 41101001 | B104: SUELDOS | C104: 45538866 | D104: ECHEVARRIA SOTO JORGE LUIS | G104: =+'[13]PLANILLA MENSUAL'!BG18 -> 6474.1598 | H104: 00 | I104: 003-2025 | J104: 45747 | K104: PROVISION PLANILLA MES MARZO 2025
A105: 41101001 | B105: SUELDOS | C105: 71127068 | D105: MONTOYA MEDRANO ANDREA BELEN JOSEPHINE | G105: =+'[13]PLANILLA MENSUAL'!BG19 -> 1836.2975 | H105: 00 | I105: 003-2025 | J105: 45747 | K105: PROVISION PLANILLA MES MARZO 2025
A106: 41101001 | B106: SUELDOS | C106: 46497553 | D106: VERGARA BALDEON GEANNINA LIZBETH | G106: =+'[13]PLANILLA MENSUAL'!BG20 -> 1070.7666 | H106: 00 | I106: 003-2025 | J106: 45747 | K106: PROVISION PLANILLA MES MARZO 2025
A107: 41101001 | B107: SUELDOS | C107: 44030334 | D107: CASTILLO ENCARNACION MANUEL LEONIDAS | G107: =+'[13]PLANILLA MENSUAL'!BG21 -> 613.0039 | H107: 00 | I107: 003-2025 | J107: 45747 | K107: PROVISION PLANILLA MES MARZO 2025
A108: 41101001 | B108: SUELDOS | C108: 07882846 | D108: QUEVEDO SALAS LUIS ALBERTO | G108: =+'[13]PLANILLA MENSUAL'!BG22 -> 4262.5647 | H108: 00 | I108: 003-2025 | J108: 45747 | K108: PROVISION PLANILLA MES MARZO 2025
A109: 41101001 | B109: SUELDOS | C109: 42544684 | D109: PORTOCARRERO GOMEZ MARIA DEICY | G109: =+'[13]PLANILLA MENSUAL'!BG23 -> 719.6019 | H109: 00 | I109: 003-2025 | J109: 45747 | K109: PROVISION PLANILLA MES MARZO 2025
A110: 41101001 | B110: SUELDOS | C110: 47291951 | D110: AREVALO ILATOMA ALBERTO | G110: =+'[13]PLANILLA MENSUAL'!BG24 -> 1143.4047 | H110: 00 | I110: 003-2025 | J110: 45747 | K110: PROVISION PLANILLA MES MARZO 2025
A111: 41101001 | B111: SUELDOS | C111: 72544254 | D111: SEGURA CHAVESTA CHRISTIAN GUILLERMO | G111: =+'[13]PLANILLA MENSUAL'!#REF! -> #REF! | H111: 00 | I111: 003-2025 | J111: 45747 | K111: PROVISION PLANILLA MES MARZO 2025
A112: 41101001 | B112: SUELDOS | C112: 43415173 | D112: LOBO QUISPE ELISA FIORELLA | G112: =+'[13]PLANILLA MENSUAL'!BG25 -> 1331.9098 | H112: 00 | I112: 003-2025 | J112: 45747 | K112: PROVISION PLANILLA MES MARZO 2025
A113: 41101001 | B113: SUELDOS | C113: 48335342 | D113: RIOS HOLSEN JAIME JUNIOR | G113: =+'[13]PLANILLA MENSUAL'!BG26 -> 1366.095 | H113: 00 | I113: 003-2025 | J113: 45747 | K113: PROVISION PLANILLA MES MARZO 2025
A114: 41101001 | B114: SUELDOS | C114: 25849757 | D114: ESTRADA SANTOS JUAN MIGUEL | G114: =+'[13]PLANILLA MENSUAL'!BG27 -> 1836.1624 | H114: 00 | I114: 003-2025 | J114: 45747 | K114: PROVISION PLANILLA MES MARZO 2025
A115: 41101001 | B115: SUELDOS | C115: 42953954 | D115: SALCEDO RIVAS DANIEL ALONSO | G115: =+'[13]PLANILLA MENSUAL'!BG28 -> 1255.097 | H115: 00 | I115: 003-2025 | J115: 45747 | K115: PROVISION PLANILLA MES MARZO 2025
A116: 41101001 | B116: SUELDOS | C116: 45654429 | D116: PORTOCARRERO TAFUR MARIA LOIDI | G116: =+'[13]PLANILLA MENSUAL'!BG29 -> 470.74 | H116: 00 | I116: 003-2025 | J116: 45747 | K116: PROVISION PLANILLA MES MARZO 2025
...

Sheet HH.EE
C2: Sueldo | D2: Dia | E2: hora | F2: HORAS 25% | G2: HORAS 35% | H2: FERIADO/ DOMINICAL | I2: Total
B3: SALVADOR ROJAS ELVIS ALFONSO | C3: 4113 | D3: =C3/30 -> 137.1 | E3: =D3/8 -> 17.1375 | F3: =C23*E3*1.25 -> 267.77344 | G3: =E3*D23*1.35 -> 161.94938 | H3: =E3*E23*2 -> 976.8375 | I3: =SUM(F3:H3) -> 1406.5603
B4: OCAMPO ORTEGA JEAN PAUL | C4: 2500 | D4: =C4/30 -> 83.333333 | E4: =D4/8 -> 10.416667 | F4: =C24*E4*1.25 -> 240.88542 | G4: =E4*D24*1.35 -> 203.90625 | H4: =E4*E24*2 -> 979.16667 | I4: =SUM(F4:H4) -> 1423.9583
B5: OLIVOS SAAVEDRA LANDHERT ANDERSON | C5: 2500 | D5: =C5/30 -> 83.333333 | E5: =D5/8 -> 10.416667 | F5: =C25*E5*1.25 -> 286.45833 | G5: =E5*D25*1.35 -> 172.26562 | H5: =E5*E25*2 -> 333.33333 | I5: =SUM(F5:H5) -> 792.05729
B6: SILVA SANTISTEBAN RONAL JHUNIOR | C6: 2000 | D6: =C6/30 -> 66.666667 | E6: =D6/8 -> 8.3333333 | F6: =C26*E6*1.25 -> 151.04167 | G6: =E6*D26*1.35 -> 137.8125 | H6: =E6*E26*2 -> 608.33333 | I6: =SUM(F6:H6) -> 897.1875
B7: HIPOLITO GUANILO ARNOLD JIMMY | C7: 1613 | D7: =C7/30 -> 53.766667 | E7: =D7/8 -> 6.7208333 | F7: =C27*E7*1.25 -> 33.604167 | G7: =E7*D27*1.35 -> 31.755938 | H7: =E7*E27*2 -> 107.53333 | I7: =SUM(F7:H7) -> 172.89344
B8: ZEVALLOS DELGADO LUIS EDUARDO | C8: 2800 | D8: =C8/30 -> 93.333333 | E8: =D8/8 -> 11.666667 | F8: =C28*E8*1.25 -> 247.91667 | G8: =E8*D28*1.35 -> 236.25 | H8: =E8*E28*2 -> 618.33333 | I8: =SUM(F8:H8) -> 1102.5
B11: HORAS | C11: 0.25 | D11: 0.35 | E11: 1.25 | F11: 1.35 | G11: FERIADO/ DOMINICAL
B12: SALVADOR ROJAS ELVIS ALFONSO | C12: 8 | D12: 7 | E12: 4.5 | G12: 3
B13: JEAN PAUL OCAMPO ORTEGA | C13: 12 | D13: 14 | E13: 6.5 | F13: 0.5 | G13: 5
B14: ANDERSON OLIVOS SAAVEDRA | C14: 22 | D14: =(12*60+15)/60 -> 12.25 | G14: 2
B15: RONAL SILVA SANTISTEBAN | C15: 10 | D15: =(12*60+15)/60 -> 12.25 | E15: 4.5 | G15: 4
B16: JIMMY HIPOLITO | C16: 4 | D16: 3.5 | G16: 1
B17: LUIS ZEVALLOS DELGADO | C17: 15 | D17: 14.5 | E17: 2 | F17: 0.5 | G17: 3
B22: HORAS | C22: HORAS 25% | D22: HORAS 35% | E22: FERIADO/ DOMINICAL
B23: SALVADOR ROJAS ELVIS ALFONSO | C23: =C12+E12 -> 12.5 | D23: 7 | E23: 28.5
B24: JEAN PAUL OCAMPO ORTEGA | C24: =C13+E13 -> 18.5 | D24: =D13+F13 -> 14.5 | E24: 47
B25: ANDERSON OLIVOS SAAVEDRA | C25: =C14+E14 -> 22 | D25: =D14+F14 -> 12.25 | E25: 16
B26: RONAL SILVA SANTISTEBAN | C26: =C15+E15 -> 14.5 | D26: =D15+F15 -> 12.25 | E26: 36.5
B27: JIMMY HIPOLITO | C27: =C16+E16 -> 4 | D27: =D16+F16 -> 3.5 | E27: 8
B28: LUIS ZEVALLOS DELGADO | C28: =C17+E17 -> 17 | D28: =D17+F17 -> 15 | E28: 26.5
C31: 2500
B32: =5500*7 -> 38500 | C32: =C31*12 -> 30000 | D32: =C31+C31*9% -> 2725 | E32: =2000 -> 2000

Sheet PLANILLA BRUTA
C1: 1 | D1: 2 | E1: 3 | F1: 4 | G1: 5 | H1: 6 | I1: 7 | J1: 8 | K1: 9 | L1: 10 | M1: 11 | O1: 12 | P1: 13 | Q1: 14 | S1: 15 | T1: 16 | U1: 17 | V1: 18 | W1: 19 | X1: 20 | Y1: 21 | Z1: 22 | AB1: 23 | AD1: 24 | AE1: 25 | AF1: 26 | AG1: 27 | AH1: 28 | AI1: 29 | AJ1: 30 | AK1: 31 | AL1: 32 | AM1: 33 | AN1: 34 | AO1: 35 | AP1: 36 | AQ1: 37 | AR1: 38 | AS1: 39 | AU1: 40 | AX1: 41 | AY1: 42 | AZ1: 43 | BA1: 44 | BC1: 48 | BF1: 57 | BG1: 58 | BH1: 59 | BI1: 60 | BJ1: 61 | BK1: 62 | BL1: 63 | BM1: 64 | BN1: 65 | BO1: 66 | BP1: 67 | BQ1: 68 | BR1: 69 | BS1: 70 | BT1: 71 | BU1: 72 | BV1: 73 | BW1: 74 | BX1: 75 | BY1: 76 | BZ1: 77 | CA1: 78 | CB1: 79 | CC1: 80 | CD1: 81 | CE1: 82 | CF1: 83 | CG1: 84 | CH1: 85 | CI1: 86 | CJ1: 87 | CK1: 88 | CL1: 89 | CM1: 90 | CN1: 91 | CO1: 92 | CP1: 93 | CQ1: 94 | CR1: 95 | CS1: 96 | CT1: 97 | CU1: 98 | CV1: 99 | CW1: 100 | CX1: 101 | CY1: 102 | CZ1: 103 | DA1: 104 | DB1: 105 | DC1: 106 | DD1: 107 | DE1: 108 | DF1: 109 | DG1: 110 | DH1: 111 | DI1: 112 | DJ1: 113 | DK1: 114 | DL1: 115 | DM1: 116 | DN1: 117 | DO1: 118 | DP1: 119 | DQ1: 120 | DR1: 121 | DS1: 122 | DT1: 123 | DU1: 124 | DV1: 125 | DW1: 126 | DX1: 127 | DY1: 128 | DZ1: 129 | EA1: 130 | EB1: 131 | EC1: 132 | ED1: 133 | EE1: 134 | EF1: 135 | EG1: 136 | EH1: 137 | EI1: 138 | EJ1: 139 | EK1: 140 | EL1: 141 | EM1: 142 | EN1: 143 | EO1: 144 | EP1: 145 | EQ1: 146 | ER1: 147 | ES1: 148 | ET1: 149 | EU1: 150 | EV1: 151 | EW1: 152 | EX1: 153 | EY1: 154 | EZ1: 155 | FA1: 156 | FB1: 157 | FC1: 158
C2: SPECIES S.A.C.
C3: Nº 20550057451
C4: PLANILLA DE REMUNERACIONES MES DE JULIO DEL AÑO 2024
C6: (EXPRESADO EN NUEVOS SOLES)
D8: TRABAJADOR | H8: DATOS DEL PERSONAL | Q8: REMUNERACIONES | AH8: DESCUENTOS | AX8: TOTAL | AY8: NETO A | AZ8: APORTACION | BF8: (Se considero de adelanto (S/1149) | BG8: SE PAGO | BH8: SE DEBIO DE PAGAR
C9: N° | D9: APELLIDOS | F9: NOMBRES | H9: AFP | L9: FECHA | M9: FECHA | N9: FECHA | Q9: REMUNER. | R9: COMPRA DE VACACIONES | S9: ASIGNAC. | T9: HORAS | U9: HORAS | V9: FERIADOS | AC9: CANASTA | AD9: BONO | AF9: REMUNER | AG9: REMUNERA. | AH9: ONP | AJ9: A.F.P. | AR9: IMP.RTA.5 | AS9: ADELAN | AT9: GRATIF | AU9: PREST | AV9: DESCUENTO | AW9: DSCTO | AX9: DESCUENT. | AY9: PAGAR | AZ9: ESSALUD | BB9: SEGURO | BC9: HORAS
D10: PATERNO | E10: MATERNO | F10: PRIMER | G10: SEGUNDO | H10: Y | I10: CUPSS | J10: AUTOGENERADO | K10: DNI, CE | L10: DE | M10: DE | N10: DE | O10: AREA | P10: CARGO | Q10: BRUTA | S10: FAMILIAR | T10: EXTRAS | U10: EXTRAS | W10: MOVIL | X10: VACACIONES | Y10: GRATIFIC. | Z10: BONIF. | AA10: OTROS INGRESOS NO COMPU | AB10: CTS | AC10: NAVIDEÑA | AD10: EXTRAOR | AE10: DESC. | AF10: BRUTA | AG10: AFECTA | AH10: % | AI10: S/. | AJ10: APORTE OBLIG. | AL10: COMISION | AN10: PRIMA SEGURO | AP10: TOTAL A.F.P. | AT10: EXTRAOR | AV10: JUDICIAL | AW10: PAGO | BB10: VIDA LEY | BC10: LAB
H11: ONP | L11: INGRESO | M11: NACIMIENTO | N11: SALIDA | T11: 0.25 | U11: 0.35 | AD11: U OTRO | AJ11: % | AK11: S/. | AL11: % | AM11: S/. | AN11: % | AO11: S/. | AP11: % | AQ11: S/. | AW11: GRATIF | AZ11: % | BA11: S/.
A12: 1ER | C12: 1 | D12: BRETONECHE | E12: DIAPIS | F12: ANA | G12: LUCIA | H12: INTEGRA | I12: 636620ABDTP8 | K12: 47355900 | L12: 44849 | M12: 33664 | O12: RESTAURANT | P12: COCINERO | Q12: =2500 -> 2500 | S12: 102.5 | AF12: =SUM(Q12:AD12)-AE12 -> 2602.5 | AG12: =+Q12+S12+T12+U12+V12+X12-AE12 -> 2602.5 | AJ12: 0.1 | AK12: =+AG12*AJ12 -> 260.25 | AL12: 0 | AM12: =+AG12*AL12 -> 0 | AN12: 0.017 | AO12: =+AG12*AN12 -> 44.2425 | AP12: =+AJ12+AL12+AN12 -> 0.117 | AQ12: =+AK12+AM12+AO12 -> 304.4925 | AX12: =+AI12+AQ12+AR12+AS12+AT12+AU12+AW12 -> 304.4925 | AY12: =(+AF12-AX12) -> 2298.0075 | AZ12: 0.09 | BA12: =AG12*AZ12 -> 234.225 | BB12: 2.88 | BG12: 1302.21 | BH12: 1256.95 | BI12: =BH12-BG12 -> -45.26
A13: 1ER | C13: 2 | D13: MAMANI | E13: HUAMANI | F13: YAMIR | G13: JOSE | H13: INTEGRA | I13: 621701YMHAM9 | K13: 44895694 | L13: 44882 | M13: 32172 | O13: RESTAURANT | P13: LOGISTICA | Q13: 1000 | AF13: =SUM(Q13:AD13)-AE13 -> 1000 | AG13: =+Q13+S13+T13+U13+V13+X13-AE13 -> 1000 | AJ13: 0.1 | AK13: =+AG13*AJ13 -> 100 | AL13: 0.0155 | AM13: =+AG13*AL13 -> 15.5 | AN13: 0.017 | AO13: =+AG13*AN13 -> 17 | AP13: =+AJ13+AL13+AN13 -> 0.1325 | AQ13: =+AK13+AM13+AO13 -> 132.5 | AX13: =+AI13+AQ13+AR13+AS13+AT13+AU13+AW13 -> 132.5 | AY13: =(+AF13-AX13) -> 867.5 | AZ13: 0.09 | BA13: =AG13*AZ13 -> 90 | BB13: 1.44 | BD13: ok | BG13: 433.75 | BH13: 433.75 | BI13: =BH13-BG13 -> 0
A14: 1ER | C14: 3 | D14: VICENTE | E14: BLAS | F14: CALIXTO | K14: 8751792 | L14: 45078 | M14: 20663 | P14: CONDUCTOR | Q14: 834 | AE14: 41.67 | AF14: =SUM(Q14:AD14)-AE14 -> 792.33 | AG14: =+Q14+S14+T14+U14+V14+X14-AE14 -> 792.33 | AX14: =+AI14+AQ14+AR14+AS14+AT14+AU14+AW14 -> 0 | AY14: =(+AF14-AX14) -> 792.33 | AZ14: 0.09 | BA14: =AG14*AZ14 -> 71.3097 | BB14: 50.42 | BD14: ok | BG14: 500.34 | BH14: 458.67 | BI14: =BH14-BG14 -> -41.67 | BJ14: (Descontar en julio)
A15: 1ER | C15: 5 | D15: PINILLOS | E15: HIDALGO | F15: MARYORI | G15: XIMENA | H15: INTEGRA | I15: 670730MPHIA2 | K15: 73994129 | L15: 45384 | M15: 37075 | O15: RESTAURANT | P15: COCINERO | Q15: =1500 -> 1500 | AF15: =SUM(Q15:AD15)-AE15 -> 1500 | AG15: =+Q15+S15+T15+U15+V15+X15-AE15 -> 1500 | AJ15: 0.1 | AK15: =+AG15*AJ15 -> 150 | AL15: 0 | AN15: 0.017 | AO15: =+AG15*AN15 -> 25.5 | AP15: =+AJ15+AL15+AN15 -> 0.117 | AQ15: =+AK15+AM15+AO15 -> 175.5 | AX15: =+AI15+AQ15+AR15+AS15+AT15+AU15+AW15 -> 175.5 | AY15: =(+AF15-AX15) -> 1324.5 | AZ15: 0.09 | BA15: =AG15*AZ15 -> 135 | BD15: ok | BG15: 750.55 | BH15: 750.55 | BI15: =BH15-BG15 -> 0
A16: 1ER | C16: 7 | D16: GUILLEN | E16: CERECEDA | F16: KATHERINN | G16: ELIZABETH | H16: INTEGRA | I16: 641760KGCLE7 | K16: 48053446 | L16: 45461 | M16: 34178 | O16: CONTABILIDAD | P16: ASIST.CONTABLE | Q16: 750 | AF16: =SUM(Q16:AD16)-AE16 -> 750 | AG16: =+Q16+S16+T16+U16+V16+X16-AE16 -> 750 | AJ16: 0.1 | AK16: =+AG16*AJ16 -> 75 | AL16: 0 | AN16: 0.017 | AO16: =+AG16*AN16 -> 12.75 | AP16: =+AJ16+AN16 -> 0.117 | AQ16: =+AK16+AM16+AO16 -> 87.75 | AX16: =+AI16+AQ16+AR16+AS16+AT16+AU16+AW16 -> 87.75 | AY16: =(+AF16-AX16) -> 662.25 | AZ16: 0.09 | BA16: =AG16*AZ16 -> 67.5 | BD16: ok | BG16: 286.98 | BH16: 286.98 | BI16: =BH16-BG16 -> 0
A17: 1ER | C17: 8 | D17: SALAS | E17: SORIA | F17: OMAR | G17: ANDRES | H17: HABITAT | I17: 638061OSSAI5 | K17: 70157117 | L17: 45425 | M17: 33808 | O17: RESTAURANT | P17: BARMAN | Q17: 1400 | AF17: =SUM(Q17:AD17)-AE17 -> 1400 | AG17: =+Q17+S17+T17+U17+V17+X17-AE17 -> 1400 | AJ17: 0.1 | AK17: =+AG17*AJ17 -> 140 | AL17: 0 | AN17: 0.017 | AO17: =+AG17*AN17 -> 23.8 | AP17: =+AJ17+AN17 -> 0.117 | AQ17: =+AK17+AM17+AO17 -> 163.8 | AX17: =+AI17+AQ17+AR17+AS17+AT17+AU17+AW17 -> 163.8 | AY17: =(+AF17-AX17) -> 1236.2 | AZ17: 0.09 | BA17: =AG17*AZ17 -> 126 | BB17: 2.09 | BD17: ok | BG17: 700.51 | BH17: 700.51 | BI17: =BH17-BG17 -> 0
A18: 1ER | C18: 9 | D18: ESTRADA | E18: MANYARI | F18: MATIAS | G18: ANTONIO | H18: INTEGRA | I18: 686101MEMRY1 | K18: 77431897 | L18: 45425 | M18: 38612 | O18: RESTAURANT | P18: MESERO | Q18: =1300 -> 1300 | AF18: =SUM(Q18:AD18)-AE18 -> 1300 | AG18: =+Q18+S18+T18+U18+V18+X18-AE18 -> 1300 | AJ18: 0.1 | AK18: =+AG18*AJ18 -> 130 | AL18: 0 | AN18: 0.017 | AO18: =+AG18*AN18 -> 22.1 | AP18: =+AJ18+AN18 -> 0.117 | AQ18: =+AK18+AM18+AO18 -> 152.1 | AX18: =+AI18+AQ18+AR18+AS18+AT18+AU18+AW18 -> 152.1 | AY18: =(+AF18-AX18) -> 1147.9 | AZ18: 0.09 | BA18: =AG18*AZ18 -> 117 | BB18: 2.88 | BD18: ok | BG18: 573.95 | BH18: 650.48 | BI18: =BH18-BG18 -> 76.53 | BK18: no pago de feriado dia 09.06
A19: 1ER | C19: 10 | D19: PINILLOS | E19: HIDALGO | F19: MIGUEL | G19: ANGEL | H19: INTEGRA | I19: 676151MPHIA6 | K19: 73994130 | L19: 45425 | M19: 37617 | O19: RESTAURANT | P19: OPERARIO DE LIMPIEZA | Q19: 650 | AF19: =SUM(Q19:AD19)-AE19 -> 650 | AG19: =+Q19+S19+T19+U19+V19+X19-AE19 -> 650 | AJ19: 0.1 | AK19: =+AG19*AJ19 -> 65 | AL19: 0 | AN19: 0.017 | AO19: =+AG19*AN19 -> 11.05 | AP19: =+AJ19+AN19 -> 0.117 | AQ19: =+AK19+AM19+AO19 -> 76.05 | AX19: =+AI19+AQ19+AR19+AS19+AT19+AU19+AW19 -> 76.05 | AY19: =(+AF19-AX19) -> 573.95 | AZ19: 0.09 | BA19: =AG19*AZ19 -> 58.5 | BB19: 2.88 | BD19: ok | BG19: 286.97 | BH19: 286.97 | BI19: =BH19-BG19 -> 0
A21: 1ER | Q21: =SUM(Q12:Q20) -> 9934 | S21: =SUM(S12:S20) -> 102.5 | T21: =SUM(T12:T20) -> 0 | U21: =SUM(U12:U20) -> 0 | V21: =SUM(V12:V20) -> 0 | W21: =SUM(W12:W20) -> 0 | X21: =SUM(X12:X20) -> 0 | Y21: =SUM(Y12:Y20) -> 0 | Z21: =SUM(Z12:Z20) -> 0 | AB21: =SUM(AB12:AB20) -> 0 | AC21: =SUM(AC12:AC20) -> 0 | AD21: =SUM(AD12:AD20) -> 0 | AE21: =SUM(AE12:AE20) -> 41.67 | AF21: =SUM(AF12:AF20) -> 9994.83 | AG21: =SUM(AG12:AG20) -> 9994.83 | AI21: =SUM(AI12:AI20) -> 0 | AK21: =SUM(AK12:AK20) -> 920.25 | AM21: =SUM(AM12:AM20) -> 15.5 | AO21: =SUM(AO12:AO20) -> 156.4425 | AQ21: =SUM(AQ12:AQ20) -> 1092.1925 | AR21: =SUM(AR12:AR20) -> 0 | AS21: =SUM(AS12:AS20) -> 0 | AT21: =SUM(AT12:AT14) -> 0 | AU21: =SUM(AU12:AU20) -> 0 | AX21: =SUM(AX12:AX20) -> 1092.1925 | AY21: =SUM(AY12:AY20) -> 8902.6375 | BA21: =SUM(BA12:BA20) -> 899.5347 | BB21: =SUM(BB12:BB20) -> 62.59
A23: 5TO | C23: 1 | D23: CHUNGA | E23: VILLAR | F23: PEDRO | G23: GIOMAR | H23: PRIMA | I23: 631631PCVNL0 | K23: 46704451 | L23: 45017 | M23: 33165 | O23: RESTAURANT | P23: JEFE DE COCINA | Q23: =3000 -> 3000 | S23: 102.5 | AF23: =SUM(Q23:AD23)-AE23 -> 3102.5 | AG23: =+Q23+S23+T23+U23+V23+X23+R23-AE23 -> 3102.5 | AJ23: 0.1 | AK23: =+AG23*AJ23 -> 310.25 | AL23: 0.016 | AM23: =+AG23*AL23 -> 49.64 | AN23: 0.017 | AO23: =+AG23*AN23 -> 52.7425 | AP23: =+AJ23+AL23+AN23 -> 0.133 | AQ23: =+AK23+AM23+AO23 -> 412.6325 | AR23: =30.41 -> 30.41 | AU23: 250 | AX23: =+AI23+AQ23+AR23+AS23+AT23+AU23+AW23 -> 693.0425 | AY23: =(+AF23-AX23) -> 2409.4575 | AZ23: 0.09 | BA23: =AG23*AZ23 -> 279.225 | BB23: 2.88 | BD23: ok | BG23: 1249.95 | BH23: 1339.61 | BI23: =BH23-BG23 -> 89.66 | BK23: no pago de feriado dia 09.06
A24: 5TO | C24: 2 | D24: MAMANI | E24: HUAMANI | F24: YAMIR | G24: JOSE | H24: INTEGRA | I24: 621701YMHAM9 | K24: 44895694 | L24: 44882 | M24: 32172 | O24: ROOFTOP | P24: LOGISTICA | Q24: 1000 | AF24: =SUM(Q24:AD24)-AE24 -> 1000 | AG24: =+Q24+S24+T24+U24+V24+X24-AE24 -> 1000 | AJ24: 0.1 | AK24: =+AG24*AJ24 -> 100 | AL24: 0.0155 | AM24: =+AG24*AL24 -> 15.5 | AN24: 0.017 | AO24: =+AG24*AN24 -> 17 | AP24: =+AJ24+AL24+AN24 -> 0.1325 | AQ24: =+AK24+AM24+AO24 -> 132.5 | AX24: =+AI24+AQ24+AR24+AS24+AT24+AU24+AW24 -> 132.5 | AY24: =(+AF24-AX24) -> 867.5 | AZ24: 0.09 | BA24: =AG24*AZ24 -> 90 | BB24: 1.44 | BD24: ok | BG24: 433.75 | BH24: 433.75 | BI24: =BH24-BG24 -> 0
A25: 5TO | C25: 3 | D25: CARRASQUEL | E25: HERNANDEZ | F25: ANGIRBER | G25: GABRIEL | H25: INTEGRA | I25: 646151ACHRN5 | K25: 004696624 | L25: 45078 | M25: 34617 | O25: SALON | P25: JEFE DE BARRA | Q25: =2000 -> 2000 | S25: 102.5 | AF25: =SUM(Q25:AD25)-AE25 -> 2102.5 | AG25: =+Q25+S25+T25+U25+V25+X25-AE25 -> 2102.5 | AJ25: 0.1 | AK25: =+AG25*AJ25 -> 210.25 | AL25: 0 | AN25: 0.017 | AO25: =+AG25*AN25 -> 35.7425 | AP25: =+AJ25+AL25+AN25 -> 0.117 | AQ25: =+AK25+AM25+AO25 -> 245.9925 | AX25: =+AI25+AQ25+AR25+AS25+AT25+AU25+AW25 -> 245.9925 | AY25: =(+AF25-AX25) -> 1856.5075 | AZ25: 0.09 | BA25: =+AG25*AZ25 -> 189.225 | BB25: 2.88 | BD25: ok | BG25: 883 | BH25: 1006.77 | BI25: =BH25-BG25 -> 123.77 | BK25: no pago de feriado dia 09.06
A26: 5TO | C26: 4 | D26: VICENTE | E26: BLAS | F26: CALIXTO | K26: 08751792 | L26: 45078 | M26: 20663 | P26: CONDUCTOR | Q26: 834 | AE26: 41.66 | AF26: =SUM(Q26:AD26)-AE26 -> 792.34 | AG26: =+Q26+S26+T26+U26+V26+X26-AE26 -> 792.34 | AX26: =+AI26+AQ26+AR26+AS26+AT26+AU26+AW26 -> 0 | AY26: =(+AF26-AX26) -> 792.34 | AZ26: 0.09 | BA26: =+AG26*AZ26 -> 71.3106 | BB26: 50.42 | BD26: ok | BG26: 500.33 | BH26: 458.67 | BI26: =BH26-BG26 -> -41.66 | BJ26: (Descontar en julio)
A27: 5TO | C27: 5 | D27: RIVERO | E27: GACON | F27: VICTOR | H27: ONP | K27: 09979245 | L27: 45385 | M27: 26727 | P27: ADMINISTRADOR | Q27: 5934.56 | AF27: =SUM(Q27:AD27)-AE27 -> 5934.56 | AG27: =+Q27+S27+T27+U27+V27+X27-AE27 -> 5934.56 | AH27: 0.13 | AI27: =AG27*AH27 -> 771.4928 | AR27: =163.06 -> 163.06 | AX27: =+AI27+AQ27+AR27+AS27+AT27+AU27+AW27 -> 934.5528 | AY27: =(+AF27-AX27) -> 5000.0072 | AZ27: 0.09 | BA27: =AG27*AZ27 -> 534.1104 | BD27: ok | BG27: 2000.01 | BH27: 2001.01 | BI27: =BH27-BG27 -> 1
A28: 5TO | C28: 7 | D28: GUILLEN | E28: CERECEDA | F28: KATHERINN | G28: ELIZABETH | H28: INTEGRA | I28: 641760KGCLE7 | K28: 48053446 | L28: 45461 | M28: 34178 | O28: CONTABILIDAD | P28: ASIST.CONTABLE | Q28: 750 | AF28: =SUM(Q28:AD28)-AE28 -> 750 | AG28: =+Q28+S28+T28+U28+V28+X28-AE28 -> 750 | AJ28: 0.1 | AK28: =+AG28*AJ28 -> 75 | AL28: 0 | AN28: 0.017 | AO28: =+AG28*AN28 -> 12.75 | AP28: =+AJ28+AN28 -> 0.117 | AQ28: =+AK28+AM28+AO28 -> 87.75 | AX28: =+AI28+AQ28+AR28+AS28+AT28+AU28+AW28 -> 87.75 | AY28: =(+AF28-AX28) -> 662.25 | AZ28: 0.09 | BA28: =AG28*AZ28 -> 67.5 | BD28: ok | BG28: 286.98 | BH28: 286.98 | BI28: =BH28-BG28 -> 0
A29: 5TO | C29: 8 | D29: PINILLOS | E29: HIDALGO | F29: MIGUEL | G29: ANGEL | H29: INTEGRA | I29: 676151MPHIA6 | K29: 73994130 | L29: 45425 | M29: 37617 | O29: RESTAURANT | P29: OPERARIO DE LIMPIEZA | Q29: 650 | AF29: =SUM(Q29:AD29)-AE29 -> 650 | AG29: =+Q29+S29+T29+U29+V29+X29-AE29 -> 650 | AJ29: 0.1 | AK29: =+AG29*AJ29 -> 65 | AL29: 0 | AN29: 0.017 | AO29: =+AG29*AN29 -> 11.05 | AP29: =+AJ29+AN29 -> 0.117 | AQ29: =+AK29+AM29+AO29 -> 76.05 | AX29: =+AI29+AQ29+AR29+AS29+AT29+AU29+AW29 -> 76.05 | AY29: =(+AF29-AX29) -> 573.95 | AZ29: 0.09 | BA29: =AG29*AZ29 -> 58.5 | BB29: 2.88 | BD29: ok | BG29: 286.97 | BH29: 286.97 | BI29: =BH29-BG29 -> 0
A30: 5TO | C30: 9 | D30: BARTESAGHI | E30: MALAGA | F30: RENATO | H30: INTEGRA | I30: 664941RBMTA8 | K30: 71455402 | L30: 45444 | M30: 36496 | O30: RESTAURANT | P30: COCINERO | Q30: =1500 -> 1500 | AF30: =SUM(Q30:AD30)-AE30 -> 1500 | AG30: =+Q30+S30+T30+U30+V30+X30-AE30 -> 1500 | AJ30: 0.1 | AK30: =+AG30*AJ30 -> 150 | AL30: 0 | AN30: 0.017 | AO30: =+AG30*AN30 -> 25.5 | AP30: =+AJ30+AL30+AN30 -> 0.117 | AQ30: =+AK30+AM30+AO30 -> 175.5 | AX30: =+AI30+AQ30+AR30+AS30+AT30+AU30+AW30 -> 175.5 | AY30: =(+AF30-AX30) -> 1324.5 | AZ30: 0.09 | BA30: =+AG30*AZ30 -> 135 | BD30: ok | BG30: 662.25 | BH30: 750.55 | BI30: =BH30-BG30 -> 88.3 | BK30: no pago de feriado dia 09.06
A31: 5TO | C31: 10 | D31: CERRON | E31: ANTO | F31: ALVARO | G31: MARCELO | H31: INTEGRA | I31: 669981ACARO4 | K31: 74221679 | L31: 45444 | M31: 37000 | O31: RESTAURANT | P31: BARMAN | Q31: =1400 -> 1400 | AF31: =SUM(Q31:AD31)-AE31 -> 1400 | AG31: =+Q31+S31+T31+U31+V31+X31-AE31 -> 1400 | AJ31: 0.1 | AK31: =+AG31*AJ31 -> 140 | AL31: 0 | AN31: 0.017 | AO31: =+AG31*AN31 -> 23.8 | AP31: =+AJ31+AL31+AN31 -> 0.117 | AQ31: =+AK31+AM31+AO31 -> 163.8 | AX31: =+AI31+AQ31+AR31+AS31+AT31+AU31+AW31 -> 163.8 | AY31: =(+AF31-AX31) -> 1236.2 | AZ31: 0.09 | BA31: =+AG31*AZ31 -> 126 | BD31: ok | BG31: 618.1 | BH31: 700.51 | BI31: =BH31-BG31 -> 82.41 | BK31: no pago de feriado dia 09.06
A33: 5TO | Q33: =SUM(Q23:Q32) -> 17068.56 | R33: =SUM(R22:R32) -> 0 | S33: =SUM(S22:S32) -> 205 | T33: =SUM(T23:T29) -> 0 | U33: =SUM(U22:U29) -> 0 | V33: =SUM(V22:V32) -> 0 | W33: =SUM(W22:W29) -> 0 | X33: =SUM(X22:X29) -> 0 | Y33: =SUM(Y22:Y29) -> 0 | Z33: =SUM(Z22:Z29) -> 0 | AA33: =SUM(AA22:AA29) -> 0 | AB33: =SUM(AB22:AB26) -> 0 | AC33: =SUM(AC22:AC32) -> 0 | AD33: =SUM(AD22:AD32) -> 0 | AE33: =SUM(AE22:AE32) -> 41.66 | AF33: =SUM(AF22:AF32) -> 17231.9 | AG33: =SUM(AG22:AG32) -> 17231.9 | AI33: =SUM(AI22:AI32) -> 771.4928 | AK33: =SUM(AK23:AK32) -> 1050.5 | AM33: =SUM(AM23:AM32) -> 65.14 | AO33: =SUM(AO23:AO32) -> 178.585 | AQ33: =SUM(AQ23:AQ32) -> 1294.225 | AR33: =SUM(AR23:AR32) -> 193.47 | AS33: =SUM(AS22:AS32) -> 0 | AT33: =SUM(AT23:AT32) -> 0 | AU33: =SUM(AU22:AU32) -> 250 | AV33: =SUM(AV23:AV32) -> 0 | AW33: =SUM(AW23:AW32) -> 0 | AX33: =SUM(AX22:AX32) -> 2509.1878 | AY33: =SUM(AY22:AY32) -> 14722.712 | BA33: =SUM(BA22:BA32) -> 1550.871 | BB33: =SUM(BB22:BB32) -> 60.5
A35: PA | C35: 1 | D35: MOYA | E35: HUAMANI | F35: FERNANDO | H35: ONP | K35: 42859800 | L35: 43374 | M35: 31072 | O35: PACHACAMAC | P35: EMPLEADO | Q35: 2230 | S35: 102.5 | AF35: =SUM(Q35:AD35)-AE35 -> 2332.5 | AG35: =+Q35+S35+T35+U35+V35+X35-AE35 -> 2332.5 | AH35: 0.13 | AI35: =AG35*AH35 -> 303.225 | AX35: =+AI35+AQ35+AR35+AS35+AT35+AU35+AW35 -> 303.225 | AY35: =(+AF35-AX35) -> 2029.275 | AZ35: 0.09 | BA35: =+AG35*AZ35 -> 209.925 | BB35: 8.3 | BD35: ok | BI35: 148.66 | BJ35: (Feriado del 07.06.24
A36: MAR | C36: 2 | D36: TELLO | E36: FLORES | F36: DARIO | H36: ONP | K36: 42617078 | L36: 43374 | M36: 30071 | O36: MARIPOSARIO | P36: SERVICIO DE PERSONAL | Q36: 2794.02 | S36: 102.5 | AF36: =SUM(Q36:AD36)-AE36 -> 2896.52 | AG36: =+Q36+S36+T36+U36+V36+X36-AE36 -> 2896.52 | AH36: 0.13 | AI36: =AG36*AH36 -> 376.5476 | AR36: 20 | AU36: 300 | AV36: 1124.3 | AX36: =+AI36+AQ36+AR36+AS36+AT36+AU36+AV36+AW36 -> 1820.8476 | AY36: =(+AF36-AX36) -> 1075.6724 | AZ36: 0.09 | BA36: =+AG36*AZ36 -> 260.6868 | BB36: 8.3 | BD36: ok
Q38: =SUM(Q35:Q37) -> 5024.02 | S38: =SUM(S34:S37) -> 205 | T38: =SUM(T35:T37) -> 0 | U38: =SUM(U35:U37) -> 0 | V38: =SUM(V37:V37) -> 0 | W38: =SUM(W35:W37) -> 0 | X38: =SUM(X34:X37) -> 0 | Y38: =SUM(Y35:Y37) -> 0 | Z38: =SUM(Z35:Z37) -> 0 | AB38: =SUM(AB35:AB37) -> 0 | AD38: =SUM(AD37:AD37) -> 0 | AE38: =SUM(AE35:AE37) -> 0 | AF38: =SUM(AF35:AF37) -> 5229.02 | AG38: =SUM(AG35:AG37) -> 5229.02 | AI38: =SUM(AI35:AI37) -> 679.7726 | AK38: =SUM(AK35:AK37) -> 0 | AL38: =SUM(AL35:AL37) -> 0 | AM38: =SUM(AM35:AM37) -> 0 | AN38: =SUM(AN35:AN37) -> 0 | AO38: =SUM(AO35:AO37) -> 0 | AP38: =SUM(AP35:AP37) -> 0 | AQ38: =SUM(AQ35:AQ37) -> 0 | AR38: =SUM(AR35:AR37) -> 20 | ... AV38: =SUM(AV35:AV37) -> 1124.3 | AX38: =SUM(AX35:AX37) -> 2124.0726 | AY38: =SUM(AY34:AY37) -> 3104.9474 | BA38: =SUM(BA35:BA37) -> 470.6118 | BB38: =SUM(BB34:BB37) -> 16.6
