Workbook

Sheet LA MAR P1
H3: =18.17% -> 0.1817 | I3: =9.72% -> 0.0972 | J3: =8.333333% -> 0.08333333 | K3: 0.09
B4: CÁLCULO DE COSTO MENSUAL DE PERSONAL EN PLANILLA MYPE | H4: =18.17%/2 -> 0.09085 | I4: =9.72%/2 -> 0.0486 | J4: =8.333333%/2 -> 0.041666665 | K4: 0.09 | M4: ↓ | N4: 30 | O4: 8 | P4: 60
B6: N° | C6: CARGO | D6: DATOS PERSONALES | E6: BASICO | F6: ASIG. FAMILIAR | G6: REMUN. IMPONIBLE | H6: GRATIFICACIONES Julio y Diciembre | I6: CTS | J6: VACACIONES | K6: ESSALUD | M6: COSTO MENSUAL | N6: COSTO DIARIO | O6: COSTO POR HORA | P6: COSTO POR MIN | R6: AFP/ONP | S6: RTA 5TA | T6: NETO
L7: MOVILIDAD
B9: 1 | C9: MOZO | D9: MEZA ARCIA ALEJANDRO JOSE | E9: 779.8 | F9: 0 | G9: =E9+F9 -> 779.8 | H9: =G9*$H$3 -> 141.68966 | I9: =G9*$I$3 -> 75.79656 | J9: =G9*$J$3 -> 64.983331 | K9: =G9*$K$4 -> 70.182 | L9: 0 | M9: =G9+H9+I9+J9+K9+L9 -> 1132.4516 | N9: =M9/$N$4 -> 37.748385 | O9: =N9/$O$4 -> 4.7185481 | P9: =O9/$P$4 -> 0.078642469 | R9: =G9*11.97% -> 93.34206 | S9: 0 | T9: =G9+L9-R9-S9 -> 686.45794
B10: =B9+1 -> 2 | C10: COCINERA | D10: BRETONECHE DIAPIS ANA LUCIA | E10: 1908.19 | F10: 102.5 | G10: =E10+F10 -> 2010.69 | H10: =G10*$H$4 -> 182.67119 | I10: =G10*$I$4 -> 97.719534 | J10: =G10*$J$4 -> 83.778747 | K10: =G10*$K$4 -> 180.9621 | L10: 0 | M10: =G10+H10+I10+J10+K10+L10 -> 2555.8216 | N10: =M10/$N$4 -> 85.194052 | O10: =N10/$O$4 -> 10.649257 | P10: =O10/$P$4 -> 0.17748761 | R10: =G10*11.74% -> 236.05501 | S10: 0 | T10: =G10+L10-R10-S10 -> 1774.635
B11: =B10+1 -> 3 | C11: COCINERO | D11: ARANA CAMPIAN THALIA MISHEL | E11: 1537.34 | G11: =E11+F11 -> 1537.34 | H11: =G11*$H$4 -> 139.66734 | I11: =G11*$I$4 -> 74.714724 | J11: =G11*$J$4 -> 64.055831 | K11: =G11*$K$4 -> 138.3606 | L11: 0 | M11: =G11+H11+I11+J11+K11+L11 -> 1954.1385 | N11: =M11/$N$4 -> 65.13795 | O11: =N11/$O$4 -> 8.1422437 | P11: =O11/$P$4 -> 0.13570406 | R11: =G11*11.92% -> 183.25093 | S11: 0 | T11: =G11+L11-R11-S11 -> 1354.0891
B12: 4 | C12: JEFA DE BARRA | D12: LLANTOY LLAMOCCA GRACE MELANY | E12: 1422.21 | F12: 0 | G12: =E12+F12 -> 1422.21 | H12: =G12*$H$4 -> 129.20778 | I12: =G12*$I$4 -> 69.119406 | J12: =G12*$J$4 -> 59.258748 | K12: =G12*$K$4 -> 127.9989 | L12: 0 | M12: =G12+H12+I12+J12+K12+L12 -> 1807.7948 | N12: =M12/$N$4 -> 60.259828 | O12: =N12/$O$4 -> 7.5324785 | P12: =O12/$P$4 -> 0.12554131 | R12: =G12*11.97% -> 170.23854 | S12: 0 | T12: =G12+L12-R12-S12 -> 1251.9715
B13: 5 | C13: AYUDANTE DE COCINA | D13: REYNA TORO FLORDELUCERO MYLIN | E13: 1025 | G13: =E13+F13 -> 1025 | H13: =G13*$H$4 -> 93.12125 | I13: =G13*$I$4 -> 49.815 | J13: =G13*$J$4 -> 42.708332 | K13: =G13*$K$4 -> 92.25 | L13: 0 | M13: =G13+H13+I13+J13+K13+L13 -> 1302.8946 | N13: =M13/$N$4 -> 43.429819 | O13: =N13/$O$4 -> 5.4287274 | P13: =O13/$P$4 -> 0.09047879 | R13: =G13*11.92% -> 122.18 | S13: 0 | T13: =G13+L13-R13-S13 -> 902.82
B14: 6 | C14: ASISTENTE DE LOGISTICA | D14: MAMANI HUAMANI YAMIR JOSE | E14: 800 | G14: =E14+F14 -> 800 | H14: =G14*$H$4 -> 72.68 | I14: =G14*$I$4 -> 38.88 | J14: =G14*$J$4 -> 33.333332 | K14: =G14*$K$4 -> 72 | L14: 0 | M14: =G14+H14+I14+J14+K14+L14 -> 1016.8933 | N14: =M14/$N$4 -> 33.896444 | O14: =N14/$O$4 -> 4.2370556 | P14: =O14/$P$4 -> 0.070617593 | R14: =G14*11.92% -> 95.36 | S14: 0 | T14: =G14+L14-R14-S14 -> 704.64
B15: 7 | C15: JEFE DE COCINA | D15: CHUNGA VILLAR PEDRO GIOMAR | E15: 3000 | F15: 102.5 | G15: =E15+F15 -> 3102.5 | H15: =G15*$H$4 -> 281.86213 | I15: =G15*$I$4 -> 150.7815 | J15: =G15*$J$4 -> 129.27083 | K15: =G15*$K$4 -> 279.225 | L15: 0 | M15: =G15+H15+I15+J15+K15+L15 -> 3943.6395 | N15: =M15/$N$4 -> 131.45465 | O15: =N15/$O$4 -> 16.431831 | P15: =O15/$P$4 -> 0.27386385 | R15: =G15*11.92% -> 369.818 | S15: 0 | T15: =G15+L15-R15-S15 -> 2732.682
B16: 8 | C16: MOZO | D16: ASIN VINCES VICTOR ANDRES | E16: 1270.8 | G16: =E16+F16 -> 1270.8 | H16: =G16*$H$4 -> 115.45218 | I16: =G16*$I$4 -> 61.76088 | J16: =G16*$J$4 -> 52.949998 | K16: =G16*$K$4 -> 114.372 | L16: 0 | M16: =G16+H16+I16+J16+K16+L16 -> 1615.3351 | N16: =M16/$N$4 -> 53.844502 | O16: =N16/$O$4 -> 6.7305627 | P16: =O16/$P$4 -> 0.11217605 | R16: =G16*11.92% -> 151.47936 | S16: 0 | T16: =G16+L16-R16-S16 -> 1119.3206
D18: TOTALES PLANILLA - | E18: =SUM(E9:E17) -> 11743.34 | F18: =SUM(F9:F17) -> 205 | G18: =SUM(G9:G17) -> 11948.34 | H18: =SUM(H9:H17) -> 1156.3515 | I18: =SUM(I9:I17) -> 618.5876 | J18: =SUM(J9:J17) -> 530.33915 | K18: =SUM(K9:K17) -> 1075.3506 | L18: =SUM(L9:L17) -> 0 | M18: =SUM(M9:M17) -> 15328.969 | N18: =SUM(N9:N13) -> 291.77003 | O18: =SUM(O9:O13) -> 36.471254 | P18: =SUM(P9:P13) -> 0.60785424 | R18: =SUM(R9:R17) -> 1421.7239 | S18: =SUM(S9:S17) -> 0 | T18: =SUM(T9:T17) -> 10526.616
B21: N° | C21: CARGO | D21: DATOS PERSONALES | E21: BASICO | F21: ASIG. FAMILIAR | G21: REMUN. IMPONIBLE | H21: GRATIFICACIONES Julio y Diciembre | I21: CTS | J21: VACACIONES | K21: ESSALUD | M21: COSTO MENSUAL | N21: COSTO DIARIO | O21: COSTO POR HORA | P21: COSTO POR MIN | R21: AFP/ONP | S21: RTA 5TA | T21: NETO
L22: MOVILIDAD
B24: 1 | C24: CHEF EJECUTIVO | D24: DANIEL BENITES SEBAN (*RGL) | E24: 4208.6 | F24: 0 | G24: =E24+F24 -> 4208.6 | H24: =G24*$H$3 -> 764.70262 | I24: =G24*$I$3 -> 409.07592 | J24: =G24*$J$3 -> 350.71665 | K24: =G24*$K$4 -> 378.774 | L24: 0 | M24: =G24+H24+I24+J24+K24+L24 -> 6111.8692 | N24: =M24/$N$4 -> 203.72897 | O24: =N24/$O$4 -> 25.466122 | P24: =O24/$P$4 -> 0.42443536 | R24: =G24*11.97% -> 503.76942 | S24: 204 | T24: =G24+L24-R24-S24 -> 3500.8306
B25: =B24+1 -> 2 | C25: BARMAN JEFE | D25: FERNANDEZ RUIZ JENNER JOEL | E25: 1706.7 | F25: 102.5 | G25: =E25+F25 -> 1809.2 | H25: =G25*$H$4 -> 164.36582 | I25: =G25*$I$4 -> 87.92712 | J25: =G25*$J$4 -> 75.38333 | K25: =G25*$K$4 -> 162.828 | L25: 0 | M25: =G25+H25+I25+J25+K25+L25 -> 2299.7043 | N25: =M25/$N$4 -> 76.656809 | O25: =N25/$O$4 -> 9.5821011 | P25: =O25/$P$4 -> 0.15970169 | R25: =G25*11.74% -> 212.40008 | S25: 0 | T25: =G25+L25-R25-S25 -> 1596.7999
B26: =B25+1 -> 3 | C26: JEFE DE SALON | D26: MORALES GONZALES CARLOS DANIEL | E26: 1562.4 | G26: =E26+F26 -> 1562.4 | H26: =G26*$H$4 -> 141.94404 | I26: =G26*$I$4 -> 75.93264 | J26: =G26*$J$4 -> 65.099997 | K26: =G26*$K$4 -> 140.616 | L26: 0 | M26: =G26+H26+I26+J26+K26+L26 -> 1985.9927 | N26: =M26/$N$4 -> 66.199756 | O26: =N26/$O$4 -> 8.2749695 | P26: =O26/$P$4 -> 0.13791616 | R26: =G26*11.92% -> 186.23808 | S26: 0 | T26: =G26+L26-R26-S26 -> 1376.1619
B27: 4 | C27: BARMAN | D27: VERA VILLALOBOS ALDA ARECELY | E27: 1463.2 | G27: =E27+F27 -> 1463.2 | H27: =G27*$H$4 -> 132.93172 | I27: =G27*$I$4 -> 71.11152 | J27: =G27*$J$4 -> 60.966664 | K27: =G27*$K$4 -> 131.688 | L27: 0 | M27: =G27+H27+I27+J27+K27+L27 -> 1859.8979 | N27: =M27/$N$4 -> 61.996597 | O27: =N27/$O$4 -> 7.7495746 | P27: =O27/$P$4 -> 0.12915958 | R27: =G27*13% -> 190.216 | S27: 0 | T27: =G27+L27-R27-S27 -> 1272.984
B28: 5 | C28: BARMAN | D28: PARIONA YUPA YERSON ALDAHIR | E28: 1459.7 | F28: 0 | G28: =E28+F28 -> 1459.7 | H28: =G28*$H$4 -> 132.61375 | I28: =G28*$I$4 -> 70.94142 | J28: =G28*$J$4 -> 60.820831 | K28: =G28*$K$4 -> 131.373 | L28: 0 | M28: =G28+H28+I28+J28+K28+L28 -> 1855.449 | N28: =M28/$N$4 -> 61.8483 | O28: =N28/$O$4 -> 7.7310375 | P28: =O28/$P$4 -> 0.12885062 | R28: =G28*11.97% -> 174.72609 | S28: 0 | T28: =G28+L28-R28-S28 -> 1284.9739
B29: 6 | C29: COCINERO | D29: SINTI SANTIVAÑEZ JEAN PAUL | E29: 1686.22 | G29: =E29+F29 -> 1686.22 | H29: =G29*$H$4 -> 153.19309 | I29: =G29*$I$4 -> 81.950292 | J29: =G29*$J$4 -> 70.259164 | K29: =G29*$K$4 -> 151.7598 | L29: 0 | M29: =G29+H29+I29+J29+K29+L29 -> 2143.3823 | N29: =M29/$N$4 -> 71.446078 | O29: =N29/$O$4 -> 8.9307598 | P29: =O29/$P$4 -> 0.148846 | R29: =G29*11.74% -> 197.96223 | S29: 0 | T29: =G29+L29-R29-S29 -> 1488.2578
B30: 7 | C30: ASISTENTE DE LOGISTICA | D30: MAMANI HUAMANI YAMIR JOSE | E30: 800 | G30: =E30+F30 -> 800 | H30: =G30*$H$4 -> 72.68 | I30: =G30*$I$4 -> 38.88 | J30: =G30*$J$4 -> 33.333332 | K30: =G30*$K$4 -> 72 | L30: 0 | M30: =G30+H30+I30+J30+K30+L30 -> 1016.8933 | N30: =M30/$N$4 -> 33.896444 | O30: =N30/$O$4 -> 4.2370556 | P30: =O30/$P$4 -> 0.070617593 | R30: =G30*11.92% -> 95.36 | S30: 0 | T30: =G30+L30-R30-S30 -> 704.64
B31: 8 | C31: COCINERO | D31: SOTERO ROMAN JULIO MARTIN | E31: 2104.35 | G31: =E31+F31 -> 2104.35 | H31: =G31*$H$4 -> 191.1802 | I31: =G31*$I$4 -> 102.27141 | J31: =G31*$J$4 -> 87.681246 | K31: =G31*$K$4 -> 189.3915 | L31: 0 | M31: =G31+H31+I31+J31+K31+L31 -> 2674.8744 | N31: =M31/$N$4 -> 89.162478 | O31: =N31/$O$4 -> 11.14531 | P31: =O31/$P$4 -> 0.18575516 | R31: =G31*13.29% -> 279.66811 | S31: 0 | T31: =G31+L31-R31-S31 -> 1824.6819
B32: 9 | C32: AYUDANTE DE COCINA | D32: ANDRICH PAREDES RODRIGO ALBERTO | E32: 1300 | G32: =E32+F32 -> 1300 | H32: =G32*$H$4 -> 118.105 | I32: =G32*$I$4 -> 63.18 | J32: =G32*$J$4 -> 54.166664 | K32: =G32*$K$4 -> 117 | L32: 0 | M32: =G32+H32+I32+J32+K32+L32 -> 1652.4517 | N32: =M32/$N$4 -> 55.081722 | O32: =N32/$O$4 -> 6.8852153 | P32: =O32/$P$4 -> 0.11475359 | R32: =G32*13.29% -> 172.77 | S32: 0 | T32: =G32+L32-R32-S32 -> 1127.23
B33: 10 | C33: COCINERA | D33: ANDRICH PAREDES VALERIA ALEJANDRA | E33: 1762.5 | G33: =E33+F33 -> 1762.5 | H33: =G33*$H$4 -> 160.12313 | I33: =G33*$I$4 -> 85.6575 | J33: =G33*$J$4 -> 73.437497 | K33: =G33*$K$4 -> 158.625 | L33: 0 | M33: =G33+H33+I33+J33+K33+L33 -> 2240.3431 | N33: =M33/$N$4 -> 74.678104 | O33: =N33/$O$4 -> 9.334763 | P33: =O33/$P$4 -> 0.15557938 | R33: =G33*13.29% -> 234.23625 | S33: 0 | T33: =G33+L33-R33-S33 -> 1528.2638
D35: TOTALES PLANILLA - | E35: =SUM(E24:E34) -> 18053.67 | F35: =SUM(F24:F34) -> 102.5 | G35: =SUM(G24:G34) -> 18156.17 | H35: =SUM(H24:H34) -> 2031.8394 | I35: =SUM(I24:I34) -> 1086.9278 | J35: =SUM(J24:J34) -> 931.86538 | K35: =SUM(K24:K34) -> 1634.0553 | L35: =SUM(L24:L34) -> 0 | M35: =SUM(M24:M34) -> 23840.858 | N35: =SUM(N24:N33) -> 794.69526 | O35: =SUM(O24:O33) -> 99.336908 | P35: =SUM(P24:P33) -> 1.6556151 | R35: =SUM(R24:R34) -> 2247.3463 | S35: =SUM(S24:S34) -> 204 | T35: =SUM(T24:T34) -> 15704.824
E37: =+E18+E35 -> 29797.01

Sheet Hoja1
D2: N° | E2: RELACIÓN DE PERSONAL LA MARIPOSARIO
D3: 1 | E3: ANA LUCIA BRETONECHE DIAPIS
D4: 2 | E4: YAMIR JOSE MAMANI HUAMANI
D5: 3 | E5: JOSE LUIS LOPEZ TOVAR
D6: 4 | E6: CALIXTO VIECENTE BLAS
D7: 5 | E7: PEDRO GIOMAR CHUNGA VILLAR
D8: 6 | E8: ALDA ARECELY VERA VILLALOBOS
D9: 7 | E9: ANGIRBER AGBRIEL CARARQUEL HERNANDEZ
D10: 8 | E10: CALIXTO VIECENTE BLAS
D11: 9 | E11: SUSY MILAGRO ALEJOS ARDELAS
D12: 10 | E12: FERNANDO MOYA HUAMANI
D13: 11 | E13: DARIO TELLO FLORES

Sheet AFP SBS
A3: Al mes de devengue 2025-02
A4: AFP | B4: Comisión | C4: Comisión | D4: Prima de | E4: Porcentaje de aporte obligatorio al Fondo de Pensiones (%) | F4: Remuneración Máxima Asegurable (S/.)
B5: Fija (S/). /2 | C5: Variable (%) | D5: Seguros (%) /3
A6: HABITAT | C6: 1.47 | D6: 1.37 | E6: 10 | F6: 12027.91
A7: INTEGRA | C7: 1.55 | D7: 1.37 | E7: 10 | F7: 12027.91
A8: PRIMA | C8: 1.6 | D8: 1.37 | E8: 10 | F8: 12027.91
A9: PROFUTURO | C9: 1.69 | D9: 1.37 | E9: 10 | F9: 12027.91
A11: * Comisiones descontadas sobre la Remuneración Bruta. No se considera descuentos por permanencia puesto que tales descuentos no afectan las retenciones del empleador.
A12: 1/ Las comisiones y primas retenidas correspondientes al mes de devengue "t" deben pagarse dentro de los 5 primeros días útiles del mes "t+1".
A13: 2/ A partir de Enero de 1997 se eliminó el cobro de Comisión Fija.
A14: 3/ Porcentaje a descontar sobre la Remuneración Bruta hasta el límite determinado por la Remuneración Máxima Asegurable (art. 67° del Título VII del Compendio de Normas reglamentarias del SPP).
A16: Al mes de devengue 2025-03
A17: AFP | B17: Comisión | C17: Comisión | D17: Prima de | E17: Porcentaje de aporte obligatorio al Fondo de Pensiones (%) | F17: Remuneración Máxima Asegurable (S/.)
B18: Fija (S/). /2 | C18: Variable (%) | D18: Seguros (%) /3
A19: HABITAT | C19: 1.47 | D19: 1.37 | E19: 10 | F19: 12027.91
A20: INTEGRA | C20: 1.55 | D20: 1.37 | E20: 10 | F20: 12027.91
A21: PRIMA | C21: 1.6 | D21: 1.37 | E21: 10 | F21: 12027.91
A22: PROFUTURO | C22: 1.69 | D22: 1.37 | E22: 10 | F22: 12027.91
A24: * Comisiones descontadas sobre la Remuneración Bruta. No se considera descuentos por permanencia puesto que tales descuentos no afectan las retenciones del empleador.
A25: 1/ Las comisiones y primas retenidas correspondientes al mes de devengue "t" deben pagarse dentro de los 5 primeros días útiles del mes "t+1".
A26: 2/ A partir de Enero de 1997 se eliminó el cobro de Comisión Fija.
A27: 3/ Porcentaje a descontar sobre la Remuneración Bruta hasta el límite determinado por la Remuneración Máxima Asegurable (art. 67° del Título VII del Compendio de Normas reglamentarias del SPP).
A29: Al mes de devengue 2025-04
A30: AFP | B30: Comisión | C30: Comisión | D30: Prima de | E30: Porcentaje de aporte obligatorio al Fondo de Pensiones (%) | F30: Remuneración Máxima Asegurable (S/.)
B31: Fija (S/). /2 | C31: Variable (%) | D31: Seguros (%) /3
A32: HABITAT | C32: 1.47 | D32: 1.37 | E32: 10 | F32: 12137.47
A33: INTEGRA | C33: 1.55 | D33: 1.37 | E33: 10 | F33: 12137.47
A34: PRIMA | C34: 1.6 | D34: 1.37 | E34: 10 | F34: 12137.47
A35: PROFUTURO | C35: 1.69 | D35: 1.37 | E35: 10 | F35: 12137.47
A36: * Comisiones descontadas sobre la Remuneración Bruta. No se considera descuentos por permanencia puesto que tales descuentos no afectan las retenciones del empleador.
A37: 1/ Las comisiones y primas retenidas correspondientes al mes de devengue "t" deben pagarse dentro de los 5 primeros días útiles del mes "t+1".
A38: 2/ A partir de Enero de 1997 se eliminó el cobro de Comisión Fija.
A39: 3/ Porcentaje a descontar sobre la Remuneración Bruta hasta el límite determinado por la Remuneración Máxima Asegurable (art. 67° del Título VII del Compendio de Normas reglamentarias del SPP).
A41: Al mes de devengue 2025-05
A42: AFP | B42: Comisión | C42: Comisión | D42: Prima de | E42: Porcentaje de aporte obligatorio al Fondo de Pensiones (%) | F42: Remuneración Máxima Asegurable (S/.)
B43: Fija (S/). /2 | C43: Variable (%) | D43: Seguros (%) /3
A44: HABITAT | C44: 1.47 | D44: 1.37 | E44: 10 | F44: 12137.47
A45: INTEGRA | C45: 1.55 | D45: 1.37 | E45: 10 | F45: 12137.47
A46: PRIMA | C46: 1.6 | D46: 1.37 | E46: 10 | F46: 12137.47
A47: PROFUTURO | C47: 1.69 | D47: 1.37 | E47: 10 | F47: 12137.47
A49: * Comisiones descontadas sobre la Remuneración Bruta. No se considera descuentos por permanencia puesto que tales descuentos no afectan las retenciones del empleador.
A50: 1/ Las comisiones y primas retenidas correspondientes al mes de devengue "t" deben pagarse dentro de los 5 primeros días útiles del mes "t+1".
A51: 2/ A partir de Enero de 1997 se eliminó el cobro de Comisión Fija.
A52: 3/ Porcentaje a descontar sobre la Remuneración Bruta hasta el límite determinado por la Remuneración Máxima Asegurable (art. 67° del Título VII del Compendio de Normas reglamentarias del SPP).
A54: Al mes de devengue 2025-06
A55: AFP | B55: Comisión | C55: Comisión | D55: Prima de | E55: Porcentaje de aporte obligatorio al Fondo de Pensiones (%) | F55: Remuneración Máxima Asegurable (S/.)
B56: Fija (S/). /2 | C56: Variable (%) | D56: Seguros (%) /3
A57: HABITAT | C57: 1.47 | D57: 1.37 | E57: 10 | F57: 12137.47
A58: INTEGRA | C58: 1.55 | D58: 1.37 | E58: 10 | F58: 12137.47
A59: PRIMA | C59: 1.6 | D59: 1.37 | E59: 10 | F59: 12137.47
A60: PROFUTURO | C60: 1.69 | D60: 1.37 | E60: 10 | F60: 12137.47
A62: * Comisiones descontadas sobre la Remuneración Bruta. No se considera descuentos por permanencia puesto que tales descuentos no afectan las retenciones del empleador.
A63: 1/ Las comisiones y primas retenidas correspondientes al mes de devengue "t" deben pagarse dentro de los 5 primeros días útiles del mes "t+1".
A64: 2/ A partir de Enero de 1997 se eliminó el cobro de Comisión Fija.
A65: 3/ Porcentaje a descontar sobre la Remuneración Bruta hasta el límite determinado por la Remuneración Máxima Asegurable (art. 67° del Título VII del Compendio de Normas reglamentarias del SPP).
A67: Al mes de devengue 2025-07
A68: AFP | B68: Comisión | C68: Comisión | D68: Prima de | E68: Porcentaje de aporte obligatorio al Fondo de Pensiones (%) | F68: Remuneración Máxima Asegurable (S/.)
B69: Fija (S/). /2 | C69: Variable (%) | D69: Seguros (%) /3
A70: HABITAT | C70: 1.47 | D70: 1.37 | E70: 10 | F70: 12184.88
A71: INTEGRA | C71: 1.55 | D71: 1.37 | E71: 10 | F71: 12184.88
A72: PRIMA | C72: 1.6 | D72: 1.37 | E72: 10 | F72: 12184.88
A73: PROFUTURO | C73: 1.69 | D73: 1.37 | E73: 10 | F73: 12184.88
A75: * Comisiones descontadas sobre la Remuneración Bruta. No se considera descuentos por permanencia puesto que tales descuentos no afectan las retenciones del empleador.
A76: 1/ Las comisiones y primas retenidas correspondientes al mes de devengue "t" deben pagarse dentro de los 5 primeros días útiles del mes "t+1".
A77: 2/ A partir de Enero de 1997 se eliminó el cobro de Comisión Fija.
A78: 3/ Porcentaje a descontar sobre la Remuneración Bruta hasta el límite determinado por la Remuneración Máxima Asegurable (art. 67° del Título VII del Compendio de Normas reglamentarias del SPP).
A80: Al mes de devengue 2025-08
A81: AFP | B81: Comisión | C81: Comisión | D81: Prima de | E81: Porcentaje de aporte obligatorio al Fondo de Pensiones (%) | F81: Remuneración Máxima Asegurable (S/.)
B82: Fija (S/). /2 | C82: Variable (%) | D82: Seguros (%) /3
A83: HABITAT | C83: 1.47 | D83: 1.37 | E83: 10 | F83: 12178.56
A84: INTEGRA | C84: 1.55 | D84: 1.37 | E84: 10 | F84: 12178.56
A85: PRIMA | C85: 1.6 | D85: 1.37 | E85: 10 | F85: 12178.56
A86: PROFUTURO | C86: 1.69 | D86: 1.37 | E86: 10 | F86: 12178.56
A88: * Comisiones descontadas sobre la Remuneración Bruta. No se considera descuentos por permanencia puesto que tales descuentos no afectan las retenciones del empleador.
A89: 1/ Las comisiones y primas retenidas correspondientes al mes de devengue "t" deben pagarse dentro de los 5 primeros días útiles del mes "t+1".
A90: 2/ A partir de Enero de 1997 se eliminó el cobro de Comisión Fija.
A91: 3/ Porcentaje a descontar sobre la Remuneración Bruta hasta el límite determinado por la Remuneración Máxima Asegurable (art. 67° del Título VII del Compendio de Normas reglamentarias del SPP).
A93: Mes de devengue :
A94: Al mes de devengue 2025-09 1/
A95: AFP | B95: COMISIÓN | C95: COMISIÓN | D95: PRIMA DE | E95: APORTE OBLIGATORIO AL FONDO DE PENSIONES | F95: REMUNERACIÓN MÁXIMA ASEGURABLE
B96: SOBRE FLUJO | C96: ANUAL SOBRE | D96: SEGUROS (%) 3/ | E96: (% Remuneración Bruta Mensual)
B97: (% Remuneración Bruta Mensual) | C97: SALDO | D97: (% Remuneración Bruta Mensual)
A98: HABITAT | B98: 1,47% | C98: 1,25% | D98: 1,37% | E98: 10,00% | F98: 12178.56
A99: INTEGRA | B99: 1,55% | C99: 0,78% | D99: 1,37% | E99: 10,00% | F99: 12178.56
A100: PRIMA | B100: 1,60% | C100: 1,25% | D100: 1,37% | E100: 10,00% | F100: 12178.56
A101: PROFUTURO | B101: 1,69% | C101: 0,68% | D101: 1,37% | E101: 10,00% | F101: 12178.56
A103: 1/ Las comisiones sobre la remuneración y las primas retenidas correspondientes a un determinado mes deben pagarse dentro de los 5 primeros dÍas útiles del mes siguiente.
A104: 2/ A partir de Enero de 1997 se eliminó el cobro de Comisión Fija.
A105: 3/ Porcentaje a descontar sobre la Remuneración Bruta hasta el límite determinado por el Reglamentode la Ley del SPP(Remuneración Máxima Asegurable Art. 67° del Título VII del Compendio de Normas reglamentarias del SPP).
A106: *** A partir de Febrero de 2023, el componente de flujo de la Comisión Mixta es 0%, resultando únicamente en Comisión anulado sobre saldo.
A108: Al mes de devengue 2025-10 1/
A109: AFP | B109: COMISIÓN | C109: COMISIÓN | D109: PRIMA DE | E109: APORTE OBLIGATORIO AL FONDO DE PENSIONES | F109: REMUNERACIÓN MÁXIMA ASEGURABLE
B110: SOBRE FLUJO | C110: ANUAL SOBRE | D110: SEGUROS (%) 3/ | E110: (% Remuneración Bruta Mensual)
B111: (% Remuneración Bruta Mensual) | C111: SALDO | D111: (% Remuneración Bruta Mensual)
A112: HABITAT | B112: 1,47% | C112: 1,25% | D112: 1,37% | E112: 10,00% | F112: 12 178,56
A113: INTEGRA | B113: 1,55% | C113: 0,78% | D113: 1,37% | E113: 10,00% | F113: 12 178,56
A114: PRIMA | B114: 1,60% | C114: 1,25% | D114: 1,37% | E114: 10,00% | F114: 12 178,56
A115: PROFUTURO | B115: 1,69% | C115: 0,68% | D115: 1,37% | E115: 10,00% | F115: 12 178,56
A117: 1/ Las comisiones sobre la remuneración y las primas retenidas correspondientes a un determinado mes deben pagarse dentro de los 5 primeros dÍas útiles del mes siguiente.
A118: 2/ A partir de Enero de 1997 se eliminó el cobro de Comisión Fija.
...

Sheet PLANILLA MENSUAL
B1: 1 | C1: 2 | I1: 6 | R1: 14 | W1: 16 | X1: 17 | Y1: 18 | Z1: 19 | AA1: 20 | AD1: 21 | AF1: 22 | AK1: 24 | AL1: 25 | AM1: 26 | AN1: 27 | AO1: 28 | AP1: 29 | AQ1: 30 | AR1: 31 | AS1: 32 | AT1: 33 | AU1: 34 | AV1: 35 | AW1: 36 | AX1: 37 | BB1: 39 | BI1: 41 | BJ1: 42 | BK1: 43 | BL1: 44 | BO1: 48 | BS1: 75 | BT1: 76 | BU1: 77 | BV1: 78 | BW1: 79 | BX1: 80 | BY1: 81 | BZ1: 82 | CA1: 83 | CB1: 84 | CC1: 85 | CD1: 86 | CE1: 87 | CF1: 88 | CG1: 89 | CH1: 90 | CI1: 91 | CJ1: 92 | CK1: 93 | CL1: 94 | CM1: 95 | CN1: 96 | CO1: 97 | CP1: 98 | CQ1: 99 | CR1: 100 | CS1: 101 | CT1: 102 | CU1: 103 | CV1: 104 | CW1: 105 | CX1: 106 | CY1: 107 | CZ1: 108 | DA1: 109 | DB1: 110 | DC1: 111 | DD1: 112 | DE1: 113 | DF1: 114 | DG1: 115 | DH1: 116 | DI1: 117 | DJ1: 118 | DK1: 119 | DL1: 120 | DM1: 121 | DN1: 122 | DO1: 123 | DP1: 124 | DQ1: 125 | DR1: 126 | DS1: 127 | DT1: 128 | DU1: 129 | DV1: 130 | DW1: 131 | DX1: 132 | DY1: 133 | DZ1: 134 | EA1: 135 | EB1: 136 | EC1: 137 | ED1: 138 | EE1: 139 | EF1: 140 | EG1: 141 | EH1: 142 | EI1: 143 | EJ1: 144 | EK1: 145 | EL1: 146 | EM1: 147 | EN1: 148 | EO1: 149 | EP1: 150 | EQ1: 151 | ER1: 152 | ES1: 153 | ET1: 154 | EU1: 155 | EV1: 156 | EW1: 157 | EX1: 158
B2: INDUSTRIAL PROCESS S.R.L.
B3: R.U.C.: 20514706302
B4: PLANILLA DE REMUNERACIONES MES DE JULIO 2026
B6: (EXPRESADO EN NUEVOS SOLES)
C8: TRABAJADOR | I8: DATOS DEL PERSONAL | R8: REMUNERACIONES | AO8: DESCUENTOS | BI8: TOTAL | BJ8: NETO A | BK8: APORTACION
B9: N° | C9: APELLIDOS | E9: FECHA | F9: FECHA | G9: FECHA | I9: AFP | R9: REMUNER. | S9: ASIGNAC. | T9: DESCA. | U9: COMISION | V9: COMISION | W9: HORAS | X9: HORAS | Y9: FERIADOS | AA9: VACACIONES | AB9: VACACIONES | AC9: VACACIONES | AD9: CTS | AE9: VALES | AF9: GRATIFIC. | AG9: BONIF | AH9: BONIF | AI9: DEVOL | AJ9: UTILIDAD | AK9: BONO | AM9: REMUNER | AN9: REMUNERA. | AO9: ONP | AQ9: A.F.P. | BB9: GRATI | BC9: PTMOS | BD9: SEGURO | BE9: SEGURO | BF9: VALES | BG9: OTROS | BH9: RENTA | BI9: DESCUENT. | BJ9: PAGAR | BK9: ESSALUD | BM9: SEGURO | BN9: SEGURO | BO9: BCO
C10: PATERNO | D10: DNI, CE | E10: DE | F10: DE | G10: DE | H10: CARGO | I10: Y | J10: SUELDO BASE | K10: ASIG FAM | L10: TOTAL DIAS | M10: DIAS NO LAB Y/O | N10: DIAS NO LAB Y/O | O10: TOTAL DIAS | P10: HRS X DIA | Q10: TOTAL HRS | R10: PERCIBIDA | S10: FAMILIAR | T10: MEDICO | U10: DEL MES | V10: PROMEDIO | W10: EXTRAS | X10: EXTRAS | Z10: MOVIL | AA10: TRUNCAS | AB10: INDE. | AE10: CONSUMO | AG10: 0.09 | AI10: RTA 5TA | AK10: EXTRAOR | AL10: DESC. | AM10: BRUTA | AN10: AFECTA | AO10: % | AP10: S/. | AQ10: APORTE | AS10: COMISION | AU10: PRIMA | AW10: TOTAL A.F.P. | AY10: FALTAS | AZ10: TARDAN | BA10: ADELANTO | BD10: PACIFICO | BE10: EPS | BF10: CONSUMO | BG10: DSCTOS | BH10: 5TA CATEG | BM10: VIDA LEY | BN10: PRIVADO | BP10: POR | BQ10: DIF | BS10: ADELANTO | BV10: A PAGAR
E11: NACIMIENTO | F11: INGRESO | G11: CESE | I11: ONP | L11: MES | M11: DESCANSO | N11: VACAC | O11: LABOR | Q11: MES | V11: VACACIONES | W11: 0.25 | X11: 0.35 | AE11: OBSEQUIO | AK11: U OTRO | AQ11: % | AR11: OBLIG | AS11: % | AT11: S/. | AU11: % | AV11: SEGURO | AW11: % | AX11: S/. | AZ11: ZAS | BF11: OBSEQUIOS | BK11: % | BL11: S/. | BN11: EPS | BP11: REEMB
A12: VTAS | B12: 1 | C12: ORIHUELA AGUIRRE ERNESTO JULIO | D12: 10305226 | E12: 27747 | F12: 39114 | H12: GERENTE GENERAL | I12: INTEGRA | J12: 13000 | K12: 113 | L12: 30 | O12: =+L12-M12-N12 -> 30 | P12: 8 | Q12: =+O12*P12 -> 240 | R12: =+J12-AC12-T12 -> 13000 | S12: =K12 -> 113 | T12: =(J12)/30*M12 -> 0 | U12: =COMISIONES!J6 -> 7965.7048 | W12: =H.E!L6 -> 0 | X12: =H.E!M6 -> 0 | Y12: =H.E!N6 -> 0 | AC12: =(J12+K12)/30*N12 -> 0 | AF12: 19419.652 | AG12: 1747.7687 | AM12: =SUM(R12:AK12)-AL12 -> 42246.125 | AN12: =+AM12-Z12-AD12-AE12-AF12-AG12-AJ12-AK12-AI12-AY12-AZ12 -> 21078.705 | AQ12: 0.1 | AR12: =+AN12*AQ12 -> 2107.8705 | AS12: 0 | AT12: =+AN12*AS12 -> 0 | AU12: 0.0137 | AV12: =12672.65*AU12 -> 173.61531 | AW12: =+AQ12+AS12+AU12 -> 0.1137 | AX12: =+AR12+AT12+AV12 -> 2281.4858 | AY12: =TARDANZA!K6 -> 0 | AZ12: =TARDANZA!L6 -> 0 | BB12: =AF12+AG12 -> 21167.421 | BD12: 279.8 | BH12: =+'RTA 5TA VTAS'!D121 -> 4742.0367 | BI12: =+AX12+SUM(AY12:BH12)+AP12 -> 28470.743 | BJ12: =(+AM12-BI12) -> 13775.382 | BK12: 0.09 | BL12: =AN12*BK12 -> 1897.0834 | BM12: 47.24 | BO12: BBVA | BU12: BBVA
A13: ADM | B13: =+B12+1 -> 2 | C13: MARTINEZ CASTILLO GIOVANNA RAQUEL | D13: 9594953 | E13: 26364 | F13: 41548 | H13: JEFE DE ADMINISTRACION | I13: PROFUTURO | J13: 6500 | K13: 113 | L13: 30 | O13: =+L13-M13-N13 -> 30 | P13: 8 | Q13: =+O13*P13 -> 240 | R13: =+J13-AC13-T13 -> 6500 | S13: =K13 -> 113 | T13: =(J13)/30*M13 -> 0 | W13: =H.E!L7 -> 0 | X13: =H.E!M7 -> 0 | Y13: =H.E!N7 -> 0 | Z13: 100 | AC13: =(J13+K13)/30*N13 -> 0 | AF13: 6613 | AG13: 595.17 | AM13: =SUM(R13:AK13)-AL13 -> 13921.17 | AN13: =+AM13-Z13-AD13-AE13-AF13-AG13-AJ13-AK13-AI13-AY13-AZ13 -> 6613 | AQ13: 0.1 | AR13: =+AN13*AQ13 -> 661.3 | AS13: 0 | AT13: =+AN13*AS13 -> 0 | AU13: 0.0137 | AV13: =+AN13*AU13 -> 90.5981 | AW13: =+AQ13+AS13+AU13 -> 0.1137 | AX13: =+AR13+AT13+AV13 -> 751.8981 | AY13: =TARDANZA!K7 -> 0 | AZ13: =TARDANZA!L7 -> 0 | BB13: =AF13+AG13 -> 7208.17 | BD13: 243.85 | BH13: =+'RTA 5TA'!D115 -> 530.03032 | BI13: =+AX13+SUM(AY13:BH13)+AP13 -> 8733.9484 | BJ13: =(+AM13-BI13) -> 5187.2216 | BK13: 0.09 | BL13: =AN13*BK13 -> 595.17 | BM13: 23.8407 | BO13: BBVA | BU13: BBVA
A14: SOPORTE | B14: =+B13+1 -> 3 | C14: SALVADOR ROJAS ELVIS ALFONSO | D14: 46335654 | E14: 33029 | F14: 42327 | H14: SUPERVISOR DE SOPORTE TECNICO Y MANTENIMINENTO | I14: INTEGRA | J14: 4000 | K14: 113 | L14: 30 | O14: =+L14-M14-N14 -> 30 | P14: 8 | Q14: =+O14*P14 -> 240 | R14: =+J14-AC14-T14 -> 4000 | S14: =K14 -> 113 | T14: =(J14)/30*M14 -> 0 | W14: =H.E!L8 -> 0 | X14: =H.E!M8 -> 0 | Y14: =H.E!N8 -> 0 | Z14: 100 | AC14: =(J14+K14)/30*N14 -> 0 | AF14: 4453.1231 | AG14: 400.78108 | AM14: =SUM(R14:AK14)-AL14 -> 9066.9042 | AN14: =+AM14-Z14-AD14-AE14-AF14-AG14-AJ14-AK14-AI14-AY14-AZ14 -> 4016.4587 | AQ14: 0.1 | AR14: =+AN14*AQ14 -> 401.64587 | AS14: 0.0155 | AT14: =+AN14*AS14 -> 62.255111 | AU14: 0.0137 | AV14: =+AN14*AU14 -> 55.025485 | AW14: =+AQ14+AS14+AU14 -> 0.1292 | AX14: =+AR14+AT14+AV14 -> 518.92647 | AY14: =TARDANZA!K8 -> 0 | AZ14: =TARDANZA!L8 -> 96.54125 | BB14: =AF14+AG14 -> 4853.9042 | BH14: =+'RTA 5TA'!H115 -> 160.75494 | BI14: =+AX14+SUM(AY14:BH14)+AP14 -> 5630.1269 | BJ14: =(+AM14-BI14) -> 3436.7773 | BK14: 0.09 | BL14: =AN14*BK14 -> 361.48129 | BM14: 6.17 | BO14: BCP | BU14: BCP
A15: SOPORTE | B15: =+B14+1 -> 4 | C15: LOLI RODRIGUEZ JANIO RICHARD | D15: 41675364 | E15: 29556 | F15: 42513 | H15: COORDINADOR DE SOPORTE TECNICO | I15: PRIMA | J15: 4000 | K15: 113 | L15: 30 | O15: =+L15-M15-N15 -> 30 | P15: 8 | Q15: =+O15*P15 -> 240 | R15: =+J15-AC15-T15 -> 4000 | S15: =K15 -> 113 | T15: =(J15)/30*M15 -> 0 | W15: =H.E!L9 -> 0 | X15: =H.E!M9 -> 0 | Y15: =H.E!N9 -> 0 | Z15: 100 | AC15: =(J15+K15)/30*N15 -> 0 | AF15: 4113 | AG15: 370.17 | AM15: =SUM(R15:AK15)-AL15 -> 8696.17 | AN15: =+AM15-Z15-AD15-AE15-AF15-AG15-AJ15-AK15-AI15-AY15-AZ15 -> 4113 | AQ15: 0.1 | AR15: =+AN15*AQ15 -> 411.3 | AS15: 0.016 | AT15: =+AN15*AS15 -> 65.808 | AU15: 0.0137 | AV15: =+AN15*AU15 -> 56.3481 | AW15: =+AQ15+AS15+AU15 -> 0.1297 | AX15: =+AR15+AT15+AV15 -> 533.4561 | AY15: =TARDANZA!K9 -> 0 | AZ15: =TARDANZA!L9 -> 0 | BB15: =AF15+AG15 -> 4483.17 | BG15: 320.22121 | BH15: =+'RTA 5TA'!E115 -> 140.09305 | BI15: =+AX15+SUM(AY15:BH15)+AP15 -> 5476.9404 | BJ15: =(+AM15-BI15) -> 3219.2296 | BK15: 0.09 | BL15: =AN15*BK15 -> 370.17 | BM15: 16.0407 | BO15: BCP | BU15: BCP
A16: LOGISTICA | B16: =+B15+1 -> 5 | C16: PEREZ CAJAHUANCA ARACELLI IRAIDA | D16: 44425022 | E16: 31996 | F16: 42917 | H16: COORDINADOR DE LOGISTICA | I16: INTEGRA | J16: 3600 | L16: 30 | N16: 6 | O16: =+L16-M16-N16 -> 24 | P16: 8 | Q16: =+O16*P16 -> 192 | R16: =+J16-AC16-T16 -> 2880 | S16: =K16 -> 0 | T16: =(J16)/30*M16 -> 0 | W16: =H.E!L10 -> 0 | X16: =H.E!M10 -> 0 | Y16: =H.E!N10 -> 240 | Z16: 73.913043 | AC16: =(J16+K16)/30*N16 -> 720 | AF16: 4240 | AG16: 381.6 | AH16: 640 | AM16: =SUM(R16:AK16)-AL16 -> 9175.513 | AN16: =+AM16-Z16-AD16-AE16-AF16-AG16-AJ16-AK16-AI16-AY16-AZ16 -> 4403 | AQ16: 0.1 | AR16: =+AN16*AQ16 -> 440.3 | AS16: 0.0155 | AT16: =+AN16*AS16 -> 68.2465 | AU16: 0.0137 | AV16: =+AN16*AU16 -> 60.3211 | AW16: =+AQ16+AS16+AU16 -> 0.1292 | AX16: =+AR16+AT16+AV16 -> 568.8676 | AY16: =TARDANZA!K10 -> 0 | AZ16: =TARDANZA!L10 -> 77 | BB16: =AF16+AG16 -> 4621.6 | BD16: 148.95 | BH16: =+'RTA 5TA'!F115 -> 149.5653 | BI16: =+AX16+SUM(AY16:BH16)+AP16 -> 5565.9829 | BJ16: =(+AM16-BI16) -> 3609.5301 | BK16: 0.09 | BL16: =AN16*BK16 -> 396.27 | BM16: 13.104 | BO16: BBVA | BU16: BBVA
A17: MARKET | B17: =+B16+1 -> 6 | C17: PORTOCARRERO TAFUR GLORI MAGRI | D17: 43172155 | E17: 31249 | F17: 42948 | H17: JEFE DE MARKETING Y CALIDAD | I17: INTEGRA | J17: 6500 | K17: 113 | L17: 30 | O17: =+L17-M17-N17 -> 30 | P17: 8 | Q17: =+O17*P17 -> 240 | R17: =+J17-AC17-T17 -> 6500 | S17: =K17 -> 113 | T17: =(J17)/30*M17 -> 0 | W17: =H.E!L11 -> 0 | X17: =H.E!M11 -> 0 | Y17: =H.E!N11 -> 0 | AC17: =(J17+K17)/30*N17 -> 0 | AF17: 6613 | AG17: 595.17 | AM17: =SUM(R17:AK17)-AL17 -> 13821.17 | AN17: =+AM17-Z17-AD17-AE17-AF17-AG17-AJ17-AK17-AI17-AY17-AZ17 -> 6613 | AQ17: 0.1 | AR17: =+AN17*AQ17 -> 661.3 | AS17: 0.0155 | AT17: =+AN17*AS17 -> 102.5015 | AU17: 0.0137 | AV17: =+AN17*AU17 -> 90.5981 | AW17: =+AQ17+AS17+AU17 -> 0.1292 | AX17: =+AR17+AT17+AV17 -> 854.3996 | AY17: =TARDANZA!K11 -> 0 | AZ17: =TARDANZA!L11 -> 0 | BB17: =AF17+AG17 -> 7208.17 | BD17: 664.74 | BH17: =+'RTA 5TA'!G115 -> 1341.4388 | BI17: =+AX17+SUM(AY17:BH17)+AP17 -> 10068.748 | BJ17: =(+AM17-BI17) -> 3752.4216 | BK17: 0.09 | BL17: =AN17*BK17 -> 595.17 | BM17: 23.8407 | BO17: BBVA | BU17: BBVA
A18: VTAS | B18: =+B17+1 -> 7 | C18: ECHEVARRIA SOTO JORGE LUIS | D18: 45538866 | E18: 32147 | F18: 42955 | H18: COORDINADOR COMERCIAL | I18: ONP | J18: 4500 | K18: 113 | L18: 30 | N18: 1 | O18: =+L18-M18-N18 -> 29 | P18: 8 | Q18: =+O18*P18 -> 232 | R18: =+J18-AC18-T18 -> 4346.2333 | S18: =K18 -> 113 | T18: =(J18)/30*M18 -> 0 | U18: =COMISIONES!J3 -> 12745.128 | V18: =(SUM(COMISIONES!D3:I3)/6)/30*'PLANILLA MENSUAL'!N18 -> 300.25418 | W18: =H.E!L12 -> 0 | X18: =H.E!M12 -> 0 | Y18: =H.E!N12 -> 0 | AC18: =(J18+K18)/30*N18 -> 153.76667 | AF18: 13620.625 | AG18: 1225.8563 | AM18: =SUM(R18:AK18)-AL18 -> 32504.863 | AN18: =+AM18-Z18-AD18-AE18-AF18-AG18-AJ18-AK18-AI18-AY18-AZ18 -> 17658.382 | AO18: 0.13 | AP18: =+AN18*AO18 -> 2295.5896 | AY18: =TARDANZA!K12 -> 0 | AZ18: =TARDANZA!L12 -> 0 | BB18: =AF18+AG18 -> 14846.482 | BE18: ='HT. EPS'!O46 -> 530.65357 | BH18: =+'RTA 5TA VTAS'!E121 -> 3473.1922 | BI18: =+AX18+SUM(AY18:BH18)+AP18 -> 21145.917 | BJ18: =(+AM18-BI18) -> 11358.946 | BK18: 0.09 | BL18: =AN18*BK18 -> 1589.2544 | BM18: 17.99 | BN18: EPS | BO18: BBVA | BU18: BBVA
A19: VTAS | B19: =+B18+1 -> 8 | C19: MONTOYA MEDRANO ANDREA BELEN JOSEPHINE | D19: 71127068 | E19: 34500 | F19: 43045 | H19: ASISTENTE DE GERENCIA | I19: ONP | J19: 2800 | L19: 30 | M19: 1 | O19: =+L19-M19-N19 -> 29 | P19: 8 | Q19: =+O19*P19 -> 232 | R19: =+J19-AC19-T19 -> 2706.6667 | S19: =K19 -> 0 | T19: =(J19)/30*M19 -> 93.333333 | W19: =H.E!L13 -> 0 | X19: =H.E!M13 -> 0 | Y19: =H.E!N13 -> 0 | AC19: =(J19+K19)/30*N19 -> 0 | AF19: 3600 | AG19: 324 | AH19: 800 | AM19: =SUM(R19:AK19)-AL19 -> 7524 | AN19: =+AM19-Z19-AD19-AE19-AF19-AG19-AJ19-AK19-AI19-AY19-AZ19 -> 3588.5278 | AO19: 0.13 | AP19: =+AN19*AO19 -> 466.50861 | AY19: =TARDANZA!K13 -> 0 | AZ19: =TARDANZA!L13 -> 11.472222 | BB19: =AF19+AG19 -> 3924 | BE19: ='HT. EPS'!O37 -> 76.41628 | BH19: =+'RTA 5TA'!O115 -> 31.898615 | BI19: =+AX19+SUM(AY19:BH19)+AP19 -> 4510.2957 | BJ19: =(+AM19-BI19) -> 3013.7043 | BK19: 0.09 | BL19: =AN19*BK19 -> 322.9675 | BM19: 3.15 | BN19: EPS | BO19: BCP | BU19: BCP
A20: MARKET | B20: =+B19+1 -> 9 | C20: VERGARA BALDEON GEANNINA LIZBETH | D20: 46497553 | E20: 33124 | F20: 44018 | H20: ESPECIALISTA EN MARKETING | I20: INTEGRA | J20: 2600 | L20: 30 | O20: =+L20-M20-N20 -> 30 | P20: 8 | Q20: =+O20*P20 -> 240 | R20: =+J20-AC20-T20 -> 2600 | S20: =K20 -> 0 | T20: =(J20)/30*M20 -> 0 | W20: =H.E!L14 -> 0 | X20: =H.E!M14 -> 0 | Y20: =H.E!N14 -> 0 | AC20: =(J20+K20)/30*N20 -> 0 | AF20: 2600 | AG20: 234 | AM20: =SUM(R20:AK20)-AL20 -> 5434 | AN20: =+AM20-Z20-AD20-AE20-AF20-AG20-AJ20-AK20-AI20-AY20-AZ20 -> 2588.625 | AQ20: 0.1 | AR20: =+AN20*AQ20 -> 258.8625 | AS20: 0 | AT20: =+AN20*AS20 -> 0 | AU20: 0.0137 | AV20: =+AN20*AU20 -> 35.464163 | AW20: =+AQ20+AS20+AU20 -> 0.1137 | AX20: =+AR20+AT20+AV20 -> 294.32666 | AY20: =TARDANZA!K14 -> 0 | AZ20: =TARDANZA!L14 -> 11.375 | BB20: =AF20+AG20 -> 2834 | BE20: ='HT. EPS'!O37 -> 76.41628 | BH20: =+'RTA 5TA'!I115 -> 0 | BI20: =+AX20+SUM(AY20:BH20)+AP20 -> 3216.1179 | BJ20: =(+AM20-BI20) -> 2217.8821 | BK20: 0.09 | BL20: =AN20*BK20 -> 232.97625 | BM20: 3.75 | BN20: EPS | BO20: BCP | BU20: BCP
A21: ALMACEN | B21: =+B20+1 -> 10 | C21: CASTILLO ENCARNACION MANUEL LEONIDAS | D21: 44030334 | E21: 31334 | F21: 44321 | H21: REPARTO | I21: PRIMA | J21: 2200 | K21: 113 | L21: 30 | O21: =+L21-M21-N21 -> 30 | P21: 8 | Q21: =+O21*P21 -> 240 | R21: =+J21-AC21-T21 -> 2200 | S21: =K21 -> 113 | T21: =(J21)/30*M21 -> 0 | W21: =H.E!L15 -> 78.304688 | X21: =H.E!M15 -> 19.515937 | Y21: =H.E!N15 -> 308.4 | Z21: 100 | AC21: =(J21+K21)/30*N21 -> 0 | AF21: 2313 | AG21: 208.17 | AM21: =SUM(R21:AK21)-AL21 -> 5340.3906 | AN21: =+AM21-Z21-AD21-AE21-AF21-AG21-AJ21-AK21-AI21-AY21-AZ21 -> 2707.1737 | AQ21: 0.1 | AR21: =+AN21*AQ21 -> 270.71738 | AS21: 0.016 | AT21: =+AN21*AS21 -> 43.31478 | AU21: 0.0137 | AV21: =+AN21*AU21 -> 37.08828 | AW21: =+AQ21+AS21+AU21 -> 0.1297 | AX21: =+AR21+AT21+AV21 -> 351.12044 | AY21: =TARDANZA!K15 -> 0 | AZ21: =TARDANZA!L15 -> 12.046875 | BB21: =AF21+AG21 -> 2521.17 | BC21: =500+500 -> 1000 | BI21: =+AX21+SUM(AY21:BH21)+AP21 -> 3884.3373 | BJ21: =(+AM21-BI21) -> 1456.0533 | BK21: 0.09 | BL21: =AN21*BK21 -> 243.64564 | BM21: 8.2407 | BO21: BBVA | BP21: =100/23*19 -> 82.608696 | BQ21: =BP21+BJ21 -> 1538.662 | BU21: BBVA
A22: VTAS | B22: =+B21+1 -> 11 | C22: QUEVEDO SALAS LUIS ALBERTO | D22: 7882846 | E22: 26945 | F22: 44593 | H22: EJECUTIVO COMERCIAL | I22: PRIMA | J22: 3800 | K22: 113 | L22: 30 | M22: 10 | N22: 14 | O22: =+L22-M22-N22 -> 6 | P22: 8 | Q22: =+O22*P22 -> 48 | R22: =+J22-AC22-T22 -> 707.26667 | S22: =K22 -> 113 | T22: =(J22)/30*M22 -> 1266.6667 | U22: =COMISIONES!J4 -> 1771.0376 | V22: =(SUM(COMISIONES!D4:I4)/6)/30*N22 -> 1445.8006 | W22: =H.E!L16 -> 0 | X22: =H.E!M16 -> 0 | Y22: =H.E!N16 -> 0 | AC22: =(J22+K22)/30*N22 -> 1826.0667 | AF22: 7011.1441 | AG22: 631.00297 | AM22: =SUM(R22:AK22)-AL22 -> 14771.985 | AN22: =+AM22-Z22-AD22-AE22-AF22-AG22-AJ22-AK22-AI22-AY22-AZ22 -> 7129.8381 | AQ22: 0.1 | AR22: =+AN22*AQ22 -> 712.98381 | AS22: 0 | AT22: =+AN22*AS22 -> 0 | AU22: 0.0137 | AV22: =+AN22*AU22 -> 97.678782 | AW22: =+AQ22+AS22+AU22 -> 0.1137 | AX22: =+AR22+AT22+AV22 -> 810.66259 | AY22: =TARDANZA!K16 -> 0 | AZ22: =TARDANZA!L16 -> 0 | BB22: =AF22+AG22 -> 7642.147 | BE22: ='HT. EPS'!O37 -> 76.41628 | BH22: =+'RTA 5TA VTAS'!F121 -> 740.27668 | BI22: =+AX22+SUM(AY22:BH22)+AP22 -> 9269.5026 | BJ22: =(+AM22-BI22) -> 5502.4826 | BK22: 0.09 | BL22: =AN22*BK22 -> 641.68543 | BM22: 14.09 | BN22: EPS | BO22: INTERB | BP22: BCP | BU22: INTERB | BV22: 1460
A23: ADM | B23: =+B22+1 -> 12 | C23: PORTOCARRERO GOMEZ MARIA DEICY | D23: 42544684 | E23: 30874 | F23: 44697 | H23: LIMPIEZA | I23: PROFUTURO | J23: 1500 | K23: 113 | L23: 30 | O23: =+L23-M23-N23 -> 30 | P23: 8 | Q23: =+O23*P23 -> 240 | R23: =+J23-AC23-T23 -> 1500 | S23: =K23 -> 113 | T23: =(J23)/30*M23 -> 0 | W23: =H.E!L17 -> 0 | X23: =H.E!M17 -> 0 | Y23: =H.E!N17 -> 0 | AC23: =(J23+K23)/30*N23 -> 0 | AF23: 1613 | AG23: 145.17 | AM23: =SUM(R23:AK23)-AL23 -> 3371.17 | AN23: =+AM23-Z23-AD23-AE23-AF23-AG23-AJ23-AK23-AI23-AY23-AZ23 -> 1613 | AQ23: 0.1 | AR23: =+AN23*AQ23 -> 161.3 | AS23: 0 | AT23: =+AN23*AS23 -> 0 | AU23: 0.0137 | AV23: =+AN23*AU23 -> 22.0981 | AW23: =+AQ23+AS23+AU23 -> 0.1137 | AX23: =+AR23+AT23+AV23 -> 183.3981 | AY23: =TARDANZA!K17 -> 0 | AZ23: =TARDANZA!L17 -> 0 | BB23: =AF23+AG23 -> 1758.17 | BI23: =+AX23+SUM(AY23:BH23)+AP23 -> 1941.5681 | BJ23: =(+AM23-BI23) -> 1429.6019 | BK23: 0.09 | BL23: =AN23*BK23 -> 145.17 | BM23: 5.1207 | BO23: BCP | BU23: BCP
A24: CONTA | B24: =+B23+1 -> 13 | C24: LOBO QUISPE ELISA FIORELLA | D24: 43415173 | E24: 31370 | F24: 45005 | H24: ASISTENTE CONTABLE | I24: INTEGRA | J24: 3000 | L24: 30 | O24: =+L24-M24-N24 -> 30 | P24: 8 | Q24: =+O24*P24 -> 240 | R24: =+J24-AC24-T24 -> 3000 | S24: =K24 -> 0 | T24: =(J24)/30*M24 -> 0 | W24: =H.E!L18 -> 0 | X24: =H.E!M18 -> 0 | Y24: =H.E!N18 -> 0 | Z24: 100 | AC24: =(J24+K24)/30*N24 -> 0 | AF24: 3000 | AG24: 270 | AM24: =SUM(R24:AK24)-AL24 -> 6370 | AN24: =+AM24-Z24-AD24-AE24-AF24-AG24-AJ24-AK24-AI24-AY24-AZ24 -> 2889.7917 | AQ24: 0.1 | AR24: =+AN24*AQ24 -> 288.97917 | AS24: 0 | AT24: =+AN24*AS24 -> 0 | AU24: 0.0137 | AV24: =+AN24*AU24 -> 39.590146 | AW24: =+AQ24+AS24+AU24 -> 0.1137 | AX24: =+AR24+AT24+AV24 -> 328.56931 | AY24: =TARDANZA!K18 -> 0 | AZ24: =TARDANZA!L18 -> 110.20833 | BB24: =AF24+AG24 -> 3270 | BE24: ='HT. EPS'!O37 -> 76.41628 | BH24: =+'RTA 5TA'!J115 -> 35.853016 | BI24: =+AX24+SUM(AY24:BH24)+AP24 -> 3821.0469 | BJ24: =(+AM24-BI24) -> 2548.9531 | BK24: 0.09 | BL24: =AN24*BK24 -> 260.08125 | BM24: 11.7 | BN24: EPS | BO24: BBVA | BU24: BBVA
A25: PROYECTO | B25: =+B24+1 -> 14 | C25: RIOS HOLSEN JAIME JUNIOR | D25: 48335342 | E25: 34355 | F25: 45307 | H25: ANALISTA DE PROYECTOS | I25: HABITAT | J25: 3200 | L25: 30 | N25: 5 | O25: =+L25-M25-N25 -> 25 | P25: 8 | Q25: =+O25*P25 -> 200 | R25: =+J25-AC25-T25 -> 2666.6667 | S25: =K25 -> 0 | T25: =(J25)/30*M25 -> 0 | W25: =H.E!L19 -> 0 | X25: =H.E!M19 -> 0 | Y25: =H.E!N19 -> 0 | AC25: =(J25+K25)/30*N25 -> 533.33333 | AF25: 3200 | AG25: 288 | AM25: =SUM(R25:AK25)-AL25 -> 6688 | AN25: =+AM25-Z25-AD25-AE25-AF25-AG25-AJ25-AK25-AI25-AY25-AZ25 -> 3152.4444 | AQ25: 0.1 | AR25: =+AN25*AQ25 -> 315.24444 | AS25: 0 | AU25: 0.0137 | AV25: =+AN25*AU25 -> 43.188489 | AW25: =+AQ25+AS25+AU25 -> 0.1137 | AX25: =+AR25+AT25+AV25 -> 358.43293 | AY25: =TARDANZA!K19 -> 0 | AZ25: =TARDANZA!L19 -> 47.555556 | BB25: =AF25+AG25 -> 3488 | BH25: =+'RTA 5TA'!M115 -> 50.065 | BI25: =+AX25+SUM(AY25:BH25)+AP25 -> 3944.0535 | BJ25: =(+AM25-BI25) -> 2743.9465 | BK25: 0.09 | BL25: =AN25*BK25 -> 283.72 | BM25: 4.2 | BO25: BCP | BU25: BCP
A26: VTAS | B26: =+B25+1 -> 15 | C26: ESTRADA SANTOS JUAN MIGUEL | D26: 25849757 | E26: 45341 | F26: 45341 | H26: INGENIERIA COMERCIAL | I26: INTEGRA | J26: 2800 | K26: 113 | L26: 30 | M26: 6 | N26: 1 | O26: =+L26-M26-N26 -> 23 | P26: 8 | Q26: =+O26*P26 -> 184 | R26: =+J26-AC26-T26 -> 2142.9 | S26: =K26 -> 113 | T26: =(J26)/30*M26 -> 560 | U26: =COMISIONES!J5 -> 2048.7845 | V26: =(SUM(COMISIONES!D5:I5)/6)/30*N26 -> 57.177925 | W26: =H.E!L20 -> 0 | X26: =H.E!M20 -> 0 | Y26: =H.E!N20 -> 0 | AC26: =(J26+K26)/30*N26 -> 97.1 | AF26: 4628.3377 | AG26: 416.5504 | AM26: =SUM(R26:AK26)-AL26 -> 10063.851 | AN26: =+AM26-Z26-AD26-AE26-AF26-AG26-AJ26-AK26-AI26-AY26-AZ26 -> 4999.3401 | AQ26: 0.1 | AR26: =+AN26*AQ26 -> 499.93401 | AS26: 0.0155 | AT26: =+AN26*AS26 -> 77.489771 | AU26: 0.0137 | AV26: =+AN26*AU26 -> 68.490959 | AW26: =+AQ26+AS26+AU26 -> 0.1292 | AX26: =+AR26+AT26+AV26 -> 645.91474 | AY26: =TARDANZA!K20 -> 0 | AZ26: =TARDANZA!L20 -> 19.622292 | BB26: =AF26+AG26 -> 5044.8881 | BC26: =1000+1000 -> 2000 | BE26: ='HT. EPS'!O42 -> 530.65357 | BH26: =+'RTA 5TA VTAS'!G121 -> 286.67662 | BI26: =+AX26+SUM(AY26:BH26)+AP26 -> 8527.7554 | BJ26: =(+AM26-BI26) -> 1536.0952 | BK26: 0.09 | BL26: =AN26*BK26 -> 449.94061 | BM26: 11.36 | BN26: EPS | BO26: BCP | BU26: BCP
A27: ALMACEN | B27: =+B26+1 -> 16 | C27: SALCEDO RIVAS DANIEL ALONSO | D27: 42953954 | E27: 31117 | F27: 45398 | H27: ENCARGADO AREA DE ALMACEN | I27: INTEGRA | J27: 2800 | K27: 113 | L27: 30 | N27: 7 | O27: =+L27-M27-N27 -> 23 | P27: 8 | Q27: =+O27*P27 -> 184 | R27: =+J27-AC27-T27 -> 2120.3 | S27: =K27 -> 113 | T27: =(J27)/30*M27 -> 0 | W27: =H.E!L21 -> 98.617188 | X27: =H.E!M21 -> 40.964063 | Y27: =H.E!N21 -> 194.2 | AC27: =(J27+K27)/30*N27 -> 679.7 | AF27: 2913 | AG27: 262.17 | AM27: =SUM(R27:AK27)-AL27 -> 6421.9513 | AN27: =+AM27-Z27-AD27-AE27-AF27-AG27-AJ27-AK27-AI27-AY27-AZ27 -> 3219.8765 | AQ27: 0.1 | AR27: =+AN27*AQ27 -> 321.98765 | AS27: 0.0155 | AT27: =+AN27*AS27 -> 49.908085 | AU27: 0.0137 | AV27: =+AN27*AU27 -> 44.112307 | AW27: =+AQ27+AS27+AU27 -> 0.1292 | AX27: =+AR27+AT27+AV27 -> 416.00804 | AY27: =TARDANZA!K21 -> 0 | AZ27: =TARDANZA!L21 -> 26.904792 | BB27: =AF27+AG27 -> 3175.17 | BH27: =+'RTA 5TA'!Q115 -> 0 | BI27: =+AX27+SUM(AY27:BH27)+AP27 -> 3618.0828 | BJ27: =(+AM27-BI27) -> 2803.8684 | BK27: 0.09 | BL27: =AN27*BK27 -> 289.78888 | BM27: 10.1907 | BO27: BBVA | BU27: BBVA
A28: ADM | B28: =+B27+1 -> 17 | C28: PORTOCARRERO TAFUR MARIA LOIDI | D28: 45654429 | E28: 30383 | F28: 45398 | H28: AUXILIAR ADMINISTRATIVO | I28: ONP | J28: 1200 | L28: 30 | O28: =+L28-M28-N28 -> 30 | P28: 8 | Q28: =+O28*P28 -> 240 | R28: =+J28-AC28-T28 -> 1200 | S28: =K28 -> 0 | T28: =(J28)/30*M28 -> 0 | W28: =H.E!L22 -> 0 | X28: =H.E!M22 -> 0 | Y28: =H.E!N22 -> 0 | AC28: =(J28+K28)/30*N28 -> 0 | AF28: 1130 | AG28: 101.7 | AM28: =SUM(R28:AK28)-AL28 -> 2431.7 | AN28: =+AM28-Z28-AD28-AE28-AF28-AG28-AJ28-AK28-AI28-AY28-AZ28 -> 1200 | AO28: 0.13 | AP28: =+AN28*AO28 -> 156 | AY28: =TARDANZA!K22 -> 0 | AZ28: =TARDANZA!L22 -> 0 | BB28: =AF28+AG28 -> 1231.7 | BG28: 22.36 | BI28: =+AX28+SUM(AY28:BH28)+AP28 -> 1410.06 | BJ28: =(+AM28-BI28) -> 1021.64 | BK28: 0.09 | BL28: =AN28*BK28 -> 108 | BM28: 4.4 | BO28: BBVA | BU28: BBVA
A29: PROYECTO | B29: =+B28+1 -> 18 | C29: ZEVALLOS DELGADO LUIS EDUARDO | D29: 74450353 | E29: 34560 | F29: 45418 | H29: INGENIERIO TECNICO EN EL AREA DE VARIADORES | I29: INTEGRA | J29: 2800 | L29: 30 | O29: =+L29-M29-N29 -> 30 | P29: 8 | Q29: =+O29*P29 -> 240 | R29: =+J29-AC29-T29 -> 2800 | S29: =K29 -> 0 | T29: =(J29)/30*M29 -> 0 | W29: =H.E!L23 -> 0 | X29: =H.E!M23 -> 0 | Y29: =H.E!N23 -> 0 | AC29: =(J29+K29)/30*N29 -> 0 | AF29: 3011.8582 | AG29: 271.06724 | AM29: =SUM(R29:AK29)-AL29 -> 6082.9254 | AN29: =+AM29-Z29-AD29-AE29-AF29-AG29-AJ29-AK29-AI29-AY29-AZ29 -> 2793.5833 | AQ29: 0.1 | AR29: =+AN29*AQ29 -> 279.35833 | AS29: 0 | AT29: =+AN29*AS29 -> 0 | AU29: 0.0137 | AV29: =+AN29*AU29 -> 38.272092 | AW29: =+AQ29+AS29+AU29 -> 0.1137 | AX29: =+AR29+AT29+AV29 -> 317.63043 | AY29: =TARDANZA!K23 -> 0 | AZ29: =TARDANZA!L23 -> 6.4166667 | BB29: =AF29+AG29 -> 3282.9254 | BC29: =350+350 -> 700 | BH29: =+'RTA 5TA'!P115 -> 20.509792 | BI29: =+AX29+SUM(AY29:BH29)+AP29 -> 4327.4823 | BJ29: =(+AM29-BI29) -> 1755.4431 | BK29: 0.09 | BL29: =AN29*BK29 -> 251.4225 | BM29: 3.75 | BO29: BCP | BU29: BCP
A30: VTAS | B30: =+B29+1 -> 19 | C30: BALLLESTEROS DI SERI MARIA PAULA | D30: 09877161 | E30: 26434 | F30: 45474 | H30: ASISTENTE ADMINISTRATIVO | I30: PRIMA | J30: 2800 | L30: 30 | N30: 8 | O30: =+L30-M30-N30 -> 22 | P30: 8 | Q30: =+O30*P30 -> 176 | R30: =+J30-AC30-T30 -> 2053.3333 | S30: =K30 -> 0 | T30: =(J30)/30*M30 -> 0 | W30: =H.E!L24 -> 0 | X30: =H.E!M24 -> 0 | Y30: =H.E!N24 -> 0 | AC30: =(J30+K30)/30*N30 -> 746.66667 | AF30: 2800 | AG30: 252 | AM30: =SUM(R30:AK30)-AL30 -> 5852 | AN30: =+AM30-Z30-AD30-AE30-AF30-AG30-AJ30-AK30-AI30-AY30-AZ30 -> 2771.8056 | AQ30: 0.1 | AR30: =+AN30*AQ30 -> 277.18056 | AS30: 0.016 | AT30: =+AN30*AS30 -> 44.348889 | AU30: 0.0137 | AV30: =+AN30*AU30 -> 37.973736 | AW30: =+AQ30+AS30+AU30 -> 0.1297 | AX30: =+AR30+AT30+AV30 -> 359.50318 | AY30: =TARDANZA!K24 -> 0 | AZ30: =TARDANZA!L24 -> 28.194444 | BB30: =AF30+AG30 -> 3052 | BE30: ='HT. EPS'!O37 -> 76.41628 | BH30: =+'RTA 5TA'!R115 -> 0.04 | BI30: =+AX30+SUM(AY30:BH30)+AP30 -> 3516.1539 | BJ30: =(+AM30-BI30) -> 2335.8461 | BK30: 0.09 | BL30: =AN30*BK30 -> 249.4625 | BM30: 9.75 | BN30: EPS | BO30: BCP | BU30: BCP
A31: SOPORTE | B31: =+B30+1 -> 20 | C31: OCAMPO ORTEGA JEAN PAUL | D31: 73231901 | E31: 34632 | F31: 45537 | H31: ASISTENTE DE SOPORTE TECNICO | I31: PRIMA | J31: 2500 | L31: 30 | N31: 12 | O31: =+L31-M31-N31 -> 18 | P31: 8 | Q31: =+O31*P31 -> 144 | R31: =+J31-AC31-T31 -> 1500 | S31: =K31 -> 0 | T31: =(J31)/30*M31 -> 0 | W31: =H.E!L25 -> 0 | X31: =H.E!M25 -> 0 | Y31: =H.E!N25 -> 0 | AC31: =(J31+K31)/30*N31 -> 1000 | AF31: 2707.9511 | AG31: 243.7156 | AM31: =SUM(R31:AK31)-AL31 -> 5451.6667 | AN31: =+AM31-Z31-AD31-AE31-AF31-AG31-AJ31-AK31-AI31-AY31-AZ31 -> 2469.9653 | AQ31: 0.1 | AR31: =+AN31*AQ31 -> 246.99653 | AS31: 0 | AT31: =+AN31*AS31 -> 0 | AU31: 0.0137 | AV31: =+AN31*AU31 -> 33.838524 | AW31: =+AQ31+AS31+AU31 -> 0.1137 | AX31: =+AR31+AT31+AV31 -> 280.83505 | AY31: =TARDANZA!K25 -> 0 | AZ31: =TARDANZA!L25 -> 30.034722 | BB31: =AF31+AG31 -> 2951.6667 | BG31: 1122.02 | BI31: =+AX31+SUM(AY31:BH31)+AP31 -> 4384.5565 | BJ31: =(+AM31-BI31) -> 1067.1102 | BK31: 0.09 | BL31: =AN31*BK31 -> 222.29688 | BM31: 3 | BO31: BBVA | BU31: BBVA
A32: SOPORTE | B32: =+B31+1 -> 21 | C32: OLIVOS SAAVEDRA LANDHERT ANDERSON | D32: 73885455 | E32: 35803 | F32: 45581 | H32: ASISTENTE DE SOPORTE TECNICO | I32: INTEGRA | J32: 2500 | L32: 30 | O32: =+L32-M32-N32 -> 30 | P32: 8 | Q32: =+O32*P32 -> 240 | R32: =+J32-AC32-T32 -> 2500 | S32: =K32 -> 0 | T32: =(J32)/30*M32 -> 0 | W32: =H.E!L26 -> 0 | X32: =H.E!M26 -> 0 | Y32: =H.E!N26 -> 0 | AC32: =(J32+K32)/30*N32 -> 0 | AF32: 2621.0019 | AG32: 235.89017 | AM32: =SUM(R32:AK32)-AL32 -> 5356.8921 | AN32: =+AM32-Z32-AD32-AE32-AF32-AG32-AJ32-AK32-AI32-AY32-AZ32 -> 2500 | AQ32: 0.1 | AR32: =+AN32*AQ32 -> 250 | AS32: 0 | AT32: =+AN32*AS32 -> 0 | AU32: 0.0137 | AV32: =+AN32*AU32 -> 34.25 | AW32: =+AQ32+AS32+AU32 -> 0.1137 | AX32: =+AR32+AT32+AV32 -> 284.25 | AY32: =TARDANZA!K26 -> 0 | AZ32: =TARDANZA!L26 -> 0 | BB32: =AF32+AG32 -> 2856.8921 | BI32: =+AX32+SUM(AY32:BH32)+AP32 -> 3141.1421 | BJ32: =(+AM32-BI32) -> 2215.75 | BK32: 0.09 | BL32: =AN32*BK32 -> 225 | BM32: 3 | BO32: BCP | BU32: BCP
A33: ALMACEN | B33: =+B32+1 -> 22 | C33: YUPANQUI SAMANIEGO RENATO LUIS | D33: 73952223 | E33: 10/09/200 | F33: 45627 | H33: ASISTENTE DE ALMACEN | I33: INTEGRA | J33: 2500 | L33: 30 | N33: 1 | O33: =+L33-M33-N33 -> 29 | P33: 8 | Q33: =+O33*P33 -> 232 | R33: =+J33-AC33-T33 -> 2416.6667 | S33: =K33 -> 0 | T33: =(J33)/30*M33 -> 0 | W33: =H.E!L27 -> 104.16667 | X33: =H.E!M27 -> 56.25 | Y33: =H.E!N27 -> 333.33333 | AC33: =(J33+K33)/30*N33 -> 83.333333 | AF33: 2500 | AG33: 225 | AM33: =SUM(R33:AK33)-AL33 -> 5718.75 | AN33: =+AM33-Z33-AD33-AE33-AF33-AG33-AJ33-AK33-AI33-AY33-AZ33 -> 2987.1528 | AQ33: 0.1 | AR33: =+AN33*AQ33 -> 298.71528 | AS33: 0 | AT33: =+AN33*AS33 -> 0 | AU33: 0.0137 | AV33: =+AN33*AU33 -> 40.923993 | AW33: =+AQ33+AS33+AU33 -> 0.1137 | AX33: =+AR33+AT33+AV33 -> 339.63927 | AY33: =TARDANZA!K27 -> 0 | AZ33: =TARDANZA!L27 -> 6.5972222 | BB33: =AF33+AG33 -> 2725 | BI33: =+AX33+SUM(AY33:BH33)+AP33 -> 3071.2365 | BJ33: =(+AM33-BI33) -> 2647.5135 | BK33: 0.09 | BL33: =AN33*BK33 -> 268.84375 | BM33: 3.3 | BO33: BCP | BU33: BCP
A34: CONTA | B34: =+B33+1 -> 23 | C34: TUCTO PEREZ CESAR ANTONIO | D34: 46452115 | E34: 32383 | F34: 45658 | H34: ASISTENTE CONTABLE | I34: PRIMA | J34: 2800 | L34: 30 | N34: 7 | O34: =+L34-M34-N34 -> 23 | P34: 8 | Q34: =+O34*P34 -> 184 | R34: =+J34-AC34-T34 -> 2146.6667 | S34: =K34 -> 0 | T34: =(J34)/30*M34 -> 0 | W34: =H.E!L28 -> 0 | X34: =H.E!M28 -> 0 | Y34: =H.E!N28 -> 0 | AC34: =(J34+K34)/30*N34 -> 653.33333 | AF34: 2800 | AG34: 252 | AM34: =SUM(R34:AK34)-AL34 -> 5852 | AN34: =+AM34-Z34-AD34-AE34-AF34-AG34-AJ34-AK34-AI34-AY34-AZ34 -> 2800 | AQ34: 0.1 | AR34: =+AN34*AQ34 -> 280 | AS34: 0 | AT34: =+AN34*AS34 -> 0 | AU34: 0.0137 | AV34: =+AN34*AU34 -> 38.36 | AW34: =+AQ34+AS34+AU34 -> 0.1137 | AX34: =+AR34+AT34+AV34 -> 318.36 | AY34: =TARDANZA!K28 -> 0 | AZ34: =TARDANZA!L28 -> 0 | BB34: =AF34+AG34 -> 3052 | BE34: ='HT. EPS'!O51 -> 73.450179 | BI34: =+AX34+SUM(AY34:BH34)+AP34 -> 3443.8102 | BJ34: =(+AM34-BI34) -> 2408.1898 | BK34: 0.09 | BL34: =AN34*BK34 -> 252 | BM34: 9.75 | BN34: EPS | BO34: BCP | BU34: BCP
A35: VTAS | B35: =+B34+1 -> 24 | C35: AREVALO VELA CESAR ANTONIO | D35: 71114663 | E35: 36860 | F35: 45658 | H35: EJECUTIVO COMERCIAL | I35: PRIMA | J35: 2500 | L35: 30 | O35: =+L35-M35-N35 -> 30 | P35: 8 | Q35: =+O35*P35 -> 240 | R35: =+J35-AC35-T35 -> 2500 | S35: =K35 -> 0 | T35: =(J35)/30*M35 -> 0 | U35: =COMISIONES!J8 -> 1891.5045 | W35: =H.E!L29 -> 0 | X35: =H.E!M29 -> 0 | Y35: =H.E!N29 -> 0 | AC35: =(J35+K35)/30*N35 -> 0 | AF35: 3997.752 | AG35: 359.79768 | AM35: =SUM(R35:AK35)-AL35 -> 8749.0542 | AN35: =+AM35-Z35-AD35-AE35-AF35-AG35-AJ35-AK35-AI35-AY35-AZ35 -> 4363.0323 | AQ35: 0.1 | AR35: =+AN35*AQ35 -> 436.30323 | AS35: 0 | AT35: =+AN35*AS35 -> 0 | AU35: 0.0137 | AV35: =+AN35*AU35 -> 59.773542 | AW35: =+AQ35+AS35+AU35 -> 0.1137 | AX35: =+AR35+AT35+AV35 -> 496.07677 | AY35: =TARDANZA!K29 -> 0 | AZ35: =TARDANZA!L29 -> 28.472222 | BB35: =AF35+AG35 -> 4357.5497 | BH35: =+'RTA 5TA VTAS'!I121 -> 156.19048 | BI35: =+AX35+SUM(AY35:BH35)+AP35 -> 5038.2892 | BJ35: =(+AM35-BI35) -> 3710.765 | BK35: 0.09 | BL35: =AN35*BK35 -> 392.6729 | BM35: 2.7 | BO35: BCP | BU35: BCP
A36: VTAS | B36: =+B35+1 -> 25 | C36: SICCHA ARCE LUIS FRANCISCO | D36: 73735818 | E36: 36161 | F36: 45689 | H36: EJECUTIVO COMERCIAL | I36: INTEGRA | J36: 2500 | L36: 30 | O36: =+L36-M36-N36 -> 30 | P36: 8 | Q36: =+O36*P36 -> 240 | R36: =+J36-AC36-T36 -> 2500 | S36: =K36 -> 0 | T36: =(J36)/30*M36 -> 0 | U36: =COMISIONES!J7 -> 600.18255 | W36: =H.E!L30 -> 0 | X36: =H.E!M30 -> 0 | Y36: =H.E!N30 -> 0 | AC36: =(J36+K36)/30*N36 -> 0 | AF36: 3704.8427 | AG36: 333.43584 | AM36: =SUM(R36:AK36)-AL36 -> 7138.4611 | AN36: =+AM36-Z36-AD36-AE36-AF36-AG36-AJ36-AK36-AI36-AY36-AZ36 -> 3100.1825 | AQ36: 0.1 | AR36: =+AN36*AQ36 -> 310.01826 | AS36: 0 | AT36: =+AN36*AS36 -> 0 | AU36: 0.0137 | AV36: =+AN36*AU36 -> 42.472501 | AW36: =+AQ36+AS36+AU36 -> 0.1137 | AX36: =+AR36+AT36+AV36 -> 352.49076 | AY36: =TARDANZA!K30 -> 0 | AZ36: =TARDANZA!L30 -> 0 | BB36: =AF36+AG36 -> 4038.2785 | BH36: =+'RTA 5TA VTAS'!H121 -> 107.2373 | BI36: =+AX36+SUM(AY36:BH36)+AP36 -> 4498.0066 | BJ36: =(+AM36-BI36) -> 2640.4545 | BK36: 0.09 | BL36: =AN36*BK36 -> 279.01643 | BM36: 3.75 | BO36: BBVA | BU36: BBVA
A37: MARKET | B37: =+B36+1 -> 26 | C37: JIMENEZ PUYEN LUIS ANTONIO | D37: 6802763 | E37: 28259 | F37: 45698 | H37: ESPECIALISTA EN GESTION Y SST | I37: ONP | J37: 2800 | L37: 30 | N37: 11 | O37: =+L37-M37-N37 -> 19 | P37: 8 | Q37: =+O37*P37 -> 152 | R37: =+J37-AC37-T37 -> 1773.3333 | S37: =K37 -> 0 | T37: =(J37)/30*M37 -> 0 | W37: =H.E!L31 -> 0 | X37: =H.E!M31 -> 0 | Y37: =H.E!N31 -> 0 | AC37: =(J37+K37)/30*N37 -> 1026.6667 | AF37: 2800 | AG37: 252 | AM37: =SUM(R37:AK37)-AL37 -> 5852 | AN37: =+AM37-Z37-AD37-AE37-AF37-AG37-AJ37-AK37-AI37-AY37-AZ37 -> 2788.3333 | AO37: 0.13 | AP37: =+AN37*AO37 -> 362.48333 | AY37: =TARDANZA!K31 -> 0 | AZ37: =TARDANZA!L31 -> 11.666667 | BB37: =AF37+AG37 -> 3052 | BG37: 230.53 | BH37: =+'RTA 5TA'!N115 -> 8.0266667 | BI37: =+AX37+SUM(AY37:BH37)+AP37 -> 3664.7067 | BJ37: =(+AM37-BI37) -> 2187.2933 | BK37: 0.09 | BL37: =AN37*BK37 -> 250.95 | BM37: 10.92 | BO37: BCP | BU37: BCP
A38: SOPORTE | B38: =+B37+1 -> 27 | C38: SILVA SANTISTEBAN RONAL JHUNIOR | D38: 48461873 | E38: 34304 | F38: 45719 | H38: ASISTENTE DE SOPORTE TECNICO | I38: INTEGRA | J38: 2000 | L38: 30 | O38: =+L38-M38-N38 -> 30 | P38: 8 | Q38: =+O38*P38 -> 240 | R38: =+J38-AC38-T38 -> 2000 | S38: =K38 -> 0 | T38: =(J38)/30*M38 -> 0 | W38: =H.E!L32 -> 0 | X38: =H.E!M32 -> 0 | Y38: =H.E!N32 -> 0 | AC38: =(J38+K38)/30*N38 -> 0 | AF38: 2113.8986 | AG38: 190.25088 | AM38: =SUM(R38:AK38)-AL38 -> 4304.1495 | AN38: =+AM38-Z38-AD38-AE38-AF38-AG38-AJ38-AK38-AI38-AY38-AZ38 -> 1988.0556 | AQ38: 0.1 | AR38: =+AN38*AQ38 -> 198.80556 | AS38: 0 | AT38: =+AN38*AS38 -> 0 | AU38: 0.0137 | AV38: =+AN38*AU38 -> 27.236361 | AW38: =+AQ38+AS38+AU38 -> 0.1137 | AX38: =+AR38+AT38+AV38 -> 226.04192 | AY38: =TARDANZA!K32 -> 0 | AZ38: =TARDANZA!L32 -> 11.944444 | BB38: =AF38+AG38 -> 2304.1495 | BG38: 281.53 | BI38: =+AX38+SUM(AY38:BH38)+AP38 -> 2823.6658 | BJ38: =(+AM38-BI38) -> 1480.4836 | BK38: 0.09 | BL38: =AN38*BK38 -> 178.925 | BM38: 2.55 | BO38: BCP | BU38: BCP
A39: LOGISTICA | B39: =+B38+1 -> 28 | C39: ELGUERA SOTO LUCERO ESTEFANIA | D39: 71932804 | E39: 35956 | F39: 45778 | H39: ASISTENTE LOGISTICA | I39: PRIMA | J39: 2200 | L39: 30 | O39: =+L39-M39-N39 -> 30 | P39: 8 | Q39: =+O39*P39 -> 240 | R39: =+J39-AC39-T39 -> 2200 | S39: =K39 -> 0 | T39: =(J39)/30*M39 -> 0 | W39: =H.E!L33 -> 0 | X39: =H.E!M33 -> 0 | Y39: =H.E!N33 -> 0 | AC39: =(J39+K39)/30*N39 -> 0 | AF39: 2200 | AG39: 198 | AM39: =SUM(R39:AK39)-AL39 -> 4598 | AN39: =+AM39-Z39-AD39-AE39-AF39-AG39-AJ39-AK39-AI39-AY39-AZ39 -> 2196.7917 | AQ39: 0.1 | AR39: =+AN39*AQ39 -> 219.67917 | AS39: 0 | AT39: =+AN39*AS39 -> 0 | AU39: 0.0137 | AV39: =+AN39*AU39 -> 30.096046 | AW39: =+AQ39+AS39+AU39 -> 0.1137 | AX39: =+AR39+AT39+AV39 -> 249.77521 | AY39: =TARDANZA!K33 -> 0 | AZ39: =TARDANZA!L33 -> 3.2083333 | BB39: =AF39+AG39 -> 2398 | BE39: ='HT. EPS'!O37 -> 76.41628 | BI39: =+AX39+SUM(AY39:BH39)+AP39 -> 2727.3998 | BJ39: =(+AM39-BI39) -> 1870.6002 | BK39: 0.09 | BL39: =AN39*BK39 -> 197.71125 | BM39: 2.86 | BN39: EPS | BO39: BCP | BU39: BCP
A40: VTAS | B40: =+B39+1 -> 29 | C40: ESTACIO CAYETANO FRANK BRIAN | D40: 72192314 | E40: 34152 | F40: 45778 | H40: EJECUTIVO COMERCIAL | I40: INTEGRA | J40: 2300 | L40: 30 | N40: 7 | O40: =+L40-M40-N40 -> 23 | P40: 8 | Q40: =+O40*P40 -> 184 | R40: =+J40-AC40-T40 -> 1763.3333 | S40: =K40 -> 0 | T40: =(J40)/30*M40 -> 0 | U40: =COMISIONES!J9 -> 3142.0137 | V40: =(SUM(COMISIONES!D9:I9)/6)/30*N40 -> 358.23108 | W40: =H.E!L34 -> 0 | X40: =H.E!M34 -> 0 | Y40: =H.E!N34 -> 0 | AC40: =(J40+K40)/30*N40 -> 536.66667 | AF40: 3835.276 | AG40: 345.17484 | AM40: =SUM(R40:AK40)-AL40 -> 9980.6957 | AN40: =+AM40-Z40-AD40-AE40-AF40-AG40-AJ40-AK40-AI40-AY40-AZ40 -> 5800.2448 | AQ40: 0.1 | AR40: =+AN40*AQ40 -> 580.02448 | AS40: 0 | AT40: =+AN40*AS40 -> 0 | AU40: 0.0137 | AV40: =+AN40*AU40 -> 79.463353 | AW40: =+AQ40+AS40+AU40 -> 0.1137 | AX40: =+AR40+AT40+AV40 -> 659.48783 | AY40: =TARDANZA!K34 -> 0 | AZ40: =TARDANZA!L34 -> 0 | BB40: =AF40+AG40 -> 4180.4509 | BE40: ='HT. EPS'!O37 -> 76.41628 | BH40: =+'RTA 5TA VTAS'!J121 -> 215.93058 | BI40: =+AX40+SUM(AY40:BH40)+AP40 -> 5132.2856 | BJ40: =(+AM40-BI40) -> 4848.4101 | BK40: 0.09 | BL40: =AN40*BK40 -> 522.02203 | BM40: 3 | BN40: EPS | BO40: BCP | BU40: BCP
A41: ALMACEN | B41: =+B40+1 -> 30 | C41: SALAZAR VELASQUEZ HECTOR ALEXANDER | D41: 41995632 | E41: 30308 | F41: 45782 | H41: CHOFER DE REPARTO | I41: ONP | J41: 2500 | K41: 113 | L41: 30 | O41: =+L41-M41-N41 -> 30 | P41: 8 | Q41: =+O41*P41 -> 240 | R41: =+J41-AC41-T41 -> 2500 | S41: =K41 -> 113 | T41: =(J41)/30*M41 -> 0 | W41: =H.E!L35 -> 108.875 | X41: =H.E!M35 -> 44.094375 | Y41: =H.E!N35 -> 174.2 | AC41: =(J41+K41)/30*N41 -> 0 | AF41: 2613 | AG41: 235.17 | AM41: =SUM(R41:AK41)-AL41 -> 5788.3394 | AN41: =+AM41-Z41-AD41-AE41-AF41-AG41-AJ41-AK41-AI41-AY41-AZ41 -> 2873.0298 | AO41: 0.13 | AP41: =+AN41*AO41 -> 373.49387 | AY41: =TARDANZA!K35 -> 0 | AZ41: =TARDANZA!L35 -> 67.139583 | BB41: =AF41+AG41 -> 2848.17 | BI41: =+AX41+SUM(AY41:BH41)+AP41 -> 3288.8035 | BJ41: =(+AM41-BI41) -> 2499.5359 | BK41: 0.09 | BL41: =AN41*BK41 -> 258.57268 | BM41: 8.24 | BO41: BBVA | BU41: BBVA
A42: VTAS | B42: =+B41+1 -> 31 | C42: RICRA DAVALOS GIUSSEPPE RENATO | D42: 70608078 | E42: 36556 | F42: 45789 | H42: ASISTENTE DE VENTAS | I42: INTEGRA | J42: 1800 | L42: 30 | O42: =+L42-M42-N42 -> 30 | P42: 8 | Q42: =+O42*P42 -> 240 | R42: =+J42-AC42-T42 -> 1800 | S42: =K42 -> 0 | T42: =(J42)/30*M42 -> 0 | U42: =COMISIONES!J10 -> 1180.9678 | W42: =H.E!L36 -> 0 | X42: =H.E!M36 -> 0 | Y42: =H.E!N36 -> 0 | AC42: =(J42+K42)/30*N42 -> 0 | AF42: 1800 | AG42: 162 | AM42: =SUM(R42:AK42)-AL42 -> 4942.9678 | AN42: =+AM42-Z42-AD42-AE42-AF42-AG42-AJ42-AK42-AI42-AY42-AZ42 -> 2974.7178 | AQ42: 0.1 | AR42: =+AN42*AQ42 -> 297.47179 | AS42: 0 | AT42: =+AN42*AS42 -> 0 | AU42: 0.0137 | AV42: =+AN42*AU42 -> 40.753635 | AW42: =+AQ42+AS42+AU42 -> 0.1137 | AX42: =+AR42+AT42+AV42 -> 338.22542 | AY42: =TARDANZA!K36 -> 0 | AZ42: =TARDANZA!L36 -> 6.25 | BB42: =AF42+AG42 -> 1962 | BI42: =+AX42+SUM(AY42:BH42)+AP42 -> 2306.4754 | BJ42: =(+AM42-BI42) -> 2636.4924 | BK42: 0.09 | BL42: =AN42*BK42 -> 267.72461 | BM42: 2.25 | BO42: BBVA | BU42: BBVA | EJ42: =4000+113 -> 4113 | EL42: =4000/30 -> 133.33333
A43: ALMACEN | B43: =+B42+1 -> 32 | C43: DIAZ ESCALANTE LUIS MIGUEL DAVID | D43: 45469176 | E43: 32412 | F43: 45796 | H43: CHOFER DE REPARTO | I43: PRIMA | J43: 1700 | K43: 113 | L43: 30 | N43: 5 | O43: =+L43-M43-N43 -> 25 | P43: 8 | Q43: =+O43*P43 -> 200 | R43: =+J43-AC43-T43 -> 1397.8333 | S43: =K43 -> 113 | T43: =(J43)/30*M43 -> 0 | W43: =H.E!L37 -> 47.213542 | X43: =H.E!M37 -> 25.495312 | Y43: =H.E!N37 -> 241.73333 | AC43: =(J43+K43)/30*N43 -> 302.16667 | AF43: 1813 | AG43: 163.17 | AM43: =SUM(R43:AK43)-AL43 -> 4103.6122 | AN43: =+AM43-Z43-AD43-AE43-AF43-AG43-AJ43-AK43-AI43-AY43-AZ43 -> 2114.726 | AQ43: 0.1 | AR43: =+AN43*AQ43 -> 211.4726 | AS43: 0 | AT43: =+AN43*AS43 -> 0 | AU43: 0.0137 | AV43: =+AN43*AU43 -> 28.971746 | AW43: =+AQ43+AS43+AU43 -> 0.1137 | AX43: =+AR43+AT43+AV43 -> 240.44435 | AY43: =TARDANZA!K37 -> 0 | AZ43: =TARDANZA!L37 -> 12.716181 | BB43: =AF43+AG43 -> 1976.17 | BI43: =+AX43+SUM(AY43:BH43)+AP43 -> 2229.3305 | BJ43: =(+AM43-BI43) -> 1874.2817 | BK43: 0.09 | BL43: =AN43*BK43 -> 190.32534 | BM43: 7.07 | BO43: BBVA | BU43: BBVA | EJ43: =EJ42/30 -> 137.1
A44: SOPORTE | B44: =+B43+1 -> 33 | C44: HIPOLITO GUANILO ARNOLD JIMMY | D44: 75676708 | E44: 34883 | F44: 45946 | H44: AUXILIAR DE SOPORTE | I44: HABITAT | J44: 1500 | K44: 113 | L44: 30 | O44: =+L44-M44-N44 -> 30 | P44: 8 | Q44: =+O44*P44 -> 240 | R44: =+J44-AC44-T44 -> 1500 | S44: =K44 -> 113 | T44: =(J44)/30*M44 -> 0 | W44: =H.E!L38 -> 0 | X44: =H.E!M38 -> 0 | Y44: =H.E!N38 -> 0 | AC44: =(J44+K44)/30*N44 -> 0 | AF44: 1642.2017 | AG44: 147.79815 | AM44: =SUM(R44:AK44)-AL44 -> 3402.9998 | AN44: =+AM44-Z44-AD44-AE44-AF44-AG44-AJ44-AK44-AI44-AY44-AZ44 -> 1607.5113 | AQ44: 0.1 | AR44: =+AN44*AQ44 -> 160.75113 | AS44: 0 | AT44: =+AN44*AS44 -> 0 | AU44: 0.0137 | AV44: =+AN44*AU44 -> 22.022905 | AW44: =+AQ44+AS44+AU44 -> 0.1137 | AX44: =+AR44+AT44+AV44 -> 182.77404 | AY44: =TARDANZA!K38 -> 0 | AZ44: =TARDANZA!L38 -> 5.4886806 | BB44: =AF44+AG44 -> 1789.9998 | BI44: =+AX44+SUM(AY44:BH44)+AP44 -> 1978.2626 | BJ44: =(+AM44-BI44) -> 1424.7373 | BK44: 0.09 | BL44: =AN44*BK44 -> 144.67602 | BM44: 2.27 | BO44: BCP | BU44: BCP
A45: VTAS | B45: =+B44+1 -> 34 | C45: MONTOYA MEDRANO VIVIAN MICHELE ALEXANDRA | D45: 71127067 | E45: 35153 | F45: 46083 | H45: ASISTENTE DE VENTAS | I45: PRIMA | J45: 2000 | L45: 30 | O45: =+L45-M45-N45 -> 30 | P45: 8 | Q45: =+O45*P45 -> 240 | R45: =+J45-AC45-T45 -> 2000 | S45: =K45 -> 0 | T45: =(J45)/30*M45 -> 0 | W45: =H.E!L39 -> 0 | X45: =H.E!M39 -> 0 | Y45: =H.E!N39 -> 0 | AC45: =(J45+K45)/30*N45 -> 0 | AF45: 1000 | AG45: 90 | AM45: =SUM(R45:AK45)-AL45 -> 3090 | AN45: =+AM45-Z45-AD45-AE45-AF45-AG45-AJ45-AK45-AI45-AY45-AZ45 -> 1997.9167 | AQ45: 0.1 | AR45: =+AN45*AQ45 -> 199.79167 | AS45: 0 | AT45: =+AN45*AS45 -> 0 | AU45: 0.0137 | AV45: =+AN45*AU45 -> 27.371458 | AW45: =+AQ45+AS45+AU45 -> 0.1137 | AX45: =+AR45+AT45+AV45 -> 227.16313 | AY45: =TARDANZA!K39 -> 0 | AZ45: =TARDANZA!L39 -> 2.0833333 | BA45: 880 | BB45: =AF45+AG45 -> 1090 | BI45: =+AX45+SUM(AY45:BH45)+AP45 -> 2199.2465 | BJ45: =(+AM45-BI45) -> 890.75354 | BK45: 0.09 | BL45: =AN45*BK45 -> 179.8125 | BM45: 3 | BO45: BBVA | BU45: BBVA
A46: ALMACEN | B46: =+B45+1 -> 35 | C46: BANCHO CANELOS EDSON OMAR AMANCIO | D46: 71562324 | E46: 35075 | F46: 46160 | H46: ASISTENTE DE ALMACEN | I46: HABITAT | J46: 1500 | L46: 30 | O46: =+L46-M46-N46 -> 30 | P46: 8 | Q46: =+O46*P46 -> 240 | R46: =+J46-AC46-T46 -> 1500 | S46: =K46 -> 0 | T46: =(J46)/30*M46 -> 0 | W46: =H.E!L40 -> 50.78125 | X46: =H.E!M40 -> 21.09375 | Y46: =H.E!N40 -> 200 | AC46: =(J46+K46)/30*N46 -> 0 | AF46: 250 | AG46: 22.5 | AM46: =SUM(R46:AK46)-AL46 -> 2044.375 | AN46: =+AM46-Z46-AD46-AE46-AF46-AG46-AJ46-AK46-AI46-AY46-AZ46 -> 1766.7708 | AQ46: 0.1 | AR46: =+AN46*AQ46 -> 176.67708 | AS46: 0 | AT46: =+AN46*AS46 -> 0 | AU46: 0.0137 | AV46: =+AN46*AU46 -> 24.20476 | AW46: =+AQ46+AS46+AU46 -> 0.1137 | AX46: =+AR46+AT46+AV46 -> 200.88184 | AY46: =TARDANZA!K40 -> 0 | AZ46: =TARDANZA!L40 -> 5.1041667 | BA46: 665 | BB46: =AF46+AG46 -> 272.5 | BI46: =+AX46+SUM(AY46:BH46)+AP46 -> 1143.486 | BJ46: =(+AM46-BI46) -> 900.88899 | BK46: 0.09 | BL46: =AN46*BK46 -> 159.00937 | BM46: 2.53 | BO46: BBVA | BU46: BBVA
A47: PROYECTO | B47: =+B46+1 -> 36 | C47: ALARCON OLIVERA AMBAR TIFFANY | D47: 74217394 | E47: 34877 | F47: 46160 | H47: ASISTENTE DE PROYECTOS | I47: PROFUTURO | J47: 2850 | L47: 30 | O47: =+L47-M47-N47 -> 30 | P47: 8 | Q47: =+O47*P47 -> 240 | R47: =+J47-AC47-T47 -> 2850 | S47: =K47 -> 0 | T47: =(J47)/30*M47 -> 0 | W47: =H.E!L41 -> 0 | X47: =H.E!M41 -> 0 | Y47: =H.E!N41 -> 0 | AC47: =(J47+K47)/30*N47 -> 0 | AF47: 475 | AG47: 42.75 | AM47: =SUM(R47:AK47)-AL47 -> 3367.75 | AN47: =+AM47-Z47-AD47-AE47-AF47-AG47-AJ47-AK47-AI47-AY47-AZ47 -> 2840.1042 | AQ47: 0.1 | AR47: =+AN47*AQ47 -> 284.01042 | AS47: 0 | AT47: =+AN47*AS47 -> 0 | AU47: 0.0137 | AV47: =+AN47*AU47 -> 38.909427 | AW47: =+AQ47+AS47+AU47 -> 0.1137 | AX47: =+AR47+AT47+AV47 -> 322.91984 | AY47: =TARDANZA!K41 -> 0 | AZ47: =TARDANZA!L41 -> 9.8958333 | BA47: 1230 | BB47: =AF47+AG47 -> 517.75 | BI47: =+AX47+SUM(AY47:BH47)+AP47 -> 2080.5657 | BJ47: =(+AM47-BI47) -> 1287.1843 | BK47: 0.09 | BL47: =AN47*BK47 -> 255.60937 | BM47: 4.81 | BO47: BBVA | BU47: BBVA
A48: SOPORTE | B48: =+B47+1 -> 37 | C48: BURGA MUÑOZ HELDER ALEXANDER | D48: 72326112 | E48: 35254 | F48: 46181 | H48: ASISTENTE DE SOPORTE TECNICO | I48: INTEGRA | J48: 1700 | L48: 30 | O48: =+L48-M48-N48 -> 30 | P48: 8 | Q48: =+O48*P48 -> 240 | R48: =+J48-AC48-T48 -> 1700 | S48: =K48 -> 0 | T48: =(J48)/30*M48 -> 0 | W48: =H.E!L42 -> 0 | X48: =H.E!M42 -> 0 | Y48: =H.E!N42 -> 0 | AC48: =(J48+K48)/30*N48 -> 0 | AM48: =SUM(R48:AK48)-AL48 -> 1700 | AN48: =+AM48-Z48-AD48-AE48-AF48-AG48-AJ48-AK48-AI48-AY48-AZ48 -> 1695.5139 | AQ48: 0.1 | AR48: =+AN48*AQ48 -> 169.55139 | AS48: 0 | AT48: =+AN48*AS48 -> 0 | AU48: 0.0137 | AV48: =+AN48*AU48 -> 23.22854 | AW48: =+AQ48+AS48+AU48 -> 0.1137 | AX48: =+AR48+AT48+AV48 -> 192.77993 | AY48: =TARDANZA!K42 -> 0 | AZ48: =TARDANZA!L42 -> 4.4861111 | BA48: 750 | BI48: =+AX48+SUM(AY48:BH48)+AP48 -> 947.26604 | BJ48: =(+AM48-BI48) -> 752.73396 | BK48: 0.09 | BL48: =AN48*BK48 -> 152.59625 | BM48: 2.55 | BO48: BBVA | BU48: BBVA
A49: CONTA | B49: =+B48+1 -> 38 | C49: JUÑO FUENTEZ STEFANIA BRISEIDA | D49: 46421278 | E49: 33084 | F49: 46182 | G49: . | H49: ASISTENTE CONTABLE | I49: PRIMA | J49: 2000 | K49: 113 | L49: 30 | O49: =+L49-M49-N49 -> 30 | P49: 8 | Q49: =+O49*P49 -> 240 | R49: =66.6666666666667*9 -> 600 | S49: =K49 -> 113 | T49: =(J49)/30*M49 -> 0 | W49: =H.E!L43 -> 0 | X49: =H.E!M43 -> 0 | Y49: =H.E!N43 -> 0 | AC49: =(J49+K49)/30*N49 -> 0 | AM49: =SUM(R49:AK49)-AL49 -> 713 | AN49: =+AM49-Z49-AD49-AE49-AF49-AG49-AJ49-AK49-AI49-AY49-AZ49 -> 713 | AQ49: 0.1 | AR49: =+AN49*AQ49 -> 71.3 | AS49: 0 | AT49: =+AN49*AS49 -> 0 | AU49: 0.0137 | AV49: =+AN49*AU49 -> 9.7681 | AW49: =+AQ49+AS49+AU49 -> 0.1137 | AX49: =+AR49+AT49+AV49 -> 81.0681 | AY49: =TARDANZA!K43 -> 0 | AZ49: =TARDANZA!L43 -> 0 | BI49: =+AX49+SUM(AY49:BH49)+AP49 -> 81.0681 | BJ49: =(+AM49-BI49) -> 631.9319 | BK49: 0.09 | BL49: =AN49*BK49 -> 64.17 | BM49: 3 | BO49: BBVA | BU49: BBVA
A50: SOPORTE | B50: =+B49+1 -> 39 | C50: RIVERA CORRALES JUAN EDUARDO | D50: 72705177 | E50: 36894 | F50: 46188 | H50: ASISTENTE DE SOPORTE TECNICO | I50: INTEGRA | J50: 2800 | L50: 30 | O50: =+L50-M50-N50 -> 30 | P50: 8 | Q50: =+O50*P50 -> 240 | R50: =+J50-AC50-T50 -> 2800 | S50: =K50 -> 0 | T50: =(J50)/30*M50 -> 0 | W50: =H.E!L44 -> 0 | X50: =H.E!M44 -> 0 | Y50: =H.E!N44 -> 0 | AC50: =(J50+K50)/30*N50 -> 0 | AM50: =SUM(R50:AK50)-AL50 -> 2800 | AN50: =+AM50-Z50-AD50-AE50-AF50-AG50-AJ50-AK50-AI50-AY50-AZ50 -> 2792.2222 | AQ50: 0.1 | AR50: =+AN50*AQ50 -> 279.22222 | AS50: 0 | AT50: =+AN50*AS50 -> 0 | AU50: 0.0137 | AV50: =+AN50*AU50 -> 38.253444 | AW50: =+AQ50+AS50+AU50 -> 0.1137 | AX50: =+AR50+AT50+AV50 -> 317.47567 | AY50: =TARDANZA!K44 -> 0 | AZ50: =TARDANZA!L44 -> 7.7777778 | BA50: 1240 | BI50: =+AX50+SUM(AY50:BH50)+AP50 -> 1565.2534 | BJ50: =(+AM50-BI50) -> 1234.7466 | BK50: 0.09 | BL50: =AN50*BK50 -> 251.3 | BM50: 4.2 | BO50: BBVA | BU50: BBVA
A51: SOPORTE | B51: =+B50+1 -> 40 | C51: MELO HUAMAN CARLOS MANUEL | D51: 72368094 | E51: 37634 | F51: 46188 | H51: AUXILIAR DE SOPORTE TECNICO | I51: PROFUTURO | J51: 1400 | L51: 30 | O51: =+L51-M51-N51 -> 30 | P51: 8 | Q51: =+O51*P51 -> 240 | R51: =+J51-AC51-T51 -> 1400 | S51: =K51 -> 0 | T51: =(J51)/30*M51 -> 0 | W51: =H.E!L45 -> 0 | X51: =H.E!M45 -> 0 | Y51: =H.E!N45 -> 0 | AC51: =(J51+K51)/30*N51 -> 0 | AM51: =SUM(R51:AK51)-AL51 -> 1400 | AN51: =+AM51-Z51-AD51-AE51-AF51-AG51-AJ51-AK51-AI51-AY51-AZ51 -> 1391.7361 | AQ51: 0.1 | AR51: =+AN51*AQ51 -> 139.17361 | AS51: 0 | AT51: =+AN51*AS51 -> 0 | AU51: 0.0137 | AV51: =+AN51*AU51 -> 19.066785 | AW51: =+AQ51+AS51+AU51 -> 0.1137 | AX51: =+AR51+AT51+AV51 -> 158.2404 | AY51: =TARDANZA!K45 -> 0 | AZ51: =TARDANZA!L45 -> 8.2638889 | BA51: 620 | BI51: =+AX51+SUM(AY51:BH51)+AP51 -> 786.50428 | BJ51: =(+AM51-BI51) -> 613.49572 | BK51: 0.09 | BL51: =AN51*BK51 -> 125.25625 | BM51: 2.1 | BO51: BBVA | BU51: BBVA
A52: RR.HH | B52: =+B51+1 -> 41 | C52: FARFAN LAUREL CIELO CARMIN | D52: 70351677 | E52: 35876 | F52: 46188 | H52: ASISTENTE DE RR.HH | I52: INTEGRA | J52: 2000 | L52: 30 | M52: 1 | O52: =+L52-M52-N52 -> 29 | P52: 8 | Q52: =+O52*P52 -> 232 | R52: =+J52-AC52-T52 -> 1933.3333 | S52: =K52 -> 0 | T52: =(J52)/30*M52 -> 66.666667 | W52: =H.E!L46 -> 0 | X52: =H.E!M46 -> 0 | Y52: =H.E!N46 -> 0 | AC52: =(J52+K52)/30*N52 -> 0 | AM52: =SUM(R52:AK52)-AL52 -> 2000 | AN52: =+AM52-Z52-AD52-AE52-AF52-AG52-AJ52-AK52-AI52-AY52-AZ52 -> 2000 | AQ52: 0.1 | AR52: =+AN52*AQ52 -> 200 | AS52: 0 | AT52: =+AN52*AS52 -> 0 | AU52: 0.0137 | AV52: =+AN52*AU52 -> 27.4 | AW52: =+AQ52+AS52+AU52 -> 0.1137 | AX52: =+AR52+AT52+AV52 -> 227.4 | AY52: =TARDANZA!K46 -> 0 | AZ52: =TARDANZA!L46 -> 0 | BA52: 880 | BI52: =+AX52+SUM(AY52:BH52)+AP52 -> 1107.4 | BJ52: =(+AM52-BI52) -> 892.6 | BK52: 0.09 | BL52: =AN52*BK52 -> 180 | BM52: 3 | BO52: BCP | BU52: BCP
A53: ALMACEN | B53: =+B52+1 -> 42 | C53: ORTIZ PAREDES CESAR PAUL | D53: 71473884 | E53: 35473 | F53: 46195 | H53: AUXILIAR DE ALMACEN | I53: PRIMA | J53: 1200 | K53: 113 | L53: 30 | O53: =+L53-M53-N53 -> 30 | P53: 8 | Q53: =+O53*P53 -> 240 | R53: =+J53-AC53-T53 -> 1200 | S53: =K53 -> 113 | T53: =(J53)/30*M53 -> 0 | W53: =H.E!L47 -> 45.026042 | X53: =H.E!M47 -> 18.703125 | Y53: =H.E!N47 -> 177.33333 | AC53: =(J53+K53)/30*N53 -> 0 | AM53: =SUM(R53:AK53)-AL53 -> 1554.0625 | AN53: =+AM53-Z53-AD53-AE53-AF53-AG53-AJ53-AK53-AI53-AY53-AZ53 -> 1550.5065 | AQ53: 0.1 | AR53: =+AN53*AQ53 -> 155.05065 | AS53: 0 | AT53: =+AN53*AS53 -> 0 | AU53: 0.0137 | AV53: =+AN53*AU53 -> 21.241938 | AW53: =+AQ53+AS53+AU53 -> 0.1137 | AX53: =+AR53+AT53+AV53 -> 176.29258 | AY53: =TARDANZA!K47 -> 0 | AZ53: =TARDANZA!L47 -> 3.5560417 | BA53: 580 | BI53: =+AX53+SUM(AY53:BH53)+AP53 -> 759.84863 | BJ53: =(+AM53-BI53) -> 794.21387 | BK53: 0.09 | BL53: =AN53*BK53 -> 139.54558 | BM53: 1.8 | BO53: BBVA | BU53: BBVA
A54: VTAS | B54: =+B53+1 -> 43 | C54: PAREDES CHAMOCHUMBI ANA GABRIEL | D54: 41782489 | E54: 30375 | F54: 46204 | H54: EJECUTIVO COMERCIAL | I54: INTEGRA | J54: 2000 | L54: 30 | O54: =+L54-M54-N54 -> 30 | P54: 8 | Q54: =+O54*P54 -> 240 | R54: =+J54-AC54-T54 -> 2000 | T54: =(J54)/30*M54 -> 0 | U54: =COMISIONES!J11 -> 72.72075 | W54: =H.E!L48 -> 0 | X54: =H.E!M48 -> 0 | Y54: =H.E!N48 -> 0 | AC54: =(J54+K54)/30*N54 -> 0 | AM54: =SUM(R54:AK54)-AL54 -> 2072.7207 | AN54: =+AM54-Z54-AD54-AE54-AF54-AG54-AJ54-AK54-AI54-AY54-AZ54 -> 2070.4985 | AQ54: 0.1 | AR54: =+AN54*AQ54 -> 207.04985 | AS54: 0 | AT54: =+AN54*AS54 -> 0 | AU54: 0.0137 | AV54: =+AN54*AU54 -> 28.36583 | AW54: =+AQ54+AS54+AU54 -> 0.1137 | AX54: =+AR54+AT54+AV54 -> 235.41568 | AY54: =TARDANZA!K48 -> 0 | AZ54: =TARDANZA!L48 -> 2.2222222 | BA54: 880 | BI54: =+AX54+SUM(AY54:BH54)+AP54 -> 1117.6379 | BJ54: =(+AM54-BI54) -> 955.08285 | BK54: 0.09 | BL54: =AN54*BK54 -> 186.34487 | BM54: 7.8 | BO54: BBVA | BU54: BBVA
AC55: =(J55+K55)/30*N55 -> 0 | BI55: =+AX55+SUM(AY55:BH55)+AP55 -> 0 | BT55: 0
J56: =SUM(J12:J55) -> 125150 | K56: =SUM(K12:K55) -> 1808 | R56: =SUM(R12:R55) -> 113404.53 | S56: =SUM(S12:S55) -> 1808 | T56: =SUM(T12:T55) -> 1986.6667 | U56: =SUM(U12:U55) -> 31418.044 | V56: =SUM(V12:V55) -> 2161.4637 | W56: =SUM(W12:W55) -> 532.98437 | X56: =SUM(X12:X55) -> 226.11656 | Y56: =SUM(Y12:Y55) -> 1869.2 | ... AA56: =SUM(AA12:AA55) -> 0 | AC56: =SUM(AC12:AC55) -> 8358.8 | AD56: =SUM(AD12:AD55) -> 0 | AE56: =SUM(AE12:AE55) -> 0 | AF56: =SUM(AF12:AF55) -> 135766.66 | AG56: =SUM(AG12:AG55) -> 12219 | AH56: =SUM(AH12:AH55) -> 1440 | AI56: =SUM(AI12:AI55) -> 0 | AJ56: =SUM(AJ12:AJ55) -> 0 | ... AN56: =SUM(AN12:AN55) -> 162531.56 | AP56: =SUM(AP12:AP55) -> 3654.0754 | AR56: =SUM(AR12:AR55) -> 13442.329 | AT56: =SUM(AT12:AT55) -> 513.87264 | AV56: =SUM(AV12:AV55) -> 1726.4361 | AX56: =SUM(AX12:AX55) -> 15682.638 | AY56: =SUM(AY12:AY55) -> 0 | AZ56: =SUM(AZ12:AZ55) -> 674.24486 | BA56: =SUM(BA12:BA55) -> 7725 | BB56: =SUM(BB12:BB55) -> 147985.66 | BC56: =SUM(BC12:BC55) -> 3700 | BD56: =SUM(BD12:BD55) -> 1337.34 | BE56: =SUM(BE12:BE55) -> 1669.6713 | ... BJ56: =SUM(BJ12:BJ55) -> 115170.27 | BL56: =SUM(BL12:BL55) -> 14627.841 | BM56: =SUM(BM12:BM55) -> 337.3782 | BT56: =SUM(BT12:BT55) -> 0
U57: =+COMISIONES!J12 -> 31418.044 | V57: =VACACIONES!T12 -> 2161.4637 | AN57: =+AM56-AN56 -> 149233.82 | AY57: 0 | AZ57: 0 | BE57: =-'HT. EPS'!Q53 -> -1669.6713 | BH57: =-'RTA 5TA'!U115 -> -12189.816
C58: LL.BB.SS | BH58: =+BH57+BH56 -> 0 | BP58: RXH | BQ58: Luis Lavi | BS58: 590 | BT58: =(2300/30*17)-BS58 -> 713.33333 | BU58: BCP | BV58: 19101207696093
BP59: RXH | BQ59: Emerson | BS59: 0 | BT59: =1800/30*19 -> 1140 | BU59: BCP | BV59: 19475759659005
B60: 20 | C60: JUÑO FUENTEZ STEFANIA BRISEIDA | D60: 46421278 | E60: 33084 | F60: 46182 | G60: . | H60: ASISTENTE CONTABLE | I60: PRIMA | J60: 2000 | K60: 113 | AA60: 181.95 | AD60: 176.08 | AM60: =SUM(Z60:AL60) -> 358.03 | AN60: =AA60 -> 181.95 | AQ60: 0.1 | AR60: =+AN60*AQ60 -> 18.195 | AS60: 0 | AT60: =+AN60*AS60 -> 0 | AU60: 0.0137 | AV60: =+AN60*AU60 -> 2.492715 | AW60: =+AQ60+AS60+AU60 -> 0.1137 | AX60: =+AR60+AT60+AV60 -> 20.687715 | BI60: =+AX60+SUM(AY60:BH60)+AP60 -> 20.687715 | BJ60: =(+AM60-BI60) -> 337.34228 | BK60: 0.09 | BL60: =AN60*BK60 -> 16.3755
B61: 16 | C61: SALCEDO RIVAS DANIEL ALONSO | D61: 42953954 | E61: 31117 | F61: 45398 | H61: SUPERVISOR DE ALMACEN | I61: INTEGRA | J61: 2800 | K61: 113 | AA61: 849.63 | AC61: 2233.3 | AD61: 849.63 | AF61: 485.5 | AG61: 43.7 | AI61: 23.09 | AK61: 2800 | AM61: =SUM(AA61:AL61) -> 7284.85 | AN61: =AC61+AA61 -> 3082.93 | AQ61: 0.1 | AR61: =+AN61*AQ61 -> 308.293 | AS61: 0 | AT61: =+AN61*AS61 -> 0 | AU61: 0.0137 | AV61: =+AN61*AU61 -> 42.236141 | AW61: =+AQ61+AS61+AU61 -> 0.1137 | AX61: =+AR61+AT61+AV61 -> 350.52914 | BI61: =AX61 -> 350.52914 | BJ61: 6934.3 | BK61: 0.09 | BL61: =AN61*BK61 -> 277.4637
B62: =+B61+1 -> 17 | C62: BANCHO CANELOS EDSON OMAR AMANCIO | D62: 71562324 | E62: 35075 | F62: 46160 | H62: ASISTENTE DE ALMACEN | I62: HABITAT | J62: 1500 | AA62: 304.17 | AD62: 312.62 | AF62: 250 | AG62: 22.5 | AM62: =SUM(AA62:AL62) -> 889.29 | AN62: =AC62+AA62 -> 304.17 | AQ62: 0.1 | AR62: =+AN62*AQ62 -> 30.417 | AS62: 0 | AT62: =+AN62*AS62 -> 0 | AU62: 0.0137 | AV62: =+AN62*AU62 -> 4.167129 | AW62: =+AQ62+AS62+AU62 -> 0.1137 | AX62: =+AR62+AT62+AV62 -> 34.584129 | BI62: =AX62 -> 34.584129 | BJ62: 854.7 | BK62: 0.09 | BL62: =AN62*BK62 -> 27.3753
R63: =SUBTOTAL(9,R59:R60) -> 0 | S63: =SUBTOTAL(9,S59:S60) -> 0 | T63: =SUBTOTAL(9,T59:T60) -> 0 | U63: =SUBTOTAL(9,U59:U60) -> 0 | V63: =SUBTOTAL(9,V59:V60) -> 0 | W63: =SUBTOTAL(9,W59:W60) -> 0 | X63: =SUBTOTAL(9,X59:X60) -> 0 | Y63: =SUBTOTAL(9,Y59:Y60) -> 0 | Z63: =SUBTOTAL(9,Z59:Z60) -> 0 | AA63: =SUBTOTAL(9,AA60:AA61) -> 1031.58 | AC63: =SUBTOTAL(9,AC59:AC60) -> 0 | AD63: =SUBTOTAL(9,AD60:AD61) -> 1025.71 | AE63: =SUBTOTAL(9,AE59:AE60) -> 0 | AF63: =SUBTOTAL(9,AF60:AF61) -> 485.5 | AG63: =SUBTOTAL(9,AG60:AG61) -> 43.7 | AH63: =SUBTOTAL(9,AH60:AH61) -> 0 | AI63: =SUBTOTAL(9,AI60:AI61) -> 23.09 | AJ63: =SUBTOTAL(9,AJ60:AJ61) -> 0 | AK63: =SUBTOTAL(9,AK60:AK61) -> 2800 | AL63: =SUBTOTAL(9,AL60:AL61) -> 0 | AM63: =SUBTOTAL(9,AM60:AM61) -> 7642.88 | AN63: =SUBTOTAL(9,AN60:AN61) -> 3264.88 | AP63: =SUBTOTAL(9,AP59:AP60) -> 0 | AR63: =SUBTOTAL(9,AR60:AR61) -> 326.488 | AT63: =SUBTOTAL(9,AT59:AT60) -> 0 | AV63: =SUBTOTAL(9,AV60:AV61) -> 44.728856 | AX63: =SUBTOTAL(9,AX60:AX61) -> 371.21686 | AY63: =SUBTOTAL(9,AY59:AY60) -> 0 | AZ63: =SUBTOTAL(9,AZ59:AZ60) -> 0 | BB63: =SUBTOTAL(9,BB59:BB60) -> 0 | BC63: =SUBTOTAL(9,BC59:BC60) -> 0 | BD63: =SUBTOTAL(9,BD59:BD60) -> 0 | BE63: =SUBTOTAL(9,BE59:BE60) -> 0 | BG63: =SUBTOTAL(9,BG59:BG60) -> 0 | BH63: =SUBTOTAL(9,BH59:BH60) -> 0 | BI63: =SUBTOTAL(9,BI60:BI61) -> 371.21686 | BJ63: =SUBTOTAL(9,BJ60:BJ61) -> 7271.6423 | BL63: =SUBTOTAL(9,BL60:BL61) -> 293.8392
R65: =+R63+R56 -> 113404.53 | S65: =+S63+S56 -> 1808 | T65: =+T63+T56 -> 1986.6667 | U65: =+U63+U56 -> 31418.044 | V65: =+V63+V56 -> 2161.4637 | W65: =+W56+W59 -> 532.98437 | X65: =+X56+X59 -> 226.11656 | Y65: =+Y56+Y59 -> 1869.2 | Z65: =+Z63+Z56 -> 573.91304 | AA65: =+AA63+AA56 -> 1031.58 | AC65: =+AC63+AC56 -> 8358.8 | AD65: =+AD56+AD59 -> 0 | AF65: =+AF56+AF59 -> 135766.66 | AG65: =+AG56+AG59 -> 12219 | AH65: =+AH63+AH56 -> 1440 | AI65: =+AI56+AI59 -> 0 | AJ65: =+AJ56+AJ59 -> 0 | AK65: =+AK56+AK59 -> 0 | AL65: =+AL56+AL59 -> 0 | AM65: =+AM63+AM56 -> 319408.27 | AN65: =+AN63+AN56 -> 165796.44 | AO65: =+AO63+AO56 -> 0 | AP65: =+AP63+AP56 -> 3654.0754 | AQ65: =+AQ63+AQ56 -> 0 | AR65: =+AR63+AR56 -> 13768.817 | AS65: =+AS63+AS56 -> 0 | AT65: =+AT63+AT56 -> 513.87264 | ... AZ65: =+AZ63+AZ56 -> 674.24486 | BB65: =+BB63+BB56 -> 147985.66 | BC65: =+BC63+BC56 -> 3700 | BD65: =+BD63+BD56 -> 1337.34 | BE65: =+BE63+BE56 -> 1669.6713 | BF65: =+BF56+BF59 -> 0 | BG65: =+BG63+BG56 -> 1976.6612 | BH65: =+BH63+BH56 -> 12189.816 | BI65: =+BI63+BI56 -> 196966.33 | BJ65: =+BJ63+BJ56 -> 122441.92 | BK65: =+BK63+BK56 -> 0 | BL65: =+BL63+BL56 -> 14921.68 | BM65: =+BM63+BM56 -> 337.3782 | BN65: =+BN63+BN56 -> 0
C66: MODIFICACIONES EN PLANILLA SEGÚN PAGO | BE66: =+'HT. EPS'!Q53 -> 1669.6713 | BH66: =+'RTA 5TA'!U115 -> 12189.816
O68: K0011 | P68: ADM | R68: =+SUMIF($A$12:$A$50,"ADM",R$12:R$55) -> 9200 | S68: =+SUMIF($A$12:$A$50,"ADM",S$12:S$55) -> 226 | T68: =+SUMIF($A$12:$A$50,"ADM",T$12:T$55) -> 0 | U68: =+SUMIF($A$12:$A$50,"ADM",U$12:U$55) -> 0 | V68: =+SUMIF($A$12:$A$50,"ADM",V$12:V$55) -> 0 | W68: =+SUMIF($A$12:$A$50,"ADM",W$12:W$55) -> 0 | X68: =+SUMIF($A$12:$A$50,"ADM",X$12:X$55) -> 0 | Y68: =+SUMIF($A$12:$A$50,"ADM",Y$12:Y$55) -> 0 | ... AA68: =+SUMIF($A$12:$A$50,"ADM",AA$12:AA$55) -> 0 | AC68: =+SUMIF($A$12:$A$50,"ADM",AC$12:AC$55) -> 0 | AD68: =+SUMIF($A$12:$A$50,"ADM",AD$12:AD$55) -> 0 | AE68: =+SUMIF($A$12:$A$50,"ADM",AE$12:AE$55) -> 0 | AF68: =+SUMIF($A$12:$A$50,"ADM",AF$12:AF$55) -> 9356 | AG68: =+SUMIF($A$12:$A$50,"ADM",AG$12:AG$55) -> 842.04 | AH68: =+SUMIF($A$12:$A$50,"ADM",AH$12:AH$55) -> 0 | AI68: =+SUMIF($A$12:$A$50,"ADM",AI$12:AI$55) -> 0 | AJ68: =+SUMIF($A$12:$A$50,"ADM",AJ$12:AJ$55) -> 0 | ... AN68: =+SUMIF($A$12:$A$50,"ADM",AN$12:AN$55) -> 9426 | AP68: CONCEPTOS | AQ68: O.N.P. | AR68: ESSALUD | AS68: APORTE | AT68: COMISION | AU68: PRIMA | AV68: I.RTA.5 | AW68: TOTALES | BG68: PAGOS FIN DE MES | BL68: =+SUMIF($A$12:$A$50,"ADM",BL$12:BL$55) -> 848.34 | BM68: =+SUMIF($A$12:$A$50,"ADM",BM$12:BM$55) -> 33.3614 | BS68: PAGOS 1RA QUINCENA MES
O69: K0012 | P69: CONTA | R69: =+SUMIF($A$12:$A$50,"CONTA",R$12:R$55) -> 5746.6667 | S69: =+SUMIF($A$12:$A$50,"CONTA",S$12:S$55) -> 113 | T69: =+SUMIF($A$12:$A$50,"CONTA",T$12:T$55) -> 0 | U69: =+SUMIF($A$12:$A$50,"CONTA",U$12:U$55) -> 0 | V69: =+SUMIF($A$12:$A$50,"CONTA",V$12:V$55) -> 0 | W69: =+SUMIF($A$12:$A$50,"CONTA",W$12:W$55) -> 0 | X69: =+SUMIF($A$12:$A$50,"CONTA",X$12:X$55) -> 0 | Y69: =+SUMIF($A$12:$A$50,"CONTA",Y$12:Y$55) -> 0 | ... AA69: =+SUMIF($A$12:$A$50,"CONTA",AA$12:AA$55) -> 0 | AC69: =+SUMIF($A$12:$A$50,"CONTA",AC$12:AC$55) -> 653.33333 | AD69: =+SUMIF($A$12:$A$50,"CONTA",AD$12:AD$55) -> 0 | AE69: =+SUMIF($A$12:$A$50,"CONTA",AE$12:AE$55) -> 0 | AF69: =+SUMIF($A$12:$A$50,"CONTA",AF$12:AF$55) -> 5800 | AG69: =+SUMIF($A$12:$A$50,"CONTA",AG$12:AG$55) -> 522 | AH69: =+SUMIF($A$12:$A$50,"CONTA",AH$12:AH$55) -> 0 | AI69: =+SUMIF($A$12:$A$50,"CONTA",AI$12:AI$55) -> 0 | AJ69: =+SUMIF($A$12:$A$50,"CONTA",AJ$12:AJ$55) -> 0 | ... AN69: =+SUMIF($A$12:$A$50,"CONTA",AN$12:AN$55) -> 6402.7917 | AP69: O.N.P. | AQ69: =+AP65 -> 3654.0754 | AW69: =SUM(AQ69:AV69) -> 3654.0754 | BG69: BBVA | BH69: =+SUMIF($BO$12:$BO$55,"BBVA",$BJ$12:$BJ$55) -> 64292.923 | BL69: =+SUMIF($A$12:$A$50,"CONTA",BL$12:BL$55) -> 576.25125 | BM69: =+SUMIF($A$12:$A$50,"CONTA",BM$12:BM$55) -> 24.45 | BS69: BBVA | BT69: =+SUMIF($BO$12:$BO$55,"BBVA",$BT$12:$BT$55) -> 0
O70: K0013 | P70: LOGISTICA | R70: =+SUMIF($A$12:$A$50,"LOGISTICA",R$12:R$55) -> 5080 | S70: =+SUMIF($A$12:$A$50,"LOGISTICA",S$12:S$55) -> 0 | T70: =+SUMIF($A$12:$A$50,"LOGISTICA",T$12:T$55) -> 0 | U70: =+SUMIF($A$12:$A$50,"LOGISTICA",U$12:U$55) -> 0 | V70: =+SUMIF($A$12:$A$50,"LOGISTICA",V$12:V$55) -> 0 | W70: =+SUMIF($A$12:$A$50,"LOGISTICA",W$12:W$55) -> 0 | X70: =+SUMIF($A$12:$A$50,"LOGISTICA",X$12:X$55) -> 0 | Y70: =+SUMIF($A$12:$A$50,"LOGISTICA",Y$12:Y$55) -> 240 | ... AA70: =+SUMIF($A$12:$A$50,"LOGISTICA",AA$12:AA$55) -> 0 | AC70: =+SUMIF($A$12:$A$50,"LOGISTICA",AC$12:AC$55) -> 720 | AD70: =+SUMIF($A$12:$A$50,"LOGISTICA",AD$12:AD$55) -> 0 | AE70: =+SUMIF($A$12:$A$50,"LOGISTICA",AE$12:AE$55) -> 0 | AF70: =+SUMIF($A$12:$A$50,"LOGISTICA",AF$12:AF$55) -> 6440 | AG70: =+SUMIF($A$12:$A$50,"LOGISTICA",AG$12:AG$55) -> 579.6 | AH70: =+SUMIF($A$12:$A$50,"LOGISTICA",AH$12:AH$55) -> 640 | AI70: =+SUMIF($A$12:$A$50,"LOGISTICA",AI$12:AI$55) -> 0 | AJ70: =+SUMIF($A$12:$A$50,"LOGISTICA",AJ$12:AJ$55) -> 0 | ... AN70: =+SUMIF($A$12:$A$50,"LOGISTICA",AN$12:AN$55) -> 6599.7917 | AP70: ESSALUD | AR70: =+BL56 -> 14627.841 | AW70: =SUM(AQ70:AV70) -> 14627.841 | BG70: BCP | BH70: =+SUMIF($BO$12:$BO$55,"BCP",$BJ$12:$BJ$55) -> 45374.869 | BL70: =+SUMIF($A$12:$A$50,"LOGISTICA",BL$12:BL$55) -> 593.98125 | BM70: =+SUMIF($A$12:$A$50,"LOGISTICA",BM$12:BM$55) -> 15.964 | BS70: BCP | BT70: =+SUMIF($BO$12:$BO$55,"BCP",$BT$12:$BT$55) -> 0 | BU70: BCP
BG71: INTERBANK | BH71: =+SUMIF($BO$12:$BO$55,"INTERB",$BJ$12:$BJ$55) -> 5502.4826 | BS71: INTERB | BT71: =+BT22 -> 0 | BU71: BCP
O72: K0021 | P72: VTAS | R72: =+SUMIF($A$12:$A$50,"VTAS",R$12:R$55) -> 35519.733 | S72: =+SUMIF($A$12:$A$50,"VTAS",S$12:S$55) -> 452 | T72: =+SUMIF($A$12:$A$50,"VTAS",T$12:T$55) -> 1920 | U72: =+SUMIF($A$12:$A$50,"VTAS",U$12:U$55) -> 31345.323 | V72: =+SUMIF($A$12:$A$50,"VTAS",V$12:V$55) -> 2161.4637 | W72: =+SUMIF($A$12:$A$50,"VTAS",W$12:W$55) -> 0 | X72: =+SUMIF($A$12:$A$50,"VTAS",X$12:X$55) -> 0 | Y72: =+SUMIF($A$12:$A$50,"VTAS",Y$12:Y$55) -> 0 | ... AA72: =+SUMIF($A$12:$A$50,"VTAS",AA$12:AA$55) -> 0 | AC72: =+SUMIF($A$12:$A$50,"VTAS",AC$12:AC$55) -> 3360.2667 | AD72: =+SUMIF($A$12:$A$50,"VTAS",AD$12:AD$55) -> 0 | AE72: =+SUMIF($A$12:$A$50,"VTAS",AE$12:AE$55) -> 0 | AF72: =+SUMIF($A$12:$A$50,"VTAS",AF$12:AF$55) -> 65417.63 | AG72: =+SUMIF($A$12:$A$50,"VTAS",AG$12:AG$55) -> 5887.5867 | AH72: =+SUMIF($A$12:$A$50,"VTAS",AH$12:AH$55) -> 800 | AI72: =+SUMIF($A$12:$A$50,"VTAS",AI$12:AI$55) -> 0 | AJ72: =+SUMIF($A$12:$A$50,"VTAS",AJ$12:AJ$55) -> 0 | ... AN72: =+SUMIF($A$12:$A$50,"VTAS",AN$12:AN$55) -> 75462.692 | AP72: PRIMA | AS72: =+SUMIF($I$12:$I$55,"PRIMA",AR$12:AR$55)+AR60 -> 3510.9706 | AT72: =+SUMIF($I$12:$I$55,"PRIMA",AT$12:AT$55) -> 153.47167 | AU72: =+SUMIF($I$12:$I$55,"PRIMA",AV$12:AV$55)+AV60 -> 481.00297 | AW72: =SUM(AQ72:AV72) -> 4145.4452 | BH72: =SUM(BH69:BH71) -> 115170.27 | BL72: =+SUMIF($A$12:$A$50,"VTAS",BL$12:BL$55) -> 6791.6423 | BM72: =+SUMIF($A$12:$A$50,"VTAS",BM$12:BM$55) -> 118.28 | BT72: =SUM(BT69:BT71) -> 0 | BU72: BBVA
O73: K0022 | P73: SOPORTE | R73: =+SUMIF($A$12:$A$50,"SOPORTE",R$12:R$55) -> 20000 | S73: =+SUMIF($A$12:$A$50,"SOPORTE",S$12:S$55) -> 339 | T73: =+SUMIF($A$12:$A$50,"SOPORTE",T$12:T$55) -> 0 | U73: =+SUMIF($A$12:$A$50,"SOPORTE",U$12:U$55) -> 0 | V73: =+SUMIF($A$12:$A$50,"SOPORTE",V$12:V$55) -> 0 | W73: =+SUMIF($A$12:$A$50,"SOPORTE",W$12:W$55) -> 0 | X73: =+SUMIF($A$12:$A$50,"SOPORTE",X$12:X$55) -> 0 | Y73: =+SUMIF($A$12:$A$50,"SOPORTE",Y$12:Y$55) -> 0 | ... AA73: =+SUMIF($A$12:$A$50,"SOPORTE",AA$12:AA$55) -> 0 | AC73: =+SUMIF($A$12:$A$50,"SOPORTE",AC$12:AC$55) -> 1000 | AD73: =+SUMIF($A$12:$A$50,"SOPORTE",AD$12:AD$55) -> 0 | AE73: =+SUMIF($A$12:$A$50,"SOPORTE",AE$12:AE$55) -> 0 | AF73: =+SUMIF($A$12:$A$50,"SOPORTE",AF$12:AF$55) -> 17651.176 | AG73: =+SUMIF($A$12:$A$50,"SOPORTE",AG$12:AG$55) -> 1588.6059 | AH73: =+SUMIF($A$12:$A$50,"SOPORTE",AH$12:AH$55) -> 0 | AI73: =+SUMIF($A$12:$A$50,"SOPORTE",AI$12:AI$55) -> 0 | AJ73: =+SUMIF($A$12:$A$50,"SOPORTE",AJ$12:AJ$55) -> 0 | ... AN73: =+SUMIF($A$12:$A$50,"SOPORTE",AN$12:AN$55) -> 21182.727 | AP73: INTEGRA | AS73: =+SUMIF($I$12:$I$55,"INTEGRA",AR$12:AR$55)+AR59 -> 8051.0968 | AT73: =+SUMIF($I$12:$I$55,"INTEGRA",AT$12:AT$55)+AT63 -> 360.40097 | AU73: =+SUMIF($I$12:$I$55,"INTEGRA",AV$12:AV$55)+AV59 -> 987.83731 | AW73: =SUM(AQ73:AV73) -> 9399.3351 | BL73: =+SUMIF($A$12:$A$50,"SOPORTE",BL$12:BL$55) -> 1906.4454 | BM73: =+SUMIF($A$12:$A$50,"SOPORTE",BM$12:BM$55) -> 39.7807 | BU73: BBVA
O74: K0023 | P74: PROYECTOS | R74: =+SUMIF($A$12:$A$50,"PROYECTO",R$12:R$55) -> 8316.6667 | S74: =+SUMIF($A$12:$A$50,"PROYECTO",S$12:S$55) -> 0 | T74: =+SUMIF($A$12:$A$50,"PROYECTO",T$12:T$55) -> 0 | U74: =+SUMIF($A$12:$A$50,"PROYECTO",U$12:U$55) -> 0 | V74: =+SUMIF($A$12:$A$50,"PROYECTO",V$12:V$55) -> 0 | W74: =+SUMIF($A$12:$A$50,"PROYECTO",W$12:W$55) -> 0 | X74: =+SUMIF($A$12:$A$50,"PROYECTO",X$12:X$55) -> 0 | Y74: =+SUMIF($A$12:$A$50,"PROYECTO",Y$12:Y$55) -> 0 | ... AA74: =+SUMIF($A$12:$A$50,"PROYECTO",AA$12:AA$55) -> 0 | AC74: =+SUMIF($A$12:$A$50,"PROYECTO",AC$12:AC$55) -> 533.33333 | AD74: =+SUMIF($A$12:$A$50,"PROYECTO",AD$12:AD$55) -> 0 | AE74: =+SUMIF($A$12:$A$50,"PROYECTO",AE$12:AE$55) -> 0 | AF74: =+SUMIF($A$12:$A$50,"PROYECTO",AF$12:AF$55) -> 6686.8582 | AG74: =+SUMIF($A$12:$A$50,"PROYECTO",AG$12:AG$55) -> 601.81724 | AH74: =+SUMIF($A$12:$A$50,"PROYECTO",AH$12:AH$55) -> 0 | AI74: =+SUMIF($A$12:$A$50,"PROYECTO",AI$12:AI$55) -> 0 | AJ74: =+SUMIF($A$12:$A$50,"PROYECTO",AJ$12:AJ$55) -> 0 | ... AN74: =+SUMIF($A$12:$A$50,"PROYECTO",AN$12:AN$55) -> 8786.1319 | AP74: PROFUTURO | AS74: =+SUMIF($I$12:$I$55,"PROFUTURO",AR$12:AR$55)+AR61 -> 1554.077 | AT74: =+SUMIF($I$12:$I$55,"PROFUTURO",AT$12:AT$55) -> 0 | AU74: =+SUMIF($I$12:$I$55,"PROFUTURO",AV$12:AV$55)+AV61 -> 212.90855 | AW74: =SUM(AQ74:AV74) -> 1766.9856 | BL74: =+SUMIF($A$12:$A$50,"PROYECTO",BL$12:BL$55) -> 790.75188 | BM74: =+SUMIF($A$12:$A$50,"PROYECTO",BM$12:BM$55) -> 12.76 | BU74: BBVA
O75: K0024 | P75: MARKETING | R75: =+SUMIF($A$12:$A$50,"MARKET",R$12:R$55) -> 10873.333 | S75: =+SUMIF($A$12:$A$50,"MARKET",S$12:S$55) -> 113 | T75: =+SUMIF($A$12:$A$50,"MARKET",T$12:T$55) -> 0 | U75: =+SUMIF($A$12:$A$50,"MARKET",U$12:U$55) -> 0 | V75: =+SUMIF($A$12:$A$50,"MARKET",V$12:V$55) -> 0 | W75: =+SUMIF($A$12:$A$50,"MARKET",W$12:W$55) -> 0 | X75: =+SUMIF($A$12:$A$50,"MARKET",X$12:X$55) -> 0 | Y75: =+SUMIF($A$12:$A$50,"MARKET",Y$12:Y$55) -> 0 | ... AA75: =+SUMIF($A$12:$A$50,"MARKET",AA$12:AA$55) -> 0 | AC75: =+SUMIF($A$12:$A$50,"MARKET",AC$12:AC$55) -> 1026.6667 | AD75: =+SUMIF($A$12:$A$50,"MARKET",AD$12:AD$55) -> 0 | AE75: =+SUMIF($A$12:$A$50,"MARKET",AE$12:AE$55) -> 0 | AF75: =+SUMIF($A$12:$A$50,"MARKET",AF$12:AF$55) -> 12013 | AG75: =+SUMIF($A$12:$A$50,"MARKET",AG$12:AG$55) -> 1081.17 | AH75: =+SUMIF($A$12:$A$50,"MARKET",AH$12:AH$55) -> 0 | AI75: =+SUMIF($A$12:$A$50,"MARKET",AI$12:AI$55) -> 0 | AJ75: =+SUMIF($A$12:$A$50,"MARKET",AJ$12:AJ$55) -> 0 | ... AN75: =+SUMIF($A$12:$A$50,"MARKET",AN$12:AN$55) -> 11989.958 | AP75: HABITAT | AS75: =+SUMIF($I$12:$I$55,"HABITAT",AR$12:AR$55) -> 652.67266 | AT75: =+SUMIF($I$12:$I$55,"HABITAT",AT$12:AT$55) -> 0 | AU75: =+SUMIF($I$12:$I$55,"HABITAT",AV$12:AV$55) -> 89.416154 | AW75: =SUM(AQ75:AV75) -> 742.08881 | BL75: =+SUMIF($A$12:$A$50,"MARKET",BL$12:BL$55) -> 1079.0963 | BM75: =+SUMIF($A$12:$A$50,"MARKET",BM$12:BM$55) -> 38.5107 | BS75: YSABEL | BT75: 2300 | BU75: BBVA
O76: K0025 | P76: ALMACEN | R76: =+SUMIF($A$12:$A$50,"ALMACEN",R$12:R$55) -> 12134.8 | S76: =+SUMIF($A$12:$A$50,"ALMACEN",S$12:S$55) -> 452 | T76: =+SUMIF($A$12:$A$50,"ALMACEN",T$12:T$55) -> 0 | U76: =+SUMIF($A$12:$A$50,"ALMACEN",U$12:U$55) -> 0 | V76: =+SUMIF($A$12:$A$50,"ALMACEN",V$12:V$55) -> 0 | W76: =+SUMIF($A$12:$A$50,"ALMACEN",W$12:W$55) -> 487.95833 | X76: =+SUMIF($A$12:$A$50,"ALMACEN",X$12:X$55) -> 207.41344 | Y76: =+SUMIF($A$12:$A$50,"ALMACEN",Y$12:Y$55) -> 1451.8667 | ... AA76: =+SUMIF($A$12:$A$50,"ALMACEN",AA$12:AA$55) -> 0 | AC76: =+SUMIF($A$12:$A$50,"ALMACEN",AC$12:AC$55) -> 1065.2 | AD76: =+SUMIF($A$12:$A$50,"ALMACEN",AD$12:AD$55) -> 0 | AE76: =+SUMIF($A$12:$A$50,"ALMACEN",AE$12:AE$55) -> 0 | AF76: =+SUMIF($A$12:$A$50,"ALMACEN",AF$12:AF$55) -> 12402 | AG76: =+SUMIF($A$12:$A$50,"ALMACEN",AG$12:AG$55) -> 1116.18 | AH76: =+SUMIF($A$12:$A$50,"ALMACEN",AH$12:AH$55) -> 0 | AI76: =+SUMIF($A$12:$A$50,"ALMACEN",AI$12:AI$55) -> 0 | AJ76: =+SUMIF($A$12:$A$50,"ALMACEN",AJ$12:AJ$55) -> 0 | ... AN76: =+SUMIF($A$12:$A$50,"ALMACEN",AN$12:AN$55) -> 15668.73 | AP76: I.RTA.5 | AV76: =+BH65 -> 12189.816 | AW76: =SUM(AQ76:AV76) -> 12189.816 | BG76: PARTN | BH76: 12000 | BI76: BBVA | BL76: =+SUMIF($A$12:$A$50,"ALMACEN",BL$12:BL$55) -> 1410.1857 | BM76: =+SUMIF($A$12:$A$50,"ALMACEN",BM$12:BM$55) -> 39.5714 | BS76: RICARDO | BT76: 1000
AP77: LLBBSS | AR77: =+BL63 -> 293.8392 | AW77: 0 | BG77: JAVIER | BH77: 700 | BI77: bbva | BS77: QUANTUM | BT77: =4984+3452.5+5945.73 -> 14382.23
R78: =SUM(R68:R76) -> 106871.2 | S78: =SUM(S68:S76) -> 1695 | U78: =SUM(U68:U76) -> 31345.323 | V78: =SUM(V68:V76) -> 2161.4637 | W78: =SUM(W68:W76) -> 487.95833 | X78: =SUM(X68:X76) -> 207.41344 | Y78: =SUM(Y68:Y76) -> 1691.8667 | Z78: =SUM(Z68:Z76) -> 573.91304 | AA78: =SUM(AA68:AA76) -> 0 | AC78: =SUM(AC68:AC76) -> 8358.8 | AD78: =SUM(AD68:AD76) -> 0 | AE78: =SUM(AE68:AE76) -> 0 | AF78: =SUM(AF68:AF76) -> 135766.66 | AG78: =SUM(AG68:AG76) -> 12219 | AH78: =SUM(AH68:AH76) -> 1440 | AJ78: =SUM(AJ68:AJ76) -> 0 | AK78: =SUM(AK68:AK76) -> 0 | AL78: =SUM(AL68:AL76) -> 0 | AM78: =SUM(AM68:AM76) -> 304738.6 | AN78: =SUM(AN68:AN76) -> 155518.82 | AQ78: =SUM(AQ69:AQ77) -> 3654.0754 | AR78: =SUM(AR69:AR77) -> 14921.68 | AS78: =SUM(AS69:AS77) -> 13768.817 | AT78: =SUM(AT69:AT77) -> 513.87264 | AU78: =SUM(AU69:AU77) -> 1771.165 | AV78: =SUM(AV69:AV77) -> 12189.816 | AW78: =SUM(AW69:AW77) -> 46525.587 | BG78: ALBE | BH78: 11000 | BI78: BCP | BL78: =SUM(BL68:BL76) -> 13996.694 | BM78: =SUM(BM68:BM76) -> 322.6782 | BS78: GLORI | BT78: 6750
BG79: HONORARIOS | BH79: =+BT59+BT58 -> 1853.3333 | BI79: BCP | BS79: GLORI | BT79: 8732
AN80: =+AN56-AN18-AN19-AN28-AN37-AN41+AN63 -> 137688.17 | AP80: BASE EPS | AR80: =+SUMIF($BN$12:$BN$55,"EPS",BL$12:BL$55) -> 4718.1012 | AS80: =+AR81*AU80 -> 947.50345 | AT80: 3904 | AU80: =+AT80/AT82 -> 0.80329218 | BS80: PARTNE | BT80: 22777 | BU80: 1000 | BV80: =+BV82-BV81 -> 24400 | BW80: =+BT84-BV80 -> -21100
AP81: CREDITO EPS | AR81: =+AR80*25/100 -> 1179.5253 | AS81: =+AR81*AU81 -> 232.02185 | AT81: 956 | AU81: =+AT81/AT82 -> 0.19670782 | AV81: =-AI59 -> 0 | BH81: =SUM(BH72:BH80) -> 140723.61 | BV81: 77000
AS82: =SUBTOTAL(9,AS80:AS81) -> 1179.5253 | AT82: =SUBTOTAL(9,AT80:AT81) -> 4860 | BV82: =30000*3.38 -> 101400
AP83: ESSALUD POR PAGAR | AR83: =+AX70-AR81 -> -1179.5253 | AV83: =+AV78+AV81 -> 12189.816
BG84: BCP | BH84: =+BH70+BH71+BH78+BH79 -> 63730.685 | BJ84: =+BJ86-BJ85 -> 65241.6 | BS84: BCP | BT84: =+BT76+BT75+BT70+BT71 -> 3300 | BV84: =25000*3.432 -> 85800
BG85: BBVA | BH85: =+BH69+BH76+BH77 -> 76992.923 | BI85: 22000 | BJ85: 57000 | BS85: BBVA | BT85: =+BT79+BT78+BT77+BT69+BT80 -> 52641.23
BH86: =SUM(BH84:BH85) -> 140723.61 | BJ86: =36000*3.3956 -> 122241.6 | BT86: =SUM(BT84:BT85) -> 55941.23
BT88: =+BT86/3.37 -> 16599.772
BU1048574: BBVA

Sheet H.E
D3: TOTAL | G3: TOTAL
D4: INGRESOS | E4: ASIGNACION FAMILIAR | G4: INGRESOS | H4: 0.25 | I4: 0.35 | J4: FERIADO/DESCANSO | K4: TOTAL | L4: PAGO 25% | M4: PAGO 35% | N4: PAGO 100%
B5: Nº | C5: APELLIDOS Y NOMBRES | H5: HORAS | I5: HORAS | J5: DIAS | K5: HORAS
B6: 1 | C6: ORIHUELA AGUIRRE ERNESTO JULIO | D6: 13000 | E6: 113 | G6: =+D6+E6 -> 13113 | K6: =SUM(H6:I6) -> 0 | L6: =((G6/30)/8)*H6*1.25 -> 0 | M6: =((G6/30)/8)*I6*1.35 -> 0 | N6: =((G6/30))*J6*2 -> 0
B7: =+B6+1 -> 2 | C7: MARTINEZ CASTILLO GIOVANNA RAQUEL | D7: 6500 | E7: 113 | G7: =+D7+E7 -> 6613 | K7: =SUM(H7:I7) -> 0 | L7: =((G7/30)/8)*H7*1.25 -> 0 | M7: =((G7/30)/8)*I7*1.35 -> 0 | N7: =((G7/30))*J7*2 -> 0
B8: =+B7+1 -> 3 | C8: SALVADOR ROJAS ELVIS ALFONSO | D8: 4000 | E8: 113 | G8: =+D8+E8 -> 4113 | K8: =SUM(H8:I8) -> 0 | L8: =((G8/30)/8)*H8*1.25 -> 0 | M8: =((G8/30)/8)*I8*1.35 -> 0 | N8: =((G8/30))*J8*2 -> 0
B9: =+B8+1 -> 4 | C9: LOLI RODRIGUEZ JANIO RICHARD | D9: 4000 | E9: 113 | G9: =+D9+E9 -> 4113 | K9: =SUM(H9:I9) -> 0 | L9: =((G9/30)/8)*H9*1.25 -> 0 | M9: =((G9/30)/8)*I9*1.35 -> 0 | N9: =((G9/30))*J9*2 -> 0
B10: =+B9+1 -> 5 | C10: PEREZ CAJAHUANCA ARACELLI IRAIDA | D10: 3600 | G10: =+D10+E10 -> 3600 | J10: 1 | K10: =SUM(H10:I10) -> 0 | L10: =((G10/30)/8)*H10*1.25 -> 0 | M10: =((G10/30)/8)*I10*1.35 -> 0 | N10: =((G10/30))*J10*2 -> 240
B11: =+B10+1 -> 6 | C11: PORTOCARRERO TAFUR GLORI MAGRI | D11: 6500 | E11: 113 | G11: =+D11+E11 -> 6613 | K11: =SUM(H11:I11) -> 0 | L11: =((G11/30)/8)*H11*1.25 -> 0 | M11: =((G11/30)/8)*I11*1.35 -> 0 | N11: =((G11/30))*J11*2 -> 0
B12: =+B11+1 -> 7 | C12: ECHEVARRIA SOTO JORGE LUIS | D12: 4500 | E12: 113 | G12: =+D12+E12 -> 4613 | K12: =SUM(H12:I12) -> 0 | L12: =((G12/30)/8)*H12*1.25 -> 0 | M12: =((G12/30)/8)*I12*1.35 -> 0 | N12: =((G12/30))*J12*2 -> 0
B13: =+B12+1 -> 8 | C13: MONTOYA MEDRANO ANDREA BELEN JOSEPHINE | D13: 2800 | G13: =+D13+E13 -> 2800 | K13: =SUM(H13:I13) -> 0 | L13: =((G13/30)/8)*H13*1.25 -> 0 | M13: =((G13/30)/8)*I13*1.35 -> 0 | N13: =((G13/30))*J13*2 -> 0
B14: =+B13+1 -> 9 | C14: VERGARA BALDEON GEANNINA LIZBETH | D14: 2600 | G14: =+D14+E14 -> 2600 | K14: =SUM(H14:I14) -> 0 | L14: =((G14/30)/8)*H14*1.25 -> 0 | M14: =((G14/30)/8)*I14*1.35 -> 0 | N14: =((G14/30))*J14*2 -> 0
B15: =+B14+1 -> 10 | C15: CASTILLO ENCARNACION MANUEL LEONIDAS | D15: 2200 | E15: 113 | G15: =+D15+E15 -> 2313 | H15: 6.5 | I15: 1.5 | J15: 2 | K15: =SUM(H15:I15) -> 8 | L15: =((G15/30)/8)*H15*1.25 -> 78.304688 | M15: =((G15/30)/8)*I15*1.35 -> 19.515937 | N15: =((G15/30))*J15*2 -> 308.4
B16: =+B15+1 -> 11 | C16: QUEVEDO SALAS LUIS ALBERTO | D16: 3800 | E16: 113 | G16: =+D16+E16 -> 3913 | K16: =SUM(H16:I16) -> 0 | L16: =((G16/30)/8)*H16*1.25 -> 0 | M16: =((G16/30)/8)*I16*1.35 -> 0 | N16: =((G16/30))*J16*2 -> 0
B17: =+B16+1 -> 12 | C17: PORTOCARRERO GOMEZ MARIA DEICY | D17: 1500 | E17: 113 | G17: =+D17+E17 -> 1613 | K17: =SUM(H17:I17) -> 0 | L17: =((G17/30)/8)*H17*1.25 -> 0 | M17: =((G17/30)/8)*I17*1.35 -> 0 | N17: =((G17/30))*J17*2 -> 0
B18: =+B17+1 -> 13 | C18: LOBO QUISPE ELISA FIORELLA | D18: 3000 | G18: =+D18+E18 -> 3000 | K18: =SUM(H18:I18) -> 0 | L18: =((G18/30)/8)*H18*1.25 -> 0 | M18: =((G18/30)/8)*I18*1.35 -> 0 | N18: =((G18/30))*J18*2 -> 0
B19: =+B18+1 -> 14 | C19: RIOS HOLSEN JAIME JUNIOR | D19: 3200 | G19: =+D19+E19 -> 3200 | K19: =SUM(H19:I19) -> 0 | L19: =((G19/30)/8)*H19*1.25 -> 0 | M19: =((G19/30)/8)*I19*1.35 -> 0 | N19: =((G19/30))*J19*2 -> 0
B20: =+B19+1 -> 15 | C20: ESTRADA SANTOS JUAN MIGUEL | D20: 2800 | E20: 113 | G20: =+D20+E20 -> 2913 | K20: =SUM(H20:I20) -> 0 | L20: =((G20/30)/8)*H20*1.25 -> 0 | M20: =((G20/30)/8)*I20*1.35 -> 0 | N20: =((G20/30))*J20*2 -> 0
B21: =+B20+1 -> 16 | C21: SALCEDO RIVAS DANIEL ALONSO | D21: 2800 | E21: 113 | G21: =+D21+E21 -> 2913 | H21: 6.5 | I21: 2.5 | J21: 1 | K21: =SUM(H21:I21) -> 9 | L21: =((G21/30)/8)*H21*1.25 -> 98.617188 | M21: =((G21/30)/8)*I21*1.35 -> 40.964063 | N21: =((G21/30))*J21*2 -> 194.2
B22: =+B21+1 -> 17 | C22: PORTOCARRERO TAFUR MARIA LOIDI | D22: 1130 | G22: =+D22+E22 -> 1130 | K22: =SUM(H22:I22) -> 0 | L22: =((G22/30)/8)*H22*1.25 -> 0 | M22: =((G22/30)/8)*I22*1.35 -> 0 | N22: =((G22/30))*J22*2 -> 0
B23: =+B22+1 -> 18 | C23: ZEVALLOS DELGADO LUIS EDUARDO | D23: 2800 | G23: =+D23+E23 -> 2800 | K23: =SUM(H23:I23) -> 0 | L23: =((G23/30)/8)*H23*1.25 -> 0 | M23: =((G23/30)/8)*I23*1.35 -> 0 | N23: =((G23/30))*J23*2 -> 0
B24: =+B23+1 -> 19 | C24: BALLLESTEROS DI SERI MARIA PAULA | D24: 2800 | G24: =+D24+E24 -> 2800 | K24: =SUM(H24:I24) -> 0 | L24: =((G24/30)/8)*H24*1.25 -> 0 | M24: =((G24/30)/8)*I24*1.35 -> 0 | N24: =((G24/30))*J24*2 -> 0
B25: =+B24+1 -> 20 | C25: OCAMPO ORTEGA JEAN PAUL | D25: 2500 | G25: =+D25+E25 -> 2500 | K25: =SUM(H25:I25) -> 0 | L25: =((G25/30)/8)*H25*1.25 -> 0 | M25: =((G25/30)/8)*I25*1.35 -> 0 | N25: =((G25/30))*J25*2 -> 0
B26: =+B25+1 -> 21 | C26: OLIVOS SAAVEDRA LANDHERT ANDERSON | D26: 2500 | G26: =+D26+E26 -> 2500 | K26: =SUM(H26:I26) -> 0 | L26: =((G26/30)/8)*H26*1.25 -> 0 | M26: =((G26/30)/8)*I26*1.35 -> 0 | N26: =((G26/30))*J26*2 -> 0
B27: =+B26+1 -> 22 | C27: YUPANQUI SAMANIEGO RENATO LUIS | D27: 2500 | G27: =+D27+E27 -> 2500 | H27: 8 | I27: 4 | J27: 2 | K27: =SUM(H27:I27) -> 12 | L27: =((G27/30)/8)*H27*1.25 -> 104.16667 | M27: =((G27/30)/8)*I27*1.35 -> 56.25 | N27: =((G27/30))*J27*2 -> 333.33333
B28: =+B27+1 -> 23 | C28: TUCTO PEREZ CESAR ANTONIO | D28: 2500 | G28: =+D28+E28 -> 2500 | K28: =SUM(H28:I28) -> 0 | L28: =((G28/30)/8)*H28*1.25 -> 0 | M28: =((G28/30)/8)*I28*1.35 -> 0 | N28: =((G28/30))*J28*2 -> 0
B29: =+B28+1 -> 24 | C29: AREVALO VELA CESAR ANTONIO | D29: 2500 | G29: =+D29+E29 -> 2500 | K29: =SUM(H29:I29) -> 0 | L29: =((G29/30)/8)*H29*1.25 -> 0 | M29: =((G29/30)/8)*I29*1.35 -> 0 | N29: =((G29/30))*J29*2 -> 0
B30: =+B29+1 -> 25 | C30: SICCHA ARCE LUIS FRANCISCO | D30: 2500 | G30: =+D30+E30 -> 2500 | K30: =SUM(H30:I30) -> 0 | L30: =((G30/30)/8)*H30*1.25 -> 0 | M30: =((G30/30)/8)*I30*1.35 -> 0 | N30: =((G30/30))*J30*2 -> 0
B31: =+B30+1 -> 26 | C31: JIMENEZ PUYEN LUIS ANTONIO | D31: 2800 | G31: =+D31+E31 -> 2800 | K31: =SUM(H31:I31) -> 0 | L31: =((G31/30)/8)*H31*1.25 -> 0 | M31: =((G31/30)/8)*I31*1.35 -> 0 | N31: =((G31/30))*J31*2 -> 0
B32: =+B31+1 -> 27 | C32: SILVA SANTISTEBAN RONAL JHUNIOR | D32: 2000 | G32: =+D32+E32 -> 2000 | K32: =SUM(H32:I32) -> 0 | L32: =((G32/30)/8)*H32*1.25 -> 0 | M32: =((G32/30)/8)*I32*1.35 -> 0 | N32: =((G32/30))*J32*2 -> 0
B33: =+B32+1 -> 28 | C33: ELGUERA SOTO LUCERO ESTEFANIA | D33: 2200 | G33: =+D33+E33 -> 2200 | K33: =SUM(H33:I33) -> 0 | L33: =((G33/30)/8)*H33*1.25 -> 0 | M33: =((G33/30)/8)*I33*1.35 -> 0 | N33: =((G33/30))*J33*2 -> 0
B34: =+B33+1 -> 29 | C34: ESTACIO CAYETANO FRANK BRIAN | D34: 2300 | G34: =+D34+E34 -> 2300 | K34: =SUM(H34:I34) -> 0 | L34: =((G34/30)/8)*H34*1.25 -> 0 | M34: =((G34/30)/8)*I34*1.35 -> 0 | N34: =((G34/30))*J34*2 -> 0
B35: =+B34+1 -> 30 | C35: SALAZAR VELASQUEZ HECTOR ALEXANDER | D35: 2500 | E35: 113 | G35: =+D35+E35 -> 2613 | H35: 8 | I35: 3 | J35: 1 | K35: =SUM(H35:I35) -> 11 | L35: =((G35/30)/8)*H35*1.25 -> 108.875 | M35: =((G35/30)/8)*I35*1.35 -> 44.094375 | N35: =((G35/30))*J35*2 -> 174.2
B36: =+B35+1 -> 31 | C36: RICRA DAVALOS GIUSSEPPE RENATO | D36: 1800 | G36: =+D36+E36 -> 1800 | K36: =SUM(H36:I36) -> 0 | L36: =((G36/30)/8)*H36*1.25 -> 0 | M36: =((G36/30)/8)*I36*1.35 -> 0 | N36: =((G36/30))*J36*2 -> 0
B37: =+B36+1 -> 32 | C37: DIAZ ESCALANTE LUIS MIGUEL DAVID | D37: 1700 | E37: 113 | G37: =+D37+E37 -> 1813 | H37: 5 | I37: 2.5 | J37: 2 | K37: =SUM(H37:I37) -> 7.5 | L37: =((G37/30)/8)*H37*1.25 -> 47.213542 | M37: =((G37/30)/8)*I37*1.35 -> 25.495312 | N37: =((G37/30))*J37*2 -> 241.73333
B38: =+B37+1 -> 33 | C38: HIPOLITO GUANILO ARNOLD JIMMY | D38: 1500 | E38: 113 | G38: =+D38+E38 -> 1613 | K38: =SUM(H38:I38) -> 0 | L38: =((G38/30)/8)*H38*1.25 -> 0 | M38: =((G38/30)/8)*I38*1.35 -> 0 | N38: =((G38/30))*J38*2 -> 0
B39: =+B38+1 -> 34 | C39: MONTOYA MEDRANO VIVIAN MICHELE ALEXANDRA | D39: 2000 | G39: =+D39+E39 -> 2000 | K39: =SUM(H39:I39) -> 0 | L39: =((G39/30)/8)*H39*1.25 -> 0 | M39: =((G39/30)/8)*I39*1.35 -> 0 | N39: =((G39/30))*J39*2 -> 0
B40: =+B39+1 -> 35 | C40: BANCHO CANELOS EDSON OMAR AMANCIO | D40: 1500 | G40: =+D40+E40 -> 1500 | H40: 6.5 | I40: 2.5 | J40: 2 | K40: =SUM(H40:I40) -> 9 | L40: =((G40/30)/8)*H40*1.25 -> 50.78125 | M40: =((G40/30)/8)*I40*1.35 -> 21.09375 | N40: =((G40/30))*J40*2 -> 200
B41: =+B40+1 -> 36 | C41: ALARCON OLIVERA AMBAR TIFFANY | D41: 2850 | G41: =+D41+E41 -> 2850 | K41: =SUM(H41:I41) -> 0 | L41: =((G41/30)/8)*H41*1.25 -> 0 | M41: =((G41/30)/8)*I41*1.35 -> 0 | N41: =((G41/30))*J41*2 -> 0
B42: =+B41+1 -> 37 | C42: BURGA MUÑOZ HELDER ALEXANDER | D42: 1700 | G42: =+D42+E42 -> 1700 | K42: =SUM(H42:I42) -> 0 | L42: =((G42/30)/8)*H42*1.25 -> 0 | M42: =((G42/30)/8)*I42*1.35 -> 0 | N42: =((G42/30))*J42*2 -> 0
B43: =+B42+1 -> 38 | C43: JUÑO FUENTEZ STEFANIA BRISEIDA | D43: 2000 | E43: 113 | G43: =+D43+E43 -> 2113 | K43: =SUM(H43:I43) -> 0 | L43: =((G43/30)/8)*H43*1.25 -> 0 | M43: =((G43/30)/8)*I43*1.35 -> 0 | N43: =((G43/30))*J43*2 -> 0
B44: =+B43+1 -> 39 | C44: RIVERA CORRALES JUAN EDUARDO | D44: 2800 | G44: =+D44+E44 -> 2800 | K44: =SUM(H44:I44) -> 0 | L44: =((G44/30)/8)*H44*1.25 -> 0 | M44: =((G44/30)/8)*I44*1.35 -> 0 | N44: =((G44/30))*J44*2 -> 0
B45: =+B44+1 -> 40 | C45: MELO HUAMAN CARLOS MANUEL | D45: 1400 | G45: =+D45+E45 -> 1400 | K45: =SUM(H45:I45) -> 0 | L45: =((G45/30)/8)*H45*1.25 -> 0 | M45: =((G45/30)/8)*I45*1.35 -> 0 | N45: =((G45/30))*J45*2 -> 0
B46: =+B45+1 -> 41 | C46: FARFAN LAUREL CIELO CARMIN | D46: 2000 | G46: =+D46+E46 -> 2000 | K46: =SUM(H46:I46) -> 0 | L46: =((G46/30)/8)*H46*1.25 -> 0 | M46: =((G46/30)/8)*I46*1.35 -> 0 | N46: =((G46/30))*J46*2 -> 0
B47: =+B46+1 -> 42 | C47: ORTIZ PAREDES CESAR PAUL | D47: 1200 | E47: 130 | G47: =+D47+E47 -> 1330 | H47: 6.5 | I47: 2.5 | J47: 2 | K47: =SUM(H47:I47) -> 9 | L47: =((G47/30)/8)*H47*1.25 -> 45.026042 | M47: =((G47/30)/8)*I47*1.35 -> 18.703125 | N47: =((G47/30))*J47*2 -> 177.33333

Sheet COMISIONES
A1: No | D1: año 2026 | P1: TOTAL | Q1: PROMEDIO COMISIONES
B2: APELLIDOS Y NOMBRES | D2: ENERO | E2: FEBRERO | F2: MARZO | G2: ABRIL | H2: MAYO | I2: JUNIO | J2: JULIO | K2: AGOSTO | L2: SETIEMBRE | M2: OCTUBRE | N2: NOVIEMBRE | O2: DICIEMBRE
A3: 1 | B3: ECHEVARRIA SOTO JORGE LUIS | D3: 9122.3397 | E3: 6019.6636 | F3: 8538.4969 | G3: 12937.093 | H3: 8462.9701 | I3: 8965.188 | J3: 12745.128 | P3: =SUM(D3:O3) -> 66790.879 | Q3: =+P3/6 -> 11131.813
A4: =+A3+1 -> 2 | B4: QUEVEDO SALAS LUIS ALBERTO | D4: 2501.7108 | E4: 2599.7564 | F4: 3287.0806 | G4: 2509.8714 | H4: 3359.019 | I4: 4331.4263 | J4: 1771.0376 | P4: =SUM(D4:O4) -> 20359.902 | Q4: =+P4/6 -> 3393.317
A5: =+A4+1 -> 3 | B5: ESTRADA SANTOS JUAN MIGUEL | D5: 1375.3927 | E5: 2137.4428 | F5: 1953.9544 | G5: 1486.9737 | H5: 1343.5632 | I5: 1994.6996 | J5: 2048.7845 | P5: =SUM(D5:O5) -> 12340.811 | Q5: =+P5/6 -> 2056.8018
A6: =+A5+1 -> 4 | B6: ERNESTO ORIHUELA AGUIRRE | D6: 5568.2823 | E6: 4483.2372 | F6: 6098.9263 | G6: 9240.781 | H6: 6044.9787 | I6: 6403.7057 | J6: 7965.7048 | P6: =SUM(D6:O6) -> 45805.616 | Q6: =+P6/6 -> 7634.2693
A7: =+A6+1 -> 5 | B7: SICCHA ARCE LUIS FRANCISCO | D7: 404.14905 | E7: 749.2803 | F7: 531.69465 | G7: 3286.2737 | H7: 700.75905 | I7: 1556.8993 | J7: 600.18255 | P7: =SUM(D7:O7) -> 7829.2386 | Q7: =+P7/6 -> 1304.8731
A8: =+A7+1 -> 6 | B8: AREVALO VELA CESAR ANTONIO | D8: 2429.1964 | E8: 842.6241 | F8: 846.33225 | G8: 2406.4389 | H8: 1799.1559 | I8: 662.7648 | J8: 1891.5045 | P8: =SUM(D8:O8) -> 10878.017 | Q8: =+P8/6 -> 1813.0028
A9: =+A8+1 -> 7 | B9: ESTACIO CAYETANO FRANK BRIAN | D9: 872.05845 | E9: 1100.9444 | F9: 3369.7662 | G9: 937.3611 | H9: 1449.1908 | I9: 1482.3352 | J9: 3142.0137 | P9: =SUM(D9:O9) -> 12353.67 | Q9: =+P9/6 -> 2058.945 | R9: =SUM(D9:I9) -> 9211.6562 | S9: =+R9/6 -> 1535.276 | T9: =+S9/30*7 -> 358.23108
A10: 8 | B10: RICRA DAVALOS GIUSSEPPE RENATO | I10: 887.808 | J10: 1180.9678 | P10: =SUM(D10:O10) -> 2068.7758 | Q10: =+P10/6 -> 344.79597
A11: 9 | B11: PAREDES CHAMOCHUMBI ANA GABRIEL | J11: 72.72075 | P11: =SUM(D11:O11) -> 72.72075 | Q11: =+P11/6 -> 12.120125
C12: =SUM(C3:C10) -> 0 | D12: =SUM(D3:D10) -> 22273.129 | E12: =SUM(E3:E10) -> 17932.949 | F12: =SUM(F3:F10) -> 24626.251 | G12: =SUM(G3:G10) -> 32804.793 | H12: =SUM(H3:H10) -> 23159.637 | I12: =SUM(I3:I10) -> 26284.827 | J12: =SUM(J3:J11) -> 31418.044 | K12: =SUM(K3:K10) -> 0 | L12: =SUM(L3:L10) -> 0 | M12: =SUM(M3:M10) -> 0 | N12: =SUM(N3:N10) -> 0 | O12: =SUM(O3:O10) -> 0 | P12: =SUM(P3:P10) -> 178426.91 | Q12: =SUM(Q3:Q10) -> 29737.818
A22: No | C22: 2024 | D22: año 2025 | P22: TOTAL | Q22: PROMEDIO COMISIONES | V22: -
B23: APELLIDOS Y NOMBRES | C23: DICIEMBRE | D23: ENERO | E23: FEBRERO | F23: MARZO | G23: ABRIL | H23: MAYO | I23: JUNIO | J23: JULIO | K23: AGOSTO | L23: SETIEMBRE | M23: OCTUBRE | N23: NOVIEMBRE | O23: DICIEMBRE
A24: 1 | B24: ECHEVARRIA SOTO JORGE LUIS | C24: 3749.9306 | D24: 5009.5509 | E24: 7448.2999 | F24: 9200.1916 | G24: 9329.5001 | H24: 8939.95 | I24: 12112.493 | J24: 7881.04 | K24: 7297.3057 | L24: 7289.3865 | M24: 10135.684 | N24: 5083.407 | O24: 4295.24 | P24: =SUM(D24:O24) -> 94022.049 | Q24: =+P24/6 -> 15670.341
A25: =+A24+1 -> 2 | B25: QUEVEDO SALAS LUIS ALBERTO | C25: 2506.3845 | D25: 7095.9636 | E25: 2310.1339 | F25: 1816.4344 | G25: 5069.9014 | H25: 1552.32 | I25: 2245.63 | J25: 4212.23 | K25: 2680.1595 | L25: 4362.1779 | M25: 4957.9692 | N25: 1243.59 | O25: 1724.21 | P25: =SUM(D25:O25) -> 39270.72 | Q25: =+P25/6 -> 6545.12
A26: =+A25+1 -> 3 | B26: VIDAL MELO ALEX FERNANDO | C26: 260.4894 | D26: 432.22245 | E26: 217.75095 | F26: 534.52605 | G26: 1015.8413 | H26: 0 | I26: 0 | P26: =SUM(D26:O26) -> 2200.3407 | Q26: =+P26/6 -> 366.72345
A27: =+A26+1 -> 4 | B27: ESTRADA SANTOS JUAN MIGUEL | C27: 872.8485 | D27: 1473.3036 | E27: 2995.61 | F27: 2739.9275 | G27: 1961.3279 | H27: 1835.52 | I27: 2977.69 | J27: 2142.75 | K27: 2792.4066 | L27: 1457.0637 | M27: 1122.8265 | N27: 2531.97 | O27: 829.3 | P27: =SUM(D27:O27) -> 24859.696 | Q27: =+P27/6 -> 4143.2826
A28: =+A27+1 -> 5 | B28: ERNESTO ORIHUELA AGUIRRE | C28: 3217.1824 | D28: 5674.875 | E28: 4496.0072 | F28: 5380.4996 | G28: 6572.6463 | H28: 5345.58 | I28: 6844.2282 | J28: 5943.65 | K28: 5512.5559 | L28: 6117.8439 | M28: 7150.9868 | N28: 4317.9892 | O28: 3580.75 | P28: =SUM(D28:O28) -> 66937.612 | Q28: =+P28/6 -> 11156.269
A29: =+A28+1 -> 6 | B29: SICCHA ARCE LUIS FRANCISCO | E29: 516.2268 | F29: 1351.7901 | G29: 1744.5441 | H29: 2470.72 | I29: 916.03 | J29: 1335.61 | K29: 1408.1795 | L29: 3396.5073 | M29: 1826.0354 | N29: 633.57 | O29: 1496.32 | P29: =SUM(D29:O29) -> 17095.533 | Q29: =+P29/6 -> 2849.2555
A30: 7 | B30: AREVALO VELA CESAR ANTONIO | F30: 498.6291 | G30: 596.82435 | H30: 1085.98 | I30: 917.48 | J30: 1345.58 | K30: 1584.3099 | L30: 1237.6771 | M30: 2344.5985 | N30: 2158.28 | O30: 1263.82 | P30: =SUM(D30:O30) -> 13033.179 | Q30: =+P30/6 -> 2172.1965
A31: 8 | B31: ESTACIO CAYETANO FRANK BRIAN | H31: 152.23 | I31: 1363.37 | J31: 913.74 | K31: 775.30635 | L31: 610.71905 | M31: 1065.8465 | N31: 1303.15 | O31: 1133.38 | P31: =SUM(D31:O31) -> 7317.7418 | Q31: =+P31/6 -> 1219.6236
P32: =SUM(D32:O32) -> 0 | Q32: =+P32/6 -> 0
C33: =SUM(C24:C32) -> 10606.835 | D33: =SUM(D24:D32) -> 19685.916 | E33: =SUM(E24:E32) -> 17984.029 | F33: =SUM(F24:F32) -> 21521.998 | G33: =SUM(G24:G32) -> 26290.585 | H33: =SUM(H24:H32) -> 21382.3 | I33: =SUM(I24:I32) -> 27376.921 | J33: =SUM(J24:J32) -> 23774.6 | ... Q33: =SUM(Q24:Q32) -> 44122.812
E34: 17984.029 | F34: 21521.998 | H34: =+'[1]PLANILLA MENSUAL'!S74 -> 0 | I34: =+'[1]PLANILLA MENSUAL'!S74 -> 0 | J34: =+[2]Resumen!$D$13 -> 23774.612 | K34: =+[3]COMISIONES!$K$13 -> 22050.223 | L34: =+[4]Resumen!$D$13 -> 24471.375 | M34: =+[5]Resumen!$D$13 -> 28603.947 | N34: =+[6]Resumen!$D$13 -> 17271.957 | O34: =+[7]Resumen!$D$13 -> 14323

Sheet RTA 5TA VTAS
B2: CALCULO QUINTA CATEGORIA DEL IMPUESTO A LA RENTA - 2026
B4: MESES | D4: ERNESTO | E4: JORGE | F4: LUIS | G4: JUAN | H4: LUIS | I4: CESAR | J4: FRANK | K4: GUSTAVO | L4: MILAGROS | M4: GIUSSEPPE | N4: TOTALES
D5: ORIHUELA | E5: ECHEVARRIA | F5: QUEVEDO | G5: ESTRADA | H5: SICCHA | I5: AREVALO | J5: ESTACIO | K5: FLORES | L5: FLORES | M5: RICRA
B6: ENERO
B7: SUELDO + ASIG FAM | D7: 12113 | E7: 4613 | F7: 3613 | G7: 2913 | H7: 2500 | I7: 1800 | J7: 2000 | K7: 4000 | L7: 3500 | M7: 1500 | N7: =SUM(D7:M7) -> 38552
B8: COMISIONES | D8: 5568.2823 | E8: 9122.3397 | F8: 2501.7108 | G8: 1375.3927 | H8: 404.14905 | I8: 2429.1964 | J8: 872.05845 | N8: =SUM(D8:K8) -> 22273.129
B9: VACACIONES PROMEDIO | E9: 1399.4021 | F9: 639.34455 | N9: =SUM(D9:K9) -> 2038.7467
B11: FEBRERO
B12: SUELDO + ASIG FAM | D12: 12113 | E12: 4613 | F12: 3613 | G12: 2913 | H12: 2500 | I12: 1800 | J12: 2000 | K12: 4113 | M12: 1500 | N12: =SUM(D12:K12) -> 33665
B13: COMISIONES | D13: =+COMISIONES!E6 -> 4483.2372 | E13: =+COMISIONES!E3 -> 6019.6636 | F13: =+COMISIONES!E4 -> 2599.7564 | G13: =+COMISIONES!E5 -> 2137.4428 | H13: =+COMISIONES!E7 -> 749.2803 | I13: =+COMISIONES!E8 -> 842.6241 | J13: =+COMISIONES!E9 -> 1100.9444 | N13: =SUM(D13:K13) -> 17932.949
N14: =SUM(D14:I14) -> 0
B15: MARZO
B16: SUELDO + ASIG FAM | D16: 12113 | E16: 4613 | F16: 3613 | G16: 2913 | H16: 2500 | I16: 1800 | J16: 2000 | K16: 4113 | M16: 1500 | N16: =SUM(D16:K16) -> 33665
B17: COMISIONES | D17: 6098.9263 | E17: 8538.4969 | F17: 3287.0806 | G17: 1953.9544 | H17: 531.69465 | I17: 846.33225 | J17: 3369.7662 | N17: =SUM(D17:K17) -> 24626.251
B18: VACACIONES PROMEDIO | N18: =SUM(D18:K18) -> 0
B19: UTILIDADES | D19: 22726.82 | E19: 17322.29 | F19: 10739.88 | G19: 8723.49 | H19: 7286.82 | I19: 6752.33 | J19: 4444.65 | K19: 598.09 | N19: =SUM(D19:K19) -> 78594.37 | O19: NO SE CONSIDERA EN LA PROYECCION DE RENTA
B21: ABRIL | N21: =SUM(D21:I21) -> 0
B22: SUELDO + ASIG FAM | D22: 12113 | E22: 4613 | F22: 3613 | G22: 2913 | H22: 2500 | I22: 2200 | J22: 2000 | K22: 4113 | M22: 1500 | N22: =SUM(D22:K22) -> 34065
B23: COMISIONES | D23: 9240.781 | E23: 12937.093 | F23: 2509.8714 | G23: 1486.9737 | H23: 2406.4389 | I23: 3286.2737 | J23: 937.3611 | N23: =SUM(D23:K23) -> 32804.793
B24: VACACIONES PROMEDIO | N24: =SUM(D24:K24) -> 0
B25: COMISION TRIMESTRAL | N25: =SUM(D25:K25) -> 0
B26: MAYO | N26: =SUM(D26:K26) -> 0
B27: SUELDO + ASIG FAM | N27: =SUM(D27:K27) -> 0
B28: COMISIONES | N28: =SUM(D28:K28) -> 0
B29: VACACIONES PROMEDIO | N29: =SUM(D29:K29) -> 0
N30: =SUM(D30:K30) -> 0
B31: JUNIO | N31: =SUM(D31:K31) -> 0
B32: SUELDO + ASIG FAM | N32: =SUM(D32:K32) -> 0
B33: COMISIONES | N33: =SUM(D33:K33) -> 0
N34: =SUM(D34:K34) -> 0
B35: JULIO | N35: =SUM(D35:K35) -> 0
B36: SUELDO + ASIG FAM | N36: =SUM(D36:K36) -> 0
B37: COMISIONES | N37: =SUM(D37:K37) -> 0
B38: GRATIFICACION JULIO | N38: =SUM(D38:K38) -> 0
B39: VACACIONES PROMEDIO | N39: =SUM(D39:K39) -> 0
N40: =SUM(D40:K40) -> 0
B41: AGOSTO | N41: =SUM(D41:K41) -> 0
B42: SUELDO + ASIG FAM | N42: =SUM(D42:K42) -> 0
B43: COMISIONES | N43: =SUM(D43:K43) -> 0
N44: =SUM(D44:K44) -> 0
B45: SEPTIEMBRE | N45: =SUM(D45:K45) -> 0
B46: SUELDO + ASIG FAM | N46: =SUM(D46:K46) -> 0
B47: COMISIONES | N47: =SUM(D47:K47) -> 0
B48: PROMEDIO DE VACACIONES | N48: =SUM(D48:K48) -> 0
N49: =SUM(D49:K49) -> 0
B50: OCTUBRE | N50: =SUM(D50:K50) -> 0
B51: SUELDO + ASIG FAM | N51: =SUM(D51:K51) -> 0
B52: COMISIONES | N52: =SUM(D52:K52) -> 0
B53: PROMEDIO DE VACACIONES | N53: =SUM(D53:K53) -> 0
B54: GRATIFICACION | N54: =SUM(D54:K54) -> 0
B55: BONO EXTRAORDINARIO | N55: =SUM(D55:K55) -> 0
N56: =SUM(D56:K56) -> 0
B57: NOVIEMBRE | N57: =SUM(D57:K57) -> 0
B58: SUELDO + ASIG FAM | N58: =SUM(D58:K58) -> 0
B59: COMISIONES | N59: =SUM(D59:K59) -> 0
N60: =SUM(D60:K60) -> 0
B61: DICIEMBRE | N61: =SUM(D61:K61) -> 0
B62: SUELDO + ASIG FAM | N62: =SUM(D62:K62) -> 0
B63: COMISIONES | N63: =SUM(D63:K63) -> 0
B64: PROMEDIO VACACIONES | N64: =SUM(D64:K64) -> 0
B65: GRATIFICACION DICIEMBRE | N65: =SUM(D65:K65) -> 0
B66: VALES PAVO OBSEQUIO | N66: =SUM(D66:K66) -> 0
N67: =SUM(D67:K67) -> 0
N68: =SUM(D68:K68) -> 0
N69: =SUM(D69:K69) -> 0
B70: MAYO | N70: =SUM(D70:K70) -> 0
B71: SUELDO + ASIG FAM | D71: 13113 | E71: 4613 | F71: =3800+113 -> 3913 | G71: 2913 | H71: 2500 | I71: 2500 | J71: =2300+113 -> 2413 | M71: 1800 | N71: =SUM(D71:K71) -> 31965
B72: COMISIONES | D72: 6044.9787 | E72: 8462.9701 | F72: 3359.019 | G72: 1343.5632 | H72: 700.75905 | I72: 1799.1559 | J72: 1449.1908 | M72: 887.808 | N72: =SUM(D72:K72) -> 23159.637
B73: VACACIONES PROMEDIO | N73: =SUM(D73:K73) -> 0
B74: COMISION TRIMESTRAL | N74: =SUM(D74:K74) -> 0
B76: JUNIO
B77: SUELDO + ASIG FAM | D77: 13113 | E77: 4613 | F77: =3800+113 -> 3913 | G77: 2913 | H77: 2500 | I77: 2500 | J77: =2300+113 -> 2413 | M77: 1800
B78: COMISIONES | D78: =+[8]Resumen!$D$15 -> 6403.7057 | E78: =+[8]Resumen!$D$23 -> 8965.188 | F78: =+[8]Resumen!$F$4 -> 4331.4263 | G78: =+[8]Resumen!$F$6 -> 1994.6996 | H78: =+[8]Resumen!$F$5 -> 1556.8993 | I78: =+[8]Resumen!$F$8 -> 662.7648 | J78: =+[8]Resumen!$F$7 -> 1482.3352 | M78: =+[8]Resumen!$F$11 -> 887.808
B79: VACACIONES PROMEDIO
B80: COMISION TRIMESTRAL
B82: JULIO
B83: SUELDO + ASIG FAM | D83: 13113 | E83: 4613 | F83: =3800+113 -> 3913 | G83: 2913 | H83: 2500 | I83: 2500 | J83: =2300+113 -> 2413 | M83: 1800
B84: COMISIONES | D84: 7965.7048 | E84: 12745.128 | F84: 1771.0376 | G84: 2048.7845 | H84: 600.18255 | I84: 1891.5045 | J84: 3142.0137 | M84: 1180.9678
B85: VACACIONES PROMEDIO | E85: ='PLANILLA MENSUAL'!V18 -> 300.25418 | F85: ='PLANILLA MENSUAL'!V22 -> 1445.8006 | G85: ='PLANILLA MENSUAL'!V26 -> 57.177925 | J85: ='PLANILLA MENSUAL'!V40 -> 358.23108
B86: GRATIFICACION | D86: ='PLANILLA MENSUAL'!BB12 -> 21167.421 | E86: ='PLANILLA MENSUAL'!BB18 -> 14846.482 | F86: ='PLANILLA MENSUAL'!BB22 -> 7642.147 | G86: ='PLANILLA MENSUAL'!BB26 -> 5044.8881 | H86: ='PLANILLA MENSUAL'!BB36 -> 4038.2785 | I86: ='PLANILLA MENSUAL'!BB35 -> 4357.5497 | J86: 4180.4509 | M86: ='PLANILLA MENSUAL'!BB42 -> 1962
B87: COMISION TRIMESTRAL
N90: =SUM(D90:K90) -> 0
N91: =SUM(D91:K91) -> 0
B92: TOTAL PERCIBIDO | D92: =SUM(D6:D91)-D19 -> 154764.04 | E92: =SUM(E6:E91)-E19 -> 115628.02 | F92: =SUM(F6:F91)-F19 -> 56278.194 | G92: =SUM(G6:G91)-G19 -> 37833.877 | H92: =SUM(H6:H91)-H19 -> 28487.682 | I92: =SUM(I6:I91)-I19 -> 31215.401 | J92: =SUM(J6:J91)-J19 -> 32131.352 | K92: =SUM(K6:K91)-K19 -> 16339 | ... M92: =SUM(M6:M91)-M19 -> 16318.584 | N92: =SUM(D92:K92) -> 472677.56
B93: TOTAL REMUNERACIONES | D93: =+D144 -> 295981.21 | E93: =+E144 -> 219643.72 | F93: =+F144 -> 106382 | G93: =+G144 -> 71218.435 | H93: =+H144 -> 52966.713 | I93: =+I144 -> 59228.996 | J93: =+J144 -> 62792.151 | K93: =+K144 -> 0 | ... M93: =+M144 -> 0 | N93: =SUM(N6:N92) -> 846019.44 | O93: =SUM(N6:N91) -> 373341.88
B94: DEDUCCION 7UITS | D94: =5500*7 -> 38500 | E94: =5500*7 -> 38500 | F94: =5500*7 -> 38500 | G94: =5500*7 -> 38500 | H94: =5500*7 -> 38500 | I94: =5500*7 -> 38500 | J94: =5500*7 -> 38500 | K94: =5500*7 -> 38500 | ... M94: =5500*7 -> 38500 | N94: =SUM(D94:I94) -> 231000
B95: BASE IMPONIBLE | D95: =+D93-D94 -> 257481.21 | E95: =+E93-E94 -> 181143.72 | F95: =+F93-F94 -> 67882.002 | G95: =+G93-G94 -> 32718.435 | H95: =+H93-H94 -> 14466.713 | I95: =+I93-I94 -> 20728.996 | J95: =+J93-J94 -> 24292.151 | K95: =+K93-K94 -> -38500 | L95: =+L93-L94 -> -38500 | N95: =SUM(D95:I95) -> 574421.08
B98: CALCULO IR 5TA CATEG.
B99: Hasta 5 UIT S/ 27,500 (5500 UIT) | C99: 0.08 | D99: =+(5500*5)*$C$99 -> 2200 | E99: =+(5500*5)*$C$99 -> 2200 | F99: =+(5500*5)*$C$99 -> 2200 | G99: =+(5500*5)*$C$99 -> 2200 | H99: =+(H95)*$C$99 -> 1157.3371 | I99: =+(I95)*$C$99 -> 1658.3197 | J99: =+(J95)*$C$99 -> 1943.3721 | K99: =+(K95)*$C$99 -> -3080 | L99: =+(L95)*$C$99 -> -3080 | N99: =SUM(D99:J99) -> 13559.029 | W99: =5350*5 -> 26750 | X99: =+W99*8/100 -> 2140
B100: Por el exceso de 5 UIT S/ 27,500 y hasta 20 UIT 110,000 | C100: 0.14 | D100: =+(110000-27500)*$C$100 -> 11550 | E100: =+(+E95-27500)*$C$100 -> 21510.121 | F100: =+(+F95-27500)*$C$100 -> 5653.4803 | G100: =+(+G95-27500)*$C$100 -> 730.58092 | N100: =SUM(D100:K100) -> 39444.182 | W100: =107000-W99 -> 80250 | X100: =+W100*14/100 -> 11235
B101: Por el exceso de 20 UIT S/ 110,000 y hasta 35 UIT 192,500 | C101: 0.17 | D101: =+(D95-110000)*$C$101 -> 25071.806 | E101: =+(+E95-110000)*$C$101 -> 12094.432 | N101: =SUM(D101:K101) -> 37166.238 | W101: =187250-107000 -> 80250 | X101: =+W101*17/100 -> 13642.5
B102: Por el exceso de 35 UIT S/ 192,500 y hasta 45 UIT 247,500 | C102: 0.2 | D102: =+(D95-192500)*$C$102 -> 12996.243 | W102: =205292.52-187250 -> 18042.52 | X102: =+W102*0.2 -> 3608.504
D103: =SUM(D99:D102) -> 51818.049 | E103: =SUM(E99:E101) -> 35804.553 | F103: =SUM(F99:F101) -> 7853.4803 | G103: =SUM(G99:G101) -> 2930.5809 | H103: =SUM(H99:H101) -> 1157.3371 | I103: =SUM(I99:I101) -> 1658.3197 | J103: =SUM(J99:J101) -> 1943.3721 | K103: =SUM(K99:K101) -> -3080 | L103: =SUM(L99:L101) -> -3080 | N103: =SUM(N99:N101) -> 90169.449 | W103: =SUM(W99:W102) -> 205292.52 | X103: =SUM(X99:X102) -> 30626.004
B104: RETENCIONES
B105: ENERO | D105: 1475.3831 | E105: 323.13515 | F105: 105.82264 | G105: 27.878218 | H105: 0 | I105: 0 | J105: 0 | K105: 138.8156 | L105: 74.2 | N105: =SUM(D105:K105) -> 2071.0347
B106: FEBRERO | D106: 1630.7248 | E106: 461.33904 | F106: 124.72995 | G106: 43.423257 | H106: 0 | I106: 0 | J106: 0 | K106: 138.8156 | N106: =SUM(D106:K106) -> 2399.0327
B107: MARZO | D107: 2745.4286 | E107: 1691.6359 | F107: 547.37392 | G107: 220.9846 | H107: 39.560262 | I107: 56.124164 | J107: 88.709162 | K107: 138.8156 | N107: =SUM(D107:K107) -> 5528.6322
B108: UTILIDADES | N108: =SUM(D108:K108) -> 0
B109: ABRIL | D109: 3701.5991 | E109: 2692.265 | F109: 545.53783 | G109: 236.2638 | H109: 105.62118 | I109: 119.58777 | J109: 106.7732 | K109: 138.8156 | N109: =SUM(D109:K109) -> 7646.4635
B110: MAYO | D110: 4539.3088 | E110: 3164.0836 | F110: 639.01232 | G110: 182.60213 | H110: 115.7477 | I110: 198.86472 | J110: 152.65707 | K110: 0 | L110: 0 | N110: =SUM(D110:K110) -> 8992.2763
...

Sheet RTA 5TA
B2: CALCULO QUINTA CATEGORIA DEL IMPUESTO A LA RENTA - 2025
D3: 1 | E3: =+D3+1 -> 2 | F3: =+E3+1 -> 3 | G3: =+F3+1 -> 4 | H3: =+G3+1 -> 5
D4: GIOVANNA | E4: RIHARD | F4: ARACELLI | G4: GLORI | H4: ELVIS | I4: GEANNINA | J4: FIORELLA | K4: ALBERTO | L4: CRISTHIAN | M4: JAIME | N4: LUIS | O4: BELEN | P4: LUIS | Q4: DANIEL | R4: MARIA PAULA | S4: TOTALES
B5: MES | D5: MARTINEZ | E5: LOLI | F5: ARAIDA | G5: PORTOCARRERO | H5: SALVADOR | I5: VERGARA | J5: LOBO | K5: AREVALO | L5: SEGURA | M5: RIOS | N5: JIMENEZ | O5: MONTOYA | P5: ZEVALLOS | Q5: SALCEDO | R5: BALLESTEROS
B6: ENERO | S6: =SUM(D6:P6) -> 0
B7: SUELDO + ASIG FAM | D7: =6000+113 -> 6113 | E7: =4000+113 -> 4113 | F7: 3360 | G7: =6000+113 -> 6113 | H7: =4000+113 -> 4113 | I7: 2500 | J7: 3000 | K7: 2800 | L7: 2800 | M7: 2800 | N7: 2800 | O7: 2100 | P7: 2500 | Q7: 2613 | R7: 2500 | S7: =SUM(D7:P7) -> 45112
B8: BONO | F8: 640 | O8: 800 | S8: =SUM(D8:P8) -> 1440
B9: MOVILIDAD | D9: 95.238095 | E9: 76.190476 | F9: 53.333333 | H9: 66.666667 | J9: 90.47619 | K9: 95.238095 | S9: =SUM(D9:P9) -> 477.14286
B10: HORAS EXTRAS | E10: 290.48063 | H10: 1311.0188 | L10: =+'[1]PLANILLA MENSUAL'!U25 -> 397.83333 | M10: =+'[1]PLANILLA MENSUAL'!U27 -> 197.75 | P10: 786.97917
S11: =SUM(D11:P11) -> 0
B12: FEBRERO | S12: =SUM(D12:P12) -> 0
B13: SUELDO + ASIG FAM | D13: =6000+113 -> 6113 | E13: =4000+113 -> 4113 | F13: 3360 | G13: =6000+113 -> 6113 | H13: =4000+113 -> 4113 | I13: 2500 | J13: 3000 | K13: 2800 | L13: 2800 | M13: 2800 | N13: 2800 | O13: 2100 | P13: 2500 | Q13: 2613 | R13: 2500 | S13: =SUM(D13:P13) -> 45112
B14: BONO | F14: 640 | O14: 800 | S14: =SUM(D14:P14) -> 1440
B15: MOVILIDAD | D15: 100 | E15: 100 | F15: 100 | H15: 65 | J15: 60 | K15: 100 | S15: =SUM(D15:P15) -> 525
S16: =SUM(D16:P16) -> 0
B17: MARZO | S17: =SUM(D17:P17) -> 0
B18: SUELDO + ASIG FAM | D18: =6000+113 -> 6113 | E18: =4000+113 -> 4113 | F18: 3360 | G18: =6000+113 -> 6113 | H18: =4000+113 -> 4113 | I18: 2500 | J18: 3000 | K18: 2800 | L18: 2800 | M18: 2800 | N18: 2800 | O18: 2100 | P18: 2500 | Q18: 2613 | R18: 2500 | S18: =SUM(D18:P18) -> 45112
B19: BONO | F19: 640 | O19: 800 | S19: =SUM(D19:P19) -> 1440
B20: MOVILIDAD | D20: 100 | E20: 100 | F20: 90 | H20: 75 | J20: 100 | K20: 100 | S20: =SUM(D20:P20) -> 565
B21: HORAS EXTRAS | D21: 407.53 | J21: 331.14 | K21: 309.41 | S21: =SUM(D21:P21) -> 1048.08
B22: UTILIDADES | D22: 10984.79 | E22: 8491.98 | F22: 7025.49 | G22: 10355.57 | H22: 7080.15 | I22: 5958.32 | J22: 7005.9 | K22: 6931.75 | L22: 6122 | M22: 6432.12 | N22: 5954.52 | O22: 5918.4 | P22: 6391.45 | S22: =SUM(D22:P22) -> 94652.44 | T22: NO SE CONSIDERA EN LA PROYECCION
S23: =SUM(D23:P23) -> 0
B24: ABRIL | S24: =SUM(D24:P24) -> 0
B25: SUELDO + ASIG FAM | D25: =6000+113 -> 6113 | E25: =4000+113 -> 4113 | F25: 3360 | G25: =6000+113 -> 6113 | H25: =4000+113 -> 4113 | I25: 2500 | J25: 3000 | K25: 2800 | L25: 2800 | M25: 2800 | N25: 2800 | O25: 2100 | P25: 2500 | Q25: 2613 | R25: 2500 | S25: =SUM(D25:P25) -> 45112
B26: BONO | F26: 640 | O26: 800 | S26: =SUM(D26:P26) -> 1440
B27: MOVILIDAD | D27: 55 | E27: 45 | F27: 90 | H27: 90 | J27: 90 | K27: 90 | S27: =SUM(D27:P27) -> 460
S28: =SUM(D28:P28) -> 0
B29: MAYO | S29: =SUM(D29:R29) -> 0
B30: SUELDO + ASIG FAM | D30: 6613 | E30: 4113 | F30: 3600 | G30: 6613 | H30: 4113 | I30: 2600 | J30: 3000 | K30: 2800 | M30: 3200 | N30: 2800 | O30: 2800 | P30: 2800 | Q30: 2913 | R30: 2800 | S30: =SUM(D30:P30) -> 45052
B31: BONO | F31: 640 | O31: 800
B32: MOVILIDAD | D32: 100 | E32: 100 | F32: 76.190476 | J32: 100 | S32: =SUM(D32:P32) -> 376.19048
B33: HORAS EXTRAS | S33: =SUM(D33:P33) -> 0
S34: =SUM(D34:P34) -> 0
B35: JUNIO | S35: =SUM(D35:R35) -> 0
B36: SUELDO + ASIG FAM | D36: 6613 | E36: 4113 | F36: 3600 | G36: 6613 | H36: 4113 | I36: 2600 | J36: 3000 | K36: 2800 | M36: 3200 | N36: 2800 | O36: 2800 | P36: 2800 | Q36: 2913 | R36: 2800 | S36: =SUM(D36:P36) -> 45052
B37: BONO | F37: 640 | O37: 800
B38: MOVILIDAD | D38: 100 | E38: 100 | F38: 100 | J38: 100 | K38: 200 | S38: =SUM(D38:P38) -> 600
B39: HORAS EXTRAS | H39: =HH.EE!I3 -> 1406.5603 | P39: =HH.EE!I8 -> 1102.5 | S39: =SUM(D39:P39) -> 2509.0603
B41: JULIO | S41: =SUM(D41:P41) -> 0
B42: SUELDO + ASIG FAM | S42: =SUM(D42:P42) -> 0
B43: MOVILIDAD | S43: =SUM(D43:P43) -> 0
B44: GRATIFICACION JULIO | S44: =SUM(D44:P44) -> 0
S45: =SUM(D45:P45) -> 0
B46: AGOSTO | S46: =SUM(D46:P46) -> 0
B47: SUELDO + ASIG FAM | S47: =SUM(D47:P47) -> 0
B48: MOVILIDAD | S48: =SUM(D48:P48) -> 0
S49: =SUM(D49:P49) -> 0
B50: SEPTIEMBRE | S50: =SUM(D50:P50) -> 0
B51: SUELDO + ASIG FAM | S51: =SUM(D51:P51) -> 0
B52: MOVILIDAD | S52: =SUM(D52:P52) -> 0
B53: BONO | S53: =SUM(D53:P53) -> 0
B54: COMPRA DE VACACIONES | S54: =SUM(D54:P54) -> 0
S55: =SUM(D55:P55) -> 0
B56: OCTUBRE | S56: =SUM(D56:P56) -> 0
B57: SUELDO + ASIG FAM | S57: =SUM(D57:P57) -> 0
B58: MOVILIDAD | S58: =SUM(D58:P58) -> 0
B59: BONO | S59: =SUM(D59:P59) -> 0
S60: =SUM(D60:P60) -> 0
B61: NOVIEMBRE | S61: =SUM(D61:P61) -> 0
B62: SUELDO + ASIG FAM | S62: =SUM(D62:P62) -> 0
B63: MOVILIDAD | S63: =SUM(D63:P63) -> 0
B64: BONO | S64: =SUM(D64:P64) -> 0
B65: HORAS EXTRAS | S65: =SUM(D65:P65) -> 0
S66: =SUM(D66:P66) -> 0
B67: DICIEMBRE | S67: =SUM(D67:P67) -> 0
B68: SUELDO + ASIG FAM | S68: =SUM(D68:P68) -> 0
B69: GRATIFICACION | S69: =SUM(D69:P69) -> 0
B70: HORAS EXTRAS | S70: =SUM(D70:P70) -> 0
B71: BONO | S71: =SUM(D71:P71) -> 0
B72: MOVILIDAD | S72: =SUM(D72:P72) -> 0 | Y72: ingresos Glori
B73: VALE CONSUMO | S73: =SUM(D73:P73) -> 0
S74: =SUM(D74:P74) -> 0 | Y74: Anthia | Z74: =+(1130+113)*12 -> 14916 | AA74: sueldo
B75: INGRESOS ANTHIA - QUANTUM | S75: =SUM(D75:P75) -> 0 | Z75: =+(1243*1.09)*2 -> 2709.74 | AA75: Gratificacion
S76: =SUM(D76:P76) -> 0 | Z76: =SUM(Z74:Z75) -> 17625.74
B77: JULIO | S77: =SUM(D77:R77) -> 0
B78: SUELDO + ASIG FAM | D78: 6613 | E78: 4113 | F78: 3600 | G78: 6613 | H78: 4113 | I78: 2600 | J78: 3000 | M78: 3200 | N78: 2800 | O78: 2800 | P78: 2800 | Q78: 2913 | R78: 2800 | S78: =SUM(D78:P78) -> 42252 | Y78: Quantum | Z78: =+(3113*12) -> 37356 | AA78: sueldo
B79: BONO | F79: 640 | O79: 800 | Z79: =+(3113*1.09)*2 -> 6786.34 | AA79: Gratificacion
B80: MOVILIDAD | D80: 100 | E80: 100 | F80: ='PLANILLA MENSUAL'!Z16 -> 73.913043 | H80: 100 | J80: 100 | S80: =SUM(D80:P80) -> 473.91304 | Z80: =SUM(Z78:Z79) -> 44142.34
B81: HORAS EXTRAS | F81: 240 | H81: =HH.EE!I45 -> 0 | P81: =HH.EE!I50 -> 0 | S81: =SUM(D81:P81) -> 240
S82: =SUM(D82:P82) -> 0 | Z82: =+Z80+Z76 -> 61768.08
S83: =SUM(D83:P83) -> 0
S84: =SUM(D84:P84) -> 0
S85: =SUM(D85:P85) -> 0
S86: =SUM(D86:P86) -> 0
S87: =SUM(D87:P87) -> 0
B88: TOTAL REMUNERACIONES | D88: =+(6113*4)+(6613*8)+7208.17+7208.17+D9+D15+D20+D21+D27+D32+D38+D80 -> 92830.108 | E88: =+(4113*12)+4483.17+4483.17+E10+E15+E8+E9+E20+E27+E32+E38+E80 -> 59234.011 | F88: =+((3360*4)+(640*12)+(3600*8))+4621.6+4621.6+F9+F15+F20+F27+F32+F38+F80+F81 -> 59986.637 | G88: =+((6113*4)+(6613*8))+7208.17+7208.17+$Z$82 -> 153540.42 | H88: =+(4113*12)+4483.17+4483.17+H10+H9+H15+H20+H27+H39+H32+H37+H80 -> 61436.586 | I88: =+((2500*4)+(2600*8))+2834+2834 -> 36468 | J88: =+(3000*12)+3270+3270+J9+J15+J20+J21+J27+J32+J38+J80 -> 43511.616 | K88: =+(2800*12)+3052+3052+K9+K15+K20+K21+K27+K32+K38 -> 40598.648 | L88: =+(2800*12)+3052+3052+L10 -> 40101.833 | M88: =+((2800*4)+(3200*8))+3488+3488+M10 -> 43973.75 | N88: =+(2800*12)+3052+3052 -> 39704 | O88: =+((2100*4)+(2800*8))+3052+3052+O8+O14+O19+O26+O31+O37+O79 -> 42504 | P88: =+((2500*4)+(2800*8))+3052+3052+P10+P39 -> 40393.479 | Q88: =+((2500*4)+(2913*8))+3175.17+3175.17 -> 39654.34 | R88: =+((2500*4)+(2800*8))+3052+3052 -> 38504 | S88: =SUM(D88:R88) -> 832441.43 | U88: =2850*6+2850*1.09 -> 20206.5
B89: DEDUCCION 7UITS | D89: =5500*7 -> 38500 | E89: =5500*7 -> 38500 | F89: =5500*7 -> 38500 | G89: =5500*7 -> 38500 | H89: =5500*7 -> 38500 | I89: =5500*7 -> 38500 | J89: =5500*7 -> 38500 | K89: =5500*7 -> 38500 | ... R89: =5500*7 -> 38500 | S89: =SUM(D89:R89) -> 577500
B90: BASE IMPONIBLE | D90: =+D88-D89 -> 54330.108 | E90: =+E88-E89 -> 20734.011 | F90: =+F88-F89 -> 21486.637 | G90: =+G88-G89 -> 115040.42 | H90: =+H88-H89 -> 22936.586 | I90: =+I88-I89 -> -2032 | J90: =+J88-J89 -> 5011.6162 | K90: =+K88-K89 -> 2098.6481 | ... R90: =+R88-R89 -> 4 | S90: =SUM(D90:R90) -> 254941.43
B93: CALCULO IR 5TA CATEG.
B94: Hasta 5 UIT S/ 27,500 (5500 UIT) | C94: 0.08 | D94: =+(5500*5)*$C$94 -> 2200 | E94: =+(E90)*$C$94 -> 1658.7209 | F94: =+(F90)*$C$94 -> 1718.9309 | G94: =+(5500*5)*$C$94 -> 2200 | H94: =+(H90)*$C$94 -> 1834.9269 | J94: =+(J90)*$C$94 -> 400.9293 | K94: =+(K90)*$C$94 -> 167.89185 | L94: =+(L90)*$C$94 -> 128.14667 | M94: =+(M90)*$C$94 -> 437.9 | N94: =+(N90)*$C$94 -> 96.32 | O94: =+(O90)*$C$94 -> 320.32 | P94: =+(P90)*$C$94 -> 151.47833 | Q94: =+(Q90)*$C$94 -> 92.3472 | R94: =+(R90)*$C$94 -> 0.32 | S94: =SUM(D94:P94) -> 11315.565
B95: Por el exceso de 5 UIT S/ 27,500 y hasta 20 UIT 110,000 | C95: 0.14 | D95: =+(+D90-27500)*$C$95 -> 3756.2151 | G95: =+(+G90-27500)*$C$95 -> 12255.659 | S95: =SUM(D95:P95) -> 16011.874
B96: Por el exceso de 20 UIT S/ 110,000 y hasta 35 UIT 192,500 | C96: 0.17 | G96: =+(+G90-110000)*$C$96 -> 856.8714 | S96: =SUM(D96:P96) -> 856.8714
D97: =SUM(D94:D96) -> 5956.2151 | E97: =SUM(E94:E96) -> 1658.7209 | F97: =SUM(F94:F96) -> 1718.9309 | G97: =SUM(G94:G96) -> 15312.53 | H97: =SUM(H94:H96) -> 1834.9269 | J97: =SUM(J94:J96) -> 400.9293 | K97: =SUM(K94:K96) -> 167.89185 | L97: =SUM(L94:L96) -> 128.14667 | M97: =SUM(M94:M96) -> 437.9 | N97: =SUM(N94:N96) -> 96.32 | O97: =SUM(O94:O96) -> 320.32 | P97: =SUM(P94:P96) -> 151.47833 | Q97: =SUM(Q94:Q96) -> 92.3472 | ... S97: =SUM(S94:S96) -> 28184.31
B98: RETENCIONES | S98: =SUM(D98:P98) -> 0
B99: ENERO | D99: 428.01624 | E99: 134.08547 | F99: 125.73333 | G99: 1145.2549 | H99: 140.88906 | I99: 0 | J99: 26.933333 | K99: 8.0266667 | L99: 10.678889 | M99: 9.345 | N99: 8.0266667 | O99: 0 | P99: 0 | Q99: 0 | R99: 0 | S99: =SUM(D99:P99) -> 2036.9896
B100: FEBRERO | D100: 426.80406 | E100: 135.36686 | F100: 131.50303 | G100: 1145.2549 | H100: 141.84663 | I100: 0 | J100: 28.027706 | K100: 9.4465801 | L100: 10.678889 | M100: 9.345 | N100: 8.0266667 | O100: 19.069091 | S100: =SUM(D100:P100) -> 2065.3694
B101: MARZO | D101: 433.90948 | E101: 136.16686 | F101: 137.34303 | G101: 1145.2549 | H101: 142.44663 | I101: 0 | J101: 31.476826 | K101: 12.72186 | L101: 10.678889 | M101: 9.345 | N101: 8.0266667 | O101: 38.269091 | S101: =SUM(D101:P101) -> 2105.6392
B102: UTILILIDADES | P102: 0 | Q102: 0 | R102: 0 | S102: =SUM(D102:P102) -> 0
B103: ABRIL | D103: 433.90948 | E103: 136.16686 | F103: 137.34303 | G103: 1145.2549 | H103: 142.44663 | I103: 0 | J103: 31.476826 | K103: 12.72186 | M103: 9.345 | N103: 8.0266667 | O103: 38.269091 | P103: 0 | Q103: 0 | R103: 0 | S103: =SUM(D103:P103) -> 2094.9603
B104: MAYO | D104: 525.69698 | E104: 137.61686 | F104: 144.23694 | G104: 1341.4388 | H104: 143.34663 | I104: 0 | J104: 33.376826 | K104: 14.62186 | L104: 0 | M104: 50.065 | N104: 8.0266667 | O104: 12.089091 | P104: 7.9097917 | Q104: 11.5434 | R104: 0.04 | S104: =SUM(D104:R104) -> 2430.0089
...

Sheet SEGURO PACIFICO
C1: SEGURO LA POSITIVA
C3: Aporte mensuales
C4: de 15 a 44 años hombres | D4: 327 | E4: Se modifico apartir del 01.01.19
C5: de 15 a 44 años mujeres | D5: 213
I8: PORCENTAJES | K8: SALDO POR DESCONTAR AL TRAB | L8: INPROCESS
I9: 0.3 | J9: 0.5
B10: Nº | C10: APELLIDOS Y NOMBRES | D10: DNI Nº | E10: Nº poliza | F10: FECHA DE NAC. | G10: FECHA DE INGRESO | H10: REMUNERACION | I10: 0 a 12 meses | J10: de 13 a 24 meses | O10: ASUME INPROCESS
M11: =+L11 -> 0 | N11: =+M11*0.18 -> 0 | O11: =+N11+M11 -> 0 | P11: =+K11+K13+K14 -> 0 | Q11: =+P11+O11 -> 0
B12: 1 | C12: GIOVANNA RAQUEL MARTINEZ CASTILLO | D12: 9594953 | E12: 611220200 | F12: 26364 | G12: 41548 | H12: 5085 | J12: =+$D$4*$J$9 -> 163.5 | K12: =+$D$4-J12 -> 163.5 | L12: =+J12/1.18 -> 138.55932 | M12: =+L12 -> 138.55932 | N12: =+M12*0.18 -> 24.940678 | O12: =+N12+M12 -> 163.5 | P12: =+K12 -> 163.5 | Q12: =+P12+O12 -> 327
I15: =SUMA(I11:I13) -> #NAME? | J15: =SUMA(J11:J14) -> #NAME? | K15: =SUMA(K11:K14) -> #NAME? | L15: =SUMA(L11:L14) -> #NAME? | O15: =SUMA(O11:O12) -> #NAME? | Q15: =SUMA(Q11:Q12) -> #NAME?
C18: SEGURO PACIFICO
C20: Aporte mensuales
C21: ORIHUELA AGUIRRE ERNESTO JULIO | D21: 605.94
C22: PORTOCARRERO TAFUR GLORI MAGRI | D22: 612.04
C23: GIOVANNA MARTINEZ | D23: 548
C24: ARACELLI PEREZ | D24: 351.5
C25: LADY OLAYA
I27: PORCENTAJES | K27: SALDO POR DESCONTAR AL TRAB | L27: INPROCESS
I28: 0.2 | J28: 0.5
B29: Nº | C29: APELLIDOS Y NOMBRES | D29: DNI Nº | E29: Nº poliza | F29: FECHA DE NAC. | G29: FECHA DE INGRESO | H29: REMUNERACION | I29: 0 a 12 meses | J29: de 13 a 24 meses | O29: ASUME INPROCESS
B30: 1 | C30: ORIHUELA AGUIRRE ERNESTO JULIO | D30: 10305226 | E30: 13481668 | F30: 27747 | G30: 35462 | H30: 10000 | J30: =+D21/2 -> 302.97 | K30: =+D21-J30 -> 302.97 | L30: =+J30/1.18 -> 256.75424 | M30: =+L30 -> 256.75424 | N30: =+M30*0.18 -> 46.215763 | O30: =+N30+M30 -> 302.97 | P30: =+D21-O30 -> 302.97 | Q30: =+P30+O30 -> 605.94
B31: 2 | C31: MARTINEZ CASTILLO GIOVANNA | D31: 9594953 | E31: 16647534 | F31: 26364 | G31: 41548 | J31: =+D23/2 -> 274 | K31: =+D23-J31 -> 274 | L31: =+J31/1.18 -> 232.20339 | M31: =+L31 -> 232.20339 | N31: =+M31*0.18 -> 41.79661 | O31: =+N31+M31 -> 274 | P31: =+D23-O31 -> 274 | Q31: =+P31+O31 -> 548
B32: 3 | C32: PEREZ CAJAHUANCA ARACELLI | D32: 44425022 | E32: 16647538 | F32: 31996 | G32: 42917 | J32: =+D24/2 -> 175.75 | K32: =+D24-J32 -> 175.75 | L32: =+J32/1.18 -> 148.94068 | M32: =+L32 -> 148.94068 | N32: =+M32*0.18 -> 26.809322 | O32: =+N32+M32 -> 175.75 | P32: =+D24-O32 -> 175.75 | Q32: =+P32+O32 -> 351.5
B33: 4 | C33: PORTOCARRERO TAFUR GLORI MAGRI | D33: 43172155 | E33: 26350 | F33: 31249 | G33: 42948 | J33: =+D22/2 -> 306.02 | K33: =+D22-J33 -> 306.02 | L33: =+J33/1.18 -> 259.33898 | M33: =+L33 -> 259.33898 | N33: =+M33*0.18 -> 46.681017 | O33: =+N33+M33 -> 306.02 | P33: =+D22-O33 -> 306.02 | Q33: =+P33+O33 -> 612.04
M34: =+L34 -> 0 | N34: =+M34*0.18 -> 0 | O34: =+N34+M34 -> 0
I35: =SUM(I30:I33) -> 0 | J35: =SUM(J30:J33) -> 1058.74 | K35: =SUM(K30:K33) -> 1058.74 | L35: =SUM(L30:L33) -> 897.23729 | O35: =SUM(O30:O33) -> 1058.74 | P35: =SUM(P30:P33) -> 1058.74 | Q35: =SUM(Q30:Q33) -> 2117.48
C41: SEGURO PACIFICO
C43: Aporte mensuales
C44: ORIHUELA AGUIRRE ERNESTO JULIO | D44: =605.94/1.18 -> 513.50847
C45: PORTOCARRERO TAFUR GLORI MAGRI | D45: =612.04/1.18 -> 518.67797
C46: GIOVANNA MARTINEZ | D46: =548/ 1.18 -> 464.40678
C47: ARACELLI PEREZ | D47: =351.5/1.18 -> 297.88136
I50: PORCENTAJES | K50: SALDO POR DESCONTAR AL TRAB | L50: INPROCESS | M50: TOTAL FACTURACION
I51: 0.2 | J51: 0.5
B52: Nº | C52: APELLIDOS Y NOMBRES | D52: DNI Nº | E52: Nº poliza | F52: FECHA DE NAC. | G52: FECHA DE INGRESO | H52: REMUNERACION | I52: 0 a 12 meses | J52: de 13 a 24 meses
B53: 1 | C53: ORIHUELA AGUIRRE ERNESTO JULIO | D53: 10305226 | E53: 13481668 | F53: 27747 | G53: 35462 | H53: 10000 | J53: =+D44/2 -> 256.75424 | K53: =+D44-J53 -> 256.75424 | L53: =605.93-K53 -> 349.17576 | M53: =+L53+K53 -> 605.93
B54: 2 | C54: MARTINEZ CASTILLO GIOVANNA | D54: 9594953 | E54: 16647534 | F54: 26364 | G54: 41548 | J54: =+D46/2 -> 232.20339 | K54: =+D46-J54 -> 232.20339 | L54: =548-K54 -> 315.79661 | M54: =+L54+K54 -> 548
B55: 3 | C55: PEREZ CAJAHUANCA ARACELLI | D55: 44425022 | E55: 16647538 | F55: 31996 | G55: 42917 | J55: =+D47/2 -> 148.94068 | K55: =+D47-J55 -> 148.94068 | L55: =351.5-K55 -> 202.55932 | M55: =+L55+K55 -> 351.5
B56: 4 | C56: PORTOCARRERO TAFUR GLORI MAGRI | D56: 43172155 | E56: 26350 | F56: 31249 | G56: 42948 | J56: =+D45/2 -> 259.33898 | K56: =+D45-J56 -> 259.33898 | L56: =612.304-K56 -> 352.96502 | M56: =+L56+K56 -> 612.304
M57: =+L57 -> 0 | N57: =+M57*0.18 -> 0
I58: =SUM(I53:I56) -> 0 | J58: =SUM(J53:J56) -> 897.23729 | K58: =SUM(K53:K56) -> 897.23729 | L58: =SUM(L53:L56) -> 1220.4967 | M58: =SUM(M53:M56) -> 2117.734

Sheet VACACIONES
B2: No | D2: año 2026 | P2: TOTAL | Q2: PROMEDIO COMISIONES
C3: APELLIDOS Y NOMBRES | D3: ENERO | E3: FEBRERO | F3: MARZO | G3: ABRIL | H3: MAYO | I3: JUNIO | J3: JULIO | K3: AGOSTO | L3: SETIEMBRE | M3: OCTUBRE | N3: NOVIEMBRE | O3: DICIEMBRE | R3: DIA | S3: VACACIONES | T3: TOTAL
B4: 1 | C4: ECHEVARRIA SOTO JORGE LUIS | D4: 9122.3397 | E4: 6019.6636 | F4: 8538.4969 | G4: 12937.093 | H4: 8462.9701 | I4: 8965.188 | P4: =SUM(D4:O4) -> 54045.752 | Q4: =+P4/6 -> 9007.6253 | R4: =Q4/30 -> 300.25418 | S4: 1 | T4: =S4*R4 -> 300.25418
B5: =+B4+1 -> 2 | C5: QUEVEDO SALAS LUIS ALBERTO | D5: 2501.7108 | E5: 2599.7564 | F5: 3287.0806 | G5: 2509.8714 | H5: 3359.019 | I5: 4331.4263 | P5: =SUM(D5:O5) -> 18588.864 | Q5: =+P5/6 -> 3098.1441 | R5: =Q5/30 -> 103.27147 | S5: 14 | T5: =S5*R5 -> 1445.8006
B6: =+B5+1 -> 3 | C6: ESTRADA SANTOS JUAN MIGUEL | D6: 1375.3927 | E6: 2137.4428 | F6: 1953.9544 | G6: 1486.9737 | H6: 1343.5632 | I6: 1994.6996 | P6: =SUM(D6:O6) -> 10292.026 | Q6: =+P6/6 -> 1715.3377 | R6: =Q6/30 -> 57.177925 | S6: 1 | T6: =S6*R6 -> 57.177925
B7: =+B6+1 -> 4 | C7: ERNESTO ORIHUELA AGUIRRE | D7: 5568.2823 | E7: 4483.2372 | F7: 6098.9263 | G7: 9240.781 | H7: 6044.9787 | I7: 6403.7057 | P7: =SUM(D7:O7) -> 37839.911 | Q7: =+P7/6 -> 6306.6519 | R7: =Q7/30 -> 210.22173 | S7: 0 | T7: =S7*R7 -> 0
B8: =+B7+1 -> 5 | C8: SICCHA ARCE LUIS FRANCISCO | D8: 404.14905 | E8: 749.2803 | F8: 531.69465 | G8: 3286.2737 | H8: 700.75905 | I8: 1556.8993 | P8: =SUM(D8:O8) -> 7229.056 | Q8: =+P8/6 -> 1204.8427 | R8: =Q8/30 -> 40.161422 | S8: 0 | T8: =S8*R8 -> 0
B9: =+B8+1 -> 6 | C9: AREVALO VELA CESAR ANTONIO | D9: 2429.1964 | E9: 842.6241 | F9: 846.33225 | G9: 2406.4389 | H9: 1799.1559 | I9: 662.7648 | P9: =SUM(D9:O9) -> 8986.5123 | Q9: =+P9/6 -> 1497.752 | R9: =Q9/30 -> 49.925068 | S9: 0 | T9: =S9*R9 -> 0
B10: =+B9+1 -> 7 | C10: ESTACIO CAYETANO FRANK BRIAN | D10: 872.05845 | E10: 1100.9444 | F10: 3369.7662 | G10: 937.3611 | H10: 1449.1908 | I10: 1482.3352 | P10: =SUM(D10:O10) -> 9211.6562 | Q10: =+P10/6 -> 1535.276 | R10: =Q10/30 -> 51.175868 | S10: 7 | T10: =S10*R10 -> 358.23108
B11: 8 | C11: RICRA DAVALOS GIUSSEPPE RENATO | I11: 887.808 | P11: =SUM(D11:O11) -> 887.808 | Q11: =+P11/6 -> 147.968 | R11: =Q11/30 -> 4.9322667 | S11: 0 | T11: =S11*R11 -> 0
D12: =SUM(D4:D11) -> 22273.129 | E12: =SUM(E4:E11) -> 17932.949 | F12: =SUM(F4:F11) -> 24626.251 | G12: =SUM(G4:G11) -> 32804.793 | H12: =SUM(H4:H11) -> 23159.637 | I12: =SUM(I4:I11) -> 26284.827 | J12: =SUM(J4:J11) -> 0 | K12: =SUM(K4:K11) -> 0 | ... Q12: =SUM(Q4:Q11) -> 24513.598 | T12: =SUM(T4:T11) -> 2161.4637

Sheet HT. EPS
A1: CALCULO DEL 2.25%
A3: NOMBRE DE LA EMPRESA: | B3: INDUSTRIAL PROCESS SRL - IN PROCESS SRL
A4: FECHA: | B4: 45771
A5: ASESOR COMERCIAL: | B5: CAROL CUBA
A7: Composición de Grupo
A8: Titular Solo | B8: 8 | C8: =+B8+B9+B10+B11+B12+B13 -> 10
A9: Titular con 1 Dependiente | E9: DH: CONYUGE, CONVIVIENTE CON UNION DE HECHOS E HIJOS HASTA LOS 18 AÑOS
A10: Titular con 2 Dependientes | B10: 1
A11: Titular con 3 Dependientes | B11: 1
A12: Titular con 4 Dependientes | B12: 0
A13: Titular con 5 Dependientes
A14: Hijos mayores de 18 años
G15: ESSALUD MENSUAL | I15: =SUMIF('PLANILLA MENSUAL'!BN12:BN55,"EPS",'PLANILLA MENSUAL'!BL12:BL54) -> 4718.1012 | J15: 5262.91 | K15: =+I15-J15 -> -544.80882
A16: Según población afiliada a la fecha | I16: =+I14*9% -> 0
A17: N° Total de Afiliados | B17: 10 | C17: total de afiliados | E17: TITULARES | G17: ESSALUD ANUAL | I17: =+I15*12 -> 56617.214
A18: Essalud Anual | B18: =+I17 -> 56617.214
A19: Credito Anual | B19: =B18*25% -> 14154.304
A20: Credito Mensual | B20: =B19/12 -> 1179.5253
A21: Credito x Afiliado | B21: =B20/B17 -> 117.95253 | C21: credito 2.25
B23: Facturación | G23: Costo sin IGV | L23: CREDITO A FAVOR DEL TRABAJADOR | M23: Descuento Trab.
A25: 10 a mas afiliados
B26: BASE PEAS | C26: BASE ESENCIAL | D26: BASE PLUS | E26: ADICIONAL 1 | F26: ADICIONAL 2 | G26: BASE PEAS | H26: BASE ESENCIAL | I26: BASE PLUS | J26: ADICIONAL 1 | K26: ADICIONAL 2 | L26: POR PERSONA | M26: BASE PEAS | N26: BASE ESENCIAL | O26: BASE PLUS | P26: ADICIONAL 1 | Q26: ADICIONAL 2
A28: Titular | B28: 185 | C28: 263 | D28: 268 | E28: 339 | F28: 416 | G28: =+B28/1.18 -> 156.77966 | H28: =+C28/1.18 -> 222.88136 | I28: =+D28/1.18 -> 227.11864 | J28: =+E28/1.18 -> 287.28814 | K28: =+F28/1.18 -> 352.54237 | L28: =+B21 -> 117.95253 | M28: =+G28-L28 -> 38.827132 | N28: =+H28-L28 -> 104.92883 | O28: =+I28-L28 -> 109.16611 | P28: =+J28-L28 -> 169.33561 | Q28: =+K28-L28 -> 234.58984
A29: Titular mas 1 | B29: =+B28*2 -> 370 | C29: =+C28*2 -> 526 | D29: =+D28*2 -> 536 | E29: =+E28*2 -> 678 | F29: =+F28*2 -> 832 | G29: =+B29/1.18 -> 313.55932 | H29: =+C29/1.18 -> 445.76271 | I29: =+D29/1.18 -> 454.23729 | J29: =+E29/1.18 -> 574.57627 | K29: =+F29/1.18 -> 705.08475 | L29: =+L28*2 -> 235.90506 | M29: =+G29-L29 -> 77.654263 | N29: =+H29-L29 -> 209.85765 | O29: =+I29-L29 -> 218.33223 | P29: =+J29-L29 -> 338.67121 | Q29: =+K29-L29 -> 469.17969 | S29: =+L28*0.18 -> 21.231455 | T29: =+L28+S29 -> 139.18398
A30: Titular mas 2 | B30: =+B28*3 -> 555 | C30: =+C28*3 -> 789 | D30: =+D28*3 -> 804 | E30: =+E28*3 -> 1017 | F30: =+F28*3 -> 1248 | G30: =+B30/1.18 -> 470.33898 | H30: =+C30/1.18 -> 668.64407 | I30: =+D30/1.18 -> 681.35593 | J30: =+E30/1.18 -> 861.86441 | K30: =+F30/1.18 -> 1057.6271 | L30: =+L28*3 -> 353.85759 | M30: =+G30-L30 -> 116.48139 | N30: =+H30-L30 -> 314.78648 | O30: =+I30-L30 -> 327.49834 | P30: =+J30-L30 -> 508.00682 | Q30: =+K30-L30 -> 703.76953
A31: Titular mas 3 | B31: =+B28*4 -> 740 | C31: =+C28*4 -> 1052 | D31: =+D28*4 -> 1072 | E31: =+E28*4 -> 1356 | F31: =+F28*4 -> 1664 | G31: =+B31/1.18 -> 627.11864 | H31: =+C31/1.18 -> 891.52542 | I31: =+D31/1.18 -> 908.47458 | J31: =+E31/1.18 -> 1149.1525 | K31: =+F31/1.18 -> 1410.1695 | L31: =+L28*4 -> 471.81012 | M31: =+G31-L31 -> 155.30853 | N31: =+H31-L31 -> 419.71531 | O31: =+I31-L31 -> 436.66446 | P31: =+J31-L31 -> 677.34242 | Q31: =+K31-L31 -> 938.35937
A32: Titular mas 4 | B32: 740 | C32: 956 | D32: 976 | E32: 1356 | F32: 1664 | G32: =+B32/1.18 -> 627.11864 | H32: =+C32/1.18 -> 810.16949 | I32: =+D32/1.18 -> 827.11864 | J32: =+E32/1.18 -> 1149.1525 | K32: =+F32/1.18 -> 1410.1695 | L32: =+L28*5 -> 589.76265 | M32: =+G32-L32 -> 37.355997 | N32: =+H32-L32 -> 220.40684 | O32: =+I32-L32 -> 237.356 | P32: =+J32-L32 -> 559.3899 | Q32: =+K32-L32 -> 820.40684
M33: BASE PEAS | N33: BASE ESENCIAL | O33: BASE PLUS | P33: ADICIONAL 1 | Q33: ADICIONAL 2
A34: Hijos mayores de 18 años | M34: 185 | N34: =+C28 -> 263 | O34: =+D28 -> 268 | P34: =+E28 -> 339 | Q34: =+F28 -> 416
A35: NOTA: CALCULO REALIZADO EN BASE A LA INFORMACION PROPORCIONADA POR LA EMPRESA. EL MONTO DEL CRÉDITO PODRÁ VARIAR SEGÚN EL NÚMERO REAL DE TITULARES, SU COMPOSICIÓN FAMILIAR Y EL APORTE A ESSALUD CORRESPONDIENTE.
K37: PLAN PLUS | M37: 01 TITULAR | O37: =+O28*0.7 -> 76.41628 | P37: 7 | Q37: =+O37*P37 -> 534.91396
L40: ESTRADA | M40: 02 DEPENDIENTES | O40: =+I28*2 -> 454.23729
M41: TITULAR | O41: =+O28*0.7 -> 76.41628
O42: =SUM(O40:O41) -> 530.65357
L44: ECHEVARRIA | M44: 02 DEPENDIENTES | O44: =+I28*2 -> 454.23729
M45: TITULAR | O45: =+O28*0.7 -> 76.41628
O46: =SUM(O44:O45) -> 530.65357
K51: PLAN ESENCIAL | M51: 01 TITULAR | O51: =+N28*0.7 -> 73.450179 | P51: 1 | Q51: =+O51*P51 -> 73.450179
Q53: =+Q37+O42+O46+Q51 -> 1669.6713 | R53: TOTAL DESCUENTO
N59: 13 | O59: 268 | P59: =+N59*O59 -> 3484
N60: 1 | O60: 263 | P60: =+N60*O60 -> 263
P61: =SUM(P59:P60) -> 3747

Sheet TARDANZA
L2: 30 | O2: REMUNER.
D3: TOTAL | G3: TOTAL | I3: FALTAS | M3: IMPORTE | O3: AFECTA A
D4: INGRESOS | E4: ASIGNACION FAMILIAR | G4: INGRESOS | H4: DESCUENTOS POR TARDANZA | I4: INJUSTIFICADAS | J4: TOTAL | K4: DESCUENTO POR FALTA | L4: DESCUENTO POR TARDANZA | M4: A | O4: IMPUESTO | P4: 30
B5: Nº | C5: APELLIDOS Y NOMBRES | H5: MINUTOS | I5: PERMISO | J5: MINUTOS | M5: DESCONTAR
B6: 1 | C6: ORIHUELA AGUIRRE ERNESTO JULIO | D6: 13000 | E6: 113 | G6: =+D6+E6 -> 13113 | I6: 0 | K6: =+D6/$L$2*I6 -> 0 | L6: =(+D6/$L$2/8/60)*H6 -> 0 | M6: 0
B7: =+B6+1 -> 2 | C7: MARTINEZ CASTILLO GIOVANNA RAQUEL | D7: 6500 | E7: 113 | G7: =+D7+E7 -> 6613 | I7: 0 | J7: 0 | K7: =+D7/$L$2*I7 -> 0 | L7: =(+D7/$L$2/8/60)*H7 -> 0 | M7: 0
B8: =+B7+1 -> 3 | C8: SALVADOR ROJAS ELVIS ALFONSO | D8: 4000 | E8: 113 | G8: =+D8+E8 -> 4113 | H8: =5*60+38 -> 338 | J8: 0 | K8: =+D8/$L$2*I8 -> 0 | L8: =(+G8/$L$2/8/60)*H8 -> 96.54125 | M8: 0
B9: =+B8+1 -> 4 | C9: LOLI RODRIGUEZ JANIO RICHARD | D9: 4000 | E9: 113 | G9: =+D9+E9 -> 4113 | J9: 0 | K9: =+D9/$L$2*I9 -> 0 | L9: =(+G9/$L$2/8/60)*H9 -> 0 | M9: 0
B10: =+B9+1 -> 5 | C10: PEREZ CAJAHUANCA ARACELLI IRAIDA | D10: 3600 | G10: =+D10+E10 -> 3600 | H10: =5*60+8 -> 308 | J10: 0 | K10: =+D10/$L$2*I10 -> 0 | L10: =(+G10/$L$2/8/60)*H10 -> 77 | M10: 0
B11: =+B10+1 -> 6 | C11: PORTOCARRERO TAFUR GLORI MAGRI | D11: 6500 | E11: 113 | G11: =+D11+E11 -> 6613 | J11: 0 | K11: =+D11/$L$2*I11 -> 0 | L11: =(+G11/$L$2/8/60)*H11 -> 0 | M11: 0
B12: =+B11+1 -> 7 | C12: ECHEVARRIA SOTO JORGE LUIS | D12: 4500 | E12: 113 | G12: =+D12+E12 -> 4613 | J12: 0 | K12: =+D12/$L$2*I12 -> 0 | L12: =(+G12/$L$2/8/60)*H12 -> 0 | M12: 0
B13: =+B12+1 -> 8 | C13: MONTOYA MEDRANO ANDREA BELEN JOSEPHINE | D13: 2800 | G13: =+D13+E13 -> 2800 | H13: 59 | J13: 0 | K13: =+D13/$L$2*I13 -> 0 | L13: =(+G13/$L$2/8/60)*H13 -> 11.472222 | M13: 0
B14: =+B13+1 -> 9 | C14: VERGARA BALDEON GEANNINA LIZBETH | D14: 2600 | G14: =+D14+E14 -> 2600 | H14: 63 | J14: 0 | K14: =+D14/$L$2*I14 -> 0 | L14: =(+G14/$L$2/8/60)*H14 -> 11.375 | M14: 0
B15: =+B14+1 -> 10 | C15: CASTILLO ENCARNACION MANUEL LEONIDAS | D15: 2200 | E15: 113 | G15: =+D15+E15 -> 2313 | H15: 75 | J15: 0 | K15: =+D15/$L$2*I15 -> 0 | L15: =(+G15/$L$2/8/60)*H15 -> 12.046875 | M15: 0
B16: =+B15+1 -> 11 | C16: QUEVEDO SALAS LUIS ALBERTO | D16: 3800 | E16: 113 | G16: =+D16+E16 -> 3913 | J16: 0 | K16: =+D16/$L$2*I16 -> 0 | L16: =(+G16/$L$2/8/60)*H16 -> 0 | M16: 0
B17: =+B16+1 -> 12 | C17: PORTOCARRERO GOMEZ MARIA DEICY | D17: 1500 | E17: 113 | G17: =+D17+E17 -> 1613 | J17: 0 | K17: =+D17/$L$2*I17 -> 0 | L17: =(+G17/$L$2/8/60)*H17 -> 0 | M17: 0
B18: =+B17+1 -> 13 | C18: LOBO QUISPE ELISA FIORELLA | D18: 3000 | G18: =+D18+E18 -> 3000 | H18: =8*60+49 -> 529 | J18: 0 | K18: =+D18/$L$2*I18 -> 0 | L18: =(+G18/$L$2/8/60)*H18 -> 110.20833 | M18: 0
B19: =+B18+1 -> 14 | C19: RIOS HOLSEN JAIME JUNIOR | D19: 3200 | G19: =+D19+E19 -> 3200 | H19: =3*60+34 -> 214 | J19: 0 | K19: =+D19/$L$2*I19 -> 0 | L19: =(+G19/$L$2/8/60)*H19 -> 47.555556 | M19: 0
B20: =+B19+1 -> 15 | C20: ESTRADA SANTOS JUAN MIGUEL | D20: 2800 | E20: 113 | G20: =+D20+E20 -> 2913 | H20: 97 | J20: 0 | K20: =+D20/$L$2*I20 -> 0 | L20: =(+G20/$L$2/8/60)*H20 -> 19.622292 | M20: 0
B21: =+B20+1 -> 16 | C21: SALCEDO RIVAS DANIEL ALONSO | D21: 2800 | E21: 113 | G21: =+D21+E21 -> 2913 | H21: 133 | J21: 0 | K21: =+D21/$L$2*I21 -> 0 | L21: =(+G21/$L$2/8/60)*H21 -> 26.904792 | M21: 0
B22: =+B21+1 -> 17 | C22: PORTOCARRERO TAFUR MARIA LOIDI | D22: 1200 | G22: =+D22+E22 -> 1200 | J22: 0 | K22: =+D22/$L$2*I22 -> 0 | L22: =(+G22/$L$2/8/60)*H22 -> 0 | M22: 0
B23: =+B22+1 -> 18 | C23: ZEVALLOS DELGADO LUIS EDUARDO | D23: 2800 | G23: =+D23+E23 -> 2800 | H23: 33 | J23: 0 | K23: =+D23/$L$2*I23 -> 0 | L23: =(+G23/$L$2/8/60)*H23 -> 6.4166667 | M23: 0
B24: =+B23+1 -> 19 | C24: BALLLESTEROS DI SERI MARIA PAULA | D24: 2800 | G24: =+D24+E24 -> 2800 | H24: 145 | J24: 0 | K24: =+D24/$L$2*I24 -> 0 | L24: =(+G24/$L$2/8/60)*H24 -> 28.194444 | M24: 0
B25: =+B24+1 -> 20 | C25: OCAMPO ORTEGA JEAN PAUL | D25: 2500 | G25: =+D25+E25 -> 2500 | H25: =2*60+53 -> 173 | J25: 0 | K25: =+D25/$L$2*I25 -> 0 | L25: =(+G25/$L$2/8/60)*H25 -> 30.034722 | M25: 0
B26: =+B25+1 -> 21 | C26: OLIVOS SAAVEDRA LANDHERT ANDERSON | D26: 2500 | G26: =+D26+E26 -> 2500 | J26: 0 | K26: =+D26/$L$2*I26 -> 0 | L26: =(+G26/$L$2/8/60)*H26 -> 0 | M26: 0
B27: =+B26+1 -> 22 | C27: YUPANQUI SAMANIEGO RENATO LUIS | D27: 2500 | G27: =+D27+E27 -> 2500 | H27: 38 | J27: 0 | K27: =+D27/$L$2*I27 -> 0 | L27: =(+G27/$L$2/8/60)*H27 -> 6.5972222 | M27: 0
B28: =+B27+1 -> 23 | C28: TUCTO PEREZ CESAR ANTONIO | D28: 2800 | G28: =+D28+E28 -> 2800 | J28: 0 | K28: =+D28/$L$2*I28 -> 0 | L28: =(+G28/$L$2/8/60)*H28 -> 0 | M28: 0
B29: =+B28+1 -> 24 | C29: AREVALO VELA CESAR ANTONIO | D29: 2500 | G29: =+D29+E29 -> 2500 | H29: =2*60+44 -> 164 | J29: 0 | K29: =+D29/$L$2*I29 -> 0 | L29: =(+G29/$L$2/8/60)*H29 -> 28.472222 | M29: 0
B30: =+B29+1 -> 25 | C30: SICCHA ARCE LUIS FRANCISCO | D30: 2500 | G30: =+D30+E30 -> 2500 | J30: 0 | K30: =+D30/$L$2*I30 -> 0 | L30: =(+G30/$L$2/8/60)*H30 -> 0
B31: =+B30+1 -> 26 | C31: JIMENEZ PUYEN LUIS ANTONIO | D31: 2800 | G31: =+D31+E31 -> 2800 | H31: 60 | J31: 0 | K31: =+D31/$L$2*I31 -> 0 | L31: =(+G31/$L$2/8/60)*H31 -> 11.666667
B32: =+B31+1 -> 27 | C32: SILVA SANTISTEBAN RONAL JHUNIOR | D32: 2000 | G32: =+D32+E32 -> 2000 | H32: 86 | J32: 0 | K32: =+D32/$L$2*I32 -> 0 | L32: =(+G32/$L$2/8/60)*H32 -> 11.944444
B33: =+B32+1 -> 28 | C33: ELGUERA SOTO LUCERO ESTEFANIA | D33: 2200 | G33: =+D33+E33 -> 2200 | H33: 21 | J33: 0 | K33: =+D33/$L$2*I33 -> 0 | L33: =(+G33/$L$2/8/60)*H33 -> 3.2083333
B34: =+B33+1 -> 29 | C34: ESTACIO CAYETANO FRANK BRIAN | D34: 2300 | G34: =+D34+E34 -> 2300 | J34: 0 | K34: =+D34/$L$2*I34 -> 0 | L34: =(+G34/$L$2/8/60)*H34 -> 0
B35: =+B34+1 -> 30 | C35: SALAZAR VELASQUEZ HECTOR ALEXANDER | D35: 2500 | E35: 113 | G35: =+D35+E35 -> 2613 | H35: =6*60+10 -> 370 | J35: 0 | K35: =+D35/$L$2*I35 -> 0 | L35: =(+G35/$L$2/8/60)*H35 -> 67.139583 | O35: 0
B36: =+B35+1 -> 31 | C36: RICRA DAVALOS GIUSSEPPE RENATO | D36: 1800 | G36: =+D36+E36 -> 1800 | H36: 50 | J36: 0 | K36: =+D36/$L$2*I36 -> 0 | L36: =(+G36/$L$2/8/60)*H36 -> 6.25
B37: =+B36+1 -> 32 | C37: DIAZ ESCALANTE LUIS MIGUEL DAVID | D37: 1700 | E37: 113 | G37: =+D37+E37 -> 1813 | H37: =60+41 -> 101 | J37: 0 | K37: =+D37/$L$2*I37 -> 0 | L37: =(+G37/$L$2/8/60)*H37 -> 12.716181
B38: =+B37+1 -> 33 | C38: HIPOLITO GUANILO ARNOLD JIMMY | D38: 1500 | E38: 113 | G38: =+D38+E38 -> 1613 | H38: 49 | J38: 0 | K38: =+D38/$L$2*I38 -> 0 | L38: =(+G38/$L$2/8/60)*H38 -> 5.4886806
B39: =+B38+1 -> 34 | C39: MONTOYA MEDRANO VIVIAN MICHELE ALEXANDRA | D39: 2000 | G39: =+D39+E39 -> 2000 | H39: 15 | J39: 0 | K39: =+D39/$L$2*I39 -> 0 | L39: =(+G39/$L$2/8/60)*H39 -> 2.0833333
B40: =+B39+1 -> 35 | C40: BANCHO CANELOS EDSON OMAR AMANCIO | D40: 1500 | G40: =+D40+E40 -> 1500 | H40: 49 | J40: 0 | K40: =+D40/$L$2*I40 -> 0 | L40: =(+G40/$L$2/8/60)*H40 -> 5.1041667
B41: =+B40+1 -> 36 | C41: ALARCON OLIVERA AMBAR TIFFANY | D41: 2850 | G41: =+D41+E41 -> 2850 | H41: 50 | J41: 0 | K41: =+D41/$L$2*I41 -> 0 | L41: =(+G41/$L$2/8/60)*H41 -> 9.8958333
B42: =+B41+1 -> 37 | C42: BURGA MUÑOZ HELDER ALEXANDER | D42: 1700 | G42: =+D42+E42 -> 1700 | H42: 38 | J42: 0 | K42: =+D42/$L$2*I42 -> 0 | L42: =(+G42/$L$2/8/60)*H42 -> 4.4861111
B43: =+B42+1 -> 38 | C43: JUÑO FUENTEZ STEFANIA BRISEIDA | D43: 2000 | E43: 113 | G43: =+D43+E43 -> 2113 | J43: 0 | K43: =+D43/$L$2*I43 -> 0 | L43: =(+G43/$L$2/8/60)*H43 -> 0
B44: =+B43+1 -> 39 | C44: RIVERA CORRALES JUAN EDUARDO | D44: 2800 | G44: =+D44+E44 -> 2800 | H44: 40 | J44: 0 | K44: =+D44/$L$2*I44 -> 0 | L44: =(+G44/$L$2/8/60)*H44 -> 7.7777778
B45: =+B44+1 -> 40 | C45: MELO HUAMAN CARLOS MANUEL | D45: 1400 | G45: =+D45+E45 -> 1400 | H45: =60+25 -> 85 | J45: 0 | K45: =+D45/$L$2*I45 -> 0 | L45: =(+G45/$L$2/8/60)*H45 -> 8.2638889
B46: =+B45+1 -> 41 | C46: FARFAN LAUREL CIELO CARMIN | D46: 2000 | G46: =+D46+E46 -> 2000 | J46: 0 | K46: =+D46/$L$2*I46 -> 0 | L46: =(+G46/$L$2/8/60)*H46 -> 0
B47: =+B46+1 -> 42 | C47: ORTIZ PAREDES CESAR PAUL | D47: 1200 | E47: 113 | G47: =+D47+E47 -> 1313 | H47: 39 | J47: 0 | K47: =+D47/$L$2*I47 -> 0 | L47: =(+G47/$L$2/8/60)*H47 -> 3.5560417
B48: =+B47+1 -> 43 | C48: PAREDES CHAMOCHUMBI ANA GABRIEL | D48: 2000 | G48: =+D48+E48 -> 2000 | H48: 16 | J48: 0 | K48: =+D48/$L$2*I48 -> 0 | L48: =(+G48/$L$2/8/60)*H48 -> 2.2222222

Sheet Hoja3
A1: 1 | B1: 2 | H1: 6 | K1: 14
A3: R.U.C.: 20514706302
B8: TRABAJADOR | H8: DATOS DEL PERSONAL
A9: N° | B9: APELLIDOS | D9: FECHA | E9: FECHA | F9: FECHA | H9: AFP | K9: REMUNER.
B10: PATERNO | C10: DNI, CE | D10: DE | E10: DE | F10: DE | G10: CARGO | H10: Y | I10: SUELDO BASE | J10: ASIG FAM | K10: PERCIBIDA | L10: SUELDO | M10: PLANILLA | N10: TASA | O10: PRIMA
D11: NACIMIENTO | E11: INGRESO | F11: CESE | H11: ONP | L11: MENSUAL | M11: PERIODO | N11: % | O11: NETA | P11: MENSUAL
A12: =+A11+1 -> 1 | B12: AREVALO ILATOMA ALBERTO | C12: 47291951 | D12: 33557 | E12: 44896 | G12: ASISTENTE CONTABLE | H12: PROFUTURO | I12: 2500 | K12: 2500 | L12: =+J12+K12 -> 2500 | M12: =+L12*12 -> 30000 | N12: 0.15 | O12: =+M12*N12/100 -> 45
A13: =+A12+1 -> 2 | B13: AREVALO VELA CESAR ANTONIO | C13: 71114663 | D13: 36860 | E13: 45658 | G13: ASISTENTE VENTAS | H13: PRIMA | I13: 1800 | K13: 1800 | L13: =+J13+K13 -> 1800 | M13: =+L13*12 -> 21600 | N13: 0.15 | O13: =+M13*N13/100 -> 32.4
A14: =+A13+1 -> 3 | B14: BALLLESTEROS DI SERI MARIA PAULA | C14: 09877161 | D14: 26434 | E14: 45474 | G14: RECEPCIONISTA | H14: PRIMA | I14: 2050 | K14: 2050 | L14: =+J14+K14 -> 2050 | M14: =+L14*12 -> 24600 | N14: 0.39 | O14: =+M14*N14/100 -> 95.94
A15: =+A14+1 -> 4 | B15: CASTILLO ENCARNACION MANUEL LEONIDAS | C15: 44030334 | D15: 31334 | E15: 44321 | G15: REPARTO | H15: PRIMA | I15: 2000 | J15: 113 | K15: 2000 | L15: =+J15+K15 -> 2113 | M15: =+L15*12 -> 25356 | N15: 0.39 | O15: =+M15*N15/100 -> 98.8884
A16: =+A15+1 -> 5 | B16: CORREIA DUARTE ALEXANDER | C16: 001216312 | D16: 29546 | E16: 45691 | G16: PRODUCT MANAGER | H16: PRIMA | I16: 3200 | J16: 113 | K16: 3200 | L16: =+J16+K16 -> 3313 | M16: =+L16*12 -> 39756 | N16: 0.39 | O16: =+M16*N16/100 -> 155.0484
A17: =+A16+1 -> 6 | B17: ECHEVARRIA SOTO JORGE LUIS | C17: 45538866 | D17: 32147 | E17: 42955 | G17: COORDINADOR COMERC IAL | H17: ONP | I17: 4500 | K17: 10158.54 | L17: =+J17+K17 -> 10158.54 | M17: =+L17*12 -> 121902.48 | N17: 0.39 | O17: =+M17*N17/100 -> 475.41967
A18: =+A17+1 -> 7 | B18: ESTRADA SANTOS JUAN MIGUEL | C18: 25849757 | E18: 45341 | G18: INGENIERIA COMERCIAL | H18: INTEGRA | I18: 2800 | J18: 113 | K18: =3570.16-113 -> 3457.16 | L18: =+J18+K18 -> 3570.16 | M18: =+L18*12 -> 42841.92 | N18: 0.39 | O18: =+M18*N18/100 -> 167.08349
A19: =+A18+1 -> 8 | B19: JIMENEZ PUYEN LUIS ANTONIO | C19: 06802763 | D19: 28259 | E19: 45698 | G19: ESPECIALISTA EN GESTION Y SST | H19: ONP | I19: 2800 | K19: 2800 | L19: =+J19+K19 -> 2800 | M19: =+L19*12 -> 33600 | N19: 0.39 | O19: =+M19*N19/100 -> 131.04
A20: =+A19+1 -> 9 | B20: LOBO QUISPE ELISA FIORELLA | C20: 43415173 | D20: 31380 | E20: 45005 | G20: ASISTENTE ADMINISTRATIVO | H20: INTEGRA | I20: 3000 | K20: 3000 | L20: =+J20+K20 -> 3000 | M20: =+L20*12 -> 36000 | N20: 0.39 | O20: =+M20*N20/100 -> 140.4
A21: =+A20+1 -> 10 | B21: LOLI RODRIGUEZ JANIO RICHARD | C21: 41675364 | D21: 29556 | E21: 42513 | G21: COORDINADOR DE SOPORTE TECNICO | H21: INTEGRA | I21: 4000 | J21: 113 | K21: 4000 | L21: =+J21+K21 -> 4113 | M21: =+L21*12 -> 49356 | N21: 0.39 | O21: =+M21*N21/100 -> 192.4884
A22: =+A21+1 -> 11 | B22: LUGO YAGUARACUTO JORGE DEYVIS | C22: 003488571 | D22: 31311 | E22: 45512 | G22: ASISTENTE DE ALMACEN | H22: INTEGRA | I22: 1600 | J22: 113 | K22: 1600 | L22: =+J22+K22 -> 1713 | M22: =+L22*12 -> 20556 | N22: 0.39 | O22: =+M22*N22/100 -> 80.1684
A23: =+A22+1 -> 12 | B23: MARTINEZ CASTILLO GIOVANNA RAQUEL | C23: 9594953 | D23: 26364 | E23: 41548 | G23: JEFE DE ADMINISTRACION | H23: PROFUTURO | I23: 6000 | J23: 113 | K23: 6000 | L23: =+J23+K23 -> 6113 | M23: =+L23*12 -> 73356 | N23: 0.39 | O23: =+M23*N23/100 -> 286.0884
A24: =+A23+1 -> 13 | B24: MONTOYA MEDRANO ANDREA BELEN JOSEPHINE | C24: 71127068 | D24: 34500 | E24: 43045 | G24: ASISTENTE DE GERENCIA | H24: ONP | I24: 2100 | K24: 2100 | L24: =+J24+K24 -> 2100 | M24: =+L24*12 -> 25200 | N24: 0.15 | O24: =+M24*N24/100 -> 37.8
A25: =+A24+1 -> 14 | B25: OCAMPO ORTEGA JEAN PAUL | C25: 73231901 | D25: 34632 | E25: 45537 | G25: ASISTENTE DE SOPORTE TECNICO | H25: PRIMA | I25: 1700 | K25: 1700 | L25: =+J25+K25 -> 1700 | M25: =+L25*12 -> 20400 | N25: 0.15 | O25: =+M25*N25/100 -> 30.6
A26: =+A25+1 -> 15 | B26: OLIVOS SAAVEDRA LANDHERT ANDERSON | C26: 73885455 | D26: 35803 | E26: 45581 | G26: ASISTENTE DE SOPORTE TECNICO | H26: INTEGRA | I26: 2000 | K26: 1800 | L26: =+J26+K26 -> 1800 | M26: =+L26*12 -> 21600 | N26: 0.15 | O26: =+M26*N26/100 -> 32.4
A27: =+A26+1 -> 16 | B27: ORDOÑEZ JULCA JESUS ORLANDO | C27: 47442636 | D27: 33567 | E27: 45691 | G27: PRODUCT MANAGER | H27: INTEGRA | I27: 3200 | K27: 3200 | L27: =+J27+K27 -> 3200 | M27: =+L27*12 -> 38400 | N27: 0.15 | O27: =+M27*N27/100 -> 57.6
A28: 1 | B28: ORIHUELA AGUIRRE ERNESTO JULIO | C28: 10305226 | D28: 27747 | E28: 39114 | G28: GERENTE GENERAL | H28: INTEGRA | I28: 12000 | J28: 113 | K28: =12027.91-113 -> 11914.91 | L28: =+J28+K28 -> 12027.91 | M28: =+L28*12 -> 144334.92 | N28: 0.39 | O28: =+M28*N28/100 -> 562.90619
A29: =+A28+1 -> 2 | B29: PEREZ CAJAHUANCA ARACELLI IRAIDA | C29: 44425022 | D29: 31996 | E29: 42917 | G29: COORDINADOR DE LOGISTICA | H29: INTEGRA | I29: 3360 | K29: 3360 | L29: =+J29+K29 -> 3360 | M29: =+L29*12 -> 40320 | N29: 0.39 | O29: =+M29*N29/100 -> 157.248
A30: =+A29+1 -> 3 | B30: PORTOCARRERO GOMEZ MARIA DEICY | C30: 42544684 | D30: 30874 | E30: 44697 | G30: LIMPIEZA | H30: PROFUTURO | I30: 1200 | J30: 113 | K30: 1200 | L30: =+J30+K30 -> 1313 | M30: =+L30*12 -> 15756 | N30: 0.39 | O30: =+M30*N30/100 -> 61.4484
A31: =+A30+1 -> 4 | B31: PORTOCARRERO TAFUR GLORI MAGRI | C31: 43172155 | D31: 31249 | E31: 42948 | G31: JEFE DE MARKETING Y CALIDAD | H31: INTEGRA | I31: 6000 | J31: 113 | K31: 6000 | L31: =+J31+K31 -> 6113 | M31: =+L31*12 -> 73356 | N31: 0.39 | O31: =+M31*N31/100 -> 286.0884
A32: =+A31+1 -> 5 | B32: PORTOCARRERO TAFUR MARIA LOIDI | C32: 45654429 | D32: 30383 | E32: 45398 | G32: AUXILIAR DE ALMACEN | H32: ONP | I32: 1130 | K32: 1130 | L32: =+J32+K32 -> 1130 | M32: =+L32*12 -> 13560 | N32: 0.39 | O32: =+M32*N32/100 -> 52.884
A33: =+A32+1 -> 6 | B33: QUEVEDO SALAS LUIS ALBERTO | C33: 07882846 | D33: 26945 | E33: 44593 | G33: EJECUTIVO COMERCIAL | H33: PRIMA | I33: 3500 | J33: 113 | K33: =6895.21-113 -> 6782.21 | L33: =+J33+K33 -> 6895.21 | M33: =+L33*12 -> 82742.52 | N33: 0.39 | O33: =+M33*N33/100 -> 322.69583
A34: =+A33+1 -> 7 | B34: RAMOS ESPEJO JHONN MIGUEL | C34: 43831490 | D34: 31666 | E34: 45628 | G34: SUPERVISOR DE ALMACEN | H34: HABITAT | I34: 2800 | K34: 2800 | L34: =+J34+K34 -> 2800 | M34: =+L34*12 -> 33600 | N34: 0.39 | O34: =+M34*N34/100 -> 131.04
A35: =+A34+1 -> 8 | B35: RIOS HOLSEN JAIME JUNIOR | C35: 48335342 | D35: 34355 | E35: 45307 | G35: ASISTENTE DE SOPORTE TECNICO | H35: HABITAT | I35: 2000 | K35: 2000 | L35: =+J35+K35 -> 2000 | M35: =+L35*12 -> 24000 | N35: 0.15 | O35: =+M35*N35/100 -> 36
A36: =+A35+1 -> 9 | B36: SALAZAR VELASQUEZ HECTOR ALEXANDER | C36: 41995632 | D36: 30308 | E36: 45446 | G36: AUXILIAR DE ALMACEN | H36: ONP | I36: 2000 | J36: 113 | K36: 2000 | L36: =+J36+K36 -> 2113 | M36: =+L36*12 -> 25356 | N36: 0.39 | O36: =+M36*N36/100 -> 98.8884
A37: =+A36+1 -> 10 | B37: SALCEDO RIVAS DANIEL ALONSO | C37: 42953954 | D37: 31117 | E37: 45398 | G37: ASISTENTE LOGISTICO | H37: INTEGRA | I37: 2500 | J37: 113 | K37: 2500 | L37: =+J37+K37 -> 2613 | M37: =+L37*12 -> 31356 | N37: 0.39 | O37: =+M37*N37/100 -> 122.2884
A38: =+A37+1 -> 11 | B38: SALVADOR ROJAS ELVIS ALFONSO | C38: 46335654 | D38: 33029 | E38: 42327 | G38: SOPORTE TECNICO Y MANTENIMINENTO | H38: INTEGRA | I38: 3000 | J38: 113 | K38: 3000 | L38: =+J38+K38 -> 3113 | M38: =+L38*12 -> 37356 | N38: 0.15 | O38: =+M38*N38/100 -> 56.034
A39: =+A38+1 -> 12 | B39: SEGURA CHAVESTA CHRISTIAN GUILLERMO | C39: 72544254 | D39: 34906 | E39: 44972 | G39: ANALISTA DE PROYECTOS | H39: INTEGRA | I39: 2000 | K39: 2000 | L39: =+J39+K39 -> 2000 | M39: =+L39*12 -> 24000 | N39: 0.15 | O39: =+M39*N39/100 -> 36
A40: =+A39+1 -> 13 | B40: SICCHA ARCE LUIS FRANCISCO | C40: 73735818 | D40: 36161 | E40: 45689 | G40: EJECUTIVO COMERCIAL | H40: INTEGRA | I40: 2500 | K40: 2500 | L40: =+J40+K40 -> 2500 | M40: =+L40*12 -> 30000 | N40: 0.15 | O40: =+M40*N40/100 -> 45
A41: =+A40+1 -> 14 | B41: TUCTO PEREZ CESAR ANTONIO | C41: 46452115 | D41: 32383 | E41: 45658 | G41: ASISTENTE CONTABLE | H41: PRIMA | I41: 2400 | K41: 2400 | L41: =+J41+K41 -> 2400 | M41: =+L41*12 -> 28800 | N41: 0.15 | O41: =+M41*N41/100 -> 43.2
A42: =+A41+1 -> 15 | B42: VERGARA BALDEON GEANNINA LIZBETH | C42: 46497553 | D42: 33124 | E42: 44018 | G42: ESPECIALISTA EN MARKETING | H42: INTEGRA | I42: 2500 | K42: 2500 | L42: =+J42+K42 -> 2500 | M42: =+L42*12 -> 30000 | N42: 0.15 | O42: =+M42*N42/100 -> 45
A43: =+A42+1 -> 16 | B43: VIDAL MELO ALEX FERNANDO | C43: 70036224 | D43: 36115 | E43: 45306 | G43: EJECUTIVO COMERCIAL | H43: PRIMA | I43: 2000 | J43: 113 | K43: =2737.4-J43 -> 2624.4 | L43: =+J43+K43 -> 2737.4 | M43: =+L43*12 -> 32848.8 | N43: 0.15 | O43: =+M43*N43/100 -> 49.2732
A44: =+A43+1 -> 17 | B44: YUPANQUI SAMANIEGO RENATO LUIS | C44: 73952223 | D44: 10/09/200 | E44: 45627 | G44: ASISTENTE DE ALMACEN | H44: INTEGRA | I44: 2200 | K44: 2200 | L44: =+J44+K44 -> 2200 | M44: =+L44*12 -> 26400 | N44: 0.15 | O44: =+M44*N44/100 -> 39.6
A45: =+A44+1 -> 18 | B45: ZEVALLOS DELGADO LUIS EDUARDO | C45: 74450353 | D45: 34560 | E45: 45418 | G45: INGENIERIO TECNICO EN EL AREA DE VARIADORES | H45: INTEGRA | I45: 2000 | K45: 2000 | L45: =+J45+K45 -> 2000 | M45: =+L45*12 -> 24000 | N45: 0.15 | O45: =+M45*N45/100 -> 36
A46: =+A45+1 -> 19 | B46: TORRES VELA JOE RAMIRO | C46: 46544434 | D46: 33107 | E46: 45719 | G46: CHOFER | H46: PROFUTURO | I46: 1500 | K46: =50*29 -> 1450 | L46: =+J46+K46 -> 1450 | M46: =+L46*12 -> 17400 | O46: =+M46*N46/100 -> 0
A47: =+A46+1 -> 20 | B47: SILVA SANTISTEBAN RONAL JHUNIOR | C47: 48461873 | D47: 34304 | E47: 45719 | G47: TECNICO ELECTRICISTA | H47: INTEGRA | I47: 1700 | K47: 1700 | L47: =+J47+K47 -> 1700 | M47: =+L47*12 -> 20400 | O47: =+M47*N47/100 -> 0
K48: 2850 | L48: 2850 | M48: =+L48*12 -> 34200 | O48: =+M48*N48/100 -> 0
J50: =SUM(J12:J49) -> 1582 | K50: =SUM(K12:K49) -> 116277.22 | O50: =SUM(O12:O49) -> 4239.96
O52: 4239.96
O53: =+O52-O50 -> 2.4e-05

Sheet TRANSF

Sheet DIARIO
A1: INDUSTRIAL PROCESS
A3: COMPROBANTE
A4: Sub-Diario: P | C4: Moneda: MN
A5: Comprobante: 030001 | C5: Conversion: S
A6: Concepto: PROVISION PLANILLA MES ABRIL 2023 | C6: Tipo de Cambio: 3.829 | F6: Usuario: | G6: LTP
F7: IMPORTES | G7: IMPORTES
A8: Cuenta | B8: Descripción Cuenta | C8: Anexo | D8: Descripcion Anexo | E8: CC | F8: Debe | G8: Haber | H8: TD | I8: Nro. Doc. | J8: Fecha | K8: Glosa
A9: 62101001 | B9: SUELDOS | D9: ADM | E9: K0011 | F9: =+'[9]PLANILLA MENSUAL'!Q64 -> 9130 | G9: 0 | H9: 00 | I9: 003-2025 | J9: 45747 | K9: PROVISION PLANILLA MES MARZO 2025
A10: 62201001 | B10: ASIGNACION FAMILIAR | D10: ADM | E10: K0011 | F10: =+'[9]PLANILLA MENSUAL'!R64 -> 226 | G10: 0 | H10: 00 | I10: 003-2025 | J10: 45747 | K10: PROVISION PLANILLA MES MARZO 2025
A11: 62201007 | B11: PLANILLA MOVILIDAD | D11: ADM | E11: K0011 | F11: =+'[9]PLANILLA MENSUAL'!X64 -> 100 | G11: 0 | H11: 00 | I11: 003-2025 | J11: 45747 | K11: PROVISION PLANILLA MES MARZO 2025
A12: 62701001 | B12: REGIMEN DE PRESTACIONES DE SALUD | D12: ADM | E12: K0011 | F12: =+'[9]PLANILLA MENSUAL'!BI64 -> 842.04 | G12: 0 | H12: 00 | I12: 003-2025 | J12: 45747 | K12: PROVISION PLANILLA MES MARZO 2025
A14: 62101001 | B14: SUELDOS | D14: CONTA | E14: K0012 | F14: =+'[9]PLANILLA MENSUAL'!Q65 -> 8300 | G14: 0 | H14: 00 | I14: 003-2025 | J14: 45747 | K14: PROVISION PLANILLA MES MARZO 2025
A15: 62201007 | B15: PLANILLA MOVILIDAD | D15: CONTA | E15: K0012 | F15: =+'[9]PLANILLA MENSUAL'!X65 -> 100 | G15: 0 | H15: 00 | I15: 003-2025 | J15: 45747 | K15: PROVISION PLANILLA MES MARZO 2025
A16: 62701001 | B16: REGIMEN DE PRESTACIONES DE SALUD | D16: CONTA | E16: K0012 | F16: =+'[9]PLANILLA MENSUAL'!BI65 -> 747 | G16: 0 | H16: 00 | I16: 003-2025 | J16: 45747 | K16: PROVISION PLANILLA MES MARZO 2025
A18: 62101001 | B18: SUELDOS | D18: LOGISTICA | E18: K0013 | F18: =+'[9]PLANILLA MENSUAL'!Q66 -> 4960 | G18: 0 | H18: 00 | I18: 003-2025 | J18: 45747 | K18: PROVISION PLANILLA MES MARZO 2025
A19: 62201007 | B19: PLANILLA MOVILIDAD | D19: LOGISTICA | E19: K0013 | F19: =+'[9]PLANILLA MENSUAL'!X66 -> 76.190476 | G19: 0 | H19: 00 | I19: 003-2025 | J19: 45747 | K19: PROVISION PLANILLA MES MARZO 2025
A20: 62701001 | B20: REGIMEN DE PRESTACIONES DE SALUD | D20: LOGISTICA | E20: K0013 | F20: =+'[9]PLANILLA MENSUAL'!BI66 -> 579.6 | G20: 0 | H20: 00 | I20: 003-2025 | J20: 45747 | K20: PROVISION PLANILLA MES MARZO 2025
A22: 62101002 | B22: SUELDOS | D22: VENTAS | E22: K0021 | F22: =+'[9]PLANILLA MENSUAL'!Q68 -> 38800 | G22: 0 | H22: 00 | I22: 003-2025 | J22: 45747 | K22: PROVISION PLANILLA MES MARZO 2025
A23: 62201002 | B23: ASIGNACION FAMILIAR | D23: VENTAS | E23: K0021 | F23: =+'[9]PLANILLA MENSUAL'!R68 -> 452 | G23: 0 | H23: 00 | I23: 003-2025 | J23: 45747 | K23: PROVISION PLANILLA MES MARZO 2025
A24: 62102002 | B24: COMISIONES DEL PERIODO | D24: VENTAS | E24: K0021 | F24: =+'[9]PLANILLA MENSUAL'!S68 -> 23159.637 | G24: 0 | H24: 00 | I24: 003-2025 | J24: 45747 | K24: PROVISION PLANILLA MES MARZO 2025
A25: 62701002 | B25: REGIMEN DE PRESTACIONES DE SALUD | D25: VENTAS | E25: K0021 | F25: =+'[9]PLANILLA MENSUAL'!BI68 -> 5689.0473 | G25: 0 | H25: 00 | I25: 003-2025 | J25: 45747 | K25: PROVISION PLANILLA MES MARZO 2025
A27: 62101002 | B27: SUELDOS | D27: SOPORTE | E27: K0022 | F27: =+'[9]PLANILLA MENSUAL'!Q69 -> 19300 | G27: 0 | H27: 00 | I27: 003-2025 | J27: 45747 | K27: PROVISION PLANILLA MES MARZO 2025
A28: 62201002 | B28: ASIGNACION FAMILIAR | D28: SOPORTE | E28: K0022 | F28: =+'[9]PLANILLA MENSUAL'!R69 -> 339 | G28: 0 | H28: 00 | I28: 003-2025 | J28: 45747 | K28: PROVISION PLANILLA MES MARZO 2025
A29: 62101004 | B29: HORAS EXTRAS | D29: SOPORTE | E29: K0022 | F29: =+'[9]PLANILLA MENSUAL'!U69+'[9]PLANILLA MENSUAL'!V69 -> 0 | G29: 0 | H29: 00 | I29: 003-2025 | J29: 45747 | K29: PROVISION PLANILLA MES MARZO 2025
A30: 62201008 | B30: PLANILLA MOVILIDAD | D30: SOPORTE | E30: K0022 | F30: =+'[9]PLANILLA MENSUAL'!X69 -> 100 | G30: 0 | H30: 00 | I30: 003-2025 | J30: 45747 | K30: PROVISION PLANILLA MES MARZO 2025
A31: 62701002 | B31: REGIMEN DE PRESTACIONES DE SALUD | D31: SOPORTE | E31: K0022 | F31: =+'[9]PLANILLA MENSUAL'!BI69 -> 1767.51 | G31: 0 | H31: 00 | I31: 003-2025 | J31: 45747 | K31: PROVISION PLANILLA MES MARZO 2025
A33: 62101002 | B33: SUELDOS | D33: PROYECTO | E33: K0023 | F33: =+'[9]PLANILLA MENSUAL'!Q70 -> 3200 | G33: 0 | H33: 00 | I33: 003-2025 | J33: 45747 | K33: PROVISION PLANILLA MES MARZO 2025
A34: 62701002 | B34: REGIMEN DE PRESTACIONES DE SALUD | D34: PROYECTO | E34: K0023 | F34: =+'[9]PLANILLA MENSUAL'!BI70 -> 288 | G34: 0 | H34: 00 | I34: 003-2025 | J34: 45747 | K34: PROVISION PLANILLA MES MARZO 2025
A36: 62101002 | B36: SUELDOS | D36: MARKETING | E36: K0024 | F36: =+'[9]PLANILLA MENSUAL'!Q71 -> 12050 | G36: 0 | H36: 00 | I36: 003-2025 | J36: 45747 | K36: PROVISION PLANILLA MES MARZO 2025
A37: 62201002 | B37: ASIGNACION FAMILIAR | D37: MARKETING | E37: K0024 | F37: =+'[9]PLANILLA MENSUAL'!R71 -> 113 | G37: 0 | H37: 00 | I37: 003-2025 | J37: 45747 | K37: PROVISION PLANILLA MES MARZO 2025
A38: 62701002 | B38: REGIMEN DE PRESTACIONES DE SALUD | D38: MARKETING | E38: K0024 | F38: =+'[9]PLANILLA MENSUAL'!BI71 -> 1114.245 | G38: 0 | H38: 00 | I38: 003-2025 | J38: 45747 | K38: PROVISION PLANILLA MES MARZO 2025
A40: 62101002 | B40: SUELDOS | D40: ALMACEN | E40: K0025 | F40: =+'[9]PLANILLA MENSUAL'!Q72 -> 13006.967 | G40: 0 | H40: 00 | I40: 003-2025 | J40: 45747 | K40: PROVISION PLANILLA MES MARZO 2025
A41: 62201002 | B41: ASIGNACION FAMILIAR | D41: ALMACEN | E41: K0025 | F41: =+'[9]PLANILLA MENSUAL'!R72 -> 452 | G41: 0 | H41: 00 | I41: 003-2025 | J41: 45747 | K41: PROVISION PLANILLA MES MARZO 2025
A42: 62101004 | B42: HORAS EXTRAS | D42: ALMACEN | E42: K0025 | F42: =+'[9]PLANILLA MENSUAL'!U72+'[9]PLANILLA MENSUAL'!V72 -> 0 | G42: 0 | H42: 00 | I42: 003-2025 | J42: 45747 | K42: PROVISION PLANILLA MES MARZO 2025
A43: 62201008 | B43: PLANILLA MOVILIDAD | D43: ALMACEN | E43: K0025 | F43: =+'[9]PLANILLA MENSUAL'!X72 -> 100 | G43: 0 | H43: 00 | I43: 003-2025 | J43: 45747 | K43: PROVISION PLANILLA MES MARZO 2025
A44: 62701002 | B44: REGIMEN DE PRESTACIONES DE SALUD | D44: ALMACEN | E44: K0025 | F44: =+'[9]PLANILLA MENSUAL'!BI72 -> 1249.38 | G44: 0 | H44: 00 | I44: 003-2025 | J44: 45747 | K44: PROVISION PLANILLA MES MARZO 2025
A46: 14111001 | B46: PRESTAMOS DE PERSONAL EMPLEADOS M.N. | C46: 44030334 | D46: CASTILLO ENCARNACION MANUEL LEONIDAS | G46: =+'[9]PLANILLA MENSUAL'!AZ21 -> 500 | H46: 00 | I46: 14496 | J46: 45747 | K46: PROVISION PLANILLA MES MARZO 2025
A47: 14111001 | B47: PRESTAMOS DE PERSONAL EMPLEADOS M.N. | C47: 74450353 | D47: ZEVALLOS DELGADO LUIS EDUARDO | G47: =+'[9]PLANILLA MENSUAL'!AZ30 -> 500 | H47: 00 | I47: 012-2024 | J47: 45747 | K47: PROVISION PLANILLA MES MARZO 2025
A48: 14121001 | B48: ADELANTO DE REMUNERACION DE PERSONAL M.N | C48: 10305226 | D48: ORIHUELA AGUIRRE ERNESTO JULIO | G48: =+'[9]PLANILLA MENSUAL'!AY12 -> 10338.515 | H48: 00 | I48: 003-2025 | J48: 45747 | K48: PROVISION PLANILLA MES MARZO 2025
A49: 14121001 | B49: ADELANTO DE REMUNERACION DE PERSONAL M.N | C49: 09594953 | D49: MARTINEZ CASTILLO GIOVANNA RAQUEL | G49: =+'[9]PLANILLA MENSUAL'!AY13 -> 3565.9167 | H49: 00 | I49: 003-2025 | J49: 45747 | K49: PROVISION PLANILLA MES MARZO 2025
A50: 14121001 | B50: ADELANTO DE REMUNERACION DE PERSONAL M.N | C50: 46335654 | D50: SALVADOR ROJAS ELVIS ALFONSO | G50: =+'[9]PLANILLA MENSUAL'!AY14 -> 2410.1267 | H50: 00 | I50: 003-2025 | J50: 45747 | K50: PROVISION PLANILLA MES MARZO 2025
A51: 14121001 | B51: ADELANTO DE REMUNERACION DE PERSONAL M.N | C51: 41675364 | D51: LOLI RODRIGUEZ JANIO RICHARD | G51: =+'[9]PLANILLA MENSUAL'!AY15 -> 2399.25 | H51: 00 | I51: 003-2025 | J51: 45747 | K51: PROVISION PLANILLA MES MARZO 2025
A52: 14121001 | B52: ADELANTO DE REMUNERACION DE PERSONAL M.N | C52: 44425022 | D52: PEREZ CAJAHUANCA ARACELLI IRAIDA | G52: =+'[9]PLANILLA MENSUAL'!AY16 -> 2302.2222 | H52: 00 | I52: 003-2025 | J52: 45747 | K52: PROVISION PLANILLA MES MARZO 2025
A53: 14121001 | B53: ADELANTO DE REMUNERACION DE PERSONAL M.N | C53: 43172155 | D53: PORTOCARRERO TAFUR GLORI MAGRI | G53: =+'[9]PLANILLA MENSUAL'!AY17 -> 3565.9167 | H53: 00 | I53: 003-2025 | J53: 45747 | K53: PROVISION PLANILLA MES MARZO 2025
A54: 14121001 | B54: ADELANTO DE REMUNERACION DE PERSONAL M.N | C54: 45538866 | D54: ECHEVARRIA SOTO JORGE LUIS | G54: =+'[9]PLANILLA MENSUAL'!AY18 -> 7206.1772 | H54: 00 | I54: 003-2025 | J54: 45747 | K54: PROVISION PLANILLA MES MARZO 2025
A55: 14121001 | B55: ADELANTO DE REMUNERACION DE PERSONAL M.N | C55: 71127068 | D55: MONTOYA MEDRANO ANDREA BELEN JOSEPHINE | G55: =+'[9]PLANILLA MENSUAL'!AY19 -> 1625 | H55: 00 | I55: 003-2025 | J55: 45747 | K55: PROVISION PLANILLA MES MARZO 2025
A56: 14121001 | B56: ADELANTO DE REMUNERACION DE PERSONAL M.N | C56: 46497553 | D56: VERGARA BALDEON GEANNINA LIZBETH | G56: =+'[9]PLANILLA MENSUAL'!AY20 -> 1458.3333 | H56: 00 | I56: 003-2025 | J56: 45747 | K56: PROVISION PLANILLA MES MARZO 2025
A57: 14121001 | B57: ADELANTO DE REMUNERACION DE PERSONAL M.N | C57: 44030334 | D57: CASTILLO ENCARNACION MANUEL LEONIDAS | G57: =+'[9]PLANILLA MENSUAL'!AY21 -> 1232.5833 | H57: 00 | I57: 003-2025 | J57: 45747 | K57: PROVISION PLANILLA MES MARZO 2025
A58: 14121001 | B58: ADELANTO DE REMUNERACION DE PERSONAL M.N | C58: 07882846 | D58: QUEVEDO SALAS LUIS ALBERTO | G58: =+'[9]PLANILLA MENSUAL'!AY22 -> 3536.7371 | H58: 00 | I58: 003-2025 | J58: 45747 | K58: PROVISION PLANILLA MES MARZO 2025
A59: 14121001 | B59: ADELANTO DE REMUNERACION DE PERSONAL M.N | C59: 42544684 | D59: PORTOCARRERO GOMEZ MARIA DEICY | G59: =+'[9]PLANILLA MENSUAL'!AY23 -> 765.91667 | H59: 00 | I59: 003-2025 | J59: 45747 | K59: PROVISION PLANILLA MES MARZO 2025
A60: 14121001 | B60: ADELANTO DE REMUNERACION DE PERSONAL M.N | C60: 47291951 | D60: AREVALO ILATOMA ALBERTO | G60: =+'[9]PLANILLA MENSUAL'!AY24 -> 1633.3333 | H60: 00 | I60: 003-2025 | J60: 45747 | K60: PROVISION PLANILLA MES MARZO 2025
A61: 14121001 | B61: ADELANTO DE REMUNERACION DE PERSONAL M.N | C61: 72544254 | D61: SEGURA CHAVESTA CHRISTIAN GUILLERMO | G61: =+'[9]PLANILLA MENSUAL'!#REF! -> #REF! | H61: 00 | I61: 003-2025 | J61: 45747 | K61: PROVISION PLANILLA MES MARZO 2025
A62: 14121001 | B62: ADELANTO DE REMUNERACION DE PERSONAL M.N | C62: 43415173 | D62: LOBO QUISPE ELISA FIORELLA | G62: =+'[9]PLANILLA MENSUAL'!AY25 -> 1750 | H62: 00 | I62: 003-2025 | J62: 45747 | K62: PROVISION PLANILLA MES MARZO 2025
A63: 14121001 | B63: ADELANTO DE REMUNERACION DE PERSONAL M.N | C63: 48335342 | D63: RIOS HOLSEN JAIME JUNIOR | G63: =+'[9]PLANILLA MENSUAL'!AY26 -> 1633.3333 | H63: 00 | I63: 003-2025 | J63: 45747 | K63: PROVISION PLANILLA MES MARZO 2025
A64: 14121001 | B64: ADELANTO DE REMUNERACION DE PERSONAL M.N | C64: 25849757 | D64: ESTRADA SANTOS JUAN MIGUEL | G64: =+'[9]PLANILLA MENSUAL'!AY27 -> 2739.7348 | H64: 00 | I64: 003-2025 | J64: 45747 | K64: PROVISION PLANILLA MES MARZO 2025
A65: 14121001 | B65: ADELANTO DE REMUNERACION DE PERSONAL M.N | C65: 42953954 | D65: SALCEDO RIVAS DANIEL ALONSO | G65: =+'[9]PLANILLA MENSUAL'!AY28 -> 1524.25 | H65: 00 | I65: 003-2025 | J65: 45747 | K65: PROVISION PLANILLA MES MARZO 2025
A66: 14121001 | B66: ADELANTO DE REMUNERACION DE PERSONAL M.N | C66: 45654429 | D66: PORTOCARRERO TAFUR MARIA LOIDI | G66: =+'[9]PLANILLA MENSUAL'!AY29 -> 659.16667 | H66: 00 | I66: 003-2025 | J66: 45747 | K66: PROVISION PLANILLA MES MARZO 2025
A67: 14121001 | B67: ADELANTO DE REMUNERACION DE PERSONAL M.N | C67: 74450353 | D67: ZEVALLOS DELGADO LUIS EDUARDO | G67: =+'[9]PLANILLA MENSUAL'!AY30 -> 1465.2415 | H67: 00 | I67: 003-2025 | J67: 45747 | K67: PROVISION PLANILLA MES MARZO 2025
A68: 14121001 | B68: ADELANTO DE REMUNERACION DE PERSONAL M.N | C68: 09877161 | D68: BALLLESTEROS DI SERI MARIA PAULA | G68: =+'[9]PLANILLA MENSUAL'!AY31 -> 1458.3333 | H68: 00 | I68: 003-2025 | J68: 45747 | K68: PROVISION PLANILLA MES MARZO 2025
A69: 14121001 | B69: ADELANTO DE REMUNERACION DE PERSONAL M.N | C69: 73231901 | D69: OCAMPO ORTEGA JEAN PAUL | G69: =+'[9]PLANILLA MENSUAL'!AY32 -> 1171.5093 | H69: 00 | I69: 003-2025 | J69: 45747 | K69: PROVISION PLANILLA MES MARZO 2025
A70: 14121001 | B70: ADELANTO DE REMUNERACION DE PERSONAL M.N | C70: 73885455 | D70: OLIVOS SAAVEDRA LANDHERT ANDERSON | G70: =+'[9]PLANILLA MENSUAL'!AY33 -> 1173.3507 | H70: 00 | I70: 003-2025 | J70: 45747 | K70: PROVISION PLANILLA MES MARZO 2025
A71: 14121001 | B71: ADELANTO DE REMUNERACION DE PERSONAL M.N | C71: 73952223 | D71: YUPANQUI SAMANIEGO RENATO LUIS | G71: =+'[9]PLANILLA MENSUAL'!AY34 -> 1283.3333 | H71: 00 | I71: 003-2025 | J71: 45747 | K71: PROVISION PLANILLA MES MARZO 2025
A72: 14121001 | B72: ADELANTO DE REMUNERACION DE PERSONAL M.N | C72: 46452115 | D72: TUCTO PEREZ CESAR ANTONIO | G72: =+'[9]PLANILLA MENSUAL'!AY35 -> 1458.3333 | H72: 00 | I72: 003-2025 | J72: 45747 | K72: PROVISION PLANILLA MES MARZO 2025
A73: 14121001 | B73: ADELANTO DE REMUNERACION DE PERSONAL M.N | C73: 71114663 | D73: AREVALO VELA CESAR ANTONIO | G73: =+'[9]PLANILLA MENSUAL'!AY36 -> 2212.0566 | H73: 00 | I73: 003-2025 | J73: 45747 | K73: PROVISION PLANILLA MES MARZO 2025
A74: 14121001 | B74: ADELANTO DE REMUNERACION DE PERSONAL M.N | C74: 73735818 | D74: SICCHA ARCE LUIS FRANCISCO | G74: =+'[9]PLANILLA MENSUAL'!AY37 -> 2182.273 | H74: 00 | I74: 003-2025 | J74: 45747 | K74: PROVISION PLANILLA MES MARZO 2025
A75: 14121001 | B75: ADELANTO DE REMUNERACION DE PERSONAL M.N | C75: 47442636 | D75: ORDOÑEZ JULCA JESUS ORLANDO | G75: =+'[9]PLANILLA MENSUAL'!#REF! -> #REF! | H75: 00 | I75: 003-2025 | J75: 45747 | K75: PROVISION PLANILLA MES MARZO 2025
A76: 14121001 | B76: ADELANTO DE REMUNERACION DE PERSONAL M.N | C76: 06802763 | D76: JIMENEZ PUYEN LUIS ANTONIO | G76: =+'[9]PLANILLA MENSUAL'!AY38 -> 1633.3333 | H76: 00 | I76: 003-2025 | J76: 45747 | K76: PROVISION PLANILLA MES MARZO 2025
A77: 14121001 | B77: ADELANTO DE REMUNERACION DE PERSONAL M.N | C77: 48461873 | D77: SILVA SANTISTEBAN RONAL JHUNIOR | G77: =+'[9]PLANILLA MENSUAL'!AY39 -> 999.86431 | H77: 00 | I77: 003-2025 | J77: 45747 | K77: PROVISION PLANILLA MES MARZO 2025
A85: 14191001 | B85: OTROS CUENTAS POR COBRAR AL PERSONAL | C85: 20332970411 | D85: PACIFICO COMPAÑÍA DE SEGUROS | G85: =+'[9]PLANILLA MENSUAL'!#REF! -> #REF! | H85: 01 | I85: F090-118980 | J85: 45747 | K85: PROVISION PLANILLA MES MARZO 2025 | N85: 10305226 | O85: ORIHUELA AGUIRRE ERNESTO JULIO | R85: 302.92 | S85: =+G85-R85 -> #REF!
A86: 14191001 | B86: OTROS CUENTAS POR COBRAR AL PERSONAL | C86: 20332970411 | D86: PACIFICO COMPAÑÍA DE SEGUROS | G86: =+'[9]PLANILLA MENSUAL'!#REF! -> #REF! | H86: 01 | I86: F072-5022558 | J86: 45747 | K86: PROVISION PLANILLA MES MARZO 2025 | N86: 9594953 | O86: MARTINEZ CASTILLO GIOVANNA RAQUEL | R86: =543.33/2 -> 271.665 | S86: =+G86-R86 -> #REF!
A87: 14191001 | B87: OTROS CUENTAS POR COBRAR AL PERSONAL | C87: 20332970411 | D87: PACIFICO COMPAÑÍA DE SEGUROS | G87: =+'[9]PLANILLA MENSUAL'!#REF! -> #REF! | H87: 01 | I87: F077-384221 | J87: 45747 | K87: PROVISION PLANILLA MES MARZO 2025 | N87: 44425022 | O87: PEREZ CAJAHUANCA ARACELLI IRAIDA | R87: 158.34 | S87: =+G87-R87 -> #REF!
A88: 14191001 | B88: OTROS CUENTAS POR COBRAR AL PERSONAL | C88: 20332970411 | D88: PACIFICO COMPAÑÍA DE SEGUROS | G88: =+'[9]PLANILLA MENSUAL'!#REF! -> #REF! | H88: 01 | I88: F072-5022561 | J88: 45747 | K88: PROVISION PLANILLA MES MARZO 2025 | N88: 43172155 | O88: PORTOCARRERO TAFUR GLORI MAGRI | R88: 285 | S88: =+G88-R88 -> #REF!
A89: 14191001 | B89: OTROS CUENTAS POR COBRAR AL PERSONAL | C89: 45654429 | D89: PORTOCARRERO TAFUR MARIA LOIDI | G89: =+'[9]PLANILLA MENSUAL'!BB29 -> 0 | H89: 00 | I89: 003-2025 | J89: 45747 | K89: PROVISION PLANILLA MES MARZO 2025 | N89: CONSIDERAR RECIBO ENTEL
A90: 14121001 | B90: ADELANTO DE REMUNERACION DE PERSONAL M.N | C90: 74450353 | D90: ZEVALLOS DELGADO LUIS EDUARDO | G90: =+'[9]PLANILLA MENSUAL'!BB30 -> 0 | H90: 00 | I90: 011-2024 | J90: 45747 | K90: PROVISION PLANILLA MES MARZO 2025
A91: 40171003 | B91: RENTA DE QUINTA CATEGORIA | C91: 20131312955 | D91: SUNAT | G91: =+'[9]PLANILLA MENSUAL'!BE54 -> -11422.285 | H91: 00 | I91: 003-2025 | J91: 45747 | K91: PROVISION PLANILLA MES MARZO 2025
A92: 40311001 | B92: ESSALUD | C92: 20131312955 | D92: SUNAT | G92: =+'[9]PLANILLA MENSUAL'!AT66 -> 12926.042 | H92: 00 | I92: 003-2025 | J92: 45747 | K92: PROVISION PLANILLA MES MARZO 2025
A93: 40321001 | B93: ONP | C93: 20131312955 | D93: SUNAT | G93: =+'[9]PLANILLA MENSUAL'!AT65 -> 3018.4661 | H93: 00 | I93: 003-2025 | J93: 45747 | K93: PROVISION PLANILLA MES MARZO 2025
A94: 41701001 | B94: ADMIN DE FONDOS DE PENN - PRIMA | C94: 20510398158 | D94: PRIMA | G94: =+'[9]PLANILLA MENSUAL'!AT68 -> 4452.7932 | H94: 00 | I94: 003-2025 | J94: 45747 | K94: PROVISION PLANILLA MES MARZO 2025
A95: 41701002 | B95: ADMIN DE FONDOS PENS - INTEGRA | C95: 20157036794 | D95: INTEGRA | G95: =+'[9]PLANILLA MENSUAL'!AT69 -> 7711.222 | H95: 00 | I95: 003-2025 | J95: 45747 | K95: PROVISION PLANILLA MES MARZO 2025
A96: 41701003 | B96: ADMIN DE FONDOS DE PENN - PROFUTURO | C96: 20142829551 | D96: PROFUTURO | G96: =+'[9]PLANILLA MENSUAL'!AT70 -> 1404.8772 | H96: 00 | I96: 003-2025 | J96: 45747 | K96: PROVISION PLANILLA MES MARZO 2025
A97: 41701004 | B97: ADMIN DE FONDOS PENS - HABITAH | C97: 20551464971 | D97: HABITAH | G97: =+'[9]PLANILLA MENSUAL'!AT71 -> 626.8281 | H97: 00 | I97: 003-2025 | J97: 45747 | K97: PROVISION PLANILLA MES MARZO 2025
A98: 41101001 | B98: SUELDOS | C98: 10305226 | D98: ORIHUELA AGUIRRE ERNESTO JULIO | G98: =+'[9]PLANILLA MENSUAL'!BG12 -> 7600.217 | H98: 00 | I98: 003-2025 | J98: 45747 | K98: PROVISION PLANILLA MES MARZO 2025
A99: 41101001 | B99: SUELDOS | C99: 09594953 | D99: MARTINEZ CASTILLO GIOVANNA RAQUEL | G99: =+'[9]PLANILLA MENSUAL'!BG13 -> 2483.2015 | H99: 00 | I99: 003-2025 | J99: 45747 | K99: PROVISION PLANILLA MES MARZO 2025
A100: 41101001 | B100: SUELDOS | C100: 46335654 | D100: SALVADOR ROJAS ELVIS ALFONSO | G100: =+'[9]PLANILLA MENSUAL'!BG14 -> 1718.2538 | H100: 00 | I100: 003-2025 | J100: 45747 | K100: PROVISION PLANILLA MES MARZO 2025
A101: 41101001 | B101: SUELDOS | C101: 41675364 | D101: LOLI RODRIGUEZ JANIO RICHARD | G101: =+'[9]PLANILLA MENSUAL'!BG15 -> 1821.927 | H101: 00 | I101: 003-2025 | J101: 45747 | K101: PROVISION PLANILLA MES MARZO 2025
A102: 41101001 | B102: SUELDOS | C102: 44425022 | D102: PEREZ CAJAHUANCA ARACELLI IRAIDA | G102: =+'[9]PLANILLA MENSUAL'!BG16 -> 1975.2049 | H102: 00 | I102: 003-2025 | J102: 45747 | K102: PROVISION PLANILLA MES MARZO 2025
A103: 41101001 | B103: SUELDOS | C103: 43172155 | D103: PORTOCARRERO TAFUR GLORI MAGRI | G103: =+'[9]PLANILLA MENSUAL'!BG17 -> 1355.3326 | H103: 00 | I103: 003-2025 | J103: 45747 | K103: PROVISION PLANILLA MES MARZO 2025
A104: 41101001 | B104: SUELDOS | C104: 45538866 | D104: ECHEVARRIA SOTO JORGE LUIS | G104: =+'[9]PLANILLA MENSUAL'!BG18 -> 6474.1598 | H104: 00 | I104: 003-2025 | J104: 45747 | K104: PROVISION PLANILLA MES MARZO 2025
A105: 41101001 | B105: SUELDOS | C105: 71127068 | D105: MONTOYA MEDRANO ANDREA BELEN JOSEPHINE | G105: =+'[9]PLANILLA MENSUAL'!BG19 -> 1836.2975 | H105: 00 | I105: 003-2025 | J105: 45747 | K105: PROVISION PLANILLA MES MARZO 2025
A106: 41101001 | B106: SUELDOS | C106: 46497553 | D106: VERGARA BALDEON GEANNINA LIZBETH | G106: =+'[9]PLANILLA MENSUAL'!BG20 -> 1070.7666 | H106: 00 | I106: 003-2025 | J106: 45747 | K106: PROVISION PLANILLA MES MARZO 2025
A107: 41101001 | B107: SUELDOS | C107: 44030334 | D107: CASTILLO ENCARNACION MANUEL LEONIDAS | G107: =+'[9]PLANILLA MENSUAL'!BG21 -> 613.0039 | H107: 00 | I107: 003-2025 | J107: 45747 | K107: PROVISION PLANILLA MES MARZO 2025
A108: 41101001 | B108: SUELDOS | C108: 07882846 | D108: QUEVEDO SALAS LUIS ALBERTO | G108: =+'[9]PLANILLA MENSUAL'!BG22 -> 4262.5647 | H108: 00 | I108: 003-2025 | J108: 45747 | K108: PROVISION PLANILLA MES MARZO 2025
A109: 41101001 | B109: SUELDOS | C109: 42544684 | D109: PORTOCARRERO GOMEZ MARIA DEICY | G109: =+'[9]PLANILLA MENSUAL'!BG23 -> 719.6019 | H109: 00 | I109: 003-2025 | J109: 45747 | K109: PROVISION PLANILLA MES MARZO 2025
A110: 41101001 | B110: SUELDOS | C110: 47291951 | D110: AREVALO ILATOMA ALBERTO | G110: =+'[9]PLANILLA MENSUAL'!BG24 -> 1143.4047 | H110: 00 | I110: 003-2025 | J110: 45747 | K110: PROVISION PLANILLA MES MARZO 2025
A111: 41101001 | B111: SUELDOS | C111: 72544254 | D111: SEGURA CHAVESTA CHRISTIAN GUILLERMO | G111: =+'[9]PLANILLA MENSUAL'!#REF! -> #REF! | H111: 00 | I111: 003-2025 | J111: 45747 | K111: PROVISION PLANILLA MES MARZO 2025
A112: 41101001 | B112: SUELDOS | C112: 43415173 | D112: LOBO QUISPE ELISA FIORELLA | G112: =+'[9]PLANILLA MENSUAL'!BG25 -> 1331.9098 | H112: 00 | I112: 003-2025 | J112: 45747 | K112: PROVISION PLANILLA MES MARZO 2025
A113: 41101001 | B113: SUELDOS | C113: 48335342 | D113: RIOS HOLSEN JAIME JUNIOR | G113: =+'[9]PLANILLA MENSUAL'!BG26 -> 1366.095 | H113: 00 | I113: 003-2025 | J113: 45747 | K113: PROVISION PLANILLA MES MARZO 2025
A114: 41101001 | B114: SUELDOS | C114: 25849757 | D114: ESTRADA SANTOS JUAN MIGUEL | G114: =+'[9]PLANILLA MENSUAL'!BG27 -> 1836.1624 | H114: 00 | I114: 003-2025 | J114: 45747 | K114: PROVISION PLANILLA MES MARZO 2025
A115: 41101001 | B115: SUELDOS | C115: 42953954 | D115: SALCEDO RIVAS DANIEL ALONSO | G115: =+'[9]PLANILLA MENSUAL'!BG28 -> 1255.097 | H115: 00 | I115: 003-2025 | J115: 45747 | K115: PROVISION PLANILLA MES MARZO 2025
A116: 41101001 | B116: SUELDOS | C116: 45654429 | D116: PORTOCARRERO TAFUR MARIA LOIDI | G116: =+'[9]PLANILLA MENSUAL'!BG29 -> 470.74 | H116: 00 | I116: 003-2025 | J116: 45747 | K116: PROVISION PLANILLA MES MARZO 2025
...

Sheet HH.EE
C2: Sueldo | D2: Dia | E2: hora | F2: HORAS 25% | G2: HORAS 35% | H2: FERIADO/ DOMINICAL | I2: Total
B3: SALVADOR ROJAS ELVIS ALFONSO | C3: 4113 | D3: =C3/30 -> 137.1 | E3: =D3/8 -> 17.1375 | F3: =C23*E3*1.25 -> 267.77344 | G3: =E3*D23*1.35 -> 161.94938 | H3: =E3*E23*2 -> 976.8375 | I3: =SUM(F3:H3) -> 1406.5603
B4: OCAMPO ORTEGA JEAN PAUL | C4: 2500 | D4: =C4/30 -> 83.333333 | E4: =D4/8 -> 10.416667 | F4: =C24*E4*1.25 -> 240.88542 | G4: =E4*D24*1.35 -> 203.90625 | H4: =E4*E24*2 -> 979.16667 | I4: =SUM(F4:H4) -> 1423.9583
B5: OLIVOS SAAVEDRA LANDHERT ANDERSON | C5: 2500 | D5: =C5/30 -> 83.333333 | E5: =D5/8 -> 10.416667 | F5: =C25*E5*1.25 -> 286.45833 | G5: =E5*D25*1.35 -> 172.26562 | H5: =E5*E25*2 -> 333.33333 | I5: =SUM(F5:H5) -> 792.05729
B6: SILVA SANTISTEBAN RONAL JHUNIOR | C6: 2000 | D6: =C6/30 -> 66.666667 | E6: =D6/8 -> 8.3333333 | F6: =C26*E6*1.25 -> 151.04167 | G6: =E6*D26*1.35 -> 137.8125 | H6: =E6*E26*2 -> 608.33333 | I6: =SUM(F6:H6) -> 897.1875
B7: HIPOLITO GUANILO ARNOLD JIMMY | C7: 1613 | D7: =C7/30 -> 53.766667 | E7: =D7/8 -> 6.7208333 | F7: =C27*E7*1.25 -> 33.604167 | G7: =E7*D27*1.35 -> 31.755938 | H7: =E7*E27*2 -> 107.53333 | I7: =SUM(F7:H7) -> 172.89344
B8: ZEVALLOS DELGADO LUIS EDUARDO | C8: 2800 | D8: =C8/30 -> 93.333333 | E8: =D8/8 -> 11.666667 | F8: =C28*E8*1.25 -> 247.91667 | G8: =E8*D28*1.35 -> 236.25 | H8: =E8*E28*2 -> 618.33333 | I8: =SUM(F8:H8) -> 1102.5
B11: HORAS | C11: 0.25 | D11: 0.35 | E11: 1.25 | F11: 1.35 | G11: FERIADO/ DOMINICAL
B12: SALVADOR ROJAS ELVIS ALFONSO | C12: 8 | D12: 7 | E12: 4.5 | G12: 3
B13: JEAN PAUL OCAMPO ORTEGA | C13: 12 | D13: 14 | E13: 6.5 | F13: 0.5 | G13: 5
B14: ANDERSON OLIVOS SAAVEDRA | C14: 22 | D14: =(12*60+15)/60 -> 12.25 | G14: 2
B15: RONAL SILVA SANTISTEBAN | C15: 10 | D15: =(12*60+15)/60 -> 12.25 | E15: 4.5 | G15: 4
B16: JIMMY HIPOLITO | C16: 4 | D16: 3.5 | G16: 1
B17: LUIS ZEVALLOS DELGADO | C17: 15 | D17: 14.5 | E17: 2 | F17: 0.5 | G17: 3
B22: HORAS | C22: HORAS 25% | D22: HORAS 35% | E22: FERIADO/ DOMINICAL
B23: SALVADOR ROJAS ELVIS ALFONSO | C23: =C12+E12 -> 12.5 | D23: 7 | E23: 28.5
B24: JEAN PAUL OCAMPO ORTEGA | C24: =C13+E13 -> 18.5 | D24: =D13+F13 -> 14.5 | E24: 47
B25: ANDERSON OLIVOS SAAVEDRA | C25: =C14+E14 -> 22 | D25: =D14+F14 -> 12.25 | E25: 16
B26: RONAL SILVA SANTISTEBAN | C26: =C15+E15 -> 14.5 | D26: =D15+F15 -> 12.25 | E26: 36.5
B27: JIMMY HIPOLITO | C27: =C16+E16 -> 4 | D27: =D16+F16 -> 3.5 | E27: 8
B28: LUIS ZEVALLOS DELGADO | C28: =C17+E17 -> 17 | D28: =D17+F17 -> 15 | E28: 26.5
C31: 2500
B32: =5500*7 -> 38500 | C32: =C31*12 -> 30000 | D32: =C31+C31*9% -> 2725 | E32: =2000 -> 2000

Sheet PLANILLA BRUTA
C1: 1 | D1: 2 | E1: 3 | F1: 4 | G1: 5 | H1: 6 | I1: 7 | J1: 8 | K1: 9 | L1: 10 | M1: 11 | O1: 12 | P1: 13 | Q1: 14 | S1: 15 | T1: 16 | U1: 17 | V1: 18 | W1: 19 | X1: 20 | Y1: 21 | Z1: 22 | AB1: 23 | AD1: 24 | AE1: 25 | AF1: 26 | AG1: 27 | AH1: 28 | AI1: 29 | AJ1: 30 | AK1: 31 | AL1: 32 | AM1: 33 | AN1: 34 | AO1: 35 | AP1: 36 | AQ1: 37 | AR1: 38 | AS1: 39 | AU1: 40 | AX1: 41 | AY1: 42 | AZ1: 43 | BA1: 44 | BC1: 48 | BF1: 57 | BG1: 58 | BH1: 59 | BI1: 60 | BJ1: 61 | BK1: 62 | BL1: 63 | BM1: 64 | BN1: 65 | BO1: 66 | BP1: 67 | BQ1: 68 | BR1: 69 | BS1: 70 | BT1: 71 | BU1: 72 | BV1: 73 | BW1: 74 | BX1: 75 | BY1: 76 | BZ1: 77 | CA1: 78 | CB1: 79 | CC1: 80 | CD1: 81 | CE1: 82 | CF1: 83 | CG1: 84 | CH1: 85 | CI1: 86 | CJ1: 87 | CK1: 88 | CL1: 89 | CM1: 90 | CN1: 91 | CO1: 92 | CP1: 93 | CQ1: 94 | CR1: 95 | CS1: 96 | CT1: 97 | CU1: 98 | CV1: 99 | CW1: 100 | CX1: 101 | CY1: 102 | CZ1: 103 | DA1: 104 | DB1: 105 | DC1: 106 | DD1: 107 | DE1: 108 | DF1: 109 | DG1: 110 | DH1: 111 | DI1: 112 | DJ1: 113 | DK1: 114 | DL1: 115 | DM1: 116 | DN1: 117 | DO1: 118 | DP1: 119 | DQ1: 120 | DR1: 121 | DS1: 122 | DT1: 123 | DU1: 124 | DV1: 125 | DW1: 126 | DX1: 127 | DY1: 128 | DZ1: 129 | EA1: 130 | EB1: 131 | EC1: 132 | ED1: 133 | EE1: 134 | EF1: 135 | EG1: 136 | EH1: 137 | EI1: 138 | EJ1: 139 | EK1: 140 | EL1: 141 | EM1: 142 | EN1: 143 | EO1: 144 | EP1: 145 | EQ1: 146 | ER1: 147 | ES1: 148 | ET1: 149 | EU1: 150 | EV1: 151 | EW1: 152 | EX1: 153 | EY1: 154 | EZ1: 155 | FA1: 156 | FB1: 157 | FC1: 158
C2: SPECIES S.A.C.
C3: Nº 20550057451
C4: PLANILLA DE REMUNERACIONES MES DE JULIO DEL AÑO 2024
C6: (EXPRESADO EN NUEVOS SOLES)
D8: TRABAJADOR | H8: DATOS DEL PERSONAL | Q8: REMUNERACIONES | AH8: DESCUENTOS | AX8: TOTAL | AY8: NETO A | AZ8: APORTACION | BF8: (Se considero de adelanto (S/1149) | BG8: SE PAGO | BH8: SE DEBIO DE PAGAR
C9: N° | D9: APELLIDOS | F9: NOMBRES | H9: AFP | L9: FECHA | M9: FECHA | N9: FECHA | Q9: REMUNER. | R9: COMPRA DE VACACIONES | S9: ASIGNAC. | T9: HORAS | U9: HORAS | V9: FERIADOS | AC9: CANASTA | AD9: BONO | AF9: REMUNER | AG9: REMUNERA. | AH9: ONP | AJ9: A.F.P. | AR9: IMP.RTA.5 | AS9: ADELAN | AT9: GRATIF | AU9: PREST | AV9: DESCUENTO | AW9: DSCTO | AX9: DESCUENT. | AY9: PAGAR | AZ9: ESSALUD | BB9: SEGURO | BC9: HORAS
D10: PATERNO | E10: MATERNO | F10: PRIMER | G10: SEGUNDO | H10: Y | I10: CUPSS | J10: AUTOGENERADO | K10: DNI, CE | L10: DE | M10: DE | N10: DE | O10: AREA | P10: CARGO | Q10: BRUTA | S10: FAMILIAR | T10: EXTRAS | U10: EXTRAS | W10: MOVIL | X10: VACACIONES | Y10: GRATIFIC. | Z10: BONIF. | AA10: OTROS INGRESOS NO COMPU | AB10: CTS | AC10: NAVIDEÑA | AD10: EXTRAOR | AE10: DESC. | AF10: BRUTA | AG10: AFECTA | AH10: % | AI10: S/. | AJ10: APORTE OBLIG. | AL10: COMISION | AN10: PRIMA SEGURO | AP10: TOTAL A.F.P. | AT10: EXTRAOR | AV10: JUDICIAL | AW10: PAGO | BB10: VIDA LEY | BC10: LAB
H11: ONP | L11: INGRESO | M11: NACIMIENTO | N11: SALIDA | T11: 0.25 | U11: 0.35 | AD11: U OTRO | AJ11: % | AK11: S/. | AL11: % | AM11: S/. | AN11: % | AO11: S/. | AP11: % | AQ11: S/. | AW11: GRATIF | AZ11: % | BA11: S/.
A12: 1ER | C12: 1 | D12: BRETONECHE | E12: DIAPIS | F12: ANA | G12: LUCIA | H12: INTEGRA | I12: 636620ABDTP8 | K12: 47355900 | L12: 44849 | M12: 33664 | O12: RESTAURANT | P12: COCINERO | Q12: =2500 -> 2500 | S12: 102.5 | AF12: =SUM(Q12:AD12)-AE12 -> 2602.5 | AG12: =+Q12+S12+T12+U12+V12+X12-AE12 -> 2602.5 | AJ12: 0.1 | AK12: =+AG12*AJ12 -> 260.25 | AL12: 0 | AM12: =+AG12*AL12 -> 0 | AN12: 0.017 | AO12: =+AG12*AN12 -> 44.2425 | AP12: =+AJ12+AL12+AN12 -> 0.117 | AQ12: =+AK12+AM12+AO12 -> 304.4925 | AX12: =+AI12+AQ12+AR12+AS12+AT12+AU12+AW12 -> 304.4925 | AY12: =(+AF12-AX12) -> 2298.0075 | AZ12: 0.09 | BA12: =AG12*AZ12 -> 234.225 | BB12: 2.88 | BG12: 1302.21 | BH12: 1256.95 | BI12: =BH12-BG12 -> -45.26
A13: 1ER | C13: 2 | D13: MAMANI | E13: HUAMANI | F13: YAMIR | G13: JOSE | H13: INTEGRA | I13: 621701YMHAM9 | K13: 44895694 | L13: 44882 | M13: 32172 | O13: RESTAURANT | P13: LOGISTICA | Q13: 1000 | AF13: =SUM(Q13:AD13)-AE13 -> 1000 | AG13: =+Q13+S13+T13+U13+V13+X13-AE13 -> 1000 | AJ13: 0.1 | AK13: =+AG13*AJ13 -> 100 | AL13: 0.0155 | AM13: =+AG13*AL13 -> 15.5 | AN13: 0.017 | AO13: =+AG13*AN13 -> 17 | AP13: =+AJ13+AL13+AN13 -> 0.1325 | AQ13: =+AK13+AM13+AO13 -> 132.5 | AX13: =+AI13+AQ13+AR13+AS13+AT13+AU13+AW13 -> 132.5 | AY13: =(+AF13-AX13) -> 867.5 | AZ13: 0.09 | BA13: =AG13*AZ13 -> 90 | BB13: 1.44 | BD13: ok | BG13: 433.75 | BH13: 433.75 | BI13: =BH13-BG13 -> 0
A14: 1ER | C14: 3 | D14: VICENTE | E14: BLAS | F14: CALIXTO | K14: 8751792 | L14: 45078 | M14: 20663 | P14: CONDUCTOR | Q14: 834 | AE14: 41.67 | AF14: =SUM(Q14:AD14)-AE14 -> 792.33 | AG14: =+Q14+S14+T14+U14+V14+X14-AE14 -> 792.33 | AX14: =+AI14+AQ14+AR14+AS14+AT14+AU14+AW14 -> 0 | AY14: =(+AF14-AX14) -> 792.33 | AZ14: 0.09 | BA14: =AG14*AZ14 -> 71.3097 | BB14: 50.42 | BD14: ok | BG14: 500.34 | BH14: 458.67 | BI14: =BH14-BG14 -> -41.67 | BJ14: (Descontar en julio)
A15: 1ER | C15: 5 | D15: PINILLOS | E15: HIDALGO | F15: MARYORI | G15: XIMENA | H15: INTEGRA | I15: 670730MPHIA2 | K15: 73994129 | L15: 45384 | M15: 37075 | O15: RESTAURANT | P15: COCINERO | Q15: =1500 -> 1500 | AF15: =SUM(Q15:AD15)-AE15 -> 1500 | AG15: =+Q15+S15+T15+U15+V15+X15-AE15 -> 1500 | AJ15: 0.1 | AK15: =+AG15*AJ15 -> 150 | AL15: 0 | AN15: 0.017 | AO15: =+AG15*AN15 -> 25.5 | AP15: =+AJ15+AL15+AN15 -> 0.117 | AQ15: =+AK15+AM15+AO15 -> 175.5 | AX15: =+AI15+AQ15+AR15+AS15+AT15+AU15+AW15 -> 175.5 | AY15: =(+AF15-AX15) -> 1324.5 | AZ15: 0.09 | BA15: =AG15*AZ15 -> 135 | BD15: ok | BG15: 750.55 | BH15: 750.55 | BI15: =BH15-BG15 -> 0
A16: 1ER | C16: 7 | D16: GUILLEN | E16: CERECEDA | F16: KATHERINN | G16: ELIZABETH | H16: INTEGRA | I16: 641760KGCLE7 | K16: 48053446 | L16: 45461 | M16: 34178 | O16: CONTABILIDAD | P16: ASIST.CONTABLE | Q16: 750 | AF16: =SUM(Q16:AD16)-AE16 -> 750 | AG16: =+Q16+S16+T16+U16+V16+X16-AE16 -> 750 | AJ16: 0.1 | AK16: =+AG16*AJ16 -> 75 | AL16: 0 | AN16: 0.017 | AO16: =+AG16*AN16 -> 12.75 | AP16: =+AJ16+AN16 -> 0.117 | AQ16: =+AK16+AM16+AO16 -> 87.75 | AX16: =+AI16+AQ16+AR16+AS16+AT16+AU16+AW16 -> 87.75 | AY16: =(+AF16-AX16) -> 662.25 | AZ16: 0.09 | BA16: =AG16*AZ16 -> 67.5 | BD16: ok | BG16: 286.98 | BH16: 286.98 | BI16: =BH16-BG16 -> 0
A17: 1ER | C17: 8 | D17: SALAS | E17: SORIA | F17: OMAR | G17: ANDRES | H17: HABITAT | I17: 638061OSSAI5 | K17: 70157117 | L17: 45425 | M17: 33808 | O17: RESTAURANT | P17: BARMAN | Q17: 1400 | AF17: =SUM(Q17:AD17)-AE17 -> 1400 | AG17: =+Q17+S17+T17+U17+V17+X17-AE17 -> 1400 | AJ17: 0.1 | AK17: =+AG17*AJ17 -> 140 | AL17: 0 | AN17: 0.017 | AO17: =+AG17*AN17 -> 23.8 | AP17: =+AJ17+AN17 -> 0.117 | AQ17: =+AK17+AM17+AO17 -> 163.8 | AX17: =+AI17+AQ17+AR17+AS17+AT17+AU17+AW17 -> 163.8 | AY17: =(+AF17-AX17) -> 1236.2 | AZ17: 0.09 | BA17: =AG17*AZ17 -> 126 | BB17: 2.09 | BD17: ok | BG17: 700.51 | BH17: 700.51 | BI17: =BH17-BG17 -> 0
A18: 1ER | C18: 9 | D18: ESTRADA | E18: MANYARI | F18: MATIAS | G18: ANTONIO | H18: INTEGRA | I18: 686101MEMRY1 | K18: 77431897 | L18: 45425 | M18: 38612 | O18: RESTAURANT | P18: MESERO | Q18: =1300 -> 1300 | AF18: =SUM(Q18:AD18)-AE18 -> 1300 | AG18: =+Q18+S18+T18+U18+V18+X18-AE18 -> 1300 | AJ18: 0.1 | AK18: =+AG18*AJ18 -> 130 | AL18: 0 | AN18: 0.017 | AO18: =+AG18*AN18 -> 22.1 | AP18: =+AJ18+AN18 -> 0.117 | AQ18: =+AK18+AM18+AO18 -> 152.1 | AX18: =+AI18+AQ18+AR18+AS18+AT18+AU18+AW18 -> 152.1 | AY18: =(+AF18-AX18) -> 1147.9 | AZ18: 0.09 | BA18: =AG18*AZ18 -> 117 | BB18: 2.88 | BD18: ok | BG18: 573.95 | BH18: 650.48 | BI18: =BH18-BG18 -> 76.53 | BK18: no pago de feriado dia 09.06
A19: 1ER | C19: 10 | D19: PINILLOS | E19: HIDALGO | F19: MIGUEL | G19: ANGEL | H19: INTEGRA | I19: 676151MPHIA6 | K19: 73994130 | L19: 45425 | M19: 37617 | O19: RESTAURANT | P19: OPERARIO DE LIMPIEZA | Q19: 650 | AF19: =SUM(Q19:AD19)-AE19 -> 650 | AG19: =+Q19+S19+T19+U19+V19+X19-AE19 -> 650 | AJ19: 0.1 | AK19: =+AG19*AJ19 -> 65 | AL19: 0 | AN19: 0.017 | AO19: =+AG19*AN19 -> 11.05 | AP19: =+AJ19+AN19 -> 0.117 | AQ19: =+AK19+AM19+AO19 -> 76.05 | AX19: =+AI19+AQ19+AR19+AS19+AT19+AU19+AW19 -> 76.05 | AY19: =(+AF19-AX19) -> 573.95 | AZ19: 0.09 | BA19: =AG19*AZ19 -> 58.5 | BB19: 2.88 | BD19: ok | BG19: 286.97 | BH19: 286.97 | BI19: =BH19-BG19 -> 0
A21: 1ER | Q21: =SUM(Q12:Q20) -> 9934 | S21: =SUM(S12:S20) -> 102.5 | T21: =SUM(T12:T20) -> 0 | U21: =SUM(U12:U20) -> 0 | V21: =SUM(V12:V20) -> 0 | W21: =SUM(W12:W20) -> 0 | X21: =SUM(X12:X20) -> 0 | Y21: =SUM(Y12:Y20) -> 0 | Z21: =SUM(Z12:Z20) -> 0 | AB21: =SUM(AB12:AB20) -> 0 | AC21: =SUM(AC12:AC20) -> 0 | AD21: =SUM(AD12:AD20) -> 0 | AE21: =SUM(AE12:AE20) -> 41.67 | AF21: =SUM(AF12:AF20) -> 9994.83 | AG21: =SUM(AG12:AG20) -> 9994.83 | AI21: =SUM(AI12:AI20) -> 0 | AK21: =SUM(AK12:AK20) -> 920.25 | AM21: =SUM(AM12:AM20) -> 15.5 | AO21: =SUM(AO12:AO20) -> 156.4425 | AQ21: =SUM(AQ12:AQ20) -> 1092.1925 | AR21: =SUM(AR12:AR20) -> 0 | AS21: =SUM(AS12:AS20) -> 0 | AT21: =SUM(AT12:AT14) -> 0 | AU21: =SUM(AU12:AU20) -> 0 | AX21: =SUM(AX12:AX20) -> 1092.1925 | AY21: =SUM(AY12:AY20) -> 8902.6375 | BA21: =SUM(BA12:BA20) -> 899.5347 | BB21: =SUM(BB12:BB20) -> 62.59
A23: 5TO | C23: 1 | D23: CHUNGA | E23: VILLAR | F23: PEDRO | G23: GIOMAR | H23: PRIMA | I23: 631631PCVNL0 | K23: 46704451 | L23: 45017 | M23: 33165 | O23: RESTAURANT | P23: JEFE DE COCINA | Q23: =3000 -> 3000 | S23: 102.5 | AF23: =SUM(Q23:AD23)-AE23 -> 3102.5 | AG23: =+Q23+S23+T23+U23+V23+X23+R23-AE23 -> 3102.5 | AJ23: 0.1 | AK23: =+AG23*AJ23 -> 310.25 | AL23: 0.016 | AM23: =+AG23*AL23 -> 49.64 | AN23: 0.017 | AO23: =+AG23*AN23 -> 52.7425 | AP23: =+AJ23+AL23+AN23 -> 0.133 | AQ23: =+AK23+AM23+AO23 -> 412.6325 | AR23: =30.41 -> 30.41 | AU23: 250 | AX23: =+AI23+AQ23+AR23+AS23+AT23+AU23+AW23 -> 693.0425 | AY23: =(+AF23-AX23) -> 2409.4575 | AZ23: 0.09 | BA23: =AG23*AZ23 -> 279.225 | BB23: 2.88 | BD23: ok | BG23: 1249.95 | BH23: 1339.61 | BI23: =BH23-BG23 -> 89.66 | BK23: no pago de feriado dia 09.06
A24: 5TO | C24: 2 | D24: MAMANI | E24: HUAMANI | F24: YAMIR | G24: JOSE | H24: INTEGRA | I24: 621701YMHAM9 | K24: 44895694 | L24: 44882 | M24: 32172 | O24: ROOFTOP | P24: LOGISTICA | Q24: 1000 | AF24: =SUM(Q24:AD24)-AE24 -> 1000 | AG24: =+Q24+S24+T24+U24+V24+X24-AE24 -> 1000 | AJ24: 0.1 | AK24: =+AG24*AJ24 -> 100 | AL24: 0.0155 | AM24: =+AG24*AL24 -> 15.5 | AN24: 0.017 | AO24: =+AG24*AN24 -> 17 | AP24: =+AJ24+AL24+AN24 -> 0.1325 | AQ24: =+AK24+AM24+AO24 -> 132.5 | AX24: =+AI24+AQ24+AR24+AS24+AT24+AU24+AW24 -> 132.5 | AY24: =(+AF24-AX24) -> 867.5 | AZ24: 0.09 | BA24: =AG24*AZ24 -> 90 | BB24: 1.44 | BD24: ok | BG24: 433.75 | BH24: 433.75 | BI24: =BH24-BG24 -> 0
A25: 5TO | C25: 3 | D25: CARRASQUEL | E25: HERNANDEZ | F25: ANGIRBER | G25: GABRIEL | H25: INTEGRA | I25: 646151ACHRN5 | K25: 004696624 | L25: 45078 | M25: 34617 | O25: SALON | P25: JEFE DE BARRA | Q25: =2000 -> 2000 | S25: 102.5 | AF25: =SUM(Q25:AD25)-AE25 -> 2102.5 | AG25: =+Q25+S25+T25+U25+V25+X25-AE25 -> 2102.5 | AJ25: 0.1 | AK25: =+AG25*AJ25 -> 210.25 | AL25: 0 | AN25: 0.017 | AO25: =+AG25*AN25 -> 35.7425 | AP25: =+AJ25+AL25+AN25 -> 0.117 | AQ25: =+AK25+AM25+AO25 -> 245.9925 | AX25: =+AI25+AQ25+AR25+AS25+AT25+AU25+AW25 -> 245.9925 | AY25: =(+AF25-AX25) -> 1856.5075 | AZ25: 0.09 | BA25: =+AG25*AZ25 -> 189.225 | BB25: 2.88 | BD25: ok | BG25: 883 | BH25: 1006.77 | BI25: =BH25-BG25 -> 123.77 | BK25: no pago de feriado dia 09.06
A26: 5TO | C26: 4 | D26: VICENTE | E26: BLAS | F26: CALIXTO | K26: 08751792 | L26: 45078 | M26: 20663 | P26: CONDUCTOR | Q26: 834 | AE26: 41.66 | AF26: =SUM(Q26:AD26)-AE26 -> 792.34 | AG26: =+Q26+S26+T26+U26+V26+X26-AE26 -> 792.34 | AX26: =+AI26+AQ26+AR26+AS26+AT26+AU26+AW26 -> 0 | AY26: =(+AF26-AX26) -> 792.34 | AZ26: 0.09 | BA26: =+AG26*AZ26 -> 71.3106 | BB26: 50.42 | BD26: ok | BG26: 500.33 | BH26: 458.67 | BI26: =BH26-BG26 -> -41.66 | BJ26: (Descontar en julio)
A27: 5TO | C27: 5 | D27: RIVERO | E27: GACON | F27: VICTOR | H27: ONP | K27: 09979245 | L27: 45385 | M27: 26727 | P27: ADMINISTRADOR | Q27: 5934.56 | AF27: =SUM(Q27:AD27)-AE27 -> 5934.56 | AG27: =+Q27+S27+T27+U27+V27+X27-AE27 -> 5934.56 | AH27: 0.13 | AI27: =AG27*AH27 -> 771.4928 | AR27: =163.06 -> 163.06 | AX27: =+AI27+AQ27+AR27+AS27+AT27+AU27+AW27 -> 934.5528 | AY27: =(+AF27-AX27) -> 5000.0072 | AZ27: 0.09 | BA27: =AG27*AZ27 -> 534.1104 | BD27: ok | BG27: 2000.01 | BH27: 2001.01 | BI27: =BH27-BG27 -> 1
A28: 5TO | C28: 7 | D28: GUILLEN | E28: CERECEDA | F28: KATHERINN | G28: ELIZABETH | H28: INTEGRA | I28: 641760KGCLE7 | K28: 48053446 | L28: 45461 | M28: 34178 | O28: CONTABILIDAD | P28: ASIST.CONTABLE | Q28: 750 | AF28: =SUM(Q28:AD28)-AE28 -> 750 | AG28: =+Q28+S28+T28+U28+V28+X28-AE28 -> 750 | AJ28: 0.1 | AK28: =+AG28*AJ28 -> 75 | AL28: 0 | AN28: 0.017 | AO28: =+AG28*AN28 -> 12.75 | AP28: =+AJ28+AN28 -> 0.117 | AQ28: =+AK28+AM28+AO28 -> 87.75 | AX28: =+AI28+AQ28+AR28+AS28+AT28+AU28+AW28 -> 87.75 | AY28: =(+AF28-AX28) -> 662.25 | AZ28: 0.09 | BA28: =AG28*AZ28 -> 67.5 | BD28: ok | BG28: 286.98 | BH28: 286.98 | BI28: =BH28-BG28 -> 0
A29: 5TO | C29: 8 | D29: PINILLOS | E29: HIDALGO | F29: MIGUEL | G29: ANGEL | H29: INTEGRA | I29: 676151MPHIA6 | K29: 73994130 | L29: 45425 | M29: 37617 | O29: RESTAURANT | P29: OPERARIO DE LIMPIEZA | Q29: 650 | AF29: =SUM(Q29:AD29)-AE29 -> 650 | AG29: =+Q29+S29+T29+U29+V29+X29-AE29 -> 650 | AJ29: 0.1 | AK29: =+AG29*AJ29 -> 65 | AL29: 0 | AN29: 0.017 | AO29: =+AG29*AN29 -> 11.05 | AP29: =+AJ29+AN29 -> 0.117 | AQ29: =+AK29+AM29+AO29 -> 76.05 | AX29: =+AI29+AQ29+AR29+AS29+AT29+AU29+AW29 -> 76.05 | AY29: =(+AF29-AX29) -> 573.95 | AZ29: 0.09 | BA29: =AG29*AZ29 -> 58.5 | BB29: 2.88 | BD29: ok | BG29: 286.97 | BH29: 286.97 | BI29: =BH29-BG29 -> 0
A30: 5TO | C30: 9 | D30: BARTESAGHI | E30: MALAGA | F30: RENATO | H30: INTEGRA | I30: 664941RBMTA8 | K30: 71455402 | L30: 45444 | M30: 36496 | O30: RESTAURANT | P30: COCINERO | Q30: =1500 -> 1500 | AF30: =SUM(Q30:AD30)-AE30 -> 1500 | AG30: =+Q30+S30+T30+U30+V30+X30-AE30 -> 1500 | AJ30: 0.1 | AK30: =+AG30*AJ30 -> 150 | AL30: 0 | AN30: 0.017 | AO30: =+AG30*AN30 -> 25.5 | AP30: =+AJ30+AL30+AN30 -> 0.117 | AQ30: =+AK30+AM30+AO30 -> 175.5 | AX30: =+AI30+AQ30+AR30+AS30+AT30+AU30+AW30 -> 175.5 | AY30: =(+AF30-AX30) -> 1324.5 | AZ30: 0.09 | BA30: =+AG30*AZ30 -> 135 | BD30: ok | BG30: 662.25 | BH30: 750.55 | BI30: =BH30-BG30 -> 88.3 | BK30: no pago de feriado dia 09.06
A31: 5TO | C31: 10 | D31: CERRON | E31: ANTO | F31: ALVARO | G31: MARCELO | H31: INTEGRA | I31: 669981ACARO4 | K31: 74221679 | L31: 45444 | M31: 37000 | O31: RESTAURANT | P31: BARMAN | Q31: =1400 -> 1400 | AF31: =SUM(Q31:AD31)-AE31 -> 1400 | AG31: =+Q31+S31+T31+U31+V31+X31-AE31 -> 1400 | AJ31: 0.1 | AK31: =+AG31*AJ31 -> 140 | AL31: 0 | AN31: 0.017 | AO31: =+AG31*AN31 -> 23.8 | AP31: =+AJ31+AL31+AN31 -> 0.117 | AQ31: =+AK31+AM31+AO31 -> 163.8 | AX31: =+AI31+AQ31+AR31+AS31+AT31+AU31+AW31 -> 163.8 | AY31: =(+AF31-AX31) -> 1236.2 | AZ31: 0.09 | BA31: =+AG31*AZ31 -> 126 | BD31: ok | BG31: 618.1 | BH31: 700.51 | BI31: =BH31-BG31 -> 82.41 | BK31: no pago de feriado dia 09.06
A33: 5TO | Q33: =SUM(Q23:Q32) -> 17068.56 | R33: =SUM(R22:R32) -> 0 | S33: =SUM(S22:S32) -> 205 | T33: =SUM(T23:T29) -> 0 | U33: =SUM(U22:U29) -> 0 | V33: =SUM(V22:V32) -> 0 | W33: =SUM(W22:W29) -> 0 | X33: =SUM(X22:X29) -> 0 | Y33: =SUM(Y22:Y29) -> 0 | Z33: =SUM(Z22:Z29) -> 0 | AA33: =SUM(AA22:AA29) -> 0 | AB33: =SUM(AB22:AB26) -> 0 | AC33: =SUM(AC22:AC32) -> 0 | AD33: =SUM(AD22:AD32) -> 0 | AE33: =SUM(AE22:AE32) -> 41.66 | AF33: =SUM(AF22:AF32) -> 17231.9 | AG33: =SUM(AG22:AG32) -> 17231.9 | AI33: =SUM(AI22:AI32) -> 771.4928 | AK33: =SUM(AK23:AK32) -> 1050.5 | AM33: =SUM(AM23:AM32) -> 65.14 | AO33: =SUM(AO23:AO32) -> 178.585 | AQ33: =SUM(AQ23:AQ32) -> 1294.225 | AR33: =SUM(AR23:AR32) -> 193.47 | AS33: =SUM(AS22:AS32) -> 0 | AT33: =SUM(AT23:AT32) -> 0 | AU33: =SUM(AU22:AU32) -> 250 | AV33: =SUM(AV23:AV32) -> 0 | AW33: =SUM(AW23:AW32) -> 0 | AX33: =SUM(AX22:AX32) -> 2509.1878 | AY33: =SUM(AY22:AY32) -> 14722.712 | BA33: =SUM(BA22:BA32) -> 1550.871 | BB33: =SUM(BB22:BB32) -> 60.5
A35: PA | C35: 1 | D35: MOYA | E35: HUAMANI | F35: FERNANDO | H35: ONP | K35: 42859800 | L35: 43374 | M35: 31072 | O35: PACHACAMAC | P35: EMPLEADO | Q35: 2230 | S35: 102.5 | AF35: =SUM(Q35:AD35)-AE35 -> 2332.5 | AG35: =+Q35+S35+T35+U35+V35+X35-AE35 -> 2332.5 | AH35: 0.13 | AI35: =AG35*AH35 -> 303.225 | AX35: =+AI35+AQ35+AR35+AS35+AT35+AU35+AW35 -> 303.225 | AY35: =(+AF35-AX35) -> 2029.275 | AZ35: 0.09 | BA35: =+AG35*AZ35 -> 209.925 | BB35: 8.3 | BD35: ok | BI35: 148.66 | BJ35: (Feriado del 07.06.24
A36: MAR | C36: 2 | D36: TELLO | E36: FLORES | F36: DARIO | H36: ONP | K36: 42617078 | L36: 43374 | M36: 30071 | O36: MARIPOSARIO | P36: SERVICIO DE PERSONAL | Q36: 2794.02 | S36: 102.5 | AF36: =SUM(Q36:AD36)-AE36 -> 2896.52 | AG36: =+Q36+S36+T36+U36+V36+X36-AE36 -> 2896.52 | AH36: 0.13 | AI36: =AG36*AH36 -> 376.5476 | AR36: 20 | AU36: 300 | AV36: 1124.3 | AX36: =+AI36+AQ36+AR36+AS36+AT36+AU36+AV36+AW36 -> 1820.8476 | AY36: =(+AF36-AX36) -> 1075.6724 | AZ36: 0.09 | BA36: =+AG36*AZ36 -> 260.6868 | BB36: 8.3 | BD36: ok
Q38: =SUM(Q35:Q37) -> 5024.02 | S38: =SUM(S34:S37) -> 205 | T38: =SUM(T35:T37) -> 0 | U38: =SUM(U35:U37) -> 0 | V38: =SUM(V37:V37) -> 0 | W38: =SUM(W35:W37) -> 0 | X38: =SUM(X34:X37) -> 0 | Y38: =SUM(Y35:Y37) -> 0 | Z38: =SUM(Z35:Z37) -> 0 | AB38: =SUM(AB35:AB37) -> 0 | AD38: =SUM(AD37:AD37) -> 0 | AE38: =SUM(AE35:AE37) -> 0 | AF38: =SUM(AF35:AF37) -> 5229.02 | AG38: =SUM(AG35:AG37) -> 5229.02 | AI38: =SUM(AI35:AI37) -> 679.7726 | AK38: =SUM(AK35:AK37) -> 0 | AL38: =SUM(AL35:AL37) -> 0 | AM38: =SUM(AM35:AM37) -> 0 | AN38: =SUM(AN35:AN37) -> 0 | AO38: =SUM(AO35:AO37) -> 0 | AP38: =SUM(AP35:AP37) -> 0 | AQ38: =SUM(AQ35:AQ37) -> 0 | AR38: =SUM(AR35:AR37) -> 20 | ... AV38: =SUM(AV35:AV37) -> 1124.3 | AX38: =SUM(AX35:AX37) -> 2124.0726 | AY38: =SUM(AY34:AY37) -> 3104.9474 | BA38: =SUM(BA35:BA37) -> 470.6118 | BB38: =SUM(BB34:BB37) -> 16.6
A39: PSM | C39: 1 | D39: RODRIGUEZ | E39: CHIMPAY | F39: CARMEN | G39: ISABEL | H39: PRIMA | I39: 627030CRCRM5 | K39: 61043871 | L39: 45002 | M39: 32705 | O39: CONTABILIDAD | P39: ANALIST.CONTABLE | Q39: 2542 | AF39: =SUM(Q39:AD39)-AE39 -> 2542 | AG39: =+Q39+S39+T39+U39+V39+X39-AE39 -> 2542 | AJ39: 0.1 | AK39: =+AG39*AJ39 -> 254.2 | AL39: 0.016 | AM39: =+AG39*AL39 -> 40.672 | AN39: 0.017 | AO39: =+AG39*AN39 -> 43.214 | AP39: =+AJ39+AL39+AN39 -> 0.133 | AQ39: =+AK39+AM39+AO39 -> 338.086 | AX39: =+AI39+AQ39+AR39+AS39+AT39+AU39+AW39 -> 338.086 | AY39: =(+AF39-AX39) -> 2203.914 | AZ39: 0.09 | BA39: =+AG39*AZ39 -> 228.78 | BB39: 2.88 | BD39: ok
A40: PSM | C40: 2 | D40: ZAMORA | E40: VELASQUEZ | F40: ELVIS | G40: IVAN | H40: HABITAT | I40: 652131EZVOA7 | K40: 76542051 | L40: 45170 | M40: 35215 | O40: CONTABILIDAD | P40: AUX. CONTABLE | Q40: 1450 | AF40: =SUM(Q40:AD40)-AE40 -> 1450 | AG40: =+Q40+S40+T40+U40+V40+X40-AE40 -> 1450 | AJ40: 0.1 | AK40: =+AG40*AJ40 -> 145 | AL40: 0 | AN40: 0.017 | AO40: =+AG40*AN40 -> 24.65 | AP40: =+AJ40+AN40 -> 0.117 | AQ40: =+AK40+AM40+AO40 -> 169.65 | AX40: =+AI40+AQ40+AR40+AS40+AT40+AU40+AW40 -> 169.65 | AY40: =(+AF40-AX40) -> 1280.35 | AZ40: 0.09 | BA40: =+AG40*AZ40 -> 130.5 | BD40: ok
